Workbook

Sheet 읽는 방법
A1: 미국 50개사 ROIC vs WACC 10% — 읽는 방법
A2: 무엇을 담았는지
A3: 질문 | B3: ROIC가 자본비용(WACC)보다 높은지, 그게 10년간 꾸준했는지
A4: WACC | B4: 전 종목 10% 고정 — 지시사항. 기업별로 다르게 잡으면 ROIC 비교가 아니라 베타 비교가 되므로 같은 문턱을 적용했습니다.
A5: 대상 | B5: 50개 미국 상장사, 기업별 최근 10개 회계연도 (FY2016~FY2026 범위). 결산월이 달라 같은 창을 강제하지 않았습니다.
A6: 자료 기준일 | B6: 2026-10-29 — 이 날짜에 SEC에서 받은 공시 기준입니다. 최신 회계연도는 FY2026.
A7: 자료 출처 | B7: SEC XBRL companyfacts API. 1차 조사가 공시 본문을 읽은 것과 달리 이번 조사는 태그 데이터를 직접 받았습니다 — 같은 정의, 다른 경로. 두 결과가 어긋나면 한쪽이 틀렸다는 뜻이고, '구 조사 대조' 시트가 어느 쪽인지 가립니다.
A9: ROIC를 어떻게 계산했는지
A10: 분자 NOPAT | B10: 영업이익 × (1 − 실효세율). 실효세율 = 법인세비용 ÷ 세전이익, 5%~40%로 제한.
A11: 분모 투하자본 | B11: 자기자본(비지배지분 포함) + 이자부채입금 − 현금 및 단기투자자산. 2007년 주주서한의 '사업 운영에 필요한 자본' 기준으로, 국채 포트폴리오는 사업 자본이 아니므로 뺍니다.
A12: 분모 평균 | B12: 기초·기말 평균. 단 어느 한쪽이 0 이하인 해는 평균이 0 근처로 내려가 비율이 폭발하므로 기말값 단독 사용.
A13: 금융업 | B13: SIC 6000~6799은 ROIC 미산출. 은행에게 차입은 자금조달이 아니라 원재료여서, 자기자본+차입금−현금은 아무것도 측정하지 않습니다.
A15: 믿을 수 있는 정도
A16: HIGH | B16: 기업이 보고한 영업이익 소계를 그대로 사용 (332개 연도), 또는 손익계산서 항목을 쌓아 세전이익으로 역검증 통과.
A17: MEDIUM | B17: 항목을 쌓아 만든 소계가 세전이익과 5% 이내로 맞은 경우.
A18: LOW | B18: 영업이익 소계를 아예 보고하지 않아 세전이익에서 거꾸로 추정한 경우 (릴리·머크·J&J·IBM·엑슨·셰브론·GE). 두 가지 추정 방식을 모두 계산해 10% 문턱 판정이 일치하는지 '계산 명세' 시트에 기록했습니다.
A19: 분모가 작은 해 | B19: 아리스타·램리서치처럼 현금이 자기자본을 거의 상계해 순투하자본이 매출의 10% 미만이 되는 해는 노란색. 비율은 민감해지지만 10% 문턱 판정은 유효.
A21: 검증
A22: 자동 검사 | B22: verify_roic.py에서 9,867건 통과. 항등식(투하자본·NOPAT·ROIC·평균 규칙), 트립와이어(차감 현금 ≤ 유동자산, 차입금 ≤ 총부채), 공시 원문에서 손으로 읽은 앵커 19건.
A23: 변이 검정 | B23: 값을 고의로 훼손한 10가지 시나리오 전부 탐지. 틀린 데이터에서도 통과하는 검사는 검사가 아닙니다.
A25: 1차 조사에서 바로잡은 것
A26: 대조 결과 | B26: 380개 기업-연도 중 221건은 1%p 이내 일치, 159건 불일치, 7건은 10% 문턱 판정까지 바뀜.
A27: 가장 큰 원인 | B27: 1차 조사가 공시된 장기차입금을 누락한 27개 기업-연도. 오라클 10년, 코카콜라 7년, 브로드컴 4년, 비자 3년. 오라클 FY2024 ROIC가 761%로 나온 이유입니다.
A28: 정정 범위 | B28: 319개 기업-연도의 ROIC·영업이익·세율·투하자본을 교체. 원본은 analysis.json.pre-roic-correction에 보존.
A29: 가치평가 파급 | B29: 순현금 입력값까지 어긋난 기업 5곳을 '정정 내역' 시트에 기록. 오라클은 시가총액의 24%에 해당하는 오차라 DCF 결론이 바뀔 수 있지만, 가치평가 재계산은 이번 작업 범위가 아니어서 표시만 했습니다.
A31: 기업 이름 | B31: 표에는 한글명과 티커만 적었습니다. 영문 정식 명칭과 SEC 등록명은 '기업 목록' 시트에 있고, '계산 명세' 시트 마지막 열에도 등록명이 있습니다.
A33: 수식 | B33: 파생 셀은 전부 같은 통합문서 안의 셀을 참조하는 수식입니다. '계산 명세' 시트의 공시 입력값만 바꾸면 모든 시트가 따라 바뀝니다. 수식이 아닌 값은 공시에서 가져온 원자료뿐입니다.

Sheet 기업 목록
A1: 기업 목록 — 티커 · 한글명 · 영문 정식 명칭
A2: SEC가 반환하는 이름은 등록명(COSTCO WHOLESALE CORP /NEW, APPLIED MATERIALS INC /DE 등)이라 표에 그대로 쓰지 않았습니다. 등록명은 '계산 명세' 시트 마지막 열에 그대로 남겨두었습니다.
A3: 티커 | B3: 한글명 | C3: 영문 정식 명칭 | D3: SEC 등록명 | E3: 구분 | F3: 비고
A4: ANET | B4: 아리스타 네트웍스 | C4: Arista Networks | D4: Arista Networks, Inc. | E4: ROIC 순위 대상 | F4: —
A5: NVDA | B5: 엔비디아 | C5: NVIDIA | D5: NVIDIA CORP | E5: ROIC 순위 대상 | F5: 1월 결산 — 본문의 회계연도 표기 참고
A6: MA | B6: 마스터카드 | C6: Mastercard | D6: Mastercard Inc | E6: ROIC 순위 대상 | F6: —
A7: AAPL | B7: 애플 | C7: Apple | D7: Apple Inc. | E7: ROIC 순위 대상 | F7: —
A8: MSFT | B8: 마이크로소프트 | C8: Microsoft | D8: MICROSOFT CORP | E8: ROIC 순위 대상 | F8: —
A9: LRCX | B9: 램리서치 | C9: Lam Research | D9: LAM RESEARCH CORP | E9: ROIC 순위 대상 | F9: —
A10: PM | B10: 필립모리스 인터내셔널 | C10: Philip Morris International | D10: Philip Morris International Inc. | E10: ROIC 순위 대상 | F10: —
A11: KLAC | B11: KLA | C11: KLA | D11: KLA CORP | E11: ROIC 순위 대상 | F11: 2019년까지 사명은 KLA-Tencor
A12: TXN | B12: 텍사스 인스트루먼츠 | C12: Texas Instruments | D12: TEXAS INSTRUMENTS INC | E12: ROIC 순위 대상 | F12: —
A13: META | B13: 메타 플랫폼스 | C13: Meta Platforms | D13: Meta Platforms, Inc. | E13: ROIC 순위 대상 | F13: 2021년까지 사명은 Facebook
A14: HD | B14: 홈디포 | C14: Home Depot | D14: HOME DEPOT, INC. | E14: ROIC 순위 대상 | F14: —
... A53: C | B53: 씨티그룹 | C53: Citigroup | D53: CITIGROUP INC | E53: 금융업 — ROIC 미산출 | F53: —

Sheet 계산 명세
A1: 기업 | B1: 티커 | C1: 회계연도 | D1: 결산일 | E1: 매출 | F1: 영업이익 | G1: 산출 경로 | H1: 신뢰도 | I1: 실효세율 | J1: NOPAT | K1: 자기자본 | L1: 이자부차입금 | M1: 현금+단기투자 | N1: 투하자본 | O1: 직전 투하자본 | P1: 평균 투하자본 | Q1: 평균 산정 | R1: ROIC | S1: ROIC−10% | T1: 분모/매출 | U1: 대안 추정 ROIC | V1: 문턱 판정 일치 | W1: 상태 | X1: SEC 등록명
A2: 엔비디아 | B2: NVDA | C2: 2015 | D2: 2016-01-31 | E2: 5010000000 | F2: 747000000 | G2: reported | H2: HIGH | I2: 0.17362046 | J2: =IF(F2="","",F2*(1-I2)) -> 6.1730552e+08 | K2: 4469000000 | L2: 0 | M2: 5037000000 | N2: =IF(COUNT(K2:M2)<3,"",K2+L2-M2) -> -568000000 | O2: — | P2: — | Q2: — | R2: — | S2: — | T2: — | U2: — | V2: — | W2: 다음 해 평균 투하자본의 기초값으로만 사용 (보고 기간 밖 — 자체 비율은 계산하지 않음) | X2: NVIDIA CORP
A3: 엔비디아 | B3: NVDA | C3: 2016 | D3: 2017-01-29 | E3: 6910000000 | F3: 1934000000 | G3: reported | H3: HIGH | I3: 0.12545932 | J3: =IF(F3="","",F3*(1-I3)) -> 1.6913617e+09 | K3: 5762000000 | L3: 1983000000 | M3: 6798000000 | N3: =IF(COUNT(K3:M3)<3,"",K3+L3-M3) -> 947000000 | O3: =N2 -> -568000000 | P3: =IF(N3="","",IF(OR(O3="",O3<=0,N3<=0),N3,(N3+O3)/2)) -> 947000000 | Q3: 기말 단독 (기초 또는 기말 자본이 0 이하) | R3: =IF(OR(P3="",P3<=0),"",J3/P3) -> 1.7860208 | S3: =IF(R3="","",R3-0.1) -> 1.6860208 | T3: =IF(OR(P3="",E3=0,E3=""),"",P3/E3) -> 0.13704776 | U3: — | V3: — | W3: OK | X3: NVIDIA CORP
A4: 엔비디아 | B4: NVDA | C4: 2017 | D4: 2018-01-28 | E4: 9714000000 | F4: 3210000000 | G4: reported | H4: HIGH | I4: 0.05 | J4: =IF(F4="","",F4*(1-I4)) -> 3049500000 | K4: 7471000000 | L4: 1985000000 | M4: 7108000000 | N4: =IF(COUNT(K4:M4)<3,"",K4+L4-M4) -> 2348000000 | O4: =N3 -> 947000000 | P4: =IF(N4="","",IF(OR(O4="",O4<=0,N4<=0),N4,(N4+O4)/2)) -> 1647500000 | Q4: 기초·기말 평균 | R4: =IF(OR(P4="",P4<=0),"",J4/P4) -> 1.8509863 | S4: =IF(R4="","",R4-0.1) -> 1.7509863 | T4: =IF(OR(P4="",E4=0,E4=""),"",P4/E4) -> 0.16960058 | U4: — | V4: — | W4: OK | X4: NVIDIA CORP
A5: 엔비디아 | B5: NVDA | C5: 2018 | D5: 2019-01-27 | E5: 11716000000 | F5: 3804000000 | G5: reported | H5: HIGH | I5: 0.05 | J5: =IF(F5="","",F5*(1-I5)) -> 3613800000 | K5: 9342000000 | L5: 1988000000 | M5: 7422000000 | N5: =IF(COUNT(K5:M5)<3,"",K5+L5-M5) -> 3908000000 | O5: =N4 -> 2348000000 | P5: =IF(N5="","",IF(OR(O5="",O5<=0,N5<=0),N5,(N5+O5)/2)) -> 3128000000 | Q5: 기초·기말 평균 | R5: =IF(OR(P5="",P5<=0),"",J5/P5) -> 1.1553069 | S5: =IF(R5="","",R5-0.1) -> 1.0553069 | T5: =IF(OR(P5="",E5=0,E5=""),"",P5/E5) -> 0.26698532 | U5: — | V5: — | W5: OK | X5: NVIDIA CORP
A6: 엔비디아 | B6: NVDA | C6: 2019 | D6: 2020-01-26 | E6: 10918000000 | F6: 2846000000 | G6: reported | H6: HIGH | I6: 0.058585859 | J6: =IF(F6="","",F6*(1-I6)) -> 2.6792646e+09 | K6: 12204000000 | L6: 1991000000 | M6: 10897000000 | N6: =IF(COUNT(K6:M6)<3,"",K6+L6-M6) -> 3298000000 | O6: =N5 -> 3908000000 | P6: =IF(N6="","",IF(OR(O6="",O6<=0,N6<=0),N6,(N6+O6)/2)) -> 3603000000 | Q6: 기초·기말 평균 | R6: =IF(OR(P6="",P6<=0),"",J6/P6) -> 0.7436205 | S6: =IF(R6="","",R6-0.1) -> 0.6436205 | T6: =IF(OR(P6="",E6=0,E6=""),"",P6/E6) -> 0.3300055 | U6: — | V6: — | W6: OK | X6: NVIDIA CORP
A7: 엔비디아 | B7: NVDA | C7: 2020 | D7: 2021-01-31 | E7: 16675000000 | F7: 4532000000 | G7: reported | H7: HIGH | I7: 0.05 | J7: =IF(F7="","",F7*(1-I7)) -> 4305400000 | K7: 16893000000 | L7: 6963000000 | M7: 11561000000 | N7: =IF(COUNT(K7:M7)<3,"",K7+L7-M7) -> 12295000000 | O7: =N6 -> 3298000000 | P7: =IF(N7="","",IF(OR(O7="",O7<=0,N7<=0),N7,(N7+O7)/2)) -> 7796500000 | Q7: 기초·기말 평균 | R7: =IF(OR(P7="",P7<=0),"",J7/P7) -> 0.55222215 | S7: =IF(R7="","",R7-0.1) -> 0.45222215 | T7: =IF(OR(P7="",E7=0,E7=""),"",P7/E7) -> 0.46755622 | U7: — | V7: — | W7: OK | X7: NVIDIA CORP
A8: 엔비디아 | B8: NVDA | C8: 2021 | D8: 2022-01-30 | E8: 26914000000 | F8: 10041000000 | G8: reported | H8: HIGH | I8: 0.05 | J8: =IF(F8="","",F8*(1-I8)) -> 9538950000 | K8: 26612000000 | L8: 10946000000 | M8: 21208000000 | N8: =IF(COUNT(K8:M8)<3,"",K8+L8-M8) -> 16350000000 | O8: =N7 -> 12295000000 | P8: =IF(N8="","",IF(OR(O8="",O8<=0,N8<=0),N8,(N8+O8)/2)) -> 14322500000 | Q8: 기초·기말 평균 | R8: =IF(OR(P8="",P8<=0),"",J8/P8) -> 0.66601152 | S8: =IF(R8="","",R8-0.1) -> 0.56601152 | T8: =IF(OR(P8="",E8=0,E8=""),"",P8/E8) -> 0.53215798 | U8: — | V8: — | W8: OK | X8: NVIDIA CORP
A9: 엔비디아 | B9: NVDA | C9: 2022 | D9: 2023-01-29 | E9: 26974000000 | F9: 4224000000 | G9: reported | H9: HIGH | I9: 0.05 | J9: =IF(F9="","",F9*(1-I9)) -> 4012800000 | K9: 22101000000 | L9: 10953000000 | M9: 13296000000 | N9: =IF(COUNT(K9:M9)<3,"",K9+L9-M9) -> 19758000000 | O9: =N8 -> 16350000000 | P9: =IF(N9="","",IF(OR(O9="",O9<=0,N9<=0),N9,(N9+O9)/2)) -> 18054000000 | Q9: 기초·기말 평균 | R9: =IF(OR(P9="",P9<=0),"",J9/P9) -> 0.22226653 | S9: =IF(R9="","",R9-0.1) -> 0.12226653 | T9: =IF(OR(P9="",E9=0,E9=""),"",P9/E9) -> 0.66931119 | U9: — | V9: — | W9: OK | X9: NVIDIA CORP
A10: 엔비디아 | B10: NVDA | C10: 2023 | D10: 2024-01-28 | E10: 60922000000 | F10: 32972000000 | G10: reported | H10: HIGH | I10: 0.11999527 | J10: =IF(F10="","",F10*(1-I10)) -> 2.9015516e+10 | K10: 42978000000 | L10: 9709000000 | M10: 25984000000 | N10: =IF(COUNT(K10:M10)<3,"",K10+L10-M10) -> 26703000000 | O10: =N9 -> 19758000000 | P10: =IF(N10="","",IF(OR(O10="",O10<=0,N10<=0),N10,(N10+O10)/2)) -> 23230500000 | Q10: 기초·기말 평균 | R10: =IF(OR(P10="",P10<=0),"",J10/P10) -> 1.2490268 | S10: =IF(R10="","",R10-0.1) -> 1.1490268 | T10: =IF(OR(P10="",E10=0,E10=""),"",P10/E10) -> 0.38131545 | U10: — | V10: — | W10: OK | X10: NVIDIA CORP
A11: 엔비디아 | B11: NVDA | C11: 2024 | D11: 2025-01-26 | E11: 130497000000 | F11: 81453000000 | G11: reported | H11: HIGH | I11: 0.13264942 | J11: =IF(F11="","",F11*(1-I11)) -> 7.0648307e+10 | K11: 79327000000 | L11: 8463000000 | M11: 43210000000 | N11: =IF(COUNT(K11:M11)<3,"",K11+L11-M11) -> 44580000000 | O11: =N10 -> 26703000000 | P11: =IF(N11="","",IF(OR(O11="",O11<=0,N11<=0),N11,(N11+O11)/2)) -> 35641500000 | Q11: 기초·기말 평균 | R11: =IF(OR(P11="",P11<=0),"",J11/P11) -> 1.9821923 | S11: =IF(R11="","",R11-0.1) -> 1.8821923 | T11: =IF(OR(P11="",E11=0,E11=""),"",P11/E11) -> 0.27312122 | U11: — | V11: — | W11: OK | X11: NVIDIA CORP
A12: 엔비디아 | B12: NVDA | C12: 2025 | D12: 2026-01-25 | E12: 215938000000 | F12: 130387000000 | G12: reported | H12: HIGH | I12: 0.15117002 | J12: =IF(F12="","",F12*(1-I12)) -> 1.1067639e+11 | K12: 157293000000 | L12: 8468000000 | M12: 10605000000 | N12: =IF(COUNT(K12:M12)<3,"",K12+L12-M12) -> 155156000000 | O12: =N11 -> 44580000000 | P12: =IF(N12="","",IF(OR(O12="",O12<=0,N12<=0),N12,(N12+O12)/2)) -> 99868000000 | Q12: 기초·기말 평균 | R12: =IF(OR(P12="",P12<=0),"",J12/P12) -> 1.1082268 | S12: =IF(R12="","",R12-0.1) -> 1.0082268 | T12: =IF(OR(P12="",E12=0,E12=""),"",P12/E12) -> 0.4624846 | U12: — | V12: — | W12: OK | X12: NVIDIA CORP
A13: 애플 | B13: AAPL | C13: 2015 | D13: 2015-09-26 | E13: 233715000000 | F13: 71230000000 | G13: reported | H13: HIGH | I13: 0.26368338 | J13: =IF(F13="","",F13*(1-I13)) -> 5.2447833e+10 | K13: 119355000000 | L13: 64328000000 | M13: 41601000000 | N13: =IF(COUNT(K13:M13)<3,"",K13+L13-M13) -> 142082000000 | O13: — | P13: — | Q13: — | R13: — | S13: — | T13: — | U13: — | V13: — | W13: 다음 해 평균 투하자본의 기초값으로만 사용 (보고 기간 밖 — 자체 비율은 계산하지 않음) | X13: Apple Inc.
A14: 애플 | B14: AAPL | C14: 2016 | D14: 2016-09-24 | E14: 215639000000 | F14: 60024000000 | G14: reported | H14: HIGH | I14: 0.25557257 | J14: =IF(F14="","",F14*(1-I14)) -> 4.4683512e+10 | K14: 128249000000 | L14: 87032000000 | M14: 67155000000 | N14: =IF(COUNT(K14:M14)<3,"",K14+L14-M14) -> 148126000000 | O14: =N13 -> 142082000000 | P14: =IF(N14="","",IF(OR(O14="",O14<=0,N14<=0),N14,(N14+O14)/2)) -> 145104000000 | Q14: 기초·기말 평균 | R14: =IF(OR(P14="",P14<=0),"",J14/P14) -> 0.30794128 | S14: =IF(R14="","",R14-0.1) -> 0.20794128 | T14: =IF(OR(P14="",E14=0,E14=""),"",P14/E14) -> 0.6729024 | U14: — | V14: — | W14: OK | X14: Apple Inc.
A15: 애플 | B15: AAPL | C15: 2017 | D15: 2017-09-30 | E15: 229234000000 | F15: 61344000000 | G15: reported | H15: HIGH | I15: 0.24556476 | J15: =IF(F15="","",F15*(1-I15)) -> 4.6280075e+10 | K15: 134047000000 | L15: 115680000000 | M15: 74181000000 | N15: =IF(COUNT(K15:M15)<3,"",K15+L15-M15) -> 175546000000 | O15: =N14 -> 148126000000 | P15: =IF(N15="","",IF(OR(O15="",O15<=0,N15<=0),N15,(N15+O15)/2)) -> 161836000000 | Q15: 기초·기말 평균 | R15: =IF(OR(P15="",P15<=0),"",J15/P15) -> 0.28596898 | S15: =IF(R15="","",R15-0.1) -> 0.18596898 | T15: =IF(OR(P15="",E15=0,E15=""),"",P15/E15) -> 0.70598602 | U15: — | V15: — | W15: OK | X15: Apple Inc.
A16: 애플 | B16: AAPL | C16: 2018 | D16: 2018-09-29 | E16: 265595000000 | F16: 70898000000 | G16: reported | H16: HIGH | I16: 0.18342181 | J16: =IF(F16="","",F16*(1-I16)) -> 5.7893761e+10 | K16: 107147000000 | L16: 114483000000 | M16: 66301000000 | N16: =IF(COUNT(K16:M16)<3,"",K16+L16-M16) -> 155329000000 | O16: =N15 -> 175546000000 | P16: =IF(N16="","",IF(OR(O16="",O16<=0,N16<=0),N16,(N16+O16)/2)) -> 165437500000 | Q16: 기초·기말 평균 | R16: =IF(OR(P16="",P16<=0),"",J16/P16) -> 0.3499434 | S16: =IF(R16="","",R16-0.1) -> 0.2499434 | T16: =IF(OR(P16="",E16=0,E16=""),"",P16/E16) -> 0.62289388 | U16: — | V16: — | W16: OK | X16: Apple Inc.
A17: 애플 | B17: AAPL | C17: 2019 | D17: 2019-09-28 | E17: 260174000000 | F17: 63930000000 | G17: reported | H17: HIGH | I17: 0.15943837 | J17: =IF(F17="","",F17*(1-I17)) -> 5.3737105e+10 | K17: 90488000000 | L17: 108047000000 | M17: 100557000000 | N17: =IF(COUNT(K17:M17)<3,"",K17+L17-M17) -> 97978000000 | O17: =N16 -> 155329000000 | P17: =IF(N17="","",IF(OR(O17="",O17<=0,N17<=0),N17,(N17+O17)/2)) -> 126653500000 | Q17: 기초·기말 평균 | R17: =IF(OR(P17="",P17<=0),"",J17/P17) -> 0.42428441 | S17: =IF(R17="","",R17-0.1) -> 0.32428441 | T17: =IF(OR(P17="",E17=0,E17=""),"",P17/E17) -> 0.48680306 | U17: — | V17: — | W17: OK | X17: Apple Inc.
A18: 애플 | B18: AAPL | C18: 2020 | D18: 2020-09-26 | E18: 274515000000 | F18: 66288000000 | G18: reported | H18: HIGH | I18: 0.14428165 | J18: =IF(F18="","",F18*(1-I18)) -> 5.6723858e+10 | K18: 65339000000 | L18: 112436000000 | M18: 90943000000 | N18: =IF(COUNT(K18:M18)<3,"",K18+L18-M18) -> 86832000000 | O18: =N17 -> 97978000000 | P18: =IF(N18="","",IF(OR(O18="",O18<=0,N18<=0),N18,(N18+O18)/2)) -> 92405000000 | Q18: 기초·기말 평균 | R18: =IF(OR(P18="",P18<=0),"",J18/P18) -> 0.61386135 | S18: =IF(R18="","",R18-0.1) -> 0.51386135 | T18: =IF(OR(P18="",E18=0,E18=""),"",P18/E18) -> 0.33661184 | U18: — | V18: — | W18: OK | X18: Apple Inc.
A19: 애플 | B19: AAPL | C19: 2021 | D19: 2021-09-25 | E19: 365817000000 | F19: 108949000000 | G19: reported | H19: HIGH | I19: 0.13302261 | J19: =IF(F19="","",F19*(1-I19)) -> 9.445632e+10 | K19: 63090000000 | L19: 124719000000 | M19: 62639000000 | N19: =IF(COUNT(K19:M19)<3,"",K19+L19-M19) -> 125170000000 | O19: =N18 -> 86832000000 | P19: =IF(N19="","",IF(OR(O19="",O19<=0,N19<=0),N19,(N19+O19)/2)) -> 106001000000 | Q19: 기초·기말 평균 | R19: =IF(OR(P19="",P19<=0),"",J19/P19) -> 0.89108895 | S19: =IF(R19="","",R19-0.1) -> 0.79108895 | T19: =IF(OR(P19="",E19=0,E19=""),"",P19/E19) -> 0.2897651 | U19: — | V19: — | W19: OK | X19: Apple Inc.
A20: 애플 | B20: AAPL | C20: 2022 | D20: 2022-09-24 | E20: 394328000000 | F20: 119437000000 | G20: reported | H20: HIGH | I20: 0.16204462 | J20: =IF(F20="","",F20*(1-I20)) -> 1.0008288e+11 | K20: 50672000000 | L20: 120069000000 | M20: 48304000000 | N20: =IF(COUNT(K20:M20)<3,"",K20+L20-M20) -> 122437000000 | O20: =N19 -> 125170000000 | P20: =IF(N20="","",IF(OR(O20="",O20<=0,N20<=0),N20,(N20+O20)/2)) -> 123803500000 | Q20: 기초·기말 평균 | R20: =IF(OR(P20="",P20<=0),"",J20/P20) -> 0.80840103 | S20: =IF(R20="","",R20-0.1) -> 0.70840103 | T20: =IF(OR(P20="",E20=0,E20=""),"",P20/E20) -> 0.31396071 | U20: — | V20: — | W20: OK | X20: Apple Inc.
A21: 애플 | B21: AAPL | C21: 2023 | D21: 2023-09-30 | E21: 383285000000 | F21: 114301000000 | G21: reported | H21: HIGH | I21: 0.14719174 | J21: =IF(F21="","",F21*(1-I21)) -> 9.7476837e+10 | K21: 62146000000 | L21: 111088000000 | M21: 61555000000 | N21: =IF(COUNT(K21:M21)<3,"",K21+L21-M21) -> 111679000000 | O21: =N20 -> 122437000000 | P21: =IF(N21="","",IF(OR(O21="",O21<=0,N21<=0),N21,(N21+O21)/2)) -> 117058000000 | Q21: 기초·기말 평균 | R21: =IF(OR(P21="",P21<=0),"",J21/P21) -> 0.83272255 | S21: =IF(R21="","",R21-0.1) -> 0.73272255 | T21: =IF(OR(P21="",E21=0,E21=""),"",P21/E21) -> 0.3054072 | U21: — | V21: — | W21: OK | X21: Apple Inc.
A22: 애플 | B22: AAPL | C22: 2024 | D22: 2024-09-28 | E22: 391035000000 | F22: 123216000000 | G22: reported | H22: HIGH | I22: 0.24091185 | J22: =IF(F22="","",F22*(1-I22)) -> 9.3531805e+10 | K22: 56950000000 | L22: 106629000000 | M22: 65171000000 | N22: =IF(COUNT(K22:M22)<3,"",K22+L22-M22) -> 98408000000 | O22: =N21 -> 111679000000 | P22: =IF(N22="","",IF(OR(O22="",O22<=0,N22<=0),N22,(N22+O22)/2)) -> 105043500000 | Q22: 기초·기말 평균 | R22: =IF(OR(P22="",P22<=0),"",J22/P22) -> 0.89041021 | S22: =IF(R22="","",R22-0.1) -> 0.79041021 | T22: =IF(OR(P22="",E22=0,E22=""),"",P22/E22) -> 0.26862941 | U22: — | V22: — | W22: OK | X22: Apple Inc.
A23: 애플 | B23: AAPL | C23: 2025 | D23: 2025-09-27 | E23: 416161000000 | F23: 133050000000 | G23: reported | H23: HIGH | I23: 0.15610002 | J23: =IF(F23="","",F23*(1-I23)) -> 1.1228089e+11 | K23: 73733000000 | L23: 98657000000 | M23: 54697000000 | N23: =IF(COUNT(K23:M23)<3,"",K23+L23-M23) -> 117693000000 | O23: =N22 -> 98408000000 | P23: =IF(N23="","",IF(OR(O23="",O23<=0,N23<=0),N23,(N23+O23)/2)) -> 108050500000 | Q23: 기초·기말 평균 | R23: =IF(OR(P23="",P23<=0),"",J23/P23) -> 1.039152 | S23: =IF(R23="","",R23-0.1) -> 0.93915199 | T23: =IF(OR(P23="",E23=0,E23=""),"",P23/E23) -> 0.25963629 | U23: — | V23: — | W23: OK | X23: Apple Inc.
A24: 알파벳 | B24: GOOG | C24: 2015 | D24: 2015-12-31 | E24: 74989000000 | F24: 19360000000 | G24: reported | H24: HIGH | I24: 0.16808305 | J24: =IF(F24="","",F24*(1-I24)) -> 1.6105912e+10 | K24: 120331000000 | L24: 5220000000 | M24: 73066000000 | N24: =IF(COUNT(K24:M24)<3,"",K24+L24-M24) -> 52485000000 | O24: — | P24: — | Q24: — | R24: — | S24: — | T24: — | U24: — | V24: — | W24: 다음 해 평균 투하자본의 기초값으로만 사용 (보고 기간 밖 — 자체 비율은 계산하지 않음) | X24: Alphabet Inc.
A25: 알파벳 | B25: GOOG | C25: 2016 | D25: 2016-12-31 | E25: 90272000000 | F25: 23716000000 | G25: reported | H25: HIGH | I25: 0.19345756 | J25: =IF(F25="","",F25*(1-I25)) -> 1.9127961e+10 | K25: 139036000000 | L25: 3935000000 | M25: 86333000000 | N25: =IF(COUNT(K25:M25)<3,"",K25+L25-M25) -> 56638000000 | O25: =N24 -> 52485000000 | P25: =IF(N25="","",IF(OR(O25="",O25<=0,N25<=0),N25,(N25+O25)/2)) -> 54561500000 | Q25: 기초·기말 평균 | R25: =IF(OR(P25="",P25<=0),"",J25/P25) -> 0.35057615 | S25: =IF(R25="","",R25-0.1) -> 0.25057615 | T25: =IF(OR(P25="",E25=0,E25=""),"",P25/E25) -> 0.60441222 | U25: — | V25: — | W25: OK | X25: Alphabet Inc.
A26: 알파벳 | B26: GOOG | C26: 2017 | D26: 2017-12-31 | E26: 110855000000 | F26: 26178000000 | G26: reported | H26: HIGH | I26: 0.4 | J26: =IF(F26="","",F26*(1-I26)) -> 15706800000 | K26: 152502000000 | L26: 3943000000 | M26: 101871000000 | N26: =IF(COUNT(K26:M26)<3,"",K26+L26-M26) -> 54574000000 | O26: =N25 -> 56638000000 | P26: =IF(N26="","",IF(OR(O26="",O26<=0,N26<=0),N26,(N26+O26)/2)) -> 55606000000 | Q26: 기초·기말 평균 | R26: =IF(OR(P26="",P26<=0),"",J26/P26) -> 0.28246592 | S26: =IF(R26="","",R26-0.1) -> 0.18246592 | T26: =IF(OR(P26="",E26=0,E26=""),"",P26/E26) -> 0.50161021 | U26: — | V26: — | W26: OK | X26: Alphabet Inc.
A27: 알파벳 | B27: GOOG | C27: 2018 | D27: 2018-12-31 | E27: 136819000000 | F27: 27524000000 | G27: reported | H27: HIGH | I27: 0.11964025 | J27: =IF(F27="","",F27*(1-I27)) -> 2.4231022e+10 | K27: 177628000000 | L27: 3950000000 | M27: 109140000000 | N27: =IF(COUNT(K27:M27)<3,"",K27+L27-M27) -> 72438000000 | O27: =N26 -> 54574000000 | P27: =IF(N27="","",IF(OR(O27="",O27<=0,N27<=0),N27,(N27+O27)/2)) -> 63506000000 | Q27: 기초·기말 평균 | R27: =IF(OR(P27="",P27<=0),"",J27/P27) -> 0.38155484 | S27: =IF(R27="","",R27-0.1) -> 0.28155484 | T27: =IF(OR(P27="",E27=0,E27=""),"",P27/E27) -> 0.46416068 | U27: — | V27: — | W27: OK | X27: Alphabet Inc.
A28: 알파벳 | B28: GOOG | C28: 2019 | D28: 2019-12-31 | E28: 161857000000 | F28: 34231000000 | G28: reported | H28: HIGH | I28: 0.13329968 | J28: =IF(F28="","",F28*(1-I28)) -> 2.9668018e+10 | K28: 201442000000 | L28: 3958000000 | M28: 119675000000 | N28: =IF(COUNT(K28:M28)<3,"",K28+L28-M28) -> 85725000000 | O28: =N27 -> 72438000000 | P28: =IF(N28="","",IF(OR(O28="",O28<=0,N28<=0),N28,(N28+O28)/2)) -> 79081500000 | Q28: 기초·기말 평균 | R28: =IF(OR(P28="",P28<=0),"",J28/P28) -> 0.37515751 | S28: =IF(R28="","",R28-0.1) -> 0.27515751 | T28: =IF(OR(P28="",E28=0,E28=""),"",P28/E28) -> 0.48858869 | U28: — | V28: — | W28: OK | X28: Alphabet Inc.
A29: 알파벳 | B29: GOOG | C29: 2020 | D29: 2020-12-31 | E29: 182527000000 | F29: 41224000000 | G29: reported | H29: HIGH | I29: 0.16249324 | J29: =IF(F29="","",F29*(1-I29)) -> 3.4525379e+10 | K29: 222544000000 | L29: 14931000000 | M29: 136694000000 | N29: =IF(COUNT(K29:M29)<3,"",K29+L29-M29) -> 100781000000 | O29: =N28 -> 85725000000 | P29: =IF(N29="","",IF(OR(O29="",O29<=0,N29<=0),N29,(N29+O29)/2)) -> 93253000000 | Q29: 기초·기말 평균 | R29: =IF(OR(P29="",P29<=0),"",J29/P29) -> 0.37023344 | S29: =IF(R29="","",R29-0.1) -> 0.27023344 | T29: =IF(OR(P29="",E29=0,E29=""),"",P29/E29) -> 0.51089976 | U29: — | V29: — | W29: OK | X29: Alphabet Inc.
A30: 알파벳 | B30: GOOG | C30: 2021 | D30: 2021-12-31 | E30: 257637000000 | F30: 78714000000 | G30: reported | H30: HIGH | I30: 0.16202306 | J30: =IF(F30="","",F30*(1-I30)) -> 6.5960517e+10 | K30: 251635000000 | L30: 14817000000 | M30: 139649000000 | N30: =IF(COUNT(K30:M30)<3,"",K30+L30-M30) -> 126803000000 | O30: =N29 -> 100781000000 | P30: =IF(N30="","",IF(OR(O30="",O30<=0,N30<=0),N30,(N30+O30)/2)) -> 113792000000 | Q30: 기초·기말 평균 | R30: =IF(OR(P30="",P30<=0),"",J30/P30) -> 0.57965865 | S30: =IF(R30="","",R30-0.1) -> 0.47965865 | T30: =IF(OR(P30="",E30=0,E30=""),"",P30/E30) -> 0.44167569 | U30: — | V30: — | W30: OK | X30: Alphabet Inc.
A31: 알파벳 | B31: GOOG | C31: 2022 | D31: 2022-12-31 | E31: 282836000000 | F31: 74842000000 | G31: reported | H31: HIGH | I31: 0.15920817 | J31: =IF(F31="","",F31*(1-I31)) -> 6.2926543e+10 | K31: 256144000000 | L31: 14701000000 | M31: 113762000000 | N31: =IF(COUNT(K31:M31)<3,"",K31+L31-M31) -> 157083000000 | O31: =N30 -> 126803000000 | P31: =IF(N31="","",IF(OR(O31="",O31<=0,N31<=0),N31,(N31+O31)/2)) -> 141943000000 | Q31: 기초·기말 평균 | R31: =IF(OR(P31="",P31<=0),"",J31/P31) -> 0.44332262 | S31: =IF(R31="","",R31-0.1) -> 0.34332262 | T31: =IF(OR(P31="",E31=0,E31=""),"",P31/E31) -> 0.5018562 | U31: — | V31: — | W31: OK | X31: Alphabet Inc.
A32: 알파벳 | B32: GOOG | C32: 2023 | D32: 2023-12-31 | E32: 307394000000 | F32: 84293000000 | G32: reported | H32: HIGH | I32: 0.1390856 | J32: =IF(F32="","",F32*(1-I32)) -> 7.2569058e+10 | K32: 283379000000 | L32: 12870000000 | M32: 110916000000 | N32: =IF(COUNT(K32:M32)<3,"",K32+L32-M32) -> 185333000000 | O32: =N31 -> 157083000000 | P32: =IF(N32="","",IF(OR(O32="",O32<=0,N32<=0),N32,(N32+O32)/2)) -> 171208000000 | Q32: 기초·기말 평균 | R32: =IF(OR(P32="",P32<=0),"",J32/P32) -> 0.42386488 | S32: =IF(R32="","",R32-0.1) -> 0.32386488 | T32: =IF(OR(P32="",E32=0,E32=""),"",P32/E32) -> 0.55696598 | U32: — | V32: — | W32: OK | X32: Alphabet Inc.
A33: 알파벳 | B33: GOOG | C33: 2024 | D33: 2024-12-31 | E33: 350018000000 | F33: 112390000000 | G33: reported | H33: HIGH | I33: 0.16439511 | J33: =IF(F33="","",F33*(1-I33)) -> 9.3913634e+10 | K33: 325084000000 | L33: 14182000000 | M33: 95657000000 | N33: =IF(COUNT(K33:M33)<3,"",K33+L33-M33) -> 243609000000 | O33: =N32 -> 185333000000 | P33: =IF(N33="","",IF(OR(O33="",O33<=0,N33<=0),N33,(N33+O33)/2)) -> 214471000000 | Q33: 기초·기말 평균 | R33: =IF(OR(P33="",P33<=0),"",J33/P33) -> 0.437885 | S33: =IF(R33="","",R33-0.1) -> 0.337885 | T33: =IF(OR(P33="",E33=0,E33=""),"",P33/E33) -> 0.61274277 | U33: — | V33: — | W33: OK | X33: Alphabet Inc.
A34: 알파벳 | B34: GOOG | C34: 2025 | D34: 2025-12-31 | E34: 402836000000 | F34: 129039000000 | G34: reported | H34: HIGH | I34: 0.16783146 | J34: =IF(F34="","",F34*(1-I34)) -> 1.073822e+11 | K34: 415265000000 | L34: 48543000000 | M34: 126843000000 | N34: =IF(COUNT(K34:M34)<3,"",K34+L34-M34) -> 336965000000 | O34: =N33 -> 243609000000 | P34: =IF(N34="","",IF(OR(O34="",O34<=0,N34<=0),N34,(N34+O34)/2)) -> 290287000000 | Q34: 기초·기말 평균 | R34: =IF(OR(P34="",P34<=0),"",J34/P34) -> 0.36991734 | S34: =IF(R34="","",R34-0.1) -> 0.26991734 | T34: =IF(OR(P34="",E34=0,E34=""),"",P34/E34) -> 0.72060839 | U34: — | V34: — | W34: OK | X34: Alphabet Inc.
A35: 마이크로소프트 | B35: MSFT | C35: 2015 | D35: 2015-06-30 | E35: 93580000000 | F35: 18161000000 | G35: reported | H35: HIGH | I35: 0.34116821 | J35: =IF(F35="","",F35*(1-I35)) -> 1.1965044e+10 | K35: 80083000000 | L35: 35292000000 | M35: 96526000000 | N35: =IF(COUNT(K35:M35)<3,"",K35+L35-M35) -> 18849000000 | O35: — | P35: — | Q35: — | R35: — | S35: — | T35: — | U35: — | V35: — | W35: 다음 해 평균 투하자본의 기초값으로만 사용 (보고 기간 밖 — 자체 비율은 계산하지 않음) | X35: MICROSOFT CORP
A36: 마이크로소프트 | B36: MSFT | C36: 2016 | D36: 2016-06-30 | E36: 91154000000 | F36: 26078000000 | G36: reported | H36: HIGH | I36: 0.19891571 | J36: =IF(F36="","",F36*(1-I36)) -> 2.0890676e+10 | K36: 83090000000 | L36: 53461000000 | M36: 113240000000 | N36: =IF(COUNT(K36:M36)<3,"",K36+L36-M36) -> 23311000000 | O36: — | P36: — | Q36: — | R36: — | S36: — | T36: — | U36: — | V36: — | W36: 다음 해 평균 투하자본의 기초값으로만 사용 (보고 기간 밖 — 자체 비율은 계산하지 않음) | X36: MICROSOFT CORP
A37: 마이크로소프트 | B37: MSFT | C37: 2017 | D37: 2017-06-30 | E37: 96571000000 | F37: 29025000000 | G37: reported | H37: HIGH | I37: 0.14755359 | J37: =IF(F37="","",F37*(1-I37)) -> 2.4742257e+10 | K37: 87711000000 | L37: 86194000000 | M37: 132981000000 | N37: =IF(COUNT(K37:M37)<3,"",K37+L37-M37) -> 40924000000 | O37: =N36 -> 23311000000 | P37: =IF(N37="","",IF(OR(O37="",O37<=0,N37<=0),N37,(N37+O37)/2)) -> 32117500000 | Q37: 기초·기말 평균 | R37: =IF(OR(P37="",P37<=0),"",J37/P37) -> 0.77036684 | S37: =IF(R37="","",R37-0.1) -> 0.67036684 | T37: =IF(OR(P37="",E37=0,E37=""),"",P37/E37) -> 0.33257914 | U37: — | V37: — | W37: OK | X37: MICROSOFT CORP
A38: 마이크로소프트 | B38: MSFT | C38: 2018 | D38: 2018-06-30 | E38: 110360000000 | F38: 35058000000 | G38: reported | H38: HIGH | I38: 0.4 | J38: =IF(F38="","",F38*(1-I38)) -> 21034800000 | K38: 82718000000 | L38: 76240000000 | M38: 133768000000 | N38: =IF(COUNT(K38:M38)<3,"",K38+L38-M38) -> 25190000000 | O38: =N37 -> 40924000000 | P38: =IF(N38="","",IF(OR(O38="",O38<=0,N38<=0),N38,(N38+O38)/2)) -> 33057000000 | Q38: 기초·기말 평균 | R38: =IF(OR(P38="",P38<=0),"",J38/P38) -> 0.63631909 | S38: =IF(R38="","",R38-0.1) -> 0.53631909 | T38: =IF(OR(P38="",E38=0,E38=""),"",P38/E38) -> 0.29953788 | U38: — | V38: — | W38: OK | X38: MICROSOFT CORP
A39: 마이크로소프트 | B39: MSFT | C39: 2019 | D39: 2019-06-30 | E39: 125843000000 | F39: 42959000000 | G39: reported | H39: HIGH | I39: 0.10181285 | J39: =IF(F39="","",F39*(1-I39)) -> 3.8585222e+10 | K39: 102330000000 | L39: 72178000000 | M39: 133819000000 | N39: =IF(COUNT(K39:M39)<3,"",K39+L39-M39) -> 40689000000 | O39: =N38 -> 25190000000 | P39: =IF(N39="","",IF(OR(O39="",O39<=0,N39<=0),N39,(N39+O39)/2)) -> 32939500000 | Q39: 기초·기말 평균 | R39: =IF(OR(P39="",P39<=0),"",J39/P39) -> 1.1713967 | S39: =IF(R39="","",R39-0.1) -> 1.0713967 | T39: =IF(OR(P39="",E39=0,E39=""),"",P39/E39) -> 0.26175075 | U39: — | V39: — | W39: OK | X39: MICROSOFT CORP
A40: 마이크로소프트 | B40: MSFT | C40: 2020 | D40: 2020-06-30 | E40: 143015000000 | F40: 52959000000 | G40: reported | H40: HIGH | I40: 0.16507655 | J40: =IF(F40="","",F40*(1-I40)) -> 4.4216711e+10 | K40: 118304000000 | L40: 63327000000 | M40: 136527000000 | N40: =IF(COUNT(K40:M40)<3,"",K40+L40-M40) -> 45104000000 | O40: =N39 -> 40689000000 | P40: =IF(N40="","",IF(OR(O40="",O40<=0,N40<=0),N40,(N40+O40)/2)) -> 42896500000 | Q40: 기초·기말 평균 | R40: =IF(OR(P40="",P40<=0),"",J40/P40) -> 1.0307767 | S40: =IF(R40="","",R40-0.1) -> 0.93077666 | T40: =IF(OR(P40="",E40=0,E40=""),"",P40/E40) -> 0.29994406 | U40: — | V40: — | W40: OK | X40: MICROSOFT CORP
A41: 마이크로소프트 | B41: MSFT | C41: 2021 | D41: 2021-06-30 | E41: 168088000000 | F41: 69916000000 | G41: reported | H41: HIGH | I41: 0.13826615 | J41: =IF(F41="","",F41*(1-I41)) -> 6.0248984e+10 | K41: 141988000000 | L41: 58146000000 | M41: 130334000000 | N41: =IF(COUNT(K41:M41)<3,"",K41+L41-M41) -> 69800000000 | O41: =N40 -> 45104000000 | P41: =IF(N41="","",IF(OR(O41="",O41<=0,N41<=0),N41,(N41+O41)/2)) -> 57452000000 | Q41: 기초·기말 평균 | R41: =IF(OR(P41="",P41<=0),"",J41/P41) -> 1.0486838 | S41: =IF(R41="","",R41-0.1) -> 0.94868383 | T41: =IF(OR(P41="",E41=0,E41=""),"",P41/E41) -> 0.34179715 | U41: — | V41: — | W41: OK | X41: MICROSOFT CORP
A42: 마이크로소프트 | B42: MSFT | C42: 2022 | D42: 2022-06-30 | E42: 198270000000 | F42: 83383000000 | G42: reported | H42: HIGH | I42: 0.13113383 | J42: =IF(F42="","",F42*(1-I42)) -> 7.2448668e+10 | K42: 166542000000 | L42: 49781000000 | M42: 104757000000 | N42: =IF(COUNT(K42:M42)<3,"",K42+L42-M42) -> 111566000000 | O42: =N41 -> 69800000000 | P42: =IF(N42="","",IF(OR(O42="",O42<=0,N42<=0),N42,(N42+O42)/2)) -> 90683000000 | Q42: 기초·기말 평균 | R42: =IF(OR(P42="",P42<=0),"",J42/P42) -> 0.79892226 | S42: =IF(R42="","",R42-0.1) -> 0.69892226 | T42: =IF(OR(P42="",E42=0,E42=""),"",P42/E42) -> 0.45737126 | U42: — | V42: — | W42: OK | X42: MICROSOFT CORP
A43: 마이크로소프트 | B43: MSFT | C43: 2023 | D43: 2023-06-30 | E43: 211915000000 | F43: 88523000000 | G43: reported | H43: HIGH | I43: 0.18978625 | J43: =IF(F43="","",F43*(1-I43)) -> 7.1722552e+10 | K43: 206223000000 | L43: 47237000000 | M43: 111262000000 | N43: =IF(COUNT(K43:M43)<3,"",K43+L43-M43) -> 142198000000 | O43: =N42 -> 111566000000 | P43: =IF(N43="","",IF(OR(O43="",O43<=0,N43<=0),N43,(N43+O43)/2)) -> 126882000000 | Q43: 기초·기말 평균 | R43: =IF(OR(P43="",P43<=0),"",J43/P43) -> 0.56526971 | S43: =IF(R43="","",R43-0.1) -> 0.46526971 | T43: =IF(OR(P43="",E43=0,E43=""),"",P43/E43) -> 0.59874006 | U43: — | V43: — | W43: OK | X43: MICROSOFT CORP
A44: 마이크로소프트 | B44: MSFT | C44: 2024 | D44: 2024-06-30 | E44: 245122000000 | F44: 109433000000 | G44: reported | H44: HIGH | I44: 0.18231327 | J44: =IF(F44="","",F44*(1-I44)) -> 8.9481912e+10 | K44: 268477000000 | L44: 51630000000 | M44: 75543000000 | N44: =IF(COUNT(K44:M44)<3,"",K44+L44-M44) -> 244564000000 | O44: =N43 -> 142198000000 | P44: =IF(N44="","",IF(OR(O44="",O44<=0,N44<=0),N44,(N44+O44)/2)) -> 193381000000 | Q44: 기초·기말 평균 | R44: =IF(OR(P44="",P44<=0),"",J44/P44) -> 0.46272339 | S44: =IF(R44="","",R44-0.1) -> 0.36272339 | T44: =IF(OR(P44="",E44=0,E44=""),"",P44/E44) -> 0.78891736 | U44: — | V44: — | W44: OK | X44: MICROSOFT CORP
A45: 마이크로소프트 | B45: MSFT | C45: 2025 | D45: 2025-06-30 | E45: 281724000000 | F45: 128528000000 | G45: reported | H45: HIGH | I45: 0.17629644 | J45: =IF(F45="","",F45*(1-I45)) -> 1.0586897e+11 | K45: 343479000000 | L45: 43151000000 | M45: 94565000000 | N45: =IF(COUNT(K45:M45)<3,"",K45+L45-M45) -> 292065000000 | O45: =N44 -> 244564000000 | P45: =IF(N45="","",IF(OR(O45="",O45<=0,N45<=0),N45,(N45+O45)/2)) -> 268314500000 | Q45: 기초·기말 평균 | R45: =IF(OR(P45="",P45<=0),"",J45/P45) -> 0.39457044 | S45: =IF(R45="","",R45-0.1) -> 0.29457044 | T45: =IF(OR(P45="",E45=0,E45=""),"",P45/E45) -> 0.952402 | U45: — | V45: — | W45: OK | X45: MICROSOFT CORP
A46: 마이크로소프트 | B46: MSFT | C46: 2026 | D46: 2026-06-30 | E46: 331839000000 | F46: 155237000000 | G46: reported | H46: HIGH | I46: 0.19396266 | J46: =IF(F46="","",F46*(1-I46)) -> 1.2512682e+11 | K46: 442387000000 | L46: 40294000000 | M46: 76843000000 | N46: =IF(COUNT(K46:M46)<3,"",K46+L46-M46) -> 405838000000 | O46: =N45 -> 292065000000 | P46: =IF(N46="","",IF(OR(O46="",O46<=0,N46<=0),N46,(N46+O46)/2)) -> 348951500000 | Q46: 기초·기말 평균 | R46: =IF(OR(P46="",P46<=0),"",J46/P46) -> 0.3585794 | S46: =IF(R46="","",R46-0.1) -> 0.2585794 | T46: =IF(OR(P46="",E46=0,E46=""),"",P46/E46) -> 1.0515687 | U46: — | V46: — | W46: OK | X46: MICROSOFT CORP
A47: 아마존 | B47: AMZN | C47: 2015 | D47: 2015-12-31 | E47: 107006000000 | F47: 2233000000 | G47: reported | H47: HIGH | I47: 0.4 | J47: =IF(F47="","",F47*(1-I47)) -> 1339800000 | K47: 13384000000 | L47: 8465000000 | M47: 19808000000 | N47: =IF(COUNT(K47:M47)<3,"",K47+L47-M47) -> 2041000000 | O47: — | P47: — | Q47: — | R47: — | S47: — | T47: — | U47: — | V47: — | W47: 다음 해 평균 투하자본의 기초값으로만 사용 (보고 기간 밖 — 자체 비율은 계산하지 않음) | X47: AMAZON COM INC
A48: 아마존 | B48: AMZN | C48: 2016 | D48: 2016-12-31 | E48: 135987000000 | F48: 4186000000 | G48: reported | H48: HIGH | I48: 0.36613566 | J48: =IF(F48="","",F48*(1-I48)) -> 2.6533561e+09 | K48: 19285000000 | L48: 8750000000 | M48: 25981000000 | N48: =IF(COUNT(K48:M48)<3,"",K48+L48-M48) -> 2054000000 | O48: =N47 -> 2041000000 | P48: =IF(N48="","",IF(OR(O48="",O48<=0,N48<=0),N48,(N48+O48)/2)) -> 2047500000 | Q48: 기초·기말 평균 | R48: =IF(OR(P48="",P48<=0),"",J48/P48) -> 1.2959004 | S48: =IF(R48="","",R48-0.1) -> 1.1959004 | T48: =IF(OR(P48="",E48=0,E48=""),"",P48/E48) -> 0.015056586 | U48: — | V48: — | W48: 투하자본이 매출의 1.5% — 분모가 작아 비율이 민감 (판정은 유효) | X48: AMAZON COM INC
A49: 아마존 | B49: AMZN | C49: 2017 | D49: 2017-12-31 | E49: 177866000000 | F49: 4106000000 | G49: reported | H49: HIGH | I49: 0.2020494 | J49: =IF(F49="","",F49*(1-I49)) -> 3.2763852e+09 | K49: 27709000000 | L49: 24843000000 | M49: 30986000000 | N49: =IF(COUNT(K49:M49)<3,"",K49+L49-M49) -> 21566000000 | O49: =N48 -> 2054000000 | P49: =IF(N49="","",IF(OR(O49="",O49<=0,N49<=0),N49,(N49+O49)/2)) -> 11810000000 | Q49: 기초·기말 평균 | R49: =IF(OR(P49="",P49<=0),"",J49/P49) -> 0.27742466 | S49: =IF(R49="","",R49-0.1) -> 0.17742466 | T49: =IF(OR(P49="",E49=0,E49=""),"",P49/E49) -> 0.0663983 | U49: — | V49: — | W49: 투하자본이 매출의 6.6% — 분모가 작아 비율이 민감 (판정은 유효) | X49: AMAZON COM INC
A50: 아마존 | B50: AMZN | C50: 2018 | D50: 2018-12-31 | E50: 232887000000 | F50: 12421000000 | G50: reported | H50: HIGH | I50: 0.10629607 | J50: =IF(F50="","",F50*(1-I50)) -> 1.1100697e+10 | K50: 43549000000 | L50: 24866000000 | M50: 41250000000 | N50: =IF(COUNT(K50:M50)<3,"",K50+L50-M50) -> 27165000000 | O50: =N49 -> 21566000000 | P50: =IF(N50="","",IF(OR(O50="",O50<=0,N50<=0),N50,(N50+O50)/2)) -> 24365500000 | Q50: 기초·기말 평균 | R50: =IF(OR(P50="",P50<=0),"",J50/P50) -> 0.45559076 | S50: =IF(R50="","",R50-0.1) -> 0.35559076 | T50: =IF(OR(P50="",E50=0,E50=""),"",P50/E50) -> 0.1046237 | U50: — | V50: — | W50: OK | X50: AMAZON COM INC
A51: 아마존 | B51: AMZN | C51: 2019 | D51: 2019-12-31 | E51: 280522000000 | F51: 14541000000 | G51: reported | H51: HIGH | I51: 0.16986262 | J51: =IF(F51="","",F51*(1-I51)) -> 1.2071028e+10 | K51: 62060000000 | L51: 24719000000 | M51: 55021000000 | N51: =IF(COUNT(K51:M51)<3,"",K51+L51-M51) -> 31758000000 | O51: =N50 -> 27165000000 | P51: =IF(N51="","",IF(OR(O51="",O51<=0,N51<=0),N51,(N51+O51)/2)) -> 29461500000 | Q51: 기초·기말 평균 | R51: =IF(OR(P51="",P51<=0),"",J51/P51) -> 0.4097221 | S51: =IF(R51="","",R51-0.1) -> 0.3097221 | T51: =IF(OR(P51="",E51=0,E51=""),"",P51/E51) -> 0.10502385 | U51: — | V51: — | W51: OK | X51: AMAZON COM INC
A52: 아마존 | B52: AMZN | C52: 2020 | D52: 2020-12-31 | E52: 386064000000 | F52: 22899000000 | G52: reported | H52: HIGH | I52: 0.11841343 | J52: =IF(F52="","",F52*(1-I52)) -> 2.0187451e+10 | K52: 93404000000 | L52: 32971000000 | M52: 84396000000 | N52: =IF(COUNT(K52:M52)<3,"",K52+L52-M52) -> 41979000000 | O52: =N51 -> 31758000000 | P52: =IF(N52="","",IF(OR(O52="",O52<=0,N52<=0),N52,(N52+O52)/2)) -> 36868500000 | Q52: 기초·기말 평균 | R52: =IF(OR(P52="",P52<=0),"",J52/P52) -> 0.54755281 | S52: =IF(R52="","",R52-0.1) -> 0.44755281 | T52: =IF(OR(P52="",E52=0,E52=""),"",P52/E52) -> 0.095498415 | U52: — | V52: — | W52: 투하자본이 매출의 9.5% — 분모가 작아 비율이 민감 (판정은 유효) | X52: AMAZON COM INC
A53: 아마존 | B53: AMZN | C53: 2021 | D53: 2021-12-31 | E53: 469822000000 | F53: 24879000000 | G53: reported | H53: HIGH | I53: 0.12557993 | J53: =IF(F53="","",F53*(1-I53)) -> 2.1754697e+10 | K53: 138245000000 | L53: 50553000000 | M53: 96049000000 | N53: =IF(COUNT(K53:M53)<3,"",K53+L53-M53) -> 92749000000 | O53: =N52 -> 41979000000 | P53: =IF(N53="","",IF(OR(O53="",O53<=0,N53<=0),N53,(N53+O53)/2)) -> 67364000000 | Q53: 기초·기말 평균 | R53: =IF(OR(P53="",P53<=0),"",J53/P53) -> 0.32294247 | S53: =IF(R53="","",R53-0.1) -> 0.22294247 | T53: =IF(OR(P53="",E53=0,E53=""),"",P53/E53) -> 0.14338196 | U53: — | V53: — | W53: OK | X53: AMAZON COM INC
A54: 아마존 | B54: AMZN | C54: 2022 | D54: 2022-12-31 | E54: 513983000000 | F54: 12248000000 | G54: reported | H54: HIGH | I54: 0.21 | J54: =IF(F54="","",F54*(1-I54)) -> 9675920000 | K54: 146043000000 | L54: 71349000000 | M54: 70026000000 | N54: =IF(COUNT(K54:M54)<3,"",K54+L54-M54) -> 147366000000 | O54: =N53 -> 92749000000 | P54: =IF(N54="","",IF(OR(O54="",O54<=0,N54<=0),N54,(N54+O54)/2)) -> 120057500000 | Q54: 기초·기말 평균 | R54: =IF(OR(P54="",P54<=0),"",J54/P54) -> 0.080594049 | S54: =IF(R54="","",R54-0.1) -> -0.019405951 | T54: =IF(OR(P54="",E54=0,E54=""),"",P54/E54) -> 0.23358263 | U54: — | V54: — | W54: OK | X54: AMAZON COM INC
A55: 아마존 | B55: AMZN | C55: 2023 | D55: 2023-12-31 | E55: 574785000000 | F55: 36852000000 | G55: reported | H55: HIGH | I55: 0.18957851 | J55: =IF(F55="","",F55*(1-I55)) -> 2.9865653e+10 | K55: 201875000000 | L55: 66955000000 | M55: 86780000000 | N55: =IF(COUNT(K55:M55)<3,"",K55+L55-M55) -> 182050000000 | O55: =N54 -> 147366000000 | P55: =IF(N55="","",IF(OR(O55="",O55<=0,N55<=0),N55,(N55+O55)/2)) -> 164708000000 | Q55: 기초·기말 평균 | R55: =IF(OR(P55="",P55<=0),"",J55/P55) -> 0.18132485 | S55: =IF(R55="","",R55-0.1) -> 0.081324847 | T55: =IF(OR(P55="",E55=0,E55=""),"",P55/E55) -> 0.28655584 | U55: — | V55: — | W55: OK | X55: AMAZON COM INC
A56: 아마존 | B56: AMZN | C56: 2024 | D56: 2024-12-31 | E56: 637959000000 | F56: 68593000000 | G56: reported | H56: HIGH | I56: 0.13503075 | J56: =IF(F56="","",F56*(1-I56)) -> 5.9330836e+10 | K56: 285970000000 | L56: 57791000000 | M56: 101202000000 | N56: =IF(COUNT(K56:M56)<3,"",K56+L56-M56) -> 242559000000 | O56: =N55 -> 182050000000 | P56: =IF(N56="","",IF(OR(O56="",O56<=0,N56<=0),N56,(N56+O56)/2)) -> 212304500000 | Q56: 기초·기말 평균 | R56: =IF(OR(P56="",P56<=0),"",J56/P56) -> 0.27946104 | S56: =IF(R56="","",R56-0.1) -> 0.17946104 | T56: =IF(OR(P56="",E56=0,E56=""),"",P56/E56) -> 0.33278706 | U56: — | V56: — | W56: OK | X56: AMAZON COM INC
A57: 아마존 | B57: AMZN | C57: 2025 | D57: 2025-12-31 | E57: 716924000000 | F57: 79975000000 | G57: reported | H57: HIGH | I57: 0.19614432 | J57: =IF(F57="","",F57*(1-I57)) -> 6.4288358e+10 | K57: 411065000000 | L57: 68851000000 | M57: 123029000000 | N57: =IF(COUNT(K57:M57)<3,"",K57+L57-M57) -> 356887000000 | O57: =N56 -> 242559000000 | P57: =IF(N57="","",IF(OR(O57="",O57<=0,N57<=0),N57,(N57+O57)/2)) -> 299723000000 | Q57: 기초·기말 평균 | R57: =IF(OR(P57="",P57<=0),"",J57/P57) -> 0.21449257 | S57: =IF(R57="","",R57-0.1) -> 0.11449257 | T57: =IF(OR(P57="",E57=0,E57=""),"",P57/E57) -> 0.41806802 | U57: — | V57: — | W57: OK | X57: AMAZON COM INC
A58: 브로드컴 | B58: AVGO | C58: 2016 | D58: 2016-10-30 | E58: 13240000000 | F58: -409000000 | G58: reported | H58: HIGH | I58: 0.21 | J58: =IF(F58="","",F58*(1-I58)) -> -323110000 | K58: 21876000000 | L58: 0 | M58: 3097000000 | N58: =IF(COUNT(K58:M58)<3,"",K58+L58-M58) -> 18779000000 | O58: — | P58: =N58 -> 18779000000 | Q58: 기말 (직전연도 없음) | R58: =IF(OR(P58="",P58<=0),"",J58/P58) -> -0.017205922 | S58: =IF(R58="","",R58-0.1) -> -0.11720592 | T58: =IF(OR(P58="",E58=0,E58=""),"",P58/E58) -> 1.4183535 | U58: — | V58: — | W58: OK | X58: Broadcom Inc.
A59: 브로드컴 | B59: AVGO | C59: 2017 | D59: 2017-10-29 | E59: 17636000000 | F59: 2371000000 | G59: reported | H59: HIGH | I59: 0.05 | J59: =IF(F59="","",F59*(1-I59)) -> 2252450000 | K59: 23186000000 | L59: 17548000000 | M59: 11204000000 | N59: =IF(COUNT(K59:M59)<3,"",K59+L59-M59) -> 29530000000 | O59: =N58 -> 18779000000 | P59: =IF(N59="","",IF(OR(O59="",O59<=0,N59<=0),N59,(N59+O59)/2)) -> 24154500000 | Q59: 기초·기말 평균 | R59: =IF(OR(P59="",P59<=0),"",J59/P59) -> 0.093251775 | S59: =IF(R59="","",R59-0.1) -> -0.006748225 | T59: =IF(OR(P59="",E59=0,E59=""),"",P59/E59) -> 1.3696133 | U59: — | V59: — | W59: OK | X59: Broadcom Inc.
A60: 브로드컴 | B60: AVGO | C60: 2018 | D60: 2018-11-04 | E60: 20848000000 | F60: 5135000000 | G60: reported | H60: HIGH | I60: 0.05 | J60: =IF(F60="","",F60*(1-I60)) -> 4878250000 | K60: 26657000000 | L60: 17609000000 | M60: 4292000000 | N60: =IF(COUNT(K60:M60)<3,"",K60+L60-M60) -> 39974000000 | O60: =N59 -> 29530000000 | P60: =IF(N60="","",IF(OR(O60="",O60<=0,N60<=0),N60,(N60+O60)/2)) -> 34752000000 | Q60: 기초·기말 평균 | R60: =IF(OR(P60="",P60<=0),"",J60/P60) -> 0.14037322 | S60: =IF(R60="","",R60-0.1) -> 0.040373216 | T60: =IF(OR(P60="",E60=0,E60=""),"",P60/E60) -> 1.6669225 | U60: — | V60: — | W60: OK | X60: Broadcom Inc.
A61: 브로드컴 | B61: AVGO | C61: 2019 | D61: 2019-11-03 | E61: 22597000000 | F61: 3444000000 | G61: reported | H61: HIGH | I61: 0.05 | J61: =IF(F61="","",F61*(1-I61)) -> 3271800000 | K61: 24941000000 | L61: 33059000000 | M61: 5055000000 | N61: =IF(COUNT(K61:M61)<3,"",K61+L61-M61) -> 52945000000 | O61: =N60 -> 39974000000 | P61: =IF(N61="","",IF(OR(O61="",O61<=0,N61<=0),N61,(N61+O61)/2)) -> 46459500000 | Q61: 기초·기말 평균 | R61: =IF(OR(P61="",P61<=0),"",J61/P61) -> 0.070422626 | S61: =IF(R61="","",R61-0.1) -> -0.029577374 | T61: =IF(OR(P61="",E61=0,E61=""),"",P61/E61) -> 2.056003 | U61: — | V61: — | W61: OK | X61: Broadcom Inc.
A62: 브로드컴 | B62: AVGO | C62: 2020 | D62: 2020-11-01 | E62: 23888000000 | F62: 4014000000 | G62: reported | H62: HIGH | I62: 0.05 | J62: =IF(F62="","",F62*(1-I62)) -> 3813300000 | K62: 23874000000 | L62: 41498000000 | M62: 7618000000 | N62: =IF(COUNT(K62:M62)<3,"",K62+L62-M62) -> 57754000000 | O62: =N61 -> 52945000000 | P62: =IF(N62="","",IF(OR(O62="",O62<=0,N62<=0),N62,(N62+O62)/2)) -> 55349500000 | Q62: 기초·기말 평균 | R62: =IF(OR(P62="",P62<=0),"",J62/P62) -> 0.068894931 | S62: =IF(R62="","",R62-0.1) -> -0.031105069 | T62: =IF(OR(P62="",E62=0,E62=""),"",P62/E62) -> 2.317042 | U62: — | V62: — | W62: OK | X62: Broadcom Inc.
A63: 브로드컴 | B63: AVGO | C63: 2021 | D63: 2021-10-31 | E63: 27450000000 | F63: 8519000000 | G63: reported | H63: HIGH | I63: 0.05 | J63: =IF(F63="","",F63*(1-I63)) -> 8093050000 | K63: 24962000000 | L63: 39704000000 | M63: 12163000000 | N63: =IF(COUNT(K63:M63)<3,"",K63+L63-M63) -> 52503000000 | O63: =N62 -> 57754000000 | P63: =IF(N63="","",IF(OR(O63="",O63<=0,N63<=0),N63,(N63+O63)/2)) -> 55128500000 | Q63: 기초·기말 평균 | R63: =IF(OR(P63="",P63<=0),"",J63/P63) -> 0.14680338 | S63: =IF(R63="","",R63-0.1) -> 0.046803378 | T63: =IF(OR(P63="",E63=0,E63=""),"",P63/E63) -> 2.0083242 | U63: — | V63: — | W63: OK | X63: Broadcom Inc.
A64: 브로드컴 | B64: AVGO | C64: 2022 | D64: 2022-10-30 | E64: 33203000000 | F64: 14225000000 | G64: reported | H64: HIGH | I64: 0.075518739 | J64: =IF(F64="","",F64*(1-I64)) -> 1.3150746e+10 | K64: 22709000000 | L64: 39478000000 | M64: 12416000000 | N64: =IF(COUNT(K64:M64)<3,"",K64+L64-M64) -> 49771000000 | O64: =N63 -> 52503000000 | P64: =IF(N64="","",IF(OR(O64="",O64<=0,N64<=0),N64,(N64+O64)/2)) -> 51137000000 | Q64: 기초·기말 평균 | R64: =IF(OR(P64="",P64<=0),"",J64/P64) -> 0.25716694 | S64: =IF(R64="","",R64-0.1) -> 0.15716694 | T64: =IF(OR(P64="",E64=0,E64=""),"",P64/E64) -> 1.5401319 | U64: — | V64: — | W64: OK | X64: Broadcom Inc.
A65: 브로드컴 | B65: AVGO | C65: 2023 | D65: 2023-10-29 | E65: 35819000000 | F65: 16207000000 | G65: reported | H65: HIGH | I65: 0.0672319 | J65: =IF(F65="","",F65*(1-I65)) -> 1.5117373e+10 | K65: 23988000000 | L65: 39184000000 | M65: 14189000000 | N65: =IF(COUNT(K65:M65)<3,"",K65+L65-M65) -> 48983000000 | O65: =N64 -> 49771000000 | P65: =IF(N65="","",IF(OR(O65="",O65<=0,N65<=0),N65,(N65+O65)/2)) -> 49377000000 | Q65: 기초·기말 평균 | R65: =IF(OR(P65="",P65<=0),"",J65/P65) -> 0.30616223 | S65: =IF(R65="","",R65-0.1) -> 0.20616223 | T65: =IF(OR(P65="",E65=0,E65=""),"",P65/E65) -> 1.3785142 | U65: — | V65: — | W65: OK | X65: Broadcom Inc.
A66: 브로드컴 | B66: AVGO | C66: 2024 | D66: 2024-11-03 | E66: 51574000000 | F66: 13463000000 | G66: reported | H66: HIGH | I66: 0.37797499 | J66: =IF(F66="","",F66*(1-I66)) -> 8.3743227e+09 | K66: 67678000000 | L66: 69847000000 | M66: 9348000000 | N66: =IF(COUNT(K66:M66)<3,"",K66+L66-M66) -> 128177000000 | O66: =N65 -> 48983000000 | P66: =IF(N66="","",IF(OR(O66="",O66<=0,N66<=0),N66,(N66+O66)/2)) -> 88580000000 | Q66: 기초·기말 평균 | R66: =IF(OR(P66="",P66<=0),"",J66/P66) -> 0.094539656 | S66: =IF(R66="","",R66-0.1) -> -0.0054603442 | T66: =IF(OR(P66="",E66=0,E66=""),"",P66/E66) -> 1.7175321 | U66: — | V66: — | W66: OK | X66: Broadcom Inc.
A67: 브로드컴 | B67: AVGO | C67: 2025 | D67: 2025-11-02 | E67: 63887000000 | F67: 25484000000 | G67: reported | H67: HIGH | I67: 0.05 | J67: =IF(F67="","",F67*(1-I67)) -> 24209800000 | K67: 81292000000 | L67: 67120000000 | M67: 16178000000 | N67: =IF(COUNT(K67:M67)<3,"",K67+L67-M67) -> 132234000000 | O67: =N66 -> 128177000000 | P67: =IF(N67="","",IF(OR(O67="",O67<=0,N67<=0),N67,(N67+O67)/2)) -> 130205500000 | Q67: 기초·기말 평균 | R67: =IF(OR(P67="",P67<=0),"",J67/P67) -> 0.18593531 | S67: =IF(R67="","",R67-0.1) -> 0.08593531 | T67: =IF(OR(P67="",E67=0,E67=""),"",P67/E67) -> 2.0380594 | U67: — | V67: — | W67: OK | X67: Broadcom Inc.
A68: 메타 플랫폼스 | B68: META | C68: 2015 | D68: 2015-12-31 | E68: 17928000000 | F68: 6225000000 | G68: reported | H68: HIGH | I68: 0.4 | J68: =IF(F68="","",F68*(1-I68)) -> 3735000000 | K68: 44218000000 | L68: 201000000 | M68: 18434000000 | N68: =IF(COUNT(K68:M68)<3,"",K68+L68-M68) -> 25985000000 | O68: — | P68: — | Q68: — | R68: — | S68: — | T68: — | U68: — | V68: — | W68: 다음 해 평균 투하자본의 기초값으로만 사용 (보고 기간 밖 — 자체 비율은 계산하지 않음) | X68: Meta Platforms, Inc.
A69: 메타 플랫폼스 | B69: META | C69: 2016 | D69: 2016-12-31 | E69: 27638000000 | F69: 12427000000 | G69: reported | H69: HIGH | I69: 0.18381531 | J69: =IF(F69="","",F69*(1-I69)) -> 1.0142727e+10 | K69: 59194000000 | L69: 0 | M69: 29449000000 | N69: =IF(COUNT(K69:M69)<3,"",K69+L69-M69) -> 29745000000 | O69: =N68 -> 25985000000 | P69: =IF(N69="","",IF(OR(O69="",O69<=0,N69<=0),N69,(N69+O69)/2)) -> 27865000000 | Q69: 기초·기말 평균 | R69: =IF(OR(P69="",P69<=0),"",J69/P69) -> 0.36399523 | S69: =IF(R69="","",R69-0.1) -> 0.26399523 | T69: =IF(OR(P69="",E69=0,E69=""),"",P69/E69) -> 1.0082133 | U69: — | V69: — | W69: OK | X69: Meta Platforms, Inc.
A70: 메타 플랫폼스 | B70: META | C70: 2017 | D70: 2017-12-31 | E70: 40653000000 | F70: 20203000000 | G70: reported | H70: HIGH | I70: 0.2262795 | J70: =IF(F70="","",F70*(1-I70)) -> 1.5631475e+10 | K70: 74347000000 | L70: 0 | M70: 41711000000 | N70: =IF(COUNT(K70:M70)<3,"",K70+L70-M70) -> 32636000000 | O70: =N69 -> 29745000000 | P70: =IF(N70="","",IF(OR(O70="",O70<=0,N70<=0),N70,(N70+O70)/2)) -> 31190500000 | Q70: 기초·기말 평균 | R70: =IF(OR(P70="",P70<=0),"",J70/P70) -> 0.50116142 | S70: =IF(R70="","",R70-0.1) -> 0.40116142 | T70: =IF(OR(P70="",E70=0,E70=""),"",P70/E70) -> 0.76723735 | U70: — | V70: — | W70: OK | X70: Meta Platforms, Inc.
A71: 메타 플랫폼스 | B71: META | C71: 2018 | D71: 2018-12-31 | E71: 55838000000 | F71: 24913000000 | G71: reported | H71: HIGH | I71: 0.12811009 | J71: =IF(F71="","",F71*(1-I71)) -> 2.1721393e+10 | K71: 84127000000 | L71: 0 | M71: 41114000000 | N71: =IF(COUNT(K71:M71)<3,"",K71+L71-M71) -> 43013000000 | O71: =N70 -> 32636000000 | P71: =IF(N71="","",IF(OR(O71="",O71<=0,N71<=0),N71,(N71+O71)/2)) -> 37824500000 | Q71: 기초·기말 평균 | R71: =IF(OR(P71="",P71<=0),"",J71/P71) -> 0.57426782 | S71: =IF(R71="","",R71-0.1) -> 0.47426782 | T71: =IF(OR(P71="",E71=0,E71=""),"",P71/E71) -> 0.67739711 | U71: — | V71: — | W71: OK | X71: Meta Platforms, Inc.
A72: 메타 플랫폼스 | B72: META | C72: 2019 | D72: 2019-12-31 | E72: 70697000000 | F72: 23986000000 | G72: reported | H72: HIGH | I72: 0.25499758 | J72: =IF(F72="","",F72*(1-I72)) -> 1.7869628e+10 | K72: 101054000000 | L72: 0 | M72: 54855000000 | N72: =IF(COUNT(K72:M72)<3,"",K72+L72-M72) -> 46199000000 | O72: =N71 -> 43013000000 | P72: =IF(N72="","",IF(OR(O72="",O72<=0,N72<=0),N72,(N72+O72)/2)) -> 44606000000 | Q72: 기초·기말 평균 | R72: =IF(OR(P72="",P72<=0),"",J72/P72) -> 0.40061041 | S72: =IF(R72="","",R72-0.1) -> 0.30061041 | T72: =IF(OR(P72="",E72=0,E72=""),"",P72/E72) -> 0.63094615 | U72: — | V72: — | W72: OK | X72: Meta Platforms, Inc.
A73: 메타 플랫폼스 | B73: META | C73: 2020 | D73: 2020-12-31 | E73: 85965000000 | F73: 32671000000 | G73: reported | H73: HIGH | I73: 0.12157926 | J73: =IF(F73="","",F73*(1-I73)) -> 2.8698884e+10 | K73: 128290000000 | L73: 0 | M73: 61954000000 | N73: =IF(COUNT(K73:M73)<3,"",K73+L73-M73) -> 66336000000 | O73: =N72 -> 46199000000 | P73: =IF(N73="","",IF(OR(O73="",O73<=0,N73<=0),N73,(N73+O73)/2)) -> 56267500000 | Q73: 기초·기말 평균 | R73: =IF(OR(P73="",P73<=0),"",J73/P73) -> 0.5100437 | S73: =IF(R73="","",R73-0.1) -> 0.4100437 | T73: =IF(OR(P73="",E73=0,E73=""),"",P73/E73) -> 0.65453964 | U73: — | V73: — | W73: OK | X73: Meta Platforms, Inc.
A74: 메타 플랫폼스 | B74: META | C74: 2021 | D74: 2021-12-31 | E74: 117929000000 | F74: 46753000000 | G74: reported | H74: HIGH | I74: 0.16737163 | J74: =IF(F74="","",F74*(1-I74)) -> 3.8927874e+10 | K74: 124879000000 | L74: 0 | M74: 47998000000 | N74: =IF(COUNT(K74:M74)<3,"",K74+L74-M74) -> 76881000000 | O74: =N73 -> 66336000000 | P74: =IF(N74="","",IF(OR(O74="",O74<=0,N74<=0),N74,(N74+O74)/2)) -> 71608500000 | Q74: 기초·기말 평균 | R74: =IF(OR(P74="",P74<=0),"",J74/P74) -> 0.54362086 | S74: =IF(R74="","",R74-0.1) -> 0.44362086 | T74: =IF(OR(P74="",E74=0,E74=""),"",P74/E74) -> 0.60721705 | U74: — | V74: — | W74: OK | X74: Meta Platforms, Inc.
A75: 메타 플랫폼스 | B75: META | C75: 2022 | D75: 2022-12-31 | E75: 116609000000 | F75: 28944000000 | G75: reported | H75: HIGH | I75: 0.19497554 | J75: =IF(F75="","",F75*(1-I75)) -> 2.3300628e+10 | K75: 125713000000 | L75: 9923000000 | M75: 40738000000 | N75: =IF(COUNT(K75:M75)<3,"",K75+L75-M75) -> 94898000000 | O75: =N74 -> 76881000000 | P75: =IF(N75="","",IF(OR(O75="",O75<=0,N75<=0),N75,(N75+O75)/2)) -> 85889500000 | Q75: 기초·기말 평균 | R75: =IF(OR(P75="",P75<=0),"",J75/P75) -> 0.27128611 | S75: =IF(R75="","",R75-0.1) -> 0.17128611 | T75: =IF(OR(P75="",E75=0,E75=""),"",P75/E75) -> 0.73655979 | U75: — | V75: — | W75: OK | X75: Meta Platforms, Inc.
A76: 메타 플랫폼스 | B76: META | C76: 2023 | D76: 2023-12-31 | E76: 134902000000 | F76: 46751000000 | G76: reported | H76: HIGH | I76: 0.17563465 | J76: =IF(F76="","",F76*(1-I76)) -> 3.8539905e+10 | K76: 153168000000 | L76: 18385000000 | M76: 65403000000 | N76: =IF(COUNT(K76:M76)<3,"",K76+L76-M76) -> 106150000000 | O76: =N75 -> 94898000000 | P76: =IF(N76="","",IF(OR(O76="",O76<=0,N76<=0),N76,(N76+O76)/2)) -> 100524000000 | Q76: 기초·기말 평균 | R76: =IF(OR(P76="",P76<=0),"",J76/P76) -> 0.38339008 | S76: =IF(R76="","",R76-0.1) -> 0.28339008 | T76: =IF(OR(P76="",E76=0,E76=""),"",P76/E76) -> 0.74516316 | U76: — | V76: — | W76: OK | X76: Meta Platforms, Inc.
A77: 메타 플랫폼스 | B77: META | C77: 2024 | D77: 2024-12-31 | E77: 164501000000 | F77: 69380000000 | G77: reported | H77: HIGH | I77: 0.11750138 | J77: =IF(F77="","",F77*(1-I77)) -> 6.1227754e+10 | K77: 182637000000 | L77: 28826000000 | M77: 77815000000 | N77: =IF(COUNT(K77:M77)<3,"",K77+L77-M77) -> 133648000000 | O77: =N76 -> 106150000000 | P77: =IF(N77="","",IF(OR(O77="",O77<=0,N77<=0),N77,(N77+O77)/2)) -> 119899000000 | Q77: 기초·기말 평균 | R77: =IF(OR(P77="",P77<=0),"",J77/P77) -> 0.51066109 | S77: =IF(R77="","",R77-0.1) -> 0.41066109 | T77: =IF(OR(P77="",E77=0,E77=""),"",P77/E77) -> 0.72886487 | U77: — | V77: — | W77: OK | X77: Meta Platforms, Inc.
A78: 메타 플랫폼스 | B78: META | C78: 2025 | D78: 2025-12-31 | E78: 200966000000 | F78: 83276000000 | G78: reported | H78: HIGH | I78: 0.2964437 | J78: =IF(F78="","",F78*(1-I78)) -> 5.8589354e+10 | K78: 217243000000 | L78: 58744000000 | M78: 81592000000 | N78: =IF(COUNT(K78:M78)<3,"",K78+L78-M78) -> 194395000000 | O78: =N77 -> 133648000000 | P78: =IF(N78="","",IF(OR(O78="",O78<=0,N78<=0),N78,(N78+O78)/2)) -> 164021500000 | Q78: 기초·기말 평균 | R78: =IF(OR(P78="",P78<=0),"",J78/P78) -> 0.35720533 | S78: =IF(R78="","",R78-0.1) -> 0.25720533 | T78: =IF(OR(P78="",E78=0,E78=""),"",P78/E78) -> 0.81616542 | U78: — | V78: — | W78: OK | X78: Meta Platforms, Inc.
A79: 테슬라 | B79: TSLA | C79: 2015 | D79: 2015-12-31 | E79: 4046025000 | F79: -716629000 | G79: reported | H79: HIGH | I79: 0.21 | J79: =IF(F79="","",F79*(1-I79)) -> -566136910 | K79: 1083704000 | L79: 2649020000 | M79: 1213608000 | N79: =IF(COUNT(K79:M79)<3,"",K79+L79-M79) -> 2519116000 | O79: — | P79: — | Q79: — | R79: — | S79: — | T79: — | U79: — | V79: — | W79: 다음 해 평균 투하자본의 기초값으로만 사용 (보고 기간 밖 — 자체 비율은 계산하지 않음) | X79: Tesla, Inc.
A80: 테슬라 | B80: TSLA | C80: 2016 | D80: 2016-12-31 | E80: 7000132000 | F80: -667340000 | G80: reported | H80: HIGH | I80: 0.21 | J80: =IF(F80="","",F80*(1-I80)) -> -527198600 | K80: 5538000000 | L80: 6974701000 | M80: 3393000000 | N80: =IF(COUNT(K80:M80)<3,"",K80+L80-M80) -> 9119701000 | O80: =N79 -> 2519116000 | P80: =IF(N80="","",IF(OR(O80="",O80<=0,N80<=0),N80,(N80+O80)/2)) -> 5819408500 | Q80: 기초·기말 평균 | R80: =IF(OR(P80="",P80<=0),"",J80/P80) -> -0.090593159 | S80: =IF(R80="","",R80-0.1) -> -0.19059316 | T80: =IF(OR(P80="",E80=0,E80=""),"",P80/E80) -> 0.83132839 | U80: — | V80: — | W80: OK | X80: Tesla, Inc.
A81: 테슬라 | B81: TSLA | C81: 2017 | D81: 2017-12-31 | E81: 11759000000 | F81: -1632000000 | G81: reported | H81: HIGH | I81: 0.21 | J81: =IF(F81="","",F81*(1-I81)) -> -1289280000 | K81: 5234000000 | L81: 10218168000 | M81: 3368000000 | N81: =IF(COUNT(K81:M81)<3,"",K81+L81-M81) -> 12084168000 | O81: =N80 -> 9119701000 | P81: =IF(N81="","",IF(OR(O81="",O81<=0,N81<=0),N81,(N81+O81)/2)) -> 10601934500 | Q81: 기초·기말 평균 | R81: =IF(OR(P81="",P81<=0),"",J81/P81) -> -0.121608 | S81: =IF(R81="","",R81-0.1) -> -0.221608 | T81: =IF(OR(P81="",E81=0,E81=""),"",P81/E81) -> 0.90160171 | U81: — | V81: — | W81: OK | X81: Tesla, Inc.
A82: 테슬라 | B82: TSLA | C82: 2018 | D82: 2018-12-31 | E82: 21461268000 | F82: -388000000 | G82: reported | H82: HIGH | I82: 0.21 | J82: =IF(F82="","",F82*(1-I82)) -> -306520000 | K82: 5757000000 | L82: 11625672000 | M82: 3686000000 | N82: =IF(COUNT(K82:M82)<3,"",K82+L82-M82) -> 13696672000 | O82: =N81 -> 12084168000 | P82: =IF(N82="","",IF(OR(O82="",O82<=0,N82<=0),N82,(N82+O82)/2)) -> 12890420000 | Q82: 기초·기말 평균 | R82: =IF(OR(P82="",P82<=0),"",J82/P82) -> -0.023778899 | S82: =IF(R82="","",R82-0.1) -> -0.1237789 | T82: =IF(OR(P82="",E82=0,E82=""),"",P82/E82) -> 0.60063646 | U82: — | V82: — | W82: OK | X82: Tesla, Inc.
A83: 테슬라 | B83: TSLA | C83: 2019 | D83: 2019-12-31 | E83: 24578000000 | F83: -69000000 | G83: reported | H83: HIGH | I83: 0.21 | J83: =IF(F83="","",F83*(1-I83)) -> -54510000 | K83: 7467000000 | L83: 10402000000 | M83: 6268000000 | N83: =IF(COUNT(K83:M83)<3,"",K83+L83-M83) -> 11601000000 | O83: =N82 -> 13696672000 | P83: =IF(N83="","",IF(OR(O83="",O83<=0,N83<=0),N83,(N83+O83)/2)) -> 12648836000 | Q83: 기초·기말 평균 | R83: =IF(OR(P83="",P83<=0),"",J83/P83) -> -0.0043094875 | S83: =IF(R83="","",R83-0.1) -> -0.10430949 | T83: =IF(OR(P83="",E83=0,E83=""),"",P83/E83) -> 0.51464057 | U83: — | V83: — | W83: OK | X83: Tesla, Inc.
A84: 테슬라 | B84: TSLA | C84: 2020 | D84: 2020-12-31 | E84: 31536000000 | F84: 1994000000 | G84: reported | H84: HIGH | I84: 0.25303293 | J84: =IF(F84="","",F84*(1-I84)) -> 1.4894523e+09 | K84: 23075000000 | L84: 8462000000 | M84: 19384000000 | N84: =IF(COUNT(K84:M84)<3,"",K84+L84-M84) -> 12153000000 | O84: =N83 -> 11601000000 | P84: =IF(N84="","",IF(OR(O84="",O84<=0,N84<=0),N84,(N84+O84)/2)) -> 11877000000 | Q84: 기초·기말 평균 | R84: =IF(OR(P84="",P84<=0),"",J84/P84) -> 0.12540644 | S84: =IF(R84="","",R84-0.1) -> 0.025406444 | T84: =IF(OR(P84="",E84=0,E84=""),"",P84/E84) -> 0.3766172 | U84: — | V84: — | W84: OK | X84: Tesla, Inc.
A85: 테슬라 | B85: TSLA | C85: 2021 | D85: 2021-12-31 | E85: 53823000000 | F85: 6523000000 | G85: reported | H85: HIGH | I85: 0.11020022 | J85: =IF(F85="","",F85*(1-I85)) -> 5.804164e+09 | K85: 31015000000 | L85: 4254000000 | M85: 17707000000 | N85: =IF(COUNT(K85:M85)<3,"",K85+L85-M85) -> 17562000000 | O85: =N84 -> 12153000000 | P85: =IF(N85="","",IF(OR(O85="",O85<=0,N85<=0),N85,(N85+O85)/2)) -> 14857500000 | Q85: 기초·기말 평균 | R85: =IF(OR(P85="",P85<=0),"",J85/P85) -> 0.39065549 | S85: =IF(R85="","",R85-0.1) -> 0.29065549 | T85: =IF(OR(P85="",E85=0,E85=""),"",P85/E85) -> 0.2760437 | U85: — | V85: — | W85: OK | X85: Tesla, Inc.
A86: 테슬라 | B86: TSLA | C86: 2022 | D86: 2022-12-31 | E86: 81462000000 | F86: 13656000000 | G86: reported | H86: HIGH | I86: 0.082513303 | J86: =IF(F86="","",F86*(1-I86)) -> 1.2529198e+10 | K86: 45489000000 | L86: 1029000000 | M86: 22185000000 | N86: =IF(COUNT(K86:M86)<3,"",K86+L86-M86) -> 24333000000 | O86: =N85 -> 17562000000 | P86: =IF(N86="","",IF(OR(O86="",O86<=0,N86<=0),N86,(N86+O86)/2)) -> 20947500000 | Q86: 기초·기말 평균 | R86: =IF(OR(P86="",P86<=0),"",J86/P86) -> 0.5981238 | S86: =IF(R86="","",R86-0.1) -> 0.4981238 | T86: =IF(OR(P86="",E86=0,E86=""),"",P86/E86) -> 0.25714444 | U86: — | V86: — | W86: OK | X86: Tesla, Inc.
A87: 테슬라 | B87: TSLA | C87: 2023 | D87: 2023-12-31 | E87: 96773000000 | F87: 8891000000 | G87: reported | H87: HIGH | I87: 0.05 | J87: =IF(F87="","",F87*(1-I87)) -> 8446450000 | K87: 63367000000 | L87: 2682000000 | M87: 29094000000 | N87: =IF(COUNT(K87:M87)<3,"",K87+L87-M87) -> 36955000000 | O87: =N86 -> 24333000000 | P87: =IF(N87="","",IF(OR(O87="",O87<=0,N87<=0),N87,(N87+O87)/2)) -> 30644000000 | Q87: 기초·기말 평균 | R87: =IF(OR(P87="",P87<=0),"",J87/P87) -> 0.27563144 | S87: =IF(R87="","",R87-0.1) -> 0.17563144 | T87: =IF(OR(P87="",E87=0,E87=""),"",P87/E87) -> 0.31665857 | U87: — | V87: — | W87: OK | X87: Tesla, Inc.
A88: 테슬라 | B88: TSLA | C88: 2024 | D88: 2024-12-31 | E88: 97690000000 | F88: 7076000000 | G88: reported | H88: HIGH | I88: 0.20433815 | J88: =IF(F88="","",F88*(1-I88)) -> 5.6301032e+09 | K88: 73617000000 | L88: 5535000000 | M88: 36563000000 | N88: =IF(COUNT(K88:M88)<3,"",K88+L88-M88) -> 42589000000 | O88: =N87 -> 36955000000 | P88: =IF(N88="","",IF(OR(O88="",O88<=0,N88<=0),N88,(N88+O88)/2)) -> 39772000000 | Q88: 기초·기말 평균 | R88: =IF(OR(P88="",P88<=0),"",J88/P88) -> 0.14155947 | S88: =IF(R88="","",R88-0.1) -> 0.04155947 | T88: =IF(OR(P88="",E88=0,E88=""),"",P88/E88) -> 0.40712458 | U88: — | V88: — | W88: OK | X88: Tesla, Inc.
A89: 테슬라 | B89: TSLA | C89: 2025 | D89: 2025-12-31 | E89: 94827000000 | F89: 4355000000 | G89: reported | H89: HIGH | I89: 0.2696097 | J89: =IF(F89="","",F89*(1-I89)) -> 3.1808498e+09 | K89: 82807000000 | L89: 6584000000 | M89: 44059000000 | N89: =IF(COUNT(K89:M89)<3,"",K89+L89-M89) -> 45332000000 | O89: =N88 -> 42589000000 | P89: =IF(N89="","",IF(OR(O89="",O89<=0,N89<=0),N89,(N89+O89)/2)) -> 43960500000 | Q89: 기초·기말 평균 | R89: =IF(OR(P89="",P89<=0),"",J89/P89) -> 0.072356997 | S89: =IF(R89="","",R89-0.1) -> -0.027643003 | T89: =IF(OR(P89="",E89=0,E89=""),"",P89/E89) -> 0.46358632 | U89: — | V89: — | W89: OK | X89: Tesla, Inc.
A90: 버크셔 해서웨이 | B90: BRK-B | C90: 2015 | D90: 2015-12-31 | E90: 210943000000 | F90: 38461000000 | G90: pretax_plus_interest_less_investment_income | H90: LOW | I90: 0.30137927 | J90: =IF(F90="","",F90*(1-I90)) -> 2.6869652e+10 | K90: 257696000000 | L90: 0 | M90: 67161000000 | N90: =IF(COUNT(K90:M90)<3,"",K90+L90-M90) -> 190535000000 | O90: — | P90: — | Q90: — | R90: — | S90: — | T90: — | U90: — | V90: — | W90: 다음 해 평균 투하자본의 기초값으로만 사용 (보고 기간 밖 — 자체 비율은 계산하지 않음) | X90: BERKSHIRE HATHAWAY INC
A91: 버크셔 해서웨이 | B91: BRK-B | C91: 2016 | D91: 2016-12-31 | E91: 215114000000 | F91: 37408000000 | G91: pretax_plus_interest_less_investment_income | H91: LOW | I91: 0.27445273 | J91: =IF(F91="","",F91*(1-I91)) -> 2.7141272e+10 | K91: 285428000000 | L91: 0 | M91: 28048000000 | N91: =IF(COUNT(K91:M91)<3,"",K91+L91-M91) -> 257380000000 | O91: =N90 -> 190535000000 | P91: =IF(N91="","",IF(OR(O91="",O91<=0,N91<=0),N91,(N91+O91)/2)) -> 223957500000 | Q91: 기초·기말 평균 | R91: — | S91: — | T91: =IF(OR(P91="",E91=0,E91=""),"",P91/E91) -> 1.0411108 | U91: — | V91: — | W91: 금융업 — ROIC 정의 부적합 | X91: BERKSHIRE HATHAWAY INC
A92: 버크셔 해서웨이 | B92: BRK-B | C92: 2017 | D92: 2017-12-31 | E92: 239933000000 | F92: 28224000000 | G92: pretax_plus_interest_less_investment_income | H92: LOW | I92: 0.05 | J92: =IF(F92="","",F92*(1-I92)) -> 26812800000 | K92: 351954000000 | L92: 0 | M92: 31583000000 | N92: =IF(COUNT(K92:M92)<3,"",K92+L92-M92) -> 320371000000 | O92: =N91 -> 257380000000 | P92: =IF(N92="","",IF(OR(O92="",O92<=0,N92<=0),N92,(N92+O92)/2)) -> 288875500000 | Q92: 기초·기말 평균 | R92: — | S92: — | T92: =IF(OR(P92="",E92=0,E92=""),"",P92/E92) -> 1.203984 | U92: — | V92: — | W92: 금융업 — ROIC 정의 부적합 | X92: BERKSHIRE HATHAWAY INC
A93: 버크셔 해서웨이 | B93: BRK-B | C93: 2018 | D93: 2018-12-31 | E93: 175445000000 | F93: 7854000000 | G93: pretax_plus_interest_less_investment_income | H93: LOW | I93: 0.05 | J93: =IF(F93="","",F93*(1-I93)) -> 7461300000 | K93: 352500000000 | L93: 0 | M93: 30811000000 | N93: =IF(COUNT(K93:M93)<3,"",K93+L93-M93) -> 321689000000 | O93: =N92 -> 320371000000 | P93: =IF(N93="","",IF(OR(O93="",O93<=0,N93<=0),N93,(N93+O93)/2)) -> 321030000000 | Q93: 기초·기말 평균 | R93: — | S93: — | T93: =IF(OR(P93="",E93=0,E93=""),"",P93/E93) -> 1.8298042 | U93: — | V93: — | W93: 금융업 — ROIC 정의 부적합 | X93: BERKSHIRE HATHAWAY INC
A94: 버크셔 해서웨이 | B94: BRK-B | C94: 2019 | D94: 2019-12-31 | E94: 176512000000 | F94: 106657000000 | G94: pretax_plus_interest_less_investment_income | H94: LOW | I94: 0.20355223 | J94: =IF(F94="","",F94*(1-I94)) -> 8.494673e+10 | K94: 428563000000 | L94: 0 | M94: 64632000000 | N94: =IF(COUNT(K94:M94)<3,"",K94+L94-M94) -> 363931000000 | O94: =N93 -> 321689000000 | P94: =IF(N94="","",IF(OR(O94="",O94<=0,N94<=0),N94,(N94+O94)/2)) -> 342810000000 | Q94: 기초·기말 평균 | R94: — | S94: — | T94: =IF(OR(P94="",E94=0,E94=""),"",P94/E94) -> 1.9421342 | U94: — | V94: — | W94: 금융업 — ROIC 정의 부적합 | X94: BERKSHIRE HATHAWAY INC
A95: 버크셔 해서웨이 | B95: BRK-B | C95: 2020 | D95: 2020-12-31 | E95: 166733000000 | F95: 59776000000 | G95: pretax_plus_interest_less_investment_income | H95: LOW | I95: 0.22336739 | J95: =IF(F95="","",F95*(1-I95)) -> 4.6423991e+10 | K95: 444908000000 | L95: 0 | M95: 48396000000 | N95: =IF(COUNT(K95:M95)<3,"",K95+L95-M95) -> 396512000000 | O95: =N94 -> 363931000000 | P95: =IF(N95="","",IF(OR(O95="",O95<=0,N95<=0),N95,(N95+O95)/2)) -> 380221500000 | Q95: 기초·기말 평균 | R95: — | S95: — | T95: =IF(OR(P95="",E95=0,E95=""),"",P95/E95) -> 2.2804214 | U95: — | V95: — | W95: 금융업 — ROIC 정의 부적합 | X95: BERKSHIRE HATHAWAY INC
A96: 버크셔 해서웨이 | B96: BRK-B | C96: 2021 | D96: 2021-12-31 | E96: 191252000000 | F96: 116033000000 | G96: pretax_plus_interest_less_investment_income | H96: LOW | I96: 0.1869463 | J96: =IF(F96="","",F96*(1-I96)) -> 9.434106e+10 | K96: 510299000000 | L96: 0 | M96: 88706000000 | N96: =IF(COUNT(K96:M96)<3,"",K96+L96-M96) -> 421593000000 | O96: =N95 -> 396512000000 | P96: =IF(N96="","",IF(OR(O96="",O96<=0,N96<=0),N96,(N96+O96)/2)) -> 409052500000 | Q96: 기초·기말 평균 | R96: — | S96: — | T96: =IF(OR(P96="",E96=0,E96=""),"",P96/E96) -> 2.1388142 | U96: — | V96: — | W96: 금융업 — ROIC 정의 부적합 | X96: BERKSHIRE HATHAWAY INC
A97: 버크셔 해서웨이 | B97: BRK-B | C97: 2022 | D97: 2022-12-31 | E97: 207771000000 | F97: -26148000000 | G97: pretax_plus_interest_less_investment_income | H97: LOW | I97: 0.21 | J97: =IF(F97="","",F97*(1-I97)) -> -20656920000 | K97: 481681000000 | L97: 0 | M97: 36399000000 | N97: =IF(COUNT(K97:M97)<3,"",K97+L97-M97) -> 445282000000 | O97: =N96 -> 421593000000 | P97: =IF(N97="","",IF(OR(O97="",O97<=0,N97<=0),N97,(N97+O97)/2)) -> 433437500000 | Q97: 기초·기말 평균 | R97: — | S97: — | T97: =IF(OR(P97="",E97=0,E97=""),"",P97/E97) -> 2.0861309 | U97: — | V97: — | W97: 금융업 — ROIC 정의 부적합 | X97: BERKSHIRE HATHAWAY INC
A98: 버크셔 해서웨이 | B98: BRK-B | C98: 2023 | D98: 2023-12-31 | E98: 254906000000 | F98: 125169000000 | G98: pretax_plus_interest_less_investment_income | H98: LOW | I98: 0.19156001 | J98: =IF(F98="","",F98*(1-I98)) -> 1.0119163e+11 | K98: 567509000000 | L98: 0 | M98: 38643000000 | N98: =IF(COUNT(K98:M98)<3,"",K98+L98-M98) -> 528866000000 | O98: =N97 -> 445282000000 | P98: =IF(N98="","",IF(OR(O98="",O98<=0,N98<=0),N98,(N98+O98)/2)) -> 487074000000 | Q98: 기초·기말 평균 | R98: — | S98: — | T98: =IF(OR(P98="",E98=0,E98=""),"",P98/E98) -> 1.9107985 | U98: — | V98: — | W98: 금융업 — ROIC 정의 부적합 | X98: BERKSHIRE HATHAWAY INC
A99: 버크셔 해서웨이 | B99: BRK-B | C99: 2024 | D99: 2024-12-31 | E99: 249714000000 | F99: 115576000000 | G99: pretax_plus_interest_less_investment_income | H99: LOW | I99: 0.18858266 | J99: =IF(F99="","",F99*(1-I99)) -> 9.378037e+10 | K99: 651655000000 | L99: 0 | M99: 48376000000 | N99: =IF(COUNT(K99:M99)<3,"",K99+L99-M99) -> 603279000000 | O99: =N98 -> 528866000000 | P99: =IF(N99="","",IF(OR(O99="",O99<=0,N99<=0),N99,(N99+O99)/2)) -> 566072500000 | Q99: 기초·기말 평균 | R99: — | S99: — | T99: =IF(OR(P99="",E99=0,E99=""),"",P99/E99) -> 2.2668833 | U99: — | V99: — | W99: 금융업 — ROIC 정의 부적합 | X99: BERKSHIRE HATHAWAY INC
A100: 버크셔 해서웨이 | B100: BRK-B | C100: 2025 | D100: 2025-12-31 | E100: 247244000000 | F100: 87528000000 | G100: pretax_plus_interest_less_investment_income | H100: LOW | I100: 0.18432191 | J100: =IF(F100="","",F100*(1-I100)) -> 7.1394672e+10 | K100: 719703000000 | L100: 0 | M100: 52569000000 | N100: =IF(COUNT(K100:M100)<3,"",K100+L100-M100) -> 667134000000 | O100: =N99 -> 603279000000 | P100: =IF(N100="","",IF(OR(O100="",O100<=0,N100<=0),N100,(N100+O100)/2)) -> 635206500000 | Q100: 기초·기말 평균 | R100: — | S100: — | T100: =IF(OR(P100="",E100=0,E100=""),"",P100/E100) -> 2.5691483 | U100: — | V100: — | W100: 금융업 — ROIC 정의 부적합 | X100: BERKSHIRE HATHAWAY INC
...

Sheet ROIC 연도별
A1: 셀은 '계산 명세' 시트의 ROIC를 참조합니다. 초록 = 10% 초과, 빨강 = 10% 이하, 기울임 = 영업이익을 세전이익에서 추정한 해, 노란 테두리 = 순투하자본이 매출의 10% 미만인 해.
A2: 순위 | B2: 기업 | C2: 티커 | D2: FY2016 | E2: FY2017 | F2: FY2018 | G2: FY2019 | H2: FY2020 | I2: FY2021 | J2: FY2022 | K2: FY2023 | L2: FY2024 | M2: FY2025 | N2: FY2026 | O2: 중위 | P2: 최소 | Q2: 최대 | R2: 10% 초과 연수 | S2: 산출 연수 | T2: 판정
A3: 순위 대상 (산출 5년 이상)
A4: 1 | B4: 아리스타 네트웍스 | C4: ANET | D4: ='계산 명세'!R478 -> 1.0861635 | E4: ='계산 명세'!R479 -> 2.2885491 | F4: ='계산 명세'!R480 -> 1.6561149 | G4: ='계산 명세'!R481 -> 4.2817166 | H4: ='계산 명세'!R482 -> 1.9455045 | I4: ='계산 명세'!R483 -> 1.6415471 | J4: ='계산 명세'!R484 -> 1.0735975 | K4: ='계산 명세'!R485 -> 0.95522267 | L4: ='계산 명세'!R486 -> 1.3182578 | M4: ='계산 명세'!R487 -> 1.9200796 | N4: — | O4: =MEDIAN(D4:N4) -> 1.648831 | P4: =MIN(D4:N4) -> 0.95522267 | Q4: =MAX(D4:N4) -> 4.2817166 | R4: =COUNTIF(D4:N4,">0.1") -> 10 | S4: =COUNT(D4:N4) -> 10 | T4: 전 기간 초과 · 매우 높음
A5: 2 | B5: 엔비디아 | C5: NVDA | D5: ='계산 명세'!R3 -> 1.7860208 | E5: ='계산 명세'!R4 -> 1.8509863 | F5: ='계산 명세'!R5 -> 1.1553069 | G5: ='계산 명세'!R6 -> 0.7436205 | H5: ='계산 명세'!R7 -> 0.55222215 | I5: ='계산 명세'!R8 -> 0.66601152 | J5: ='계산 명세'!R9 -> 0.22226653 | K5: ='계산 명세'!R10 -> 1.2490268 | L5: ='계산 명세'!R11 -> 1.9821923 | M5: ='계산 명세'!R12 -> 1.1082268 | N5: — | O5: =MEDIAN(D5:N5) -> 1.1317669 | P5: =MIN(D5:N5) -> 0.22226653 | Q5: =MAX(D5:N5) -> 1.9821923 | R5: =COUNTIF(D5:N5,">0.1") -> 10 | S5: =COUNT(D5:N5) -> 10 | T5: 전 기간 초과 · 매우 높음
A6: 3 | B6: 마스터카드 | C6: MA | D6: ='계산 명세'!R202 -> 1.617526 | E6: ='계산 명세'!R203 -> 1.4026209 | F6: ='계산 명세'!R204 -> 1.8186511 | G6: ='계산 명세'!R205 -> 1.5898454 | H6: ='계산 명세'!R206 -> 0.87088407 | I6: ='계산 명세'!R207 -> 0.77410625 | J6: ='계산 명세'!R208 -> 0.78754876 | K6: ='계산 명세'!R209 -> 0.86950339 | L6: ='계산 명세'!R210 -> 0.89324666 | M6: ='계산 명세'!R211 -> 0.95703638 | N6: — | O6: =MEDIAN(D6:N6) -> 0.92514152 | P6: =MIN(D6:N6) -> 0.77410625 | Q6: =MAX(D6:N6) -> 1.8186511 | R6: =COUNTIF(D6:N6,">0.1") -> 10 | S6: =COUNT(D6:N6) -> 10 | T6: 전 기간 초과 · 매우 높음
A7: 4 | B7: 애플 | C7: AAPL | D7: ='계산 명세'!R14 -> 0.30794128 | E7: ='계산 명세'!R15 -> 0.28596898 | F7: ='계산 명세'!R16 -> 0.3499434 | G7: ='계산 명세'!R17 -> 0.42428441 | H7: ='계산 명세'!R18 -> 0.61386135 | I7: ='계산 명세'!R19 -> 0.89108895 | J7: ='계산 명세'!R20 -> 0.80840103 | K7: ='계산 명세'!R21 -> 0.83272255 | L7: ='계산 명세'!R22 -> 0.89041021 | M7: ='계산 명세'!R23 -> 1.039152 | N7: — | O7: =MEDIAN(D7:N7) -> 0.71113119 | P7: =MIN(D7:N7) -> 0.28596898 | Q7: =MAX(D7:N7) -> 1.039152 | R7: =COUNTIF(D7:N7,">0.1") -> 10 | S7: =COUNT(D7:N7) -> 10 | T7: 전 기간 초과 · 매우 높음
A8: 5 | B8: 마이크로소프트 | C8: MSFT | D8: ='계산 명세'!R36 -> — | E8: ='계산 명세'!R37 -> 0.77036684 | F8: ='계산 명세'!R38 -> 0.63631909 | G8: ='계산 명세'!R39 -> 1.1713967 | H8: ='계산 명세'!R40 -> 1.0307767 | I8: ='계산 명세'!R41 -> 1.0486838 | J8: ='계산 명세'!R42 -> 0.79892226 | K8: ='계산 명세'!R43 -> 0.56526971 | L8: ='계산 명세'!R44 -> 0.46272339 | M8: ='계산 명세'!R45 -> 0.39457044 | N8: ='계산 명세'!R46 -> 0.3585794 | O8: =MEDIAN(D8:N8) -> 0.70334296 | P8: =MIN(D8:N8) -> 0.3585794 | Q8: =MAX(D8:N8) -> 1.1713967 | R8: =COUNTIF(D8:N8,">0.1") -> 10 | S8: =COUNT(D8:N8) -> 10 | T8: 전 기간 초과 · 매우 높음
A9: 6 | B9: 램리서치 | C9: LRCX | D9: ='계산 명세'!R290 -> — | E9: ='계산 명세'!R291 -> 0.52055414 | F9: ='계산 명세'!R292 -> 0.65722234 | G9: ='계산 명세'!R293 -> 0.58097307 | H9: ='계산 명세'!R294 -> 0.58903545 | I9: ='계산 명세'!R295 -> 0.84195609 | J9: ='계산 명세'!R296 -> 0.74328038 | K9: ='계산 명세'!R297 -> 0.5939825 | L9: ='계산 명세'!R298 -> 0.48425258 | M9: ='계산 명세'!R299 -> 0.68039171 | N9: ='계산 명세'!R300 -> 0.77721561 | O9: =MEDIAN(D9:N9) -> 0.62560242 | P9: =MIN(D9:N9) -> 0.48425258 | Q9: =MAX(D9:N9) -> 0.84195609 | R9: =COUNTIF(D9:N9,">0.1") -> 10 | S9: =COUNT(D9:N9) -> 10 | T9: 전 기간 초과 · 매우 높음
A10: 7 | B10: 필립모리스 인터내셔널 | C10: PM | D10: ='계산 명세'!R425 -> 0.57146557 | E10: ='계산 명세'!R426 -> 0.46965867 | F10: ='계산 명세'!R427 -> 0.58295306 | G10: ='계산 명세'!R428 -> 0.55735089 | H10: ='계산 명세'!R429 -> 0.64770167 | I10: ='계산 명세'!R430 -> 0.70607841 | J10: ='계산 명세'!R431 -> 0.4058536 | K10: ='계산 명세'!R432 -> 0.25995382 | L10: ='계산 명세'!R433 -> 0.30106487 | M10: ='계산 명세'!R434 -> 0.3540046 | N10: — | O10: =MEDIAN(D10:N10) -> 0.51350478 | P10: =MIN(D10:N10) -> 0.25995382 | Q10: =MAX(D10:N10) -> 0.70607841 | R10: =COUNTIF(D10:N10,">0.1") -> 10 | S10: =COUNT(D10:N10) -> 10 | T10: 전 기간 초과 · 매우 높음
A11: 8 | B11: KLA | C11: KLAC | D11: ='계산 명세'!R466 -> — | E11: ='계산 명세'!R467 -> 0.80700967 | F11: ='계산 명세'!R468 -> 0.8306849 | G11: ='계산 명세'!R469 -> 0.44209264 | H11: ='계산 명세'!R470 -> 0.28539867 | I11: ='계산 명세'!R471 -> 0.42946699 | J11: ='계산 명세'!R472 -> 0.55978314 | K11: ='계산 명세'!R473 -> 0.49316571 | L11: ='계산 명세'!R474 -> 0.35845898 | M11: ='계산 명세'!R475 -> 0.4814352 | N11: ='계산 명세'!R476 -> 0.49384768 | O11: =MEDIAN(D11:N11) -> 0.48730046 | P11: =MIN(D11:N11) -> 0.28539867 | Q11: =MAX(D11:N11) -> 0.8306849 | R11: =COUNTIF(D11:N11,">0.1") -> 10 | S11: =COUNT(D11:N11) -> 10 | T11: 전 기간 초과 · 매우 높음
A12: 9 | B12: 텍사스 인스트루먼츠 | C12: TXN | D12: ='계산 명세'!R455 -> 0.33025274 | E12: ='계산 명세'!R456 -> 0.35874926 | F12: ='계산 명세'!R457 -> 0.56665658 | G12: ='계산 명세'!R458 -> 0.52345662 | H12: ='계산 명세'!R459 -> 0.58491212 | I12: ='계산 명세'!R460 -> 0.75218905 | J12: ='계산 명세'!R461 -> 0.69141421 | K12: ='계산 명세'!R462 -> 0.38080197 | L12: ='계산 명세'!R463 -> 0.22652415 | M12: ='계산 명세'!R464 -> 0.21816561 | N12: — | O12: =MEDIAN(D12:N12) -> 0.4521293 | P12: =MIN(D12:N12) -> 0.21816561 | Q12: =MAX(D12:N12) -> 0.75218905 | R12: =COUNTIF(D12:N12,">0.1") -> 10 | S12: =COUNT(D12:N12) -> 10 | T12: 전 기간 초과 · 매우 높음
A13: 10 | B13: 메타 플랫폼스 | C13: META | D13: ='계산 명세'!R69 -> 0.36399523 | E13: ='계산 명세'!R70 -> 0.50116142 | F13: ='계산 명세'!R71 -> 0.57426782 | G13: ='계산 명세'!R72 -> 0.40061041 | H13: ='계산 명세'!R73 -> 0.5100437 | I13: ='계산 명세'!R74 -> 0.54362086 | J13: ='계산 명세'!R75 -> 0.27128611 | K13: ='계산 명세'!R76 -> 0.38339008 | L13: ='계산 명세'!R77 -> 0.51066109 | M13: ='계산 명세'!R78 -> 0.35720533 | N13: — | O13: =MEDIAN(D13:N13) -> 0.45088592 | P13: =MIN(D13:N13) -> 0.27128611 | Q13: =MAX(D13:N13) -> 0.57426782 | R13: =COUNTIF(D13:N13,">0.1") -> 10 | S13: =COUNT(D13:N13) -> 10 | T13: 전 기간 초과 · 매우 높음
A14: 11 | B14: 홈디포 | C14: HD | D14: ='계산 명세'!R357 -> 0.33732645 | E14: ='계산 명세'!R358 -> 0.36789009 | F14: ='계산 명세'!R359 -> 0.47053122 | G14: ='계산 명세'!R360 -> 0.46750761 | H14: ='계산 명세'!R361 -> 0.47051924 | I14: ='계산 명세'!R362 -> 0.50715712 | J14: ='계산 명세'!R363 -> 0.46879831 | K14: ='계산 명세'!R364 -> 0.39534415 | L14: ='계산 명세'!R365 -> 0.32926302 | M14: ='계산 명세'!R366 -> 0.25322002 | N14: — | O14: =MEDIAN(D14:N14) -> 0.43142588 | P14: =MIN(D14:N14) -> 0.25322002 | Q14: =MAX(D14:N14) -> 0.50715712 | R14: =COUNTIF(D14:N14,">0.1") -> 10 | S14: =COUNT(D14:N14) -> 10 | T14: 전 기간 초과 · 매우 높음
A15: 12 | B15: 어플라이드 머티리얼즈 | C15: AMAT | D15: ='계산 명세'!R247 -> 0.25951577 | E15: ='계산 명세'!R248 -> 0.49561827 | F15: ='계산 명세'!R249 -> 0.39331553 | G15: ='계산 명세'!R250 -> 0.3075528 | H15: ='계산 명세'!R251 -> 0.37548855 | I15: ='계산 명세'!R252 -> 0.53183698 | J15: ='계산 명세'!R253 -> 0.48973181 | K15: ='계산 명세'!R254 -> 0.45172265 | L15: ='계산 명세'!R255 -> 0.43933313 | M15: ='계산 명세'!R256 -> 0.35869747 | N15: — | O15: =MEDIAN(D15:N15) -> 0.41632433 | P15: =MIN(D15:N15) -> 0.25951577 | Q15: =MAX(D15:N15) -> 0.53183698 | R15: =COUNTIF(D15:N15,">0.1") -> 10 | S15: =COUNT(D15:N15) -> 10 | T15: 전 기간 초과 · 매우 높음
A16: 13 | B16: 알파벳 | C16: GOOG | D16: ='계산 명세'!R25 -> 0.35057615 | E16: ='계산 명세'!R26 -> 0.28246592 | F16: ='계산 명세'!R27 -> 0.38155484 | G16: ='계산 명세'!R28 -> 0.37515751 | H16: ='계산 명세'!R29 -> 0.37023344 | I16: ='계산 명세'!R30 -> 0.57965865 | J16: ='계산 명세'!R31 -> 0.44332262 | K16: ='계산 명세'!R32 -> 0.42386488 | L16: ='계산 명세'!R33 -> 0.437885 | M16: ='계산 명세'!R34 -> 0.36991734 | N16: — | O16: =MEDIAN(D16:N16) -> 0.37835618 | P16: =MIN(D16:N16) -> 0.28246592 | Q16: =MAX(D16:N16) -> 0.57965865 | R16: =COUNTIF(D16:N16,">0.1") -> 10 | S16: =COUNT(D16:N16) -> 10 | T16: 전 기간 초과 · 매우 높음
A17: 14 | B17: 코스트코 | C17: COST | D17: ='계산 명세'!R270 -> — | E17: ='계산 명세'!R271 -> 0.22346643 | F17: ='계산 명세'!R272 -> 0.26301849 | G17: ='계산 명세'!R273 -> 0.29012249 | H17: ='계산 명세'!R274 -> 0.31652762 | I17: ='계산 명세'!R275 -> 0.38574264 | J17: ='계산 명세'!R276 -> 0.39622213 | K17: ='계산 명세'!R277 -> 0.36989819 | L17: ='계산 명세'!R278 -> 0.40527765 | M17: ='계산 명세'!R279 -> 0.40866036 | N17: ='계산 명세'!R280 -> 0.43636596 | O17: =MEDIAN(D17:N17) -> 0.37782042 | P17: =MIN(D17:N17) -> 0.22346643 | Q17: =MAX(D17:N17) -> 0.43636596 | R17: =COUNTIF(D17:N17,">0.1") -> 10 | S17: =COUNT(D17:N17) -> 10 | T17: 전 기간 초과 · 매우 높음
A18: 15 | B18: 시스코 시스템즈 | C18: CSCO | D18: ='계산 명세'!R213 -> — | E18: ='계산 명세'!R214 -> 0.33540271 | F18: ='계산 명세'!R215 -> 0.28632795 | G18: ='계산 명세'!R216 -> 0.48206189 | H18: ='계산 명세'!R217 -> 0.45641847 | I18: ='계산 명세'!R218 -> 0.39902668 | J18: ='계산 명세'!R219 -> 0.39096855 | K18: ='계산 명세'!R220 -> 0.4371918 | L18: ='계산 명세'!R221 -> 0.24130883 | M18: ='계산 명세'!R222 -> 0.18133865 | N18: ='계산 명세'!R223 -> 0.2023031 | O18: =MEDIAN(D18:N18) -> 0.36318563 | P18: =MIN(D18:N18) -> 0.18133865 | Q18: =MAX(D18:N18) -> 0.48206189 | R18: =COUNTIF(D18:N18,">0.1") -> 10 | S18: =COUNT(D18:N18) -> 10 | T18: 전 기간 초과 · 매우 높음
A19: 16 | B19: 비자 | C19: V | D19: ='계산 명세'!R158 -> 0.18472391 | E19: ='계산 명세'!R159 -> 0.18755695 | F19: ='계산 명세'!R160 -> 0.2713166 | G19: ='계산 명세'!R161 -> 0.31017027 | H19: ='계산 명세'!R162 -> 0.27789653 | I19: ='계산 명세'!R163 -> 0.30115233 | J19: ='계산 명세'!R164 -> 0.39001372 | K19: ='계산 명세'!R165 -> 0.43887194 | L19: ='계산 명세'!R166 -> 0.46450313 | M19: ='계산 명세'!R167 -> 0.44761401 | N19: — | O19: =MEDIAN(D19:N19) -> 0.3056613 | P19: =MIN(D19:N19) -> 0.18472391 | Q19: =MAX(D19:N19) -> 0.46450313 | R19: =COUNTIF(D19:N19,">0.1") -> 10 | S19: =COUNT(D19:N19) -> 10 | T19: 전 기간 초과 · 매우 높음
A20: 17 | B20: 아마존 | C20: AMZN | D20: ='계산 명세'!R48 -> 1.2959004 | E20: ='계산 명세'!R49 -> 0.27742466 | F20: ='계산 명세'!R50 -> 0.45559076 | G20: ='계산 명세'!R51 -> 0.4097221 | H20: ='계산 명세'!R52 -> 0.54755281 | I20: ='계산 명세'!R53 -> 0.32294247 | J20: ='계산 명세'!R54 -> 0.080594049 | K20: ='계산 명세'!R55 -> 0.18132485 | L20: ='계산 명세'!R56 -> 0.27946104 | M20: ='계산 명세'!R57 -> 0.21449257 | N20: — | O20: =MEDIAN(D20:N20) -> 0.30120176 | P20: =MIN(D20:N20) -> 0.080594049 | Q20: =MAX(D20:N20) -> 1.2959004 | R20: =COUNTIF(D20:N20,">0.1") -> 9 | S20: =COUNT(D20:N20) -> 10 | T20: 대체로 초과
A21: 18 | B21: 일라이 릴리 | C21: LLY | D21: ='계산 명세'!R102 -> 0.14513322 | E21: ='계산 명세'!R103 -> 0.067473897 | F21: ='계산 명세'!R104 -> 0.19472191 | G21: ='계산 명세'!R105 -> 0.29826975 | H21: ='계산 명세'!R106 -> 0.30245991 | I21: ='계산 명세'!R107 -> 0.28208922 | J21: ='계산 명세'!R108 -> 0.27866143 | K21: ='계산 명세'!R109 -> 0.17812752 | L21: ='계산 명세'!R110 -> 0.2774587 | M21: ='계산 명세'!R111 -> 0.39709146 | N21: — | O21: =MEDIAN(D21:N21) -> 0.27806007 | P21: =MIN(D21:N21) -> 0.067473897 | Q21: =MAX(D21:N21) -> 0.39709146 | R21: =COUNTIF(D21:N21,">0.1") -> 9 | S21: =COUNT(D21:N21) -> 10 | T21: 대체로 초과
A22: 19 | B22: 존슨앤드존슨 | C22: JNJ | D22: ='계산 명세'!R180 -> 0.30873255 | E22: ='계산 명세'!R181 -> 0.16017018 | F22: ='계산 명세'!R182 -> 0.22438678 | G22: ='계산 명세'!R183 -> 0.25027067 | H22: ='계산 명세'!R184 -> 0.24502748 | I22: ='계산 명세'!R185 -> 0.24462619 | J22: ='계산 명세'!R186 -> 0.20016475 | K22: ='계산 명세'!R187 -> 0.22657844 | L22: ='계산 명세'!R188 -> 0.22691925 | M22: ='계산 명세'!R189 -> 0.21630414 | N22: — | O22: =MEDIAN(D22:N22) -> 0.22674884 | P22: =MIN(D22:N22) -> 0.16017018 | Q22: =MAX(D22:N22) -> 0.30873255 | R22: =COUNTIF(D22:N22,">0.1") -> 10 | S22: =COUNT(D22:N22) -> 10 | T22: 전 기간 초과
A23: 20 | B23: 프록터앤드갬블 | C23: PG | D23: ='계산 명세'!R368 -> — | E23: ='계산 명세'!R369 -> 0.13149065 | F23: ='계산 명세'!R370 -> 0.11992158 | G23: ='계산 명세'!R371 -> 0.047131415 | H23: ='계산 명세'!R372 -> 0.18723456 | I23: ='계산 명세'!R373 -> 0.20776987 | J23: ='계산 명세'!R374 -> 0.20996057 | K23: ='계산 명세'!R375 -> 0.2014698 | L23: ='계산 명세'!R376 -> 0.20143302 | M23: ='계산 명세'!R377 -> 0.2161028 | N23: ='계산 명세'!R378 -> 0.20091644 | O23: =MEDIAN(D23:N23) -> 0.20117473 | P23: =MIN(D23:N23) -> 0.047131415 | Q23: =MAX(D23:N23) -> 0.2161028 | R23: =COUNTIF(D23:N23,">0.1") -> 9 | S23: =COUNT(D23:N23) -> 10 | T23: 대체로 초과
A24: 21 | B24: 애브비 | C24: ABBV | D24: ='계산 명세'!R236 -> 0.22653177 | E24: ='계산 명세'!R237 -> 0.19365123 | F24: ='계산 명세'!R238 -> 0.21472937 | G24: ='계산 명세'!R239 -> 0.57239499 | H24: ='계산 명세'!R240 -> 0.19751615 | I24: ='계산 명세'!R241 -> 0.18427986 | J24: ='계산 명세'!R242 -> 0.20730663 | K24: ='계산 명세'!R243 -> 0.1550548 | L24: ='계산 명세'!R244 -> 0.14239208 | M24: ='계산 명세'!R245 -> 0.15606069 | N24: — | O24: =MEDIAN(D24:N24) -> 0.19558369 | P24: =MIN(D24:N24) -> 0.14239208 | Q24: =MAX(D24:N24) -> 0.57239499 | R24: =COUNTIF(D24:N24,">0.1") -> 10 | S24: =COUNT(D24:N24) -> 10 | T24: 전 기간 초과
A25: 22 | B25: 넷플릭스 | C25: NFLX | D25: ='계산 명세'!R391 -> 0.082542055 | E25: ='계산 명세'!R392 -> 0.13773886 | F25: ='계산 명세'!R393 -> 0.15999266 | G25: ='계산 명세'!R394 -> 0.16188264 | H25: ='계산 명세'!R395 -> 0.21690532 | I25: ='계산 명세'!R396 -> 0.24469037 | J25: ='계산 명세'!R397 -> 0.17725326 | K25: ='계산 명세'!R398 -> 0.21249354 | L25: ='계산 명세'!R399 -> 0.31009653 | M25: ='계산 명세'!R400 -> 0.36656571 | N25: — | O25: =MEDIAN(D25:N25) -> 0.1948734 | P25: =MIN(D25:N25) -> 0.082542055 | Q25: =MAX(D25:N25) -> 0.36656571 | R25: =COUNTIF(D25:N25,">0.1") -> 9 | S25: =COUNT(D25:N25) -> 10 | T25: 대체로 초과
A26: 23 | B26: 오라클 | C26: ORCL | D26: ='계산 명세'!R258 -> — | E26: ='계산 명세'!R259 -> 0.25254154 | F26: ='계산 명세'!R260 -> 0.18254886 | G26: ='계산 명세'!R261 -> 0.26423135 | H26: ='계산 명세'!R262 -> 0.26788287 | I26: ='계산 명세'!R263 -> 0.2831159 | J26: ='계산 명세'!R264 -> 0.18798545 | K26: ='계산 명세'!R265 -> 0.15908258 | L26: ='계산 명세'!R266 -> 0.14499806 | M26: ='계산 명세'!R267 -> 0.1487437 | N26: ='계산 명세'!R268 -> 0.133961 | O26: =MEDIAN(D26:N26) -> 0.18526715 | P26: =MIN(D26:N26) -> 0.133961 | Q26: =MAX(D26:N26) -> 0.2831159 | R26: =COUNTIF(D26:N26,">0.1") -> 10 | S26: =COUNT(D26:N26) -> 10 | T26: 전 기간 초과
A27: 24 | B27: 마이크론 테크놀로지 | C27: MU | D27: ='계산 명세'!R113 -> — | E27: ='계산 명세'!R114 -> 0.25562179 | F27: ='계산 명세'!R115 -> 0.50714921 | G27: ='계산 명세'!R116 -> 0.20256911 | H27: ='계산 명세'!R117 -> 0.075416008 | I27: ='계산 명세'!R118 -> 0.14791151 | J27: ='계산 명세'!R119 -> 0.19656191 | K27: ='계산 명세'!R120 -> -0.095209675 | L27: ='계산 명세'!R121 -> 0.016885215 | M27: ='계산 명세'!R122 -> 0.15860247 | N27: ='계산 명세'!R123 -> 1.0674708 | O27: =MEDIAN(D27:N27) -> 0.17758219 | P27: =MIN(D27:N27) -> -0.095209675 | Q27: =MAX(D27:N27) -> 1.0674708 | R27: =COUNTIF(D27:N27,">0.1") -> 7 | S27: =COUNT(D27:N27) -> 10 | T27: 절반 이상 초과
A28: 25 | B28: 캐터필러 | C28: CAT | D28: ='계산 명세'!R302 -> 0.018169972 | E28: ='계산 명세'!R303 -> 0.076055137 | F28: ='계산 명세'!R304 -> 0.18254742 | G28: ='계산 명세'!R305 -> 0.17225952 | H28: ='계산 명세'!R306 -> 0.094845956 | I28: ='계산 명세'!R307 -> 0.14895879 | J28: ='계산 명세'!R308 -> 0.15234682 | K28: ='계산 명세'!R309 -> 0.2482518 | L28: ='계산 명세'!R310 -> 0.24426784 | M28: ='계산 명세'!R311 -> 0.1844791 | N28: — | O28: =MEDIAN(D28:N28) -> 0.16230317 | P28: =MIN(D28:N28) -> 0.018169972 | Q28: =MAX(D28:N28) -> 0.2482518 | R28: =COUNTIF(D28:N28,">0.1") -> 7 | S28: =COUNT(D28:N28) -> 10 | T28: 절반 이상 초과
A29: 26 | B29: 델 테크놀로지스 | C29: DELL | D29: ='계산 명세'!R436 -> -0.07635391 | E29: ='계산 명세'!R437 -> -0.034160328 | F29: ='계산 명세'!R438 -> -0.0031392905 | G29: — | H29: ='계산 명세'!R440 -> 0.085513459 | I29: ='계산 명세'!R441 -> 0.15529525 | J29: ='계산 명세'!R442 -> 0.28463966 | K29: ='계산 명세'!R443 -> 0.28570158 | L29: ='계산 명세'!R444 -> 0.34324899 | M29: ='계산 명세'!R445 -> 0.39348468 | N29: — | O29: =MEDIAN(D29:N29) -> 0.15529525 | P29: =MIN(D29:N29) -> -0.07635391 | Q29: =MAX(D29:N29) -> 0.39348468 | R29: =COUNTIF(D29:N29,">0.1") -> 5 | S29: =COUNT(D29:N29) -> 9 | T29: 절반 이상 초과
A30: 27 | B30: 코카콜라 | C30: KO | D30: ='계산 명세'!R324 -> 0.13304771 | E30: ='계산 명세'!R325 -> 0.091557541 | F30: ='계산 명세'!R326 -> 0.14070134 | G30: ='계산 명세'!R327 -> 0.15658795 | H30: ='계산 명세'!R328 -> 0.12867501 | I30: ='계산 명세'!R329 -> 0.14497571 | J30: ='계산 명세'!R330 -> 0.16082777 | K30: ='계산 명세'!R331 -> 0.16804101 | L30: ='계산 명세'!R332 -> 0.14200603 | M30: ='계산 명세'!R333 -> 0.18297308 | N30: — | O30: =MEDIAN(D30:N30) -> 0.14349087 | P30: =MIN(D30:N30) -> 0.091557541 | Q30: =MAX(D30:N30) -> 0.18297308 | R30: =COUNTIF(D30:N30,">0.1") -> 9 | S30: =COUNT(D30:N30) -> 10 | T30: 대체로 초과
A31: 28 | B31: 월마트 | C31: WMT | D31: ='계산 명세'!R136 -> 0.13936391 | E31: ='계산 명세'!R137 -> 0.12940313 | F31: ='계산 명세'!R138 -> 0.12217909 | G31: ='계산 명세'!R139 -> 0.1303518 | H31: ='계산 명세'!R140 -> 0.12775837 | I31: ='계산 명세'!R141 -> 0.16900806 | J31: ='계산 명세'!R142 -> 0.11851569 | K31: ='계산 명세'!R143 -> 0.17190601 | L31: ='계산 명세'!R144 -> 0.18397155 | M31: ='계산 명세'!R145 -> 0.17491847 | N31: — | O31: =MEDIAN(D31:N31) -> 0.13485785 | P31: =MIN(D31:N31) -> 0.11851569 | Q31: =MAX(D31:N31) -> 0.18397155 | R31: =COUNTIF(D31:N31,">0.1") -> 10 | S31: =COUNT(D31:N31) -> 10 | T31: 전 기간 초과
A32: 29 | B32: 인텔 | C32: INTC | D32: ='계산 명세'!R191 -> 0.14106231 | E32: ='계산 명세'!R192 -> 0.12452355 | F32: ='계산 명세'!R193 -> 0.22596088 | G32: ='계산 명세'!R194 -> 0.19637072 | H32: ='계산 명세'!R195 -> 0.18747045 | I32: ='계산 명세'!R196 -> 0.16683123 | J32: ='계산 명세'!R197 -> 0.020044477 | K32: ='계산 명세'!R198 -> 0.00070343477 | L32: ='계산 명세'!R199 -> -0.069059728 | M32: ='계산 명세'!R200 -> -0.0098946036 | N32: — | O32: =MEDIAN(D32:N32) -> 0.13279293 | P32: =MIN(D32:N32) -> -0.069059728 | Q32: =MAX(D32:N32) -> 0.22596088 | R32: =COUNTIF(D32:N32,">0.1") -> 6 | S32: =COUNT(D32:N32) -> 10 | T32: 절반 이상 초과
A33: 30 | B33: 머크 | C33: MRK | D33: ='계산 명세'!R380 -> 0.07545999 | E33: ='계산 명세'!R381 -> 0.071309291 | F33: ='계산 명세'!R382 -> 0.12620176 | G33: ='계산 명세'!R383 -> 0.13428033 | H33: ='계산 명세'!R384 -> 0.084288943 | I33: ='계산 명세'!R385 -> 0.19862047 | J33: ='계산 명세'!R386 -> 0.24997715 | K33: ='계산 명세'!R387 -> 0.021871711 | L33: ='계산 명세'!R388 -> 0.25272105 | M33: ='계산 명세'!R389 -> 0.23404889 | N33: — | O33: =MEDIAN(D33:N33) -> 0.13024105 | P33: =MIN(D33:N33) -> 0.021871711 | Q33: =MAX(D33:N33) -> 0.25272105 | R33: =COUNTIF(D33:N33,">0.1") -> 6 | S33: =COUNT(D33:N33) -> 10 | T33: 절반 이상 초과
A34: 31 | B34: IBM | C34: IBM | D34: ='계산 명세'!R510 -> 0.25087619 | E34: ='계산 명세'!R511 -> 0.13863195 | F34: ='계산 명세'!R512 -> 0.18067919 | G34: ='계산 명세'!R513 -> 0.12188443 | H34: ='계산 명세'!R514 -> 0.046477731 | I34: ='계산 명세'!R515 -> 0.077939646 | J34: ='계산 명세'!R516 -> 0.032042887 | K34: ='계산 명세'!R517 -> 0.12509172 | L34: ='계산 명세'!R518 -> 0.09772321 | M34: ='계산 명세'!R519 -> 0.14533699 | N34: — | O34: =MEDIAN(D34:N34) -> 0.12348807 | P34: =MIN(D34:N34) -> 0.032042887 | Q34: =MAX(D34:N34) -> 0.25087619 | R34: =COUNTIF(D34:N34,">0.1") -> 6 | S34: =COUNT(D34:N34) -> 10 | T34: 절반 이상 초과
A35: 32 | B35: 브로드컴 | C35: AVGO | D35: ='계산 명세'!R58 -> -0.017205922 | E35: ='계산 명세'!R59 -> 0.093251775 | F35: ='계산 명세'!R60 -> 0.14037322 | G35: ='계산 명세'!R61 -> 0.070422626 | H35: ='계산 명세'!R62 -> 0.068894931 | I35: ='계산 명세'!R63 -> 0.14680338 | J35: ='계산 명세'!R64 -> 0.25716694 | K35: ='계산 명세'!R65 -> 0.30616223 | L35: ='계산 명세'!R66 -> 0.094539656 | M35: ='계산 명세'!R67 -> 0.18593531 | N35: — | O35: =MEDIAN(D35:N35) -> 0.11745644 | P35: =MIN(D35:N35) -> -0.017205922 | Q35: =MAX(D35:N35) -> 0.30616223 | R35: =COUNTIF(D35:N35,">0.1") -> 5 | S35: =COUNT(D35:N35) -> 10 | T35: 절반 이상 초과
A36: 33 | B36: AMD | C36: AMD | D36: ='계산 명세'!R147 -> -0.29764646 | E36: ='계산 명세'!R148 -> 0.1380055 | F36: ='계산 명세'!R149 -> 0.39561404 | G36: ='계산 명세'!R150 -> 0.36493165 | H36: ='계산 명세'!R151 -> 0.45737647 | I36: ='계산 명세'!R152 -> 0.77701918 | J36: ='계산 명세'!R153 -> 0.04322223 | K36: ='계산 명세'!R154 -> 0.0073295558 | L36: ='계산 명세'!R155 -> 0.028891331 | M36: ='계산 명세'!R156 -> 0.063906543 | N36: — | O36: =MEDIAN(D36:N36) -> 0.10095602 | P36: =MIN(D36:N36) -> -0.29764646 | Q36: =MAX(D36:N36) -> 0.77701918 | R36: =COUNTIF(D36:N36,">0.1") -> 5 | S36: =COUNT(D36:N36) -> 10 | T36: 절반 이상 초과
A37: 34 | B37: 테슬라 | C37: TSLA | D37: ='계산 명세'!R80 -> -0.090593159 | E37: ='계산 명세'!R81 -> -0.121608 | F37: ='계산 명세'!R82 -> -0.023778899 | G37: ='계산 명세'!R83 -> -0.0043094875 | H37: ='계산 명세'!R84 -> 0.12540644 | I37: ='계산 명세'!R85 -> 0.39065549 | J37: ='계산 명세'!R86 -> 0.5981238 | K37: ='계산 명세'!R87 -> 0.27563144 | L37: ='계산 명세'!R88 -> 0.14155947 | M37: ='계산 명세'!R89 -> 0.072356997 | N37: — | O37: =MEDIAN(D37:N37) -> 0.098881721 | P37: =MIN(D37:N37) -> -0.121608 | Q37: =MAX(D37:N37) -> 0.5981238 | R37: =COUNTIF(D37:N37,">0.1") -> 5 | S37: =COUNT(D37:N37) -> 10 | T37: 절반 이상 초과
A38: 35 | B38: 엑슨모빌 | C38: XOM | D38: ='계산 명세'!R169 -> 0.037759727 | E38: ='계산 명세'!R170 -> 0.082318672 | F38: ='계산 명세'!R171 -> 0.094094381 | G38: ='계산 명세'!R172 -> 0.064377689 | H38: ='계산 명세'!R173 -> -0.093333163 | I38: ='계산 명세'!R174 -> 0.10941009 | J38: ='계산 명세'!R175 -> 0.26863067 | K38: ='계산 명세'!R176 -> 0.16858854 | L38: ='계산 명세'!R177 -> 0.1397946 | M38: ='계산 명세'!R178 -> 0.10258321 | N38: — | O38: =MEDIAN(D38:N38) -> 0.098338793 | P38: =MIN(D38:N38) -> -0.093333163 | Q38: =MAX(D38:N38) -> 0.26863067 | R38: =COUNTIF(D38:N38,">0.1") -> 5 | S38: =COUNT(D38:N38) -> 10 | T38: 절반 이상 초과
A39: 36 | B39: 셰브론 | C39: CVX | D39: ='계산 명세'!R346 -> -0.0080651524 | E39: ='계산 명세'!R347 -> 0.046667354 | F39: ='계산 명세'!R348 -> 0.080257196 | G39: ='계산 명세'!R349 -> 0.020792039 | H39: ='계산 명세'!R350 -> -0.029967995 | I39: ='계산 명세'!R351 -> 0.091391774 | J39: ='계산 명세'!R352 -> 0.20970839 | K39: ='계산 명세'!R353 -> 0.12471042 | L39: ='계산 명세'!R354 -> 0.10164669 | M39: ='계산 명세'!R355 -> 0.064144067 | N39: — | O39: =MEDIAN(D39:N39) -> 0.072200631 | P39: =MIN(D39:N39) -> -0.029967995 | Q39: =MAX(D39:N39) -> 0.20970839 | R39: =COUNTIF(D39:N39,">0.1") -> 3 | S39: =COUNT(D39:N39) -> 10 | T39: 대부분 미달
A40: 37 | B40: RTX | C40: RTX | D40: ='계산 명세'!R402 -> 0.14221698 | E40: ='계산 명세'!R403 -> 0.1076375 | F40: ='계산 명세'!R404 -> 0.026080453 | G40: ='계산 명세'!R405 -> 0.053524067 | H40: ='계산 명세'!R406 -> -0.016717001 | I40: ='계산 명세'!R407 -> 0.04310354 | J40: ='계산 명세'!R408 -> 0.048797841 | K40: ='계산 명세'!R409 -> 0.031854239 | L40: ='계산 명세'!R410 -> 0.054347516 | M40: ='계산 명세'!R411 -> 0.077751746 | N40: — | O40: =MEDIAN(D40:N40) -> 0.051160954 | P40: =MIN(D40:N40) -> -0.016717001 | Q40: =MAX(D40:N40) -> 0.14221698 | R40: =COUNTIF(D40:N40,">0.1") -> 2 | S40: =COUNT(D40:N40) -> 10 | T40: 대부분 미달
A41: 38 | B41: 제너럴 일렉트릭 | C41: GE | D41: ='계산 명세'!R313 -> 0.017846027 | E41: ='계산 명세'!R314 -> -0.087783589 | F41: ='계산 명세'!R315 -> -0.17032338 | G41: ='계산 명세'!R316 -> -0.031629469 | H41: ='계산 명세'!R317 -> -0.092166714 | I41: ='계산 명세'!R318 -> -0.10340917 | J41: ='계산 명세'!R319 -> 0.013175846 | K41: ='계산 명세'!R320 -> 0.08737603 | L41: ='계산 명세'!R321 -> 0.15825181 | M41: ='계산 명세'!R322 -> 0.28024526 | N41: — | O41: =MEDIAN(D41:N41) -> -0.0092268118 | P41: =MIN(D41:N41) -> -0.17032338 | Q41: =MAX(D41:N41) -> 0.28024526 | R41: =COUNTIF(D41:N41,">0.1") -> 2 | S41: =COUNT(D41:N41) -> 10 | T41: 대부분 미달
A42: 39 | B42: 팔로알토 네트웍스 | C42: PANW | D42: ='계산 명세'!R413 -> — | E42: ='계산 명세'!R414 -> -0.76687354 | F42: — | G42: ='계산 명세'!R416 -> -0.20046435 | H42: ='계산 명세'!R417 -> -0.43423921 | I42: ='계산 명세'!R418 -> -0.34381252 | J42: ='계산 명세'!R419 -> -0.24618635 | K42: ='계산 명세'!R420 -> 0.3753796 | L42: ='계산 명세'!R421 -> 0.3298226 | M42: ='계산 명세'!R422 -> 0.23518966 | N42: ='계산 명세'!R423 -> 0.028424389 | O42: =MEDIAN(D42:N42) -> -0.20046435 | P42: =MIN(D42:N42) -> -0.76687354 | Q42: =MAX(D42:N42) -> 0.3753796 | R42: =COUNTIF(D42:N42,">0.1") -> 3 | S42: =COUNT(D42:N42) -> 9 | T42: 대부분 미달
A44: 표본 부족
A45: — | B45: 팔란티어 테크놀로지스 | C45: PLTR | D45: — | E45: — | F45: — | G45: — | H45: — | I45: — | J45: ='계산 명세'!R285 -> -14.534215 | K45: — | L45: — | M45: ='계산 명세'!R288 -> 4.3197829 | N45: — | O45: =MEDIAN(D45:N45) -> -5.1072159 | P45: =MIN(D45:N45) -> -14.534215 | Q45: =MAX(D45:N45) -> 4.3197829 | R45: =COUNTIF(D45:N45,">0.1") -> 1 | S45: =COUNT(D45:N45) -> 2 | T45: 절반 이상 초과
A46: — | B46: GE 버노바 | C46: GEV | D46: — | E46: — | F46: — | G46: — | H46: — | I46: — | J46: ='계산 명세'!R450 -> -0.23857338 | K46: ='계산 명세'!R451 -> -0.088309313 | L46: ='계산 명세'!R452 -> 0.06239668 | M46: ='계산 명세'!R453 -> 0.42208707 | N46: — | O46: =MEDIAN(D46:N46) -> -0.012956317 | P46: =MIN(D46:N46) -> -0.23857338 | Q46: =MAX(D46:N46) -> 0.42208707 | R46: =COUNTIF(D46:N46,">0.1") -> 1 | S46: =COUNT(D46:N46) -> 4 | T46: 대부분 미달
A48: 금융업 — ROIC 정의 부적합
A49: — | B49: 버크셔 해서웨이 | C49: BRK-B | D49: — | E49: — | F49: — | G49: — | H49: — | I49: — | J49: — | K49: — | L49: — | M49: — | N49: — | O49: — | P49: — | Q49: — | R49: — | S49: — | T49: 금융업 — ROIC 정의 부적합
A50: — | B50: JP모건 체이스 | C50: JPM | D50: — | E50: — | F50: — | G50: — | H50: — | I50: — | J50: — | K50: — | L50: — | M50: — | N50: — | O50: — | P50: — | Q50: — | R50: — | S50: — | T50: 금융업 — ROIC 정의 부적합
A51: — | B51: 뱅크오브아메리카 | C51: BAC | D51: — | E51: — | F51: — | G51: — | H51: — | I51: — | J51: — | K51: — | L51: — | M51: — | N51: — | O51: — | P51: — | Q51: — | R51: — | S51: — | T51: 금융업 — ROIC 정의 부적합
A52: — | B52: 유나이티드헬스 그룹 | C52: UNH | D52: — | E52: — | F52: — | G52: — | H52: — | I52: — | J52: — | K52: — | L52: — | M52: — | N52: — | O52: — | P52: — | Q52: — | R52: — | S52: — | T52: 금융업 — ROIC 정의 부적합
A53: — | B53: 모건스탠리 | C53: MS | D53: — | E53: — | F53: — | G53: — | H53: — | I53: — | J53: — | K53: — | L53: — | M53: — | N53: — | O53: — | P53: — | Q53: — | R53: — | S53: — | T53: 금융업 — ROIC 정의 부적합
A54: — | B54: 골드만삭스 | C54: GS | D54: — | E54: — | F54: — | G54: — | H54: — | I54: — | J54: — | K54: — | L54: — | M54: — | N54: — | O54: — | P54: — | Q54: — | R54: — | S54: — | T54: 금융업 — ROIC 정의 부적합
A55: — | B55: 웰스파고 | C55: WFC | D55: — | E55: — | F55: — | G55: — | H55: — | I55: — | J55: — | K55: — | L55: — | M55: — | N55: — | O55: — | P55: — | Q55: — | R55: — | S55: — | T55: 금융업 — ROIC 정의 부적합
A56: — | B56: 아메리칸 익스프레스 | C56: AXP | D56: — | E56: — | F56: — | G56: — | H56: — | I56: — | J56: — | K56: — | L56: — | M56: — | N56: — | O56: — | P56: — | Q56: — | R56: — | S56: — | T56: 금융업 — ROIC 정의 부적합
A57: — | B57: 씨티그룹 | C57: C | D57: — | E57: — | F57: — | G57: — | H57: — | I57: — | J57: — | K57: — | L57: — | M57: — | N57: — | O57: — | P57: — | Q57: — | R57: — | S57: — | T57: 금융업 — ROIC 정의 부적합

Sheet ROIC−WACC 스프레드
A1: ROIC에서 10%를 뺀 값. 0보다 크면 자본비용을 넘겨 가치를 창출한 해입니다.
A2: 순위 | B2: 기업 | C2: 티커 | D2: FY2016 | E2: FY2017 | F2: FY2018 | G2: FY2019 | H2: FY2020 | I2: FY2021 | J2: FY2022 | K2: FY2023 | L2: FY2024 | M2: FY2025 | N2: FY2026 | O2: 중위 | P2: 최소 | Q2: 최대 | R2: 10% 초과 연수 | S2: 산출 연수 | T2: 판정
A3: 순위 대상 (산출 5년 이상)
A4: 1 | B4: 아리스타 네트웍스 | C4: ANET | D4: ='계산 명세'!S478 -> 0.98616349 | E4: ='계산 명세'!S479 -> 2.1885491 | F4: ='계산 명세'!S480 -> 1.5561149 | G4: ='계산 명세'!S481 -> 4.1817166 | H4: ='계산 명세'!S482 -> 1.8455045 | I4: ='계산 명세'!S483 -> 1.5415471 | J4: ='계산 명세'!S484 -> 0.97359752 | K4: ='계산 명세'!S485 -> 0.85522267 | L4: ='계산 명세'!S486 -> 1.2182578 | M4: ='계산 명세'!S487 -> 1.8200796 | N4: — | O4: =MEDIAN(D4:N4) -> 1.548831 | P4: =MIN(D4:N4) -> 0.85522267 | Q4: =MAX(D4:N4) -> 4.1817166 | R4: =COUNTIF(D4:N4,">0") -> 10 | S4: =COUNT(D4:N4) -> 10 | T4: 전 기간 초과 · 매우 높음
A5: 2 | B5: 엔비디아 | C5: NVDA | D5: ='계산 명세'!S3 -> 1.6860208 | E5: ='계산 명세'!S4 -> 1.7509863 | F5: ='계산 명세'!S5 -> 1.0553069 | G5: ='계산 명세'!S6 -> 0.6436205 | H5: ='계산 명세'!S7 -> 0.45222215 | I5: ='계산 명세'!S8 -> 0.56601152 | J5: ='계산 명세'!S9 -> 0.12226653 | K5: ='계산 명세'!S10 -> 1.1490268 | L5: ='계산 명세'!S11 -> 1.8821923 | M5: ='계산 명세'!S12 -> 1.0082268 | N5: — | O5: =MEDIAN(D5:N5) -> 1.0317669 | P5: =MIN(D5:N5) -> 0.12226653 | Q5: =MAX(D5:N5) -> 1.8821923 | R5: =COUNTIF(D5:N5,">0") -> 10 | S5: =COUNT(D5:N5) -> 10 | T5: 전 기간 초과 · 매우 높음
A6: 3 | B6: 마스터카드 | C6: MA | D6: ='계산 명세'!S202 -> 1.517526 | E6: ='계산 명세'!S203 -> 1.3026209 | F6: ='계산 명세'!S204 -> 1.7186511 | G6: ='계산 명세'!S205 -> 1.4898454 | H6: ='계산 명세'!S206 -> 0.77088407 | I6: ='계산 명세'!S207 -> 0.67410625 | J6: ='계산 명세'!S208 -> 0.68754876 | K6: ='계산 명세'!S209 -> 0.76950339 | L6: ='계산 명세'!S210 -> 0.79324666 | M6: ='계산 명세'!S211 -> 0.85703638 | N6: — | O6: =MEDIAN(D6:N6) -> 0.82514152 | P6: =MIN(D6:N6) -> 0.67410625 | Q6: =MAX(D6:N6) -> 1.7186511 | R6: =COUNTIF(D6:N6,">0") -> 10 | S6: =COUNT(D6:N6) -> 10 | T6: 전 기간 초과 · 매우 높음
A7: 4 | B7: 애플 | C7: AAPL | D7: ='계산 명세'!S14 -> 0.20794128 | E7: ='계산 명세'!S15 -> 0.18596898 | F7: ='계산 명세'!S16 -> 0.2499434 | G7: ='계산 명세'!S17 -> 0.32428441 | H7: ='계산 명세'!S18 -> 0.51386135 | I7: ='계산 명세'!S19 -> 0.79108895 | J7: ='계산 명세'!S20 -> 0.70840103 | K7: ='계산 명세'!S21 -> 0.73272255 | L7: ='계산 명세'!S22 -> 0.79041021 | M7: ='계산 명세'!S23 -> 0.93915199 | N7: — | O7: =MEDIAN(D7:N7) -> 0.61113119 | P7: =MIN(D7:N7) -> 0.18596898 | Q7: =MAX(D7:N7) -> 0.93915199 | R7: =COUNTIF(D7:N7,">0") -> 10 | S7: =COUNT(D7:N7) -> 10 | T7: 전 기간 초과 · 매우 높음
A8: 5 | B8: 마이크로소프트 | C8: MSFT | D8: ='계산 명세'!S36 -> — | E8: ='계산 명세'!S37 -> 0.67036684 | F8: ='계산 명세'!S38 -> 0.53631909 | G8: ='계산 명세'!S39 -> 1.0713967 | H8: ='계산 명세'!S40 -> 0.93077666 | I8: ='계산 명세'!S41 -> 0.94868383 | J8: ='계산 명세'!S42 -> 0.69892226 | K8: ='계산 명세'!S43 -> 0.46526971 | L8: ='계산 명세'!S44 -> 0.36272339 | M8: ='계산 명세'!S45 -> 0.29457044 | N8: ='계산 명세'!S46 -> 0.2585794 | O8: =MEDIAN(D8:N8) -> 0.60334296 | P8: =MIN(D8:N8) -> 0.2585794 | Q8: =MAX(D8:N8) -> 1.0713967 | R8: =COUNTIF(D8:N8,">0") -> 10 | S8: =COUNT(D8:N8) -> 10 | T8: 전 기간 초과 · 매우 높음
A9: 6 | B9: 램리서치 | C9: LRCX | D9: ='계산 명세'!S290 -> — | E9: ='계산 명세'!S291 -> 0.42055414 | F9: ='계산 명세'!S292 -> 0.55722234 | G9: ='계산 명세'!S293 -> 0.48097307 | H9: ='계산 명세'!S294 -> 0.48903545 | I9: ='계산 명세'!S295 -> 0.74195609 | J9: ='계산 명세'!S296 -> 0.64328038 | K9: ='계산 명세'!S297 -> 0.4939825 | L9: ='계산 명세'!S298 -> 0.38425258 | M9: ='계산 명세'!S299 -> 0.58039171 | N9: ='계산 명세'!S300 -> 0.67721561 | O9: =MEDIAN(D9:N9) -> 0.52560242 | P9: =MIN(D9:N9) -> 0.38425258 | Q9: =MAX(D9:N9) -> 0.74195609 | R9: =COUNTIF(D9:N9,">0") -> 10 | S9: =COUNT(D9:N9) -> 10 | T9: 전 기간 초과 · 매우 높음
A10: 7 | B10: 필립모리스 인터내셔널 | C10: PM | D10: ='계산 명세'!S425 -> 0.47146557 | E10: ='계산 명세'!S426 -> 0.36965867 | F10: ='계산 명세'!S427 -> 0.48295306 | G10: ='계산 명세'!S428 -> 0.45735089 | H10: ='계산 명세'!S429 -> 0.54770167 | I10: ='계산 명세'!S430 -> 0.60607841 | J10: ='계산 명세'!S431 -> 0.3058536 | K10: ='계산 명세'!S432 -> 0.15995382 | L10: ='계산 명세'!S433 -> 0.20106487 | M10: ='계산 명세'!S434 -> 0.2540046 | N10: — | O10: =MEDIAN(D10:N10) -> 0.41350478 | P10: =MIN(D10:N10) -> 0.15995382 | Q10: =MAX(D10:N10) -> 0.60607841 | R10: =COUNTIF(D10:N10,">0") -> 10 | S10: =COUNT(D10:N10) -> 10 | T10: 전 기간 초과 · 매우 높음
A11: 8 | B11: KLA | C11: KLAC | D11: ='계산 명세'!S466 -> — | E11: ='계산 명세'!S467 -> 0.70700967 | F11: ='계산 명세'!S468 -> 0.7306849 | G11: ='계산 명세'!S469 -> 0.34209264 | H11: ='계산 명세'!S470 -> 0.18539867 | I11: ='계산 명세'!S471 -> 0.32946699 | J11: ='계산 명세'!S472 -> 0.45978314 | K11: ='계산 명세'!S473 -> 0.39316571 | L11: ='계산 명세'!S474 -> 0.25845898 | M11: ='계산 명세'!S475 -> 0.3814352 | N11: ='계산 명세'!S476 -> 0.39384768 | O11: =MEDIAN(D11:N11) -> 0.38730046 | P11: =MIN(D11:N11) -> 0.18539867 | Q11: =MAX(D11:N11) -> 0.7306849 | R11: =COUNTIF(D11:N11,">0") -> 10 | S11: =COUNT(D11:N11) -> 10 | T11: 전 기간 초과 · 매우 높음
A12: 9 | B12: 텍사스 인스트루먼츠 | C12: TXN | D12: ='계산 명세'!S455 -> 0.23025274 | E12: ='계산 명세'!S456 -> 0.25874926 | F12: ='계산 명세'!S457 -> 0.46665658 | G12: ='계산 명세'!S458 -> 0.42345662 | H12: ='계산 명세'!S459 -> 0.48491212 | I12: ='계산 명세'!S460 -> 0.65218905 | J12: ='계산 명세'!S461 -> 0.59141421 | K12: ='계산 명세'!S462 -> 0.28080197 | L12: ='계산 명세'!S463 -> 0.12652415 | M12: ='계산 명세'!S464 -> 0.11816561 | N12: — | O12: =MEDIAN(D12:N12) -> 0.3521293 | P12: =MIN(D12:N12) -> 0.11816561 | Q12: =MAX(D12:N12) -> 0.65218905 | R12: =COUNTIF(D12:N12,">0") -> 10 | S12: =COUNT(D12:N12) -> 10 | T12: 전 기간 초과 · 매우 높음
A13: 10 | B13: 메타 플랫폼스 | C13: META | D13: ='계산 명세'!S69 -> 0.26399523 | E13: ='계산 명세'!S70 -> 0.40116142 | F13: ='계산 명세'!S71 -> 0.47426782 | G13: ='계산 명세'!S72 -> 0.30061041 | H13: ='계산 명세'!S73 -> 0.4100437 | I13: ='계산 명세'!S74 -> 0.44362086 | J13: ='계산 명세'!S75 -> 0.17128611 | K13: ='계산 명세'!S76 -> 0.28339008 | L13: ='계산 명세'!S77 -> 0.41066109 | M13: ='계산 명세'!S78 -> 0.25720533 | N13: — | O13: =MEDIAN(D13:N13) -> 0.35088592 | P13: =MIN(D13:N13) -> 0.17128611 | Q13: =MAX(D13:N13) -> 0.47426782 | R13: =COUNTIF(D13:N13,">0") -> 10 | S13: =COUNT(D13:N13) -> 10 | T13: 전 기간 초과 · 매우 높음
A14: 11 | B14: 홈디포 | C14: HD | D14: ='계산 명세'!S357 -> 0.23732645 | E14: ='계산 명세'!S358 -> 0.26789009 | F14: ='계산 명세'!S359 -> 0.37053122 | G14: ='계산 명세'!S360 -> 0.36750761 | H14: ='계산 명세'!S361 -> 0.37051924 | I14: ='계산 명세'!S362 -> 0.40715712 | J14: ='계산 명세'!S363 -> 0.36879831 | K14: ='계산 명세'!S364 -> 0.29534415 | L14: ='계산 명세'!S365 -> 0.22926302 | M14: ='계산 명세'!S366 -> 0.15322002 | N14: — | O14: =MEDIAN(D14:N14) -> 0.33142588 | P14: =MIN(D14:N14) -> 0.15322002 | Q14: =MAX(D14:N14) -> 0.40715712 | R14: =COUNTIF(D14:N14,">0") -> 10 | S14: =COUNT(D14:N14) -> 10 | T14: 전 기간 초과 · 매우 높음
A15: 12 | B15: 어플라이드 머티리얼즈 | C15: AMAT | D15: ='계산 명세'!S247 -> 0.15951577 | E15: ='계산 명세'!S248 -> 0.39561827 | F15: ='계산 명세'!S249 -> 0.29331553 | G15: ='계산 명세'!S250 -> 0.2075528 | H15: ='계산 명세'!S251 -> 0.27548855 | I15: ='계산 명세'!S252 -> 0.43183698 | J15: ='계산 명세'!S253 -> 0.38973181 | K15: ='계산 명세'!S254 -> 0.35172265 | L15: ='계산 명세'!S255 -> 0.33933313 | M15: ='계산 명세'!S256 -> 0.25869747 | N15: — | O15: =MEDIAN(D15:N15) -> 0.31632433 | P15: =MIN(D15:N15) -> 0.15951577 | Q15: =MAX(D15:N15) -> 0.43183698 | R15: =COUNTIF(D15:N15,">0") -> 10 | S15: =COUNT(D15:N15) -> 10 | T15: 전 기간 초과 · 매우 높음
A16: 13 | B16: 알파벳 | C16: GOOG | D16: ='계산 명세'!S25 -> 0.25057615 | E16: ='계산 명세'!S26 -> 0.18246592 | F16: ='계산 명세'!S27 -> 0.28155484 | G16: ='계산 명세'!S28 -> 0.27515751 | H16: ='계산 명세'!S29 -> 0.27023344 | I16: ='계산 명세'!S30 -> 0.47965865 | J16: ='계산 명세'!S31 -> 0.34332262 | K16: ='계산 명세'!S32 -> 0.32386488 | L16: ='계산 명세'!S33 -> 0.337885 | M16: ='계산 명세'!S34 -> 0.26991734 | N16: — | O16: =MEDIAN(D16:N16) -> 0.27835618 | P16: =MIN(D16:N16) -> 0.18246592 | Q16: =MAX(D16:N16) -> 0.47965865 | R16: =COUNTIF(D16:N16,">0") -> 10 | S16: =COUNT(D16:N16) -> 10 | T16: 전 기간 초과 · 매우 높음
A17: 14 | B17: 코스트코 | C17: COST | D17: ='계산 명세'!S270 -> — | E17: ='계산 명세'!S271 -> 0.12346643 | F17: ='계산 명세'!S272 -> 0.16301849 | G17: ='계산 명세'!S273 -> 0.19012249 | H17: ='계산 명세'!S274 -> 0.21652762 | I17: ='계산 명세'!S275 -> 0.28574264 | J17: ='계산 명세'!S276 -> 0.29622213 | K17: ='계산 명세'!S277 -> 0.26989819 | L17: ='계산 명세'!S278 -> 0.30527765 | M17: ='계산 명세'!S279 -> 0.30866036 | N17: ='계산 명세'!S280 -> 0.33636596 | O17: =MEDIAN(D17:N17) -> 0.27782042 | P17: =MIN(D17:N17) -> 0.12346643 | Q17: =MAX(D17:N17) -> 0.33636596 | R17: =COUNTIF(D17:N17,">0") -> 10 | S17: =COUNT(D17:N17) -> 10 | T17: 전 기간 초과 · 매우 높음
A18: 15 | B18: 시스코 시스템즈 | C18: CSCO | D18: ='계산 명세'!S213 -> — | E18: ='계산 명세'!S214 -> 0.23540271 | F18: ='계산 명세'!S215 -> 0.18632795 | G18: ='계산 명세'!S216 -> 0.38206189 | H18: ='계산 명세'!S217 -> 0.35641847 | I18: ='계산 명세'!S218 -> 0.29902668 | J18: ='계산 명세'!S219 -> 0.29096855 | K18: ='계산 명세'!S220 -> 0.3371918 | L18: ='계산 명세'!S221 -> 0.14130883 | M18: ='계산 명세'!S222 -> 0.081338646 | N18: ='계산 명세'!S223 -> 0.1023031 | O18: =MEDIAN(D18:N18) -> 0.26318563 | P18: =MIN(D18:N18) -> 0.081338646 | Q18: =MAX(D18:N18) -> 0.38206189 | R18: =COUNTIF(D18:N18,">0") -> 10 | S18: =COUNT(D18:N18) -> 10 | T18: 전 기간 초과 · 매우 높음
A19: 16 | B19: 비자 | C19: V | D19: ='계산 명세'!S158 -> 0.084723905 | E19: ='계산 명세'!S159 -> 0.087556951 | F19: ='계산 명세'!S160 -> 0.1713166 | G19: ='계산 명세'!S161 -> 0.21017027 | H19: ='계산 명세'!S162 -> 0.17789653 | I19: ='계산 명세'!S163 -> 0.20115233 | J19: ='계산 명세'!S164 -> 0.29001372 | K19: ='계산 명세'!S165 -> 0.33887194 | L19: ='계산 명세'!S166 -> 0.36450313 | M19: ='계산 명세'!S167 -> 0.34761401 | N19: — | O19: =MEDIAN(D19:N19) -> 0.2056613 | P19: =MIN(D19:N19) -> 0.084723905 | Q19: =MAX(D19:N19) -> 0.36450313 | R19: =COUNTIF(D19:N19,">0") -> 10 | S19: =COUNT(D19:N19) -> 10 | T19: 전 기간 초과 · 매우 높음
A20: 17 | B20: 아마존 | C20: AMZN | D20: ='계산 명세'!S48 -> 1.1959004 | E20: ='계산 명세'!S49 -> 0.17742466 | F20: ='계산 명세'!S50 -> 0.35559076 | G20: ='계산 명세'!S51 -> 0.3097221 | H20: ='계산 명세'!S52 -> 0.44755281 | I20: ='계산 명세'!S53 -> 0.22294247 | J20: ='계산 명세'!S54 -> -0.019405951 | K20: ='계산 명세'!S55 -> 0.081324847 | L20: ='계산 명세'!S56 -> 0.17946104 | M20: ='계산 명세'!S57 -> 0.11449257 | N20: — | O20: =MEDIAN(D20:N20) -> 0.20120176 | P20: =MIN(D20:N20) -> -0.019405951 | Q20: =MAX(D20:N20) -> 1.1959004 | R20: =COUNTIF(D20:N20,">0") -> 9 | S20: =COUNT(D20:N20) -> 10 | T20: 대체로 초과
A21: 18 | B21: 일라이 릴리 | C21: LLY | D21: ='계산 명세'!S102 -> 0.045133225 | E21: ='계산 명세'!S103 -> -0.032526103 | F21: ='계산 명세'!S104 -> 0.094721906 | G21: ='계산 명세'!S105 -> 0.19826975 | H21: ='계산 명세'!S106 -> 0.20245991 | I21: ='계산 명세'!S107 -> 0.18208922 | J21: ='계산 명세'!S108 -> 0.17866143 | K21: ='계산 명세'!S109 -> 0.078127524 | L21: ='계산 명세'!S110 -> 0.1774587 | M21: ='계산 명세'!S111 -> 0.29709146 | N21: — | O21: =MEDIAN(D21:N21) -> 0.17806007 | P21: =MIN(D21:N21) -> -0.032526103 | Q21: =MAX(D21:N21) -> 0.29709146 | R21: =COUNTIF(D21:N21,">0") -> 9 | S21: =COUNT(D21:N21) -> 10 | T21: 대체로 초과
A22: 19 | B22: 존슨앤드존슨 | C22: JNJ | D22: ='계산 명세'!S180 -> 0.20873255 | E22: ='계산 명세'!S181 -> 0.060170184 | F22: ='계산 명세'!S182 -> 0.12438678 | G22: ='계산 명세'!S183 -> 0.15027067 | H22: ='계산 명세'!S184 -> 0.14502748 | I22: ='계산 명세'!S185 -> 0.14462619 | J22: ='계산 명세'!S186 -> 0.10016475 | K22: ='계산 명세'!S187 -> 0.12657844 | L22: ='계산 명세'!S188 -> 0.12691925 | M22: ='계산 명세'!S189 -> 0.11630414 | N22: — | O22: =MEDIAN(D22:N22) -> 0.12674884 | P22: =MIN(D22:N22) -> 0.060170184 | Q22: =MAX(D22:N22) -> 0.20873255 | R22: =COUNTIF(D22:N22,">0") -> 10 | S22: =COUNT(D22:N22) -> 10 | T22: 전 기간 초과
A23: 20 | B23: 프록터앤드갬블 | C23: PG | D23: ='계산 명세'!S368 -> — | E23: ='계산 명세'!S369 -> 0.031490654 | F23: ='계산 명세'!S370 -> 0.019921584 | G23: ='계산 명세'!S371 -> -0.052868585 | H23: ='계산 명세'!S372 -> 0.087234558 | I23: ='계산 명세'!S373 -> 0.10776987 | J23: ='계산 명세'!S374 -> 0.10996057 | K23: ='계산 명세'!S375 -> 0.1014698 | L23: ='계산 명세'!S376 -> 0.10143302 | M23: ='계산 명세'!S377 -> 0.1161028 | N23: ='계산 명세'!S378 -> 0.10091644 | O23: =MEDIAN(D23:N23) -> 0.10117473 | P23: =MIN(D23:N23) -> -0.052868585 | Q23: =MAX(D23:N23) -> 0.1161028 | R23: =COUNTIF(D23:N23,">0") -> 9 | S23: =COUNT(D23:N23) -> 10 | T23: 대체로 초과
A24: 21 | B24: 애브비 | C24: ABBV | D24: ='계산 명세'!S236 -> 0.12653177 | E24: ='계산 명세'!S237 -> 0.093651227 | F24: ='계산 명세'!S238 -> 0.11472937 | G24: ='계산 명세'!S239 -> 0.47239499 | H24: ='계산 명세'!S240 -> 0.097516147 | I24: ='계산 명세'!S241 -> 0.084279861 | J24: ='계산 명세'!S242 -> 0.10730663 | K24: ='계산 명세'!S243 -> 0.0550548 | L24: ='계산 명세'!S244 -> 0.04239208 | M24: ='계산 명세'!S245 -> 0.056060689 | N24: — | O24: =MEDIAN(D24:N24) -> 0.095583687 | P24: =MIN(D24:N24) -> 0.04239208 | Q24: =MAX(D24:N24) -> 0.47239499 | R24: =COUNTIF(D24:N24,">0") -> 10 | S24: =COUNT(D24:N24) -> 10 | T24: 전 기간 초과
A25: 22 | B25: 넷플릭스 | C25: NFLX | D25: ='계산 명세'!S391 -> -0.017457945 | E25: ='계산 명세'!S392 -> 0.037738858 | F25: ='계산 명세'!S393 -> 0.059992662 | G25: ='계산 명세'!S394 -> 0.061882639 | H25: ='계산 명세'!S395 -> 0.11690532 | I25: ='계산 명세'!S396 -> 0.14469037 | J25: ='계산 명세'!S397 -> 0.077253262 | K25: ='계산 명세'!S398 -> 0.11249354 | L25: ='계산 명세'!S399 -> 0.21009653 | M25: ='계산 명세'!S400 -> 0.26656571 | N25: — | O25: =MEDIAN(D25:N25) -> 0.094873401 | P25: =MIN(D25:N25) -> -0.017457945 | Q25: =MAX(D25:N25) -> 0.26656571 | R25: =COUNTIF(D25:N25,">0") -> 9 | S25: =COUNT(D25:N25) -> 10 | T25: 대체로 초과
A26: 23 | B26: 오라클 | C26: ORCL | D26: ='계산 명세'!S258 -> — | E26: ='계산 명세'!S259 -> 0.15254154 | F26: ='계산 명세'!S260 -> 0.082548858 | G26: ='계산 명세'!S261 -> 0.16423135 | H26: ='계산 명세'!S262 -> 0.16788287 | I26: ='계산 명세'!S263 -> 0.1831159 | J26: ='계산 명세'!S264 -> 0.087985452 | K26: ='계산 명세'!S265 -> 0.059082583 | L26: ='계산 명세'!S266 -> 0.044998057 | M26: ='계산 명세'!S267 -> 0.048743696 | N26: ='계산 명세'!S268 -> 0.033961002 | O26: =MEDIAN(D26:N26) -> 0.085267155 | P26: =MIN(D26:N26) -> 0.033961002 | Q26: =MAX(D26:N26) -> 0.1831159 | R26: =COUNTIF(D26:N26,">0") -> 10 | S26: =COUNT(D26:N26) -> 10 | T26: 전 기간 초과
A27: 24 | B27: 마이크론 테크놀로지 | C27: MU | D27: ='계산 명세'!S113 -> — | E27: ='계산 명세'!S114 -> 0.15562179 | F27: ='계산 명세'!S115 -> 0.40714921 | G27: ='계산 명세'!S116 -> 0.10256911 | H27: ='계산 명세'!S117 -> -0.024583992 | I27: ='계산 명세'!S118 -> 0.04791151 | J27: ='계산 명세'!S119 -> 0.09656191 | K27: ='계산 명세'!S120 -> -0.19520968 | L27: ='계산 명세'!S121 -> -0.083114785 | M27: ='계산 명세'!S122 -> 0.058602466 | N27: ='계산 명세'!S123 -> 0.96747083 | O27: =MEDIAN(D27:N27) -> 0.077582188 | P27: =MIN(D27:N27) -> -0.19520968 | Q27: =MAX(D27:N27) -> 0.96747083 | R27: =COUNTIF(D27:N27,">0") -> 7 | S27: =COUNT(D27:N27) -> 10 | T27: 절반 이상 초과
A28: 25 | B28: 캐터필러 | C28: CAT | D28: ='계산 명세'!S302 -> -0.081830028 | E28: ='계산 명세'!S303 -> -0.023944863 | F28: ='계산 명세'!S304 -> 0.082547418 | G28: ='계산 명세'!S305 -> 0.072259517 | H28: ='계산 명세'!S306 -> -0.0051540439 | I28: ='계산 명세'!S307 -> 0.048958792 | J28: ='계산 명세'!S308 -> 0.052346822 | K28: ='계산 명세'!S309 -> 0.1482518 | L28: ='계산 명세'!S310 -> 0.14426784 | M28: ='계산 명세'!S311 -> 0.084479098 | N28: — | O28: =MEDIAN(D28:N28) -> 0.06230317 | P28: =MIN(D28:N28) -> -0.081830028 | Q28: =MAX(D28:N28) -> 0.1482518 | R28: =COUNTIF(D28:N28,">0") -> 7 | S28: =COUNT(D28:N28) -> 10 | T28: 절반 이상 초과
A29: 26 | B29: 델 테크놀로지스 | C29: DELL | D29: ='계산 명세'!S436 -> -0.17635391 | E29: ='계산 명세'!S437 -> -0.13416033 | F29: ='계산 명세'!S438 -> -0.10313929 | G29: — | H29: ='계산 명세'!S440 -> -0.014486541 | I29: ='계산 명세'!S441 -> 0.055295249 | J29: ='계산 명세'!S442 -> 0.18463966 | K29: ='계산 명세'!S443 -> 0.18570158 | L29: ='계산 명세'!S444 -> 0.24324899 | M29: ='계산 명세'!S445 -> 0.29348468 | N29: — | O29: =MEDIAN(D29:N29) -> 0.055295249 | P29: =MIN(D29:N29) -> -0.17635391 | Q29: =MAX(D29:N29) -> 0.29348468 | R29: =COUNTIF(D29:N29,">0") -> 5 | S29: =COUNT(D29:N29) -> 9 | T29: 절반 이상 초과
A30: 27 | B30: 코카콜라 | C30: KO | D30: ='계산 명세'!S324 -> 0.033047712 | E30: ='계산 명세'!S325 -> -0.0084424592 | F30: ='계산 명세'!S326 -> 0.040701345 | G30: ='계산 명세'!S327 -> 0.056587949 | H30: ='계산 명세'!S328 -> 0.028675013 | I30: ='계산 명세'!S329 -> 0.044975705 | J30: ='계산 명세'!S330 -> 0.060827771 | K30: ='계산 명세'!S331 -> 0.06804101 | L30: ='계산 명세'!S332 -> 0.04200603 | M30: ='계산 명세'!S333 -> 0.082973078 | N30: — | O30: =MEDIAN(D30:N30) -> 0.043490867 | P30: =MIN(D30:N30) -> -0.0084424592 | Q30: =MAX(D30:N30) -> 0.082973078 | R30: =COUNTIF(D30:N30,">0") -> 9 | S30: =COUNT(D30:N30) -> 10 | T30: 대체로 초과
A31: 28 | B31: 월마트 | C31: WMT | D31: ='계산 명세'!S136 -> 0.039363909 | E31: ='계산 명세'!S137 -> 0.02940313 | F31: ='계산 명세'!S138 -> 0.022179088 | G31: ='계산 명세'!S139 -> 0.030351796 | H31: ='계산 명세'!S140 -> 0.027758372 | I31: ='계산 명세'!S141 -> 0.069008063 | J31: ='계산 명세'!S142 -> 0.018515693 | K31: ='계산 명세'!S143 -> 0.071906014 | L31: ='계산 명세'!S144 -> 0.083971555 | M31: ='계산 명세'!S145 -> 0.074918474 | N31: — | O31: =MEDIAN(D31:N31) -> 0.034857852 | P31: =MIN(D31:N31) -> 0.018515693 | Q31: =MAX(D31:N31) -> 0.083971555 | R31: =COUNTIF(D31:N31,">0") -> 10 | S31: =COUNT(D31:N31) -> 10 | T31: 전 기간 초과
A32: 29 | B32: 인텔 | C32: INTC | D32: ='계산 명세'!S191 -> 0.041062308 | E32: ='계산 명세'!S192 -> 0.024523551 | F32: ='계산 명세'!S193 -> 0.12596088 | G32: ='계산 명세'!S194 -> 0.096370719 | H32: ='계산 명세'!S195 -> 0.087470452 | I32: ='계산 명세'!S196 -> 0.066831225 | J32: ='계산 명세'!S197 -> -0.079955523 | K32: ='계산 명세'!S198 -> -0.099296565 | L32: ='계산 명세'!S199 -> -0.16905973 | M32: ='계산 명세'!S200 -> -0.1098946 | N32: — | O32: =MEDIAN(D32:N32) -> 0.032792929 | P32: =MIN(D32:N32) -> -0.16905973 | Q32: =MAX(D32:N32) -> 0.12596088 | R32: =COUNTIF(D32:N32,">0") -> 6 | S32: =COUNT(D32:N32) -> 10 | T32: 절반 이상 초과
A33: 30 | B33: 머크 | C33: MRK | D33: ='계산 명세'!S380 -> -0.02454001 | E33: ='계산 명세'!S381 -> -0.028690709 | F33: ='계산 명세'!S382 -> 0.026201764 | G33: ='계산 명세'!S383 -> 0.034280333 | H33: ='계산 명세'!S384 -> -0.015711057 | I33: ='계산 명세'!S385 -> 0.098620473 | J33: ='계산 명세'!S386 -> 0.14997715 | K33: ='계산 명세'!S387 -> -0.078128289 | L33: ='계산 명세'!S388 -> 0.15272105 | M33: ='계산 명세'!S389 -> 0.13404889 | N33: — | O33: =MEDIAN(D33:N33) -> 0.030241049 | P33: =MIN(D33:N33) -> -0.078128289 | Q33: =MAX(D33:N33) -> 0.15272105 | R33: =COUNTIF(D33:N33,">0") -> 6 | S33: =COUNT(D33:N33) -> 10 | T33: 절반 이상 초과
A34: 31 | B34: IBM | C34: IBM | D34: ='계산 명세'!S510 -> 0.15087619 | E34: ='계산 명세'!S511 -> 0.038631949 | F34: ='계산 명세'!S512 -> 0.080679191 | G34: ='계산 명세'!S513 -> 0.021884426 | H34: ='계산 명세'!S514 -> -0.053522269 | I34: ='계산 명세'!S515 -> -0.022060354 | J34: ='계산 명세'!S516 -> -0.067957113 | K34: ='계산 명세'!S517 -> 0.025091716 | L34: ='계산 명세'!S518 -> -0.0022767903 | M34: ='계산 명세'!S519 -> 0.045336993 | N34: — | O34: =MEDIAN(D34:N34) -> 0.023488071 | P34: =MIN(D34:N34) -> -0.067957113 | Q34: =MAX(D34:N34) -> 0.15087619 | R34: =COUNTIF(D34:N34,">0") -> 6 | S34: =COUNT(D34:N34) -> 10 | T34: 절반 이상 초과
A35: 32 | B35: 브로드컴 | C35: AVGO | D35: ='계산 명세'!S58 -> -0.11720592 | E35: ='계산 명세'!S59 -> -0.006748225 | F35: ='계산 명세'!S60 -> 0.040373216 | G35: ='계산 명세'!S61 -> -0.029577374 | H35: ='계산 명세'!S62 -> -0.031105069 | I35: ='계산 명세'!S63 -> 0.046803378 | J35: ='계산 명세'!S64 -> 0.15716694 | K35: ='계산 명세'!S65 -> 0.20616223 | L35: ='계산 명세'!S66 -> -0.0054603442 | M35: ='계산 명세'!S67 -> 0.08593531 | N35: — | O35: =MEDIAN(D35:N35) -> 0.017456436 | P35: =MIN(D35:N35) -> -0.11720592 | Q35: =MAX(D35:N35) -> 0.20616223 | R35: =COUNTIF(D35:N35,">0") -> 5 | S35: =COUNT(D35:N35) -> 10 | T35: 절반 이상 초과
A36: 33 | B36: AMD | C36: AMD | D36: ='계산 명세'!S147 -> -0.39764646 | E36: ='계산 명세'!S148 -> 0.038005502 | F36: ='계산 명세'!S149 -> 0.29561404 | G36: ='계산 명세'!S150 -> 0.26493165 | H36: ='계산 명세'!S151 -> 0.35737647 | I36: ='계산 명세'!S152 -> 0.67701918 | J36: ='계산 명세'!S153 -> -0.05677777 | K36: ='계산 명세'!S154 -> -0.092670444 | L36: ='계산 명세'!S155 -> -0.071108669 | M36: ='계산 명세'!S156 -> -0.036093457 | N36: — | O36: =MEDIAN(D36:N36) -> 0.00095602257 | P36: =MIN(D36:N36) -> -0.39764646 | Q36: =MAX(D36:N36) -> 0.67701918 | R36: =COUNTIF(D36:N36,">0") -> 5 | S36: =COUNT(D36:N36) -> 10 | T36: 절반 이상 초과
A37: 34 | B37: 테슬라 | C37: TSLA | D37: ='계산 명세'!S80 -> -0.19059316 | E37: ='계산 명세'!S81 -> -0.221608 | F37: ='계산 명세'!S82 -> -0.1237789 | G37: ='계산 명세'!S83 -> -0.10430949 | H37: ='계산 명세'!S84 -> 0.025406444 | I37: ='계산 명세'!S85 -> 0.29065549 | J37: ='계산 명세'!S86 -> 0.4981238 | K37: ='계산 명세'!S87 -> 0.17563144 | L37: ='계산 명세'!S88 -> 0.04155947 | M37: ='계산 명세'!S89 -> -0.027643003 | N37: — | O37: =MEDIAN(D37:N37) -> -0.0011182795 | P37: =MIN(D37:N37) -> -0.221608 | Q37: =MAX(D37:N37) -> 0.4981238 | R37: =COUNTIF(D37:N37,">0") -> 5 | S37: =COUNT(D37:N37) -> 10 | T37: 절반 이상 초과
A38: 35 | B38: 엑슨모빌 | C38: XOM | D38: ='계산 명세'!S169 -> -0.062240273 | E38: ='계산 명세'!S170 -> -0.017681328 | F38: ='계산 명세'!S171 -> -0.0059056189 | G38: ='계산 명세'!S172 -> -0.035622311 | H38: ='계산 명세'!S173 -> -0.19333316 | I38: ='계산 명세'!S174 -> 0.009410091 | J38: ='계산 명세'!S175 -> 0.16863067 | K38: ='계산 명세'!S176 -> 0.068588539 | L38: ='계산 명세'!S177 -> 0.039794596 | M38: ='계산 명세'!S178 -> 0.0025832059 | N38: — | O38: =MEDIAN(D38:N38) -> -0.0016612065 | P38: =MIN(D38:N38) -> -0.19333316 | Q38: =MAX(D38:N38) -> 0.16863067 | R38: =COUNTIF(D38:N38,">0") -> 5 | S38: =COUNT(D38:N38) -> 10 | T38: 절반 이상 초과
A39: 36 | B39: 셰브론 | C39: CVX | D39: ='계산 명세'!S346 -> -0.10806515 | E39: ='계산 명세'!S347 -> -0.053332646 | F39: ='계산 명세'!S348 -> -0.019742804 | G39: ='계산 명세'!S349 -> -0.079207961 | H39: ='계산 명세'!S350 -> -0.129968 | I39: ='계산 명세'!S351 -> -0.0086082257 | J39: ='계산 명세'!S352 -> 0.10970839 | K39: ='계산 명세'!S353 -> 0.024710417 | L39: ='계산 명세'!S354 -> 0.0016466853 | M39: ='계산 명세'!S355 -> -0.035855933 | N39: — | O39: =MEDIAN(D39:N39) -> -0.027799369 | P39: =MIN(D39:N39) -> -0.129968 | Q39: =MAX(D39:N39) -> 0.10970839 | R39: =COUNTIF(D39:N39,">0") -> 3 | S39: =COUNT(D39:N39) -> 10 | T39: 대부분 미달
A40: 37 | B40: RTX | C40: RTX | D40: ='계산 명세'!S402 -> 0.042216981 | E40: ='계산 명세'!S403 -> 0.0076374951 | F40: ='계산 명세'!S404 -> -0.073919547 | G40: ='계산 명세'!S405 -> -0.046475933 | H40: ='계산 명세'!S406 -> -0.116717 | I40: ='계산 명세'!S407 -> -0.05689646 | J40: ='계산 명세'!S408 -> -0.051202159 | K40: ='계산 명세'!S409 -> -0.068145761 | L40: ='계산 명세'!S410 -> -0.045652484 | M40: ='계산 명세'!S411 -> -0.022248254 | N40: — | O40: =MEDIAN(D40:N40) -> -0.048839046 | P40: =MIN(D40:N40) -> -0.116717 | Q40: =MAX(D40:N40) -> 0.042216981 | R40: =COUNTIF(D40:N40,">0") -> 2 | S40: =COUNT(D40:N40) -> 10 | T40: 대부분 미달
A41: 38 | B41: 제너럴 일렉트릭 | C41: GE | D41: ='계산 명세'!S313 -> -0.082153973 | E41: ='계산 명세'!S314 -> -0.18778359 | F41: ='계산 명세'!S315 -> -0.27032338 | G41: ='계산 명세'!S316 -> -0.13162947 | H41: ='계산 명세'!S317 -> -0.19216671 | I41: ='계산 명세'!S318 -> -0.20340917 | J41: ='계산 명세'!S319 -> -0.086824154 | K41: ='계산 명세'!S320 -> -0.01262397 | L41: ='계산 명세'!S321 -> 0.058251812 | M41: ='계산 명세'!S322 -> 0.18024526 | N41: — | O41: =MEDIAN(D41:N41) -> -0.10922681 | P41: =MIN(D41:N41) -> -0.27032338 | Q41: =MAX(D41:N41) -> 0.18024526 | R41: =COUNTIF(D41:N41,">0") -> 2 | S41: =COUNT(D41:N41) -> 10 | T41: 대부분 미달
A42: 39 | B42: 팔로알토 네트웍스 | C42: PANW | D42: ='계산 명세'!S413 -> — | E42: ='계산 명세'!S414 -> -0.86687354 | F42: — | G42: ='계산 명세'!S416 -> -0.30046435 | H42: ='계산 명세'!S417 -> -0.53423921 | I42: ='계산 명세'!S418 -> -0.44381252 | J42: ='계산 명세'!S419 -> -0.34618635 | K42: ='계산 명세'!S420 -> 0.2753796 | L42: ='계산 명세'!S421 -> 0.2298226 | M42: ='계산 명세'!S422 -> 0.13518966 | N42: ='계산 명세'!S423 -> -0.071575611 | O42: =MEDIAN(D42:N42) -> -0.30046435 | P42: =MIN(D42:N42) -> -0.86687354 | Q42: =MAX(D42:N42) -> 0.2753796 | R42: =COUNTIF(D42:N42,">0") -> 3 | S42: =COUNT(D42:N42) -> 9 | T42: 대부분 미달
A44: 표본 부족
A45: — | B45: 팔란티어 테크놀로지스 | C45: PLTR | D45: — | E45: — | F45: — | G45: — | H45: — | I45: — | J45: ='계산 명세'!S285 -> -14.634215 | K45: — | L45: — | M45: ='계산 명세'!S288 -> 4.2197829 | N45: — | O45: =MEDIAN(D45:N45) -> -5.2072159 | P45: =MIN(D45:N45) -> -14.634215 | Q45: =MAX(D45:N45) -> 4.2197829 | R45: =COUNTIF(D45:N45,">0") -> 1 | S45: =COUNT(D45:N45) -> 2 | T45: 절반 이상 초과
A46: — | B46: GE 버노바 | C46: GEV | D46: — | E46: — | F46: — | G46: — | H46: — | I46: — | J46: ='계산 명세'!S450 -> -0.33857338 | K46: ='계산 명세'!S451 -> -0.18830931 | L46: ='계산 명세'!S452 -> -0.03760332 | M46: ='계산 명세'!S453 -> 0.32208707 | N46: — | O46: =MEDIAN(D46:N46) -> -0.11295632 | P46: =MIN(D46:N46) -> -0.33857338 | Q46: =MAX(D46:N46) -> 0.32208707 | R46: =COUNTIF(D46:N46,">0") -> 1 | S46: =COUNT(D46:N46) -> 4 | T46: 대부분 미달
A48: 금융업 — ROIC 정의 부적합
A49: — | B49: 버크셔 해서웨이 | C49: BRK-B | D49: — | E49: — | F49: — | G49: — | H49: — | I49: — | J49: — | K49: — | L49: — | M49: — | N49: — | O49: — | P49: — | Q49: — | R49: — | S49: — | T49: 금융업 — ROIC 정의 부적합
A50: — | B50: JP모건 체이스 | C50: JPM | D50: — | E50: — | F50: — | G50: — | H50: — | I50: — | J50: — | K50: — | L50: — | M50: — | N50: — | O50: — | P50: — | Q50: — | R50: — | S50: — | T50: 금융업 — ROIC 정의 부적합
A51: — | B51: 뱅크오브아메리카 | C51: BAC | D51: — | E51: — | F51: — | G51: — | H51: — | I51: — | J51: — | K51: — | L51: — | M51: — | N51: — | O51: — | P51: — | Q51: — | R51: — | S51: — | T51: 금융업 — ROIC 정의 부적합
A52: — | B52: 유나이티드헬스 그룹 | C52: UNH | D52: — | E52: — | F52: — | G52: — | H52: — | I52: — | J52: — | K52: — | L52: — | M52: — | N52: — | O52: — | P52: — | Q52: — | R52: — | S52: — | T52: 금융업 — ROIC 정의 부적합
A53: — | B53: 모건스탠리 | C53: MS | D53: — | E53: — | F53: — | G53: — | H53: — | I53: — | J53: — | K53: — | L53: — | M53: — | N53: — | O53: — | P53: — | Q53: — | R53: — | S53: — | T53: 금융업 — ROIC 정의 부적합
A54: — | B54: 골드만삭스 | C54: GS | D54: — | E54: — | F54: — | G54: — | H54: — | I54: — | J54: — | K54: — | L54: — | M54: — | N54: — | O54: — | P54: — | Q54: — | R54: — | S54: — | T54: 금융업 — ROIC 정의 부적합
A55: — | B55: 웰스파고 | C55: WFC | D55: — | E55: — | F55: — | G55: — | H55: — | I55: — | J55: — | K55: — | L55: — | M55: — | N55: — | O55: — | P55: — | Q55: — | R55: — | S55: — | T55: 금융업 — ROIC 정의 부적합
A56: — | B56: 아메리칸 익스프레스 | C56: AXP | D56: — | E56: — | F56: — | G56: — | H56: — | I56: — | J56: — | K56: — | L56: — | M56: — | N56: — | O56: — | P56: — | Q56: — | R56: — | S56: — | T56: 금융업 — ROIC 정의 부적합
A57: — | B57: 씨티그룹 | C57: C | D57: — | E57: — | F57: — | G57: — | H57: — | I57: — | J57: — | K57: — | L57: — | M57: — | N57: — | O57: — | P57: — | Q57: — | R57: — | S57: — | T57: 금융업 — ROIC 정의 부적합

Sheet 구 조사 대조
A1: 1차 조사(analysis.json, 공시 본문 파싱)와 이번 재산출(companyfacts API)의 기업-연도별 대조. 정의는 같고 경로만 다릅니다.
A2: 기업 | B2: 티커 | C2: 연도 | D2: 재산출 ROIC | E2: 1차 조사 ROIC | F2: 차이(%p) | G2: 문턱 판정 바뀜 | H2: 재산출 영업이익 | I2: 1차 영업이익 | J2: 재산출 평균자본 | K2: 1차 평균자본 | L2: 재산출 경로 | M2: 원인
A3: 오라클 | B3: ORCL | C3: FY2024 | D3: 0.14499806 | E3: 7.6145017 | F3: =D3-E3 -> -7.4695036 | H3: 15353000000 | I3: 15353000000 | J3: 83648500000 | K3: 1797500000 | L3: reported | M3: 투하자본(분모) +4553.6%, 실효세율 +93.5%
A4: 엔비디아 | B4: NVDA | C4: FY2016 | D4: 1.7860208 | E4: 8.9253915 | F4: =D4-E4 -> -7.1393707 | H4: 1934000000 | I4: 1934000000 | J4: 947000000 | K4: 189500000 | L4: reported | M4: 투하자본(분모) +399.7%
A5: 오라클 | B5: ORCL | C5: FY2025 | D5: 0.1487437 | E5: 1.2345069 | F5: =D5-E5 -> -1.0857632 | H5: 17678000000 | I5: 17678000000 | J5: 93890500000 | K5: 12583500000 | L5: reported | M5: 투하자본(분모) +646.1%, 실효세율 +73.2%
A6: 마이크로소프트 | B6: MSFT | C6: FY2016 | D6: 0.99101879 | E6: 1.7214516 | F6: =D6-E6 -> -0.73043282 | H6: 26078000000 | I6: 26078000000 | J6: 21080000000 | K6: 12135500000 | L6: reported | M6: 투하자본(분모) +73.7%
A7: 마스터카드 | B7: MA | C7: FY2018 | D7: 1.8186511 | E7: 1.1837772 | F7: =D7-E7 -> 0.6348739 | H7: 7282000000 | I7: 7282000000 | J7: 3256500000 | K7: 5003000000 | L7: reported | M7: 투하자본(분모) -34.9%
A8: 팔로알토 네트웍스 | B8: PANW | C8: FY2017 | D8: -0.76687354 | E8: -0.21817606 | F8: =D8-E8 -> -0.54869747 | H8: -165800000 | I8: -165800000 | J8: 170800000 | K8: 600350000 | L8: reported | M8: 투하자본(분모) -71.5%
A9: 마스터카드 | B9: MA | C9: FY2016 | D9: 1.617526 | E9: 1.080813 | F9: =D9-E9 -> 0.53671303 | H9: 5761000000 | I9: 5761000000 | J9: 2560500000 | K9: 3832000000 | L9: reported | M9: 투하자본(분모) -33.2%
A10: 마스터카드 | B10: MA | C10: FY2017 | D10: 1.4026209 | E10: 0.87613568 | F10: =D10-E10 -> 0.5264852 | H10: 6622000000 | I10: 6622000000 | J10: 2834000000 | K10: 4537000000 | L10: reported | M10: 투하자본(분모) -37.5%
A11: KLA | B11: KLAC | C11: FY2017 | D11: 0.80700967 | E11: 0.30908516 | F11: =D11-E11 -> 0.49792451 | H11: 1275900000 | I11: 1173246000 | J11: 1247945000 | K11: 2996184000 | L11: verified_line_build | M11: 영업이익(분자) +8.7%, 투하자본(분모) -58.3%, 신규 분자 추정경로(verified_line_build), 구 분자 = 세전이익+이자
A12: 코카콜라 | B12: KO | C12: FY2021 | D12: 0.14497571 | E12: 0.61161575 | F12: =D12-E12 -> -0.46664004 | H12: 10308000000 | I12: 10308000000 | J12: 56103000000 | K12: 13298500000 | L12: reported | M12: 투하자본(분모) +321.9%
A13: 오라클 | B13: ORCL | C13: FY2018 | D13: 0.18254886 | E13: 0.62480079 | F13: =D13-E13 -> -0.44225193 | H13: 13264000000 | I13: 13264000000 | J13: 43596000000 | K13: 12737500000 | L13: reported | M13: 투하자본(분모) +242.3%
A14: 코카콜라 | B14: KO | C14: FY2022 | D14: 0.16082777 | E14: 0.59122723 | F14: =D14-E14 -> -0.43039946 | H14: 10909000000 | I14: 10909000000 | J14: 55554000000 | K14: 15112000000 | L14: reported | M14: 투하자본(분모) +267.6%
... A24: 필립모리스 인터내셔널 | B24: PM | C24: FY2018 | D24: 0.58295306 | E24: 0.87908959 | F24: =D24-E24 -> -0.29613653 | H24: 11377000000 | I24: 11377000000 | J24: 15044500000 | K24: 9976500000 | L24: reported | M24: 투하자본(분모) +50.8%
A25: 팔로알토 네트웍스 | B25: PANW | C25: FY2023 | D25: 0.3753796 | E25: 0.082722398 | F25: =D25-E25 -> 0.2926572 | G25: 예 | H25: 387300000 | I25: 387300000 | J25: 801100000 | K25: 3635250000 | L25: reported | M25: 투하자본(분모) -78.0%
A26: 코카콜라 | B26: KO | C26: FY2018 | D26: 0.14070134 | E26: 0.42908736 | F26: =D26-E26 -> -0.28838602 | H26: 9152000000 | I26: 9152000000 | J26: 51214000000 | K26: 16793500000 | L26: reported | M26: 투하자본(분모) +205.0%
A27: 시스코 시스템즈 | B27: CSCO | C27: FY2016 | D27: 0.41171783 | E27: 0.12929528 | F27: =D27-E27 -> 0.28242255 | H27: 12660000000 | I27: 12660000000 | J27: 25558500000 | K27: 81386500000 | L27: reported | M27: 투하자본(분모) -68.6%
A28: 코카콜라 | B28: KO | C28: FY2019 | D28: 0.15658795 | E28: 0.42027277 | F28: =D28-E28 -> -0.26368482 | H28: 10086000000 | I28: 10086000000 | J28: 53656000000 | K28: 19991500000 | L28: reported | M28: 투하자본(분모) +168.4%
A29: 필립모리스 인터내셔널 | B29: PM | C29: FY2016 | D29: 0.57146557 | E29: 0.82840077 | F29: =D29-E29 -> -0.25693521 | H29: 10903000000 | I29: 10903000000 | J29: 13757500000 | K29: 9490500000 | L29: reported | M29: 투하자본(분모) +45.0%
A30: 램리서치 | B30: LRCX | C30: FY2018 | D30: 0.65722234 | E30: 0.41759899 | F30: =D30-E30 -> 0.23962334 | H30: 3213299000 | I30: 3213299000 | J30: 3693030500 | K30: 5812136000 | L30: reported | M30: 투하자본(분모) -36.5%
A31: 램리서치 | B31: LRCX | C31: FY2017 | D31: 0.52055414 | E31: 0.28983754 | F31: =D31-E31 -> 0.23071661 | H31: 1902132000 | I31: 1902132000 | J31: 3424301500 | K31: 6150115500 | L31: reported | M31: 투하자본(분모) -44.3%
A32: 시스코 시스템즈 | B32: CSCO | C32: FY2017 | D32: 0.33540271 | E32: 0.10840825 | F32: =D32-E32 -> 0.22699446 | H32: 11973000000 | I32: 11973000000 | J32: 27917000000 | K32: 86372000000 | L32: reported | M32: 투하자본(분모) -67.7%
A33: 코카콜라 | B33: KO | C33: FY2016 | D33: 0.13304771 | E33: 0.34673822 | F33: =D33-E33 -> -0.21369051 | H33: 8657000000 | I33: 8657000000 | J33: 52383000000 | K33: 20100000000 | L33: reported | M33: 투하자본(분모) +160.6%
A34: 램리서치 | B34: LRCX | C34: FY2021 | D34: 0.84195609 | E34: 0.63503448 | F34: =D34-E34 -> 0.2069216 | H34: 4482023000 | I34: 4482023000 | J34: 4760239000 | K34: 6311330000 | L34: reported | M34: 투하자본(분모) -24.6%
A35: 코카콜라 | B35: KO | C35: FY2017 | D35: 0.091557541 | E35: 0.29184307 | F35: =D35-E35 -> -0.20028553 | G35: 예 | H35: 7755000000 | I35: 7755000000 | J35: 50820500000 | K35: 15943500000 | L35: reported | M35: 투하자본(분모) +218.8%
A36: 팔로알토 네트웍스 | B36: PANW | C36: FY2022 | D36: -0.24618635 | E36: -0.04627451 | F36: =D36-E36 -> -0.19991184 | H36: -188800000 | I36: -188800000 | J36: 605850000 | K36: 3223200000 | L36: reported | M36: 투하자본(분모) -81.2%
A37: 필립모리스 인터내셔널 | B37: PM | C37: FY2017 | D37: 0.46965867 | E37: 0.66598936 | F37: =D37-E37 -> -0.19633069 | H37: 11581000000 | I37: 11581000000 | J37: 14795000000 | K37: 10433500000 | L37: reported | M37: 투하자본(분모) +41.8%
A38: 제너럴 일렉트릭 | B38: GE | C38: FY2023 | D38: 0.08737603 | E38: 0.27060239 | F38: =D38-E38 -> -0.18322636 | G38: 예 | H38: 3723000000 | I38: 10441000000 | J38: 38552500000 | K38: 34911000000 | L38: pretax_less_nonoperating | M38: 영업이익(분자) -64.3%, 투하자본(분모) +10.4%, 신규 분자 추정경로(pretax_less_nonoperating), 구 분자 = 세전이익+이자
A39: 램리서치 | B39: LRCX | C39: FY2020 | D39: 0.58903545 | E39: 0.40669319 | F39: =D39-E39 -> 0.18234226 | H39: 2673802000 | I39: 2673802000 | J39: 3969493000 | K39: 5749228500 | L39: reported | M39: 투하자본(분모) -31.0%
A40: 팔로알토 네트웍스 | B40: PANW | C40: FY2021 | D40: -0.34381252 | E40: -0.1625763 | F40: =D40-E40 -> -0.18123622 | H40: -304100000 | I40: -304100000 | J40: 698750000 | K40: 1477700000 | L40: reported | M40: 투하자본(분모) -52.7%
A41: 비자 | B41: V | C41: FY2018 | D41: 0.2713166 | E41: 0.44298223 | F41: =D41-E41 -> -0.17166563 | H41: 12954000000 | I41: 12954000000 | J41: 38405500000 | K41: 23522500000 | L41: reported | M41: 투하자본(분모) +63.3%
A42: 제너럴 일렉트릭 | B42: GE | C42: FY2020 | D42: -0.092166714 | E42: 0.072075793 | F42: =D42-E42 -> -0.16424251 | H42: -5426000000 | I42: 5970000000 | J42: 55928000000 | K42: 78688000000 | L42: pretax_less_nonoperating | M42: 영업이익(분자) -190.9%, 투하자본(분모) -28.9%, 신규 분자 추정경로(pretax_less_nonoperating), 구 분자 = 세전이익+이자
A43: 시스코 시스템즈 | B43: CSCO | C43: FY2018 | D43: 0.28632795 | E43: 0.13382863 | F43: =D43-E43 -> 0.15249932 | H43: 12309000000 | I43: 12309000000 | J43: 25793500000 | K43: 55185500000 | L43: reported | M43: 투하자본(분모) -53.3%
A44: 브로드컴 | B44: AVGO | C44: FY2018 | D44: 0.14037322 | E44: 0.2830925 | F44: =D44-E44 -> -0.14271929 | H44: 5135000000 | I44: 5135000000 | J44: 34752000000 | K44: 17232000000 | L44: reported | M44: 투하자본(분모) +101.7%
A45: 팔로알토 네트웍스 | B45: PANW | C45: FY2024 | D45: 0.3298226 | E45: 0.18842406 | F45: =D45-E45 -> 0.14139854 | H45: 684000000 | I45: 683900000 | J45: 1970150000 | K45: 3448100000 | L45: reported | M45: 투하자본(분모) -42.9%
A46: 램리서치 | B46: LRCX | C46: FY2019 | D46: 0.58097307 | E46: 0.44405481 | F46: =D46-E46 -> 0.13691826 | H46: 2464732000 | I46: 2464732000 | J46: 3799999000 | K46: 4971677000 | L46: reported | M46: 투하자본(분모) -23.6%
A47: 브로드컴 | B47: AVGO | C47: FY2020 | D47: 0.068894931 | E47: 0.19183519 | F47: =D47-E47 -> -0.12294026 | G47: 예 | H47: 4014000000 | I47: 4014000000 | J47: 55349500000 | K47: 19878000000 | L47: reported | M47: 투하자본(분모) +178.4%
A48: 필립모리스 인터내셔널 | B48: PM | C48: FY2022 | D48: 0.4058536 | E48: 0.51008699 | F48: =D48-E48 -> -0.10423339 | H48: 12246000000 | I48: 12246000000 | J48: 24353500000 | K48: 19377000000 | L48: reported | M48: 투하자본(분모) +25.7%
A49: 코카콜라 | B49: KO | C49: FY2023 | D49: 0.16804101 | E49: 0.27083567 | F49: =D49-E49 -> -0.10279466 | H49: 11311000000 | I49: 11311000000 | J49: 55623000000 | K49: 34511500000 | L49: reported | M49: 투하자본(분모) +61.2%
A50: 마이크로소프트 | B50: MSFT | C50: FY2018 | D50: 0.63631909 | E50: 0.73751972 | F50: =D50-E50 -> -0.10120064 | H50: 35058000000 | I50: 35058000000 | J50: 33057000000 | K50: 28521000000 | L50: reported | M50: 투하자본(분모) +15.9%
A51: 애플 | B51: AAPL | C51: FY2025 | D51: 1.039152 | E51: 1.1332633 | F51: =D51-E51 -> -0.094111284 | H51: 133050000000 | I51: 133050000000 | J51: 108050500000 | K51: 99077500000 | L51: reported | M51: 투하자본(분모) +9.1%
A52: 비자 | B52: V | C52: FY2017 | D52: 0.18755695 | E52: 0.28063473 | F52: =D52-E52 -> -0.093077774 | H52: 12144000000 | I52: 12144000000 | J52: 38849000000 | K52: 25964000000 | L52: reported | M52: 투하자본(분모) +49.6%
A53: 브로드컴 | B53: AVGO | C53: FY2017 | D53: 0.093251775 | E53: 0.18616828 | F53: =D53-E53 -> -0.092916503 | G53: 예 | H53: 2371000000 | I53: 2371000000 | J53: 24154500000 | K53: 12099000000 | L53: reported | M53: 투하자본(분모) +99.6%
A54: 브로드컴 | B54: AVGO | C54: FY2021 | D54: 0.14680338 | E54: 0.2326057 | F54: =D54-E54 -> -0.085802319 | H54: 8519000000 | I54: 8519000000 | J54: 55128500000 | K54: 34793000000 | L54: reported | M54: 투하자본(분모) +58.4%
A55: 제너럴 일렉트릭 | B55: GE | C55: FY2024 | D55: 0.15825181 | E55: 0.24400344 | F55: =D55-E55 -> -0.085751633 | H55: 5356000000 | I55: 7620000000 | J55: 29572000000 | K55: 27286500000 | L55: pretax_less_nonoperating | M55: 영업이익(분자) -29.7%, 투하자본(분모) +8.4%, 신규 분자 추정경로(pretax_less_nonoperating), 구 분자 = 세전이익+이자
A56: 비자 | B56: V | C56: FY2019 | D56: 0.31017027 | E56: 0.39353401 | F56: =D56-E56 -> -0.083363742 | H56: 15001000000 | I56: 15001000000 | J56: 39252500000 | K56: 30937500000 | L56: reported | M56: 투하자본(분모) +26.9%
A57: 애브비 | B57: ABBV | C57: FY2019 | D57: 0.57239499 | E57: 0.65518251 | F57: =D57-E57 -> -0.082787525 | H57: 12983000000 | I57: 12983000000 | J57: 21217500000 | K57: 18536500000 | L57: reported | M57: 투하자본(분모) +14.5%
A58: GE 버노바 | B58: GEV | C58: FY2023 | D58: -0.088309313 | E58: -0.16859422 | F58: =D58-E58 -> 0.080284906 | H58: -923000000 | I58: -923000000 | J58: 8257000000 | K58: 4325000000 | L58: reported | M58: 투하자본(분모) +90.9%
A59: 제너럴 일렉트릭 | B59: GE | C59: FY2025 | D59: 0.28024526 | E59: 0.3575663 | F59: =D59-E59 -> -0.077321042 | H59: 8513000000 | I59: 10000000000 | J59: 26109000000 | K59: 24037500000 | L59: pretax_less_nonoperating | M59: 영업이익(분자) -14.9%, 투하자본(분모) +8.6%, 신규 분자 추정경로(pretax_less_nonoperating), 구 분자 = 세전이익+이자
A60: 램리서치 | B60: LRCX | C60: FY2022 | D60: 0.74328038 | E60: 0.66802981 | F60: =D60-E60 -> 0.075250571 | H60: 5381822000 | I60: 5381822000 | J60: 6421040500 | K60: 7144342000 | L60: reported | M60: 투하자본(분모) -10.1%
A61: 브로드컴 | B61: AVGO | C61: FY2019 | D61: 0.070422626 | E61: 0.14529064 | F61: =D61-E61 -> -0.074868017 | G61: 예 | H61: 3444000000 | I61: 3444000000 | J61: 46459500000 | K61: 22519000000 | L61: reported | M61: 투하자본(분모) +106.3%
A62: 애플 | B62: AAPL | C62: FY2024 | D62: 0.89041021 | E62: 0.96357489 | F62: =D62-E62 -> -0.073164673 | H62: 123216000000 | I62: 123216000000 | J62: 105043500000 | K62: 97067500000 | L62: reported | M62: 투하자본(분모) +8.2%
A63: 존슨앤드존슨 | B63: JNJ | C63: FY2025 | D63: 0.21630414 | E63: 0.28604117 | F63: =D63-E63 -> -0.069737029 | H63: 25372000000 | I63: 33552000000 | J63: 96499500000 | K63: 96499500000 | L63: pretax_less_nonoperating | M63: 영업이익(분자) -24.4%, 신규 분자 추정경로(pretax_less_nonoperating), 구 분자 = 세전이익+이자
A64: 필립모리스 인터내셔널 | B64: PM | C64: FY2025 | D64: 0.3540046 | E64: 0.42116652 | F64: =D64-E64 -> -0.067161919 | H64: 14892000000 | I64: 14892000000 | J64: 33772000000 | K64: 28386500000 | L64: reported | M64: 투하자본(분모) +19.0%
A65: 필립모리스 인터내셔널 | B65: PM | C65: FY2024 | D65: 0.30106487 | E65: 0.36507173 | F65: =D65-E65 -> -0.064006862 | H65: 13402000000 | I65: 13402000000 | J65: 33506000000 | K65: 27631500000 | L65: reported | M65: 투하자본(분모) +21.3%
A66: 엔비디아 | B66: NVDA | C66: FY2023 | D66: 1.2490268 | E66: 1.1852501 | F66: =D66-E66 -> 0.063776616 | H66: 32972000000 | I66: 32972000000 | J66: 23230500000 | K66: 24480500000 | L66: reported | M66: 투하자본(분모) -5.1%
A67: 램리서치 | B67: LRCX | C67: FY2016 | D67: 0.30176676 | E67: 0.23865656 | F67: =D67-E67 -> 0.063110197 | H67: 1074256000 | I67: 1074256000 | J67: 3381894000 | K67: 4276200000 | L67: reported | M67: 투하자본(분모) -20.9%
A68: 일라이 릴리 | B68: LLY | C68: FY2020 | D68: 0.30245991 | E68: 0.36389434 | F68: =D68-E68 -> -0.061434425 | H68: 6058000000 | I68: 7229900000 | J68: 17158500000 | K68: 17020600000 | L68: pretax_less_nonoperating | M68: 영업이익(분자) -16.2%, 신규 분자 추정경로(pretax_less_nonoperating), 구 분자 = 세전이익+이자
A69: 존슨앤드존슨 | B69: JNJ | C69: FY2023 | D69: 0.22657844 | E69: 0.16535965 | F69: =D69-E69 -> 0.061218787 | H69: 21696000000 | I69: 15834000000 | J69: 84718500000 | K69: 84718500000 | L69: pretax_less_nonoperating | M69: 영업이익(분자) +37.0%, 신규 분자 추정경로(pretax_less_nonoperating), 구 분자 = 세전이익+이자
A70: 애플 | B70: AAPL | C70: FY2023 | D70: 0.83272255 | E70: 0.89367209 | F70: =D70-E70 -> -0.060949539 | H70: 114301000000 | I70: 114301000000 | J70: 117058000000 | K70: 109074500000 | L70: reported | M70: 투하자본(분모) +7.3%
A71: 애플 | B71: AAPL | C71: FY2017 | D71: 0.28596898 | E71: 0.22902255 | F71: =D71-E71 -> 0.056946427 | H71: 61344000000 | I71: 61344000000 | J71: 161836000000 | K71: 202076500000 | L71: reported | M71: 투하자본(분모) -19.9%
A72: 오라클 | B72: ORCL | C72: FY2016 | D72: 0.27157509 | E72: 0.32774379 | F72: =D72-E72 -> -0.056168698 | H72: 12604000000 | I72: 12604000000 | J72: 36104000000 | K72: 29916500000 | L72: reported | M72: 투하자본(분모) +20.7%
A73: 마스터카드 | B73: MA | C73: FY2020 | D73: 0.87088407 | E73: 0.81506499 | F73: =D73-E73 -> 0.055819087 | H73: 8081000000 | I73: 8081000000 | J73: 7666000000 | K73: 8191000000 | L73: reported | M73: 투하자본(분모) -6.4%
... A161: 홈디포 | B161: HD | C161: FY2025 | D161: 0.25322002 | E161: 0.26324148 | F161: =D161-E161 -> -0.010021458 | H161: 20890000000 | I161: 20890000000 | J161: 62780000000 | K161: 60390000000 | L161: reported | M161: 투하자본(분모) +4.0%

Sheet 차입금 누락
A1: 1차 조사가 장기차입금을 0으로 기록했으나 10-K에 해당 태그가 존재하는 기업-연도. 어느 쪽이 맞는지 판단이 필요 없는 유형의 오류입니다.
A2: 기업 | B2: 기업-연도 | C2: 공시된 장기차입금 | D2: 1차 조사 총차입금 | E2: 재산출 총차입금 | F2: 사용 태그 | G2: 1차 ROIC | H2: 재산출 ROIC
A3: 오라클 | B3: ORCL FY2023 | C3: 86420000000 | D3: 4061000000 | E3: 90481000000 | F3: LongTermNotesAndLoans | H3: 0.15908258
A4: 오라클 | B4: ORCL FY2025 | C4: 85297000000 | D4: 7271000000 | E4: 92568000000 | F4: LongTermNotesAndLoans | G4: 1.2345069 | H4: 0.1487437
A5: 오라클 | B5: ORCL FY2024 | C5: 76264000000 | D5: 10605000000 | E5: 86869000000 | F5: LongTermNotesAndLoans | G5: 7.6145017 | H5: 0.14499806
A6: 오라클 | B6: ORCL FY2021 | C6: 75995000000 | D6: 8250000000 | E6: 84245000000 | F6: LongTermNotesAndLoans | H6: 0.2831159
A7: 오라클 | B7: ORCL FY2022 | C7: 72110000000 | D7: 3749000000 | E7: 75859000000 | F7: LongTermNotesAndLoans | H7: 0.18798545
A8: 오라클 | B8: ORCL FY2020 | C8: 69226000000 | D8: 2371000000 | E8: 71597000000 | F8: LongTermNotesAndLoans | H8: 0.26788287
A9: 오라클 | B9: ORCL FY2018 | C9: 56128000000 | D9: 4491000000 | E9: 60619000000 | F9: LongTermNotesAndLoans | G9: 0.62480079 | H9: 0.18254886
A10: 오라클 | B10: ORCL FY2019 | C10: 51673000000 | D10: 4494000000 | E10: 56167000000 | F10: LongTermNotesAndLoans | H10: 0.26423135
A11: 오라클 | B11: ORCL FY2017 | C11: 48112000000 | D11: 9797000000 | E11: 57909000000 | F11: LongTermNotesAndLoans | G11: 0.28628201 | H11: 0.25254154
A12: 브로드컴 | B12: AVGO FY2020 | C12: 40235000000 | D12: 827000000 | E12: 41498000000 | F12: LongTermDebtNoncurrent | G12: 0.19183519 | H12: 0.068894931
A13: 코카콜라 | B13: KO FY2020 | C13: 40125000000 | D13: 1329000000 | E13: 42793000000 | F13: LongTermDebtNoncurrent | G13: 0.43312127 | H13: 0.12867501
A14: 오라클 | B14: ORCL FY2016 | C14: 40105000000 | D14: 3750000000 | E14: 43855000000 | F14: LongTermNotesAndLoans | G14: 0.32774379 | H14: 0.27157509
A15: 코카콜라 | B15: KO FY2021 | C15: 38116000000 | D15: 2462000000 | E15: 42761000000 | F15: LongTermDebtNoncurrent | G15: 0.61161575 | H15: 0.14497571
A16: 코카콜라 | B16: KO FY2022 | C16: 36377000000 | D16: 2146000000 | E16: 39149000000 | F16: LongTermDebtNoncurrent | G16: 0.59122723 | H16: 0.16082777
A17: 셰브론 | B17: CVX FY2016 | C17: 35193000000 | D17: 19840000000 | E17: 55033000000 | F17: LongTermDebtNoncurrent | G17: -0.0099787865 | H17: -0.0080651524
A18: 셰브론 | B18: CVX FY2017 | C18: 33477000000 | D18: 15192000000 | E18: 48669000000 | F18: LongTermDebtNoncurrent | G18: 0.057592426 | H18: 0.046667354
A19: 코카콜라 | B19: KO FY2017 | C19: 31182000000 | D19: 12931000000 | E19: 47411000000 | F19: LongTermDebtNoncurrent | G19: 0.29184307 | H19: 0.091557541
A20: 브로드컴 | B20: AVGO FY2019 | C20: 30011000000 | D20: 2787000000 | E20: 33059000000 | F20: LongTermDebtNoncurrent | G20: 0.14529064 | H20: 0.070422626
A21: 코카콜라 | B21: KO FY2016 | C21: 29684000000 | D21: 12330000000 | E21: 45541000000 | F21: LongTermDebtNoncurrent | G21: 0.34673822 | H21: 0.13304771
A22: 코카콜라 | B22: KO FY2019 | C22: 27516000000 | D22: 10007000000 | E22: 42763000000 | F22: LongTermDebtNoncurrent | G22: 0.42027277 | H22: 0.15658795
... A29: GE 버노바 | B29: GEV FY2025 | C29: 265000000 | D29: 63000000 | E29: 352000000 | F29: LongTermDebtAndCapitalLeaseObligations | G29: 0.44255748 | H29: 0.42208707

Sheet 정정 내역
A1: analysis.json에 반영한 정정 319건. 원본은 analysis.json.pre-roic-correction에 보존.
A2: 기업 | B2: 티커 | C2: 연도 | D2: 구 ROIC | E2: 정정 ROIC | F2: 변화(%p) | G2: 구 영업이익 | H2: 정정 영업이익 | I2: 구 평균자본 | J2: 정정 평균자본 | K2: 바뀐 항목
A3: 팔란티어 테크놀로지스 | B3: PLTR | C3: FY2022 | E3: -14.534215 | F3: — | G3: -161201000 | H3: -161201000 | I3: -203590500 | J3: 8762000 | K3: roic, invested_capital, invested_capital_avg
A4: 오라클 | B4: ORCL | C4: FY2024 | D4: 7.6145017 | E4: 0.14499806 | F4: =E4-D4 -> -7.4695036 | G4: 15353000000 | H4: 15353000000 | I4: 1797500000 | J4: 83648500000 | K4: roic, tax_rate, nopat, invested_capital, invested_capital_avg
A5: 엔비디아 | B5: NVDA | C5: FY2016 | D5: 8.9253915 | E5: 1.7860208 | F5: =E5-D5 -> -7.1393707 | G5: 1934000000 | H5: 1934000000 | I5: 189500000 | J5: 947000000 | K5: roic, invested_capital_avg
A6: 팔란티어 테크놀로지스 | B6: PLTR | C6: FY2025 | E6: 4.3197829 | F6: — | G6: 1414015000 | H6: 1414015000 | I6: -32764000 | J6: 310968000 | K6: roic, invested_capital, invested_capital_avg
A7: 오라클 | B7: ORCL | C7: FY2025 | D7: 1.2345069 | E7: 0.1487437 | F7: =E7-D7 -> -1.0857632 | G7: 17678000000 | H7: 17678000000 | I7: 12583500000 | J7: 93890500000 | K7: roic, tax_rate, nopat, invested_capital, invested_capital_avg
A8: 마이크로소프트 | B8: MSFT | C8: FY2016 | D8: 1.7214516 | E8: 0.99101879 | F8: =E8-D8 -> -0.73043282 | G8: 26078000000 | H8: 26078000000 | I8: 12135500000 | J8: 21080000000 | K8: roic, invested_capital, invested_capital_avg
A9: 마스터카드 | B9: MA | C9: FY2018 | D9: 1.1837772 | E9: 1.8186511 | F9: =E9-D9 -> 0.6348739 | G9: 7282000000 | H9: 7282000000 | I9: 5003000000 | J9: 3256500000 | K9: roic, invested_capital, invested_capital_avg
A10: 메타 플랫폼스 | B10: META | C10: FY2018 | E10: 0.57426782 | F10: — | G10: 24913000000 | H10: 24913000000 | J10: 37824500000 | K10: roic, invested_capital, invested_capital_avg
A11: 팔로알토 네트웍스 | B11: PANW | C11: FY2017 | D11: -0.21817606 | E11: -0.76687354 | F11: =E11-D11 -> -0.54869747 | G11: -165800000 | H11: -165800000 | I11: 600350000 | J11: 170800000 | K11: roic, invested_capital, invested_capital_avg
A12: 마스터카드 | B12: MA | C12: FY2016 | D12: 1.080813 | E12: 1.617526 | F12: =E12-D12 -> 0.53671303 | G12: 5761000000 | H12: 5761000000 | I12: 3832000000 | J12: 2560500000 | K12: roic, invested_capital, invested_capital_avg
A13: 마스터카드 | B13: MA | C13: FY2017 | D13: 0.87613568 | E13: 1.4026209 | F13: =E13-D13 -> 0.5264852 | G13: 6622000000 | H13: 6622000000 | I13: 4537000000 | J13: 2834000000 | K13: roic, invested_capital, invested_capital_avg
A14: 메타 플랫폼스 | B14: META | C14: FY2020 | E14: 0.5100437 | F14: — | G14: 32671000000 | H14: 32671000000 | J14: 56267500000 | K14: roic, invested_capital, invested_capital_avg
A15: 메타 플랫폼스 | B15: META | C15: FY2017 | E15: 0.50116142 | F15: — | G15: 20203000000 | H15: 20203000000 | J15: 31190500000 | K15: roic, invested_capital, invested_capital_avg
A16: KLA | B16: KLAC | C16: FY2017 | D16: 0.30908516 | E16: 0.80700967 | F16: =E16-D16 -> 0.49792451 | G16: 1173246000 | H16: 1275900000 | I16: 2996184000 | J16: 1247945000 | K16: roic, ebit, nopat, invested_capital, invested_capital_avg
A17: 코카콜라 | B17: KO | C17: FY2021 | D17: 0.61161575 | E17: 0.14497571 | F17: =E17-D17 -> -0.46664004 | G17: 10308000000 | H17: 10308000000 | I17: 13298500000 | J17: 56103000000 | K17: roic, invested_capital, invested_capital_avg
A18: 오라클 | B18: ORCL | C18: FY2018 | D18: 0.62480079 | E18: 0.18254886 | F18: =E18-D18 -> -0.44225193 | G18: 13264000000 | H18: 13264000000 | I18: 12737500000 | J18: 43596000000 | K18: roic, invested_capital, invested_capital_avg
A19: 코카콜라 | B19: KO | C19: FY2022 | D19: 0.59122723 | E19: 0.16082777 | F19: =E19-D19 -> -0.43039946 | G19: 10909000000 | H19: 10909000000 | I19: 15112000000 | J19: 55554000000 | K19: roic, invested_capital, invested_capital_avg
A20: KLA | B20: KLAC | C20: FY2018 | D20: 0.40336076 | E20: 0.8306849 | F20: =E20-D20 -> 0.42732414 | G20: 1455931000 | H20: 1535195000 | I20: 2165700500 | J20: 1108864500 | K20: roic, ebit, nopat, invested_capital_avg
A21: 필립모리스 인터내셔널 | B21: PM | C21: FY2020 | D21: 1.0672078 | E21: 0.64770167 | F21: =E21-D21 -> -0.41950609 | G21: 11668000000 | H21: 11668000000 | I21: 8560500000 | J21: 14105000000 | K21: roic, invested_capital, invested_capital_avg
A22: 마이크로소프트 | B22: MSFT | C22: FY2017 | D22: 1.1709817 | E22: 0.77036684 | F22: =E22-D22 -> -0.40061482 | G22: 29025000000 | H22: 29025000000 | I22: 21129500000 | J22: 32117500000 | K22: roic, invested_capital, invested_capital_avg
A23: 메타 플랫폼스 | B23: META | C23: FY2019 | E23: 0.40061041 | F23: — | G23: 23986000000 | H23: 23986000000 | J23: 44606000000 | K23: roic, invested_capital, invested_capital_avg
A24: 필립모리스 인터내셔널 | B24: PM | C24: FY2019 | D24: 0.93961672 | E24: 0.55735089 | F24: =E24-D24 -> -0.38226582 | G24: 10531000000 | H24: 10531000000 | I24: 8604500000 | J24: 14506000000 | K24: roic, invested_capital, invested_capital_avg
A25: KLA | B25: KLAC | C25: FY2016 | D25: 0.25948558 | E25: 0.62472071 | F25: =E25-D25 -> 0.36523513 | G25: 858192000 | H25: 943945000 | I25: 2714686500 | J25: 1240250000 | K25: roic, ebit, nopat, invested_capital, invested_capital_avg
A26: 필립모리스 인터내셔널 | B26: PM | C26: FY2021 | D26: 1.0691853 | E26: 0.70607841 | F26: =E26-D26 -> -0.3631069 | G26: 12975000000 | H26: 12975000000 | I26: 9485500000 | J26: 14363500000 | K26: roic, invested_capital, invested_capital_avg
A27: 팔로알토 네트웍스 | B27: PANW | C27: FY2016 | D27: -0.14226331 | E27: -0.47621 | F27: =E27-D27 -> -0.33394669 | G27: -157300000 | H27: -157300000 | I27: 873500000 | J27: 260950000 | K27: roic, invested_capital, invested_capital_avg
A28: 코카콜라 | B28: KO | C28: FY2020 | D28: 0.43312127 | E28: 0.12867501 | F28: =E28-D28 -> -0.30444625 | G28: 8997000000 | H28: 8997000000 | I28: 16551500000 | J28: 55712500000 | K28: roic, invested_capital, invested_capital_avg
A29: 마스터카드 | B29: MA | C29: FY2019 | D29: 1.2921077 | E29: 1.5898454 | F29: =E29-D29 -> 0.29773769 | G29: 9664000000 | H29: 9664000000 | I29: 6239500000 | J29: 5071000000 | K29: roic, invested_capital, invested_capital_avg
A30: 필립모리스 인터내셔널 | B30: PM | C30: FY2018 | D30: 0.87908959 | E30: 0.58295306 | F30: =E30-D30 -> -0.29613653 | G30: 11377000000 | H30: 11377000000 | I30: 9976500000 | J30: 15044500000 | K30: roic, invested_capital, invested_capital_avg
A31: 팔로알토 네트웍스 | B31: PANW | C31: FY2023 | D31: 0.082722398 | E31: 0.3753796 | F31: =E31-D31 -> 0.2926572 | G31: 387300000 | H31: 387300000 | I31: 3635250000 | J31: 801100000 | K31: roic, invested_capital, invested_capital_avg
A32: 코카콜라 | B32: KO | C32: FY2018 | D32: 0.42908736 | E32: 0.14070134 | F32: =E32-D32 -> -0.28838602 | G32: 9152000000 | H32: 9152000000 | I32: 16793500000 | J32: 51214000000 | K32: roic, invested_capital, invested_capital_avg
A33: 오라클 | B33: ORCL | C33: FY2021 | E33: 0.2831159 | F33: — | G33: 15213000000 | H33: 15213000000 | I33: -30839000000 | J33: 42450000000 | K33: roic, tax_rate, nopat, invested_capital, invested_capital_avg
A34: 시스코 시스템즈 | B34: CSCO | C34: FY2016 | D34: 0.12929528 | E34: 0.41171783 | F34: =E34-D34 -> 0.28242255 | G34: 12660000000 | H34: 12660000000 | I34: 81386500000 | J34: 25558500000 | K34: roic, invested_capital, invested_capital_avg
A35: 오라클 | B35: ORCL | C35: FY2020 | E35: 0.26788287 | F35: — | G35: 13896000000 | H35: 13896000000 | I35: -20080000000 | J35: 40980000000 | K35: roic, tax_rate, nopat, invested_capital, invested_capital_avg
A36: 오라클 | B36: ORCL | C36: FY2019 | E36: 0.26423135 | F36: — | G36: 13535000000 | H36: 13535000000 | I36: -13973000000 | J36: 40467000000 | K36: roic, tax_rate, nopat, invested_capital, invested_capital_avg
A37: 코카콜라 | B37: KO | C37: FY2019 | D37: 0.42027277 | E37: 0.15658795 | F37: =E37-D37 -> -0.26368482 | G37: 10086000000 | H37: 10086000000 | I37: 19991500000 | J37: 53656000000 | K37: roic, invested_capital, invested_capital_avg
A38: 필립모리스 인터내셔널 | B38: PM | C38: FY2016 | D38: 0.82840077 | E38: 0.57146557 | F38: =E38-D38 -> -0.25693521 | G38: 10903000000 | H38: 10903000000 | I38: 9490500000 | J38: 13757500000 | K38: roic, invested_capital, invested_capital_avg
A39: 램리서치 | B39: LRCX | C39: FY2018 | D39: 0.41759899 | E39: 0.65722234 | F39: =E39-D39 -> 0.23962334 | G39: 3213299000 | H39: 3213299000 | I39: 5812136000 | J39: 3693030500 | K39: roic, invested_capital, invested_capital_avg
A40: GE 버노바 | B40: GEV | C40: FY2022 | E40: -0.23857338 | F40: — | G40: -2881000000 | H40: -2881000000 | J40: 9540000000 | K40: roic, invested_capital, invested_capital_avg
A41: 램리서치 | B41: LRCX | C41: FY2017 | D41: 0.28983754 | E41: 0.52055414 | F41: =E41-D41 -> 0.23071661 | G41: 1902132000 | H41: 1902132000 | I41: 6150115500 | J41: 3424301500 | K41: roic, invested_capital, invested_capital_avg
A42: 시스코 시스템즈 | B42: CSCO | C42: FY2017 | D42: 0.10840825 | E42: 0.33540271 | F42: =E42-D42 -> 0.22699446 | G42: 11973000000 | H42: 11973000000 | I42: 86372000000 | J42: 27917000000 | K42: roic, invested_capital, invested_capital_avg
A43: 팔로알토 네트웍스 | B43: PANW | C43: FY2018 | D43: -0.2145374 | F43: — | G43: -104200000 | H43: -104200000 | I43: 383700000 | J43: -323000000 | K43: roic, invested_capital, invested_capital_avg
A44: 코카콜라 | B44: KO | C44: FY2016 | D44: 0.34673822 | E44: 0.13304771 | F44: =E44-D44 -> -0.21369051 | G44: 8657000000 | H44: 8657000000 | I44: 20100000000 | J44: 52383000000 | K44: roic, invested_capital, invested_capital_avg
A45: 램리서치 | B45: LRCX | C45: FY2021 | D45: 0.63503448 | E45: 0.84195609 | F45: =E45-D45 -> 0.2069216 | G45: 4482023000 | H45: 4482023000 | I45: 6311330000 | J45: 4760239000 | K45: roic, invested_capital, invested_capital_avg
A46: 코카콜라 | B46: KO | C46: FY2017 | D46: 0.29184307 | E46: 0.091557541 | F46: =E46-D46 -> -0.20028553 | G46: 7755000000 | H46: 7755000000 | I46: 15943500000 | J46: 50820500000 | K46: roic, invested_capital, invested_capital_avg
A47: 팔로알토 네트웍스 | B47: PANW | C47: FY2022 | D47: -0.04627451 | E47: -0.24618635 | F47: =E47-D47 -> -0.19991184 | G47: -188800000 | H47: -188800000 | I47: 3223200000 | J47: 605850000 | K47: roic, invested_capital, invested_capital_avg
A48: 필립모리스 인터내셔널 | B48: PM | C48: FY2017 | D48: 0.66598936 | E48: 0.46965867 | F48: =E48-D48 -> -0.19633069 | G48: 11581000000 | H48: 11581000000 | I48: 10433500000 | J48: 14795000000 | K48: roic, invested_capital, invested_capital_avg
A49: 오라클 | B49: ORCL | C49: FY2022 | E49: 0.18798545 | F49: — | G49: 10926000000 | H49: 10926000000 | I49: -28719500000 | J49: 45916000000 | K49: roic, tax_rate, nopat, invested_capital, invested_capital_avg
A50: 제너럴 일렉트릭 | B50: GE | C50: FY2023 | D50: 0.27060239 | E50: 0.08737603 | F50: =E50-D50 -> -0.18322636 | G50: 10441000000 | H50: 3723000000 | I50: 34911000000 | J50: 38552500000 | K50: roic, ebit, nopat, invested_capital, invested_capital_avg
A51: 램리서치 | B51: LRCX | C51: FY2020 | D51: 0.40669319 | E51: 0.58903545 | F51: =E51-D51 -> 0.18234226 | G51: 2673802000 | H51: 2673802000 | I51: 5749228500 | J51: 3969493000 | K51: roic, invested_capital, invested_capital_avg
A52: 팔로알토 네트웍스 | B52: PANW | C52: FY2021 | D52: -0.1625763 | E52: -0.34381252 | F52: =E52-D52 -> -0.18123622 | G52: -304100000 | H52: -304100000 | I52: 1477700000 | J52: 698750000 | K52: roic, invested_capital, invested_capital_avg
A53: 비자 | B53: V | C53: FY2018 | D53: 0.44298223 | E53: 0.2713166 | F53: =E53-D53 -> -0.17166563 | G53: 12954000000 | H53: 12954000000 | I53: 23522500000 | J53: 38405500000 | K53: roic, invested_capital, invested_capital_avg
A54: 제너럴 일렉트릭 | B54: GE | C54: FY2020 | D54: 0.072075793 | E54: -0.092166714 | F54: =E54-D54 -> -0.16424251 | G54: 5970000000 | H54: -5426000000 | I54: 78688000000 | J54: 55928000000 | K54: roic, ebit, nopat, invested_capital, invested_capital_avg
A55: 오라클 | B55: ORCL | C55: FY2023 | E55: 0.15908258 | F55: — | G55: 13093000000 | H55: 13093000000 | I55: -14713000000 | J55: 65019500000 | K55: roic, tax_rate, nopat, invested_capital, invested_capital_avg
A56: 시스코 시스템즈 | B56: CSCO | C56: FY2018 | D56: 0.13382863 | E56: 0.28632795 | F56: =E56-D56 -> 0.15249932 | G56: 12309000000 | H56: 12309000000 | I56: 55185500000 | J56: 25793500000 | K56: roic, invested_capital_avg
A57: 브로드컴 | B57: AVGO | C57: FY2018 | D57: 0.2830925 | E57: 0.14037322 | F57: =E57-D57 -> -0.14271929 | G57: 5135000000 | H57: 5135000000 | I57: 17232000000 | J57: 34752000000 | K57: roic, invested_capital, invested_capital_avg
A58: 팔로알토 네트웍스 | B58: PANW | C58: FY2024 | D58: 0.18842406 | E58: 0.3298226 | F58: =E58-D58 -> 0.14139854 | G58: 683900000 | H58: 684000000 | I58: 3448100000 | J58: 1970150000 | K58: roic, ebit, nopat, invested_capital, invested_capital_avg
A59: 램리서치 | B59: LRCX | C59: FY2019 | D59: 0.44405481 | E59: 0.58097307 | F59: =E59-D59 -> 0.13691826 | G59: 2464732000 | H59: 2464732000 | I59: 4971677000 | J59: 3799999000 | K59: roic, invested_capital, invested_capital_avg
A60: 브로드컴 | B60: AVGO | C60: FY2020 | D60: 0.19183519 | E60: 0.068894931 | F60: =E60-D60 -> -0.12294026 | G60: 4014000000 | H60: 4014000000 | I60: 19878000000 | J60: 55349500000 | K60: roic, invested_capital, invested_capital_avg
A61: 프록터앤드갬블 | B61: PG | C61: FY2016 | E61: 0.11486472 | F61: — | G61: 13441000000 | H61: 13441000000 | J61: 78014500000 | K61: roic, tax_rate, nopat, invested_capital, invested_capital_avg
A62: 필립모리스 인터내셔널 | B62: PM | C62: FY2022 | D62: 0.51008699 | E62: 0.4058536 | F62: =E62-D62 -> -0.10423339 | G62: 12246000000 | H62: 12246000000 | I62: 19377000000 | J62: 24353500000 | K62: roic, invested_capital, invested_capital_avg
A63: 코카콜라 | B63: KO | C63: FY2023 | D63: 0.27083567 | E63: 0.16804101 | F63: =E63-D63 -> -0.10279466 | G63: 11311000000 | H63: 11311000000 | I63: 34511500000 | J63: 55623000000 | K63: roic, invested_capital, invested_capital_avg
A64: 마이크로소프트 | B64: MSFT | C64: FY2018 | D64: 0.73751972 | E64: 0.63631909 | F64: =E64-D64 -> -0.10120064 | G64: 35058000000 | H64: 35058000000 | I64: 28521000000 | J64: 33057000000 | K64: roic, invested_capital_avg
A65: 애플 | B65: AAPL | C65: FY2025 | D65: 1.1332633 | E65: 1.039152 | F65: =E65-D65 -> -0.094111284 | G65: 133050000000 | H65: 133050000000 | I65: 99077500000 | J65: 108050500000 | K65: roic, invested_capital, invested_capital_avg
A66: 비자 | B66: V | C66: FY2017 | D66: 0.28063473 | E66: 0.18755695 | F66: =E66-D66 -> -0.093077774 | G66: 12144000000 | H66: 12144000000 | I66: 25964000000 | J66: 38849000000 | K66: roic, invested_capital, invested_capital_avg
A67: 브로드컴 | B67: AVGO | C67: FY2017 | D67: 0.18616828 | E67: 0.093251775 | F67: =E67-D67 -> -0.092916503 | G67: 2371000000 | H67: 2371000000 | I67: 12099000000 | J67: 24154500000 | K67: roic, invested_capital, invested_capital_avg
A68: 브로드컴 | B68: AVGO | C68: FY2021 | D68: 0.2326057 | E68: 0.14680338 | F68: =E68-D68 -> -0.085802319 | G68: 8519000000 | H68: 8519000000 | I68: 34793000000 | J68: 55128500000 | K68: roic, invested_capital_avg
A69: 제너럴 일렉트릭 | B69: GE | C69: FY2024 | D69: 0.24400344 | E69: 0.15825181 | F69: =E69-D69 -> -0.085751633 | G69: 7620000000 | H69: 5356000000 | I69: 27286500000 | J69: 29572000000 | K69: roic, ebit, nopat, invested_capital, invested_capital_avg
A70: 비자 | B70: V | C70: FY2019 | D70: 0.39353401 | E70: 0.31017027 | F70: =E70-D70 -> -0.083363742 | G70: 15001000000 | H70: 15001000000 | I70: 30937500000 | J70: 39252500000 | K70: roic, invested_capital_avg
A71: 애브비 | B71: ABBV | C71: FY2019 | D71: 0.65518251 | E71: 0.57239499 | F71: =E71-D71 -> -0.082787525 | G71: 12983000000 | H71: 12983000000 | I71: 18536500000 | J71: 21217500000 | K71: roic, invested_capital, invested_capital_avg
A72: GE 버노바 | B72: GEV | C72: FY2023 | D72: -0.16859422 | E72: -0.088309313 | F72: =E72-D72 -> 0.080284906 | G72: -923000000 | H72: -923000000 | I72: 4325000000 | J72: 8257000000 | K72: roic, invested_capital, invested_capital_avg
A73: 제너럴 일렉트릭 | B73: GE | C73: FY2025 | D73: 0.3575663 | E73: 0.28024526 | F73: =E73-D73 -> -0.077321042 | G73: 10000000000 | H73: 8513000000 | I73: 24037500000 | J73: 26109000000 | K73: roic, ebit, nopat, invested_capital, invested_capital_avg
... A92: KLA | B92: KLAC | C92: FY2024 | D92: 0.40678799 | E92: 0.35845898 | F92: =E92-D92 -> -0.048329009 | G92: 3501285000 | H92: 3085310000 | I92: 7451979000 | J92: 7451979000 | K92: roic, ebit, nopat
A93: 델 테크놀로지스 | B93: DELL | C93: FY2019 | D93: 0.047164774 | F93: — | G93: 2366000000 | H93: 2366000000 | I93: 39630000000 | J93: 44406000000 | K93: roic, invested_capital, invested_capital_avg
A94: 애플 | B94: AAPL | C94: FY2016 | D94: 0.26226104 | E94: 0.30794128 | F94: =E94-D94 -> 0.04568024 | G94: 60024000000 | H94: 60024000000 | I94: 170378000000 | J94: 145104000000 | K94: roic, invested_capital, invested_capital_avg
A95: KLA | B95: KLAC | C95: FY2025 | D95: 0.52374312 | E95: 0.4814352 | F95: =E95-D95 -> -0.042307919 | G95: 4946614000 | H95: 4547027000 | I95: 8259568000 | J95: 8259568000 | K95: roic, ebit, nopat
A96: 존슨앤드존슨 | B96: JNJ | C96: FY2024 | D96: 0.18511415 | E96: 0.22691925 | F96: =E96-D96 -> 0.041805104 | G96: 17442000000 | H96: 21381000000 | I96: 79423500000 | J96: 79423500000 | K96: roic, ebit, nopat
A97: AMD | B97: AMD | C97: FY2016 | D97: -0.33676571 | E97: -0.29764646 | F97: =E97-D97 -> 0.03911925 | G97: -373000000 | H97: -373000000 | I97: 875000000 | J97: 990000000 | K97: roic, invested_capital_avg
A98: 애플 | B98: AAPL | C98: FY2020 | D98: 0.65262099 | E98: 0.61386135 | F98: =E98-D98 -> -0.038759634 | G98: 66288000000 | H98: 66288000000 | I98: 86917000000 | J98: 92405000000 | K98: roic, invested_capital, invested_capital_avg
A99: IBM | B99: IBM | C99: FY2016 | D99: 0.28942512 | E99: 0.25087619 | F99: =E99-D99 -> -0.038548931 | G99: 12960000000 | H99: 12960000000 | I99: 42539500000 | J99: 49076000000 | K99: roic, invested_capital, invested_capital_avg
A100: 메타 플랫폼스 | B100: META | C100: FY2021 | D100: 0.50633933 | E100: 0.54362086 | F100: =E100-D100 -> 0.037281526 | G100: 46753000000 | H100: 46753000000 | I100: 76881000000 | J100: 71608500000 | K100: roic, invested_capital_avg
A101: 존슨앤드존슨 | B101: JNJ | C101: FY2020 | D101: 0.20840474 | E101: 0.24502748 | F101: =E101-D101 -> 0.03662274 | G101: 16497000000 | H101: 19396000000 | I101: 70603000000 | J101: 70603000000 | K101: roic, ebit, nopat
A102: 비자 | B102: V | C102: FY2024 | D102: 0.42852136 | E102: 0.46450313 | F102: =E102-D102 -> 0.035981774 | G102: 23595000000 | H102: 23595000000 | I102: 45454000000 | J102: 41933000000 | K102: roic, invested_capital, invested_capital_avg
A103: 제너럴 일렉트릭 | B103: GE | C103: FY2018 | D103: -0.13465388 | E103: -0.17032338 | F103: =E103-D103 -> -0.035669502 | G103: -20987000000 | H103: -23308000000 | I103: 123128500000 | J103: 108108000000 | K103: roic, ebit, nopat, invested_capital, invested_capital_avg
A104: 비자 | B104: V | C104: FY2023 | D104: 0.40450946 | E104: 0.43887194 | F104: =E104-D104 -> 0.034362481 | G104: 21000000000 | H104: 21000000000 | I104: 42626000000 | J104: 39288500000 | K104: roic, invested_capital, invested_capital_avg
A105: 엔비디아 | B105: NVDA | C105: FY2024 | D105: 1.9480321 | E105: 1.9821923 | F105: =E105-D105 -> 0.034160181 | G105: 81453000000 | H105: 81453000000 | I105: 36266500000 | J105: 35641500000 | K105: roic, invested_capital_avg
... A147: 홈디포 | B147: HD | C147: FY2017 | D147: 0.38527549 | E147: 0.36789009 | F147: =E147-D147 -> -0.0173854 | G147: 14681000000 | H147: 14681000000 | I147: 24007000000 | J147: 25141500000 | K147: roic, invested_capital, invested_capital_avg
A148: 브로드컴 | B148: AVGO | C148: FY2016 | E148: -0.017205922 | F148: — | G148: -409000000 | H148: -409000000 | J148: 18779000000 | K148: roic, invested_capital, invested_capital_avg
A149: 일라이 릴리 | B149: LLY | C149: FY2023 | D149: 0.19494174 | E149: 0.17812752 | F149: =E149-D149 -> -0.01681422 | G149: 7040000000 | H149: 6457000000 | I149: 28873050000 | J149: 28981750000 | K149: roic, ebit, nopat, invested_capital, invested_capital_avg
A150: 머크 | B150: MRK | C150: FY2024 | D150: 0.26944954 | E150: 0.25272105 | F150: =E150-D150 -> -0.016728487 | G150: 21207000000 | H150: 19912000000 | I150: 67639000000 | J150: 67712500000 | K150: roic, ebit, nopat, invested_capital, invested_capital_avg
A151: 월마트 | B151: WMT | C151: FY2021 | D151: 0.18565832 | E151: 0.16900806 | F151: =E151-D151 -> -0.016650258 | G151: 25942000000 | H151: 25942000000 | I151: 104184500000 | J151: 114448500000 | K151: roic, invested_capital, invested_capital_avg
A152: 존슨앤드존슨 | B152: JNJ | C152: FY2018 | D152: 0.20813944 | E152: 0.22438678 | F152: =E152-D152 -> 0.016247342 | G152: 17999000000 | H152: 19404000000 | I152: 73494000000 | J152: 73494000000 | K152: roic, ebit, nopat
A153: 월마트 | B153: WMT | C153: FY2023 | D153: 0.18791443 | E153: 0.17190601 | F153: =E153-D153 -> -0.016008418 | G153: 27012000000 | H153: 27012000000 | I153: 107046500000 | J153: 117015000000 | K153: roic, invested_capital, invested_capital_avg
A154: 일라이 릴리 | B154: LLY | C154: FY2018 | D154: 0.21057627 | E154: 0.19472191 | F154: =E154-D154 -> -0.015854361 | G154: 3680100000 | H154: 3534500000 | I154: 14961800000 | J154: 15539850000 | K154: roic, ebit, nopat, invested_capital, invested_capital_avg
A155: 제너럴 일렉트릭 | B155: GE | C155: FY2022 | D155: 0.028919525 | E155: 0.013175846 | F155: =E155-D155 -> -0.01574368 | G155: 1522000000 | H155: 711000000 | I155: 46785000000 | J155: 47970500000 | K155: roic, ebit, nopat, invested_capital, invested_capital_avg
A156: 델 테크놀로지스 | B156: DELL | C156: FY2016 | D156: -0.060971357 | E156: -0.07635391 | F156: =E156-D156 -> -0.015382553 | G156: -2390000000 | H156: -3252000000 | I156: 30967000000 | J156: 33647000000 | K156: roic, ebit, nopat, invested_capital, invested_capital_avg
A157: 머크 | B157: MRK | C157: FY2020 | D157: 0.099558667 | E157: 0.084288943 | F157: =E157-D157 -> -0.015269724 | G157: 5863000000 | H157: 4973000000 | I157: 45430500000 | J157: 45515000000 | K157: roic, ebit, nopat, invested_capital, invested_capital_avg
A158: 애브비 | B158: ABBV | C158: FY2023 | D158: 0.17017045 | E158: 0.1550548 | F158: =E158-D158 -> -0.015115651 | G158: 12757000000 | H158: 12757000000 | I158: 58449500000 | J158: 64147500000 | K158: roic, invested_capital, invested_capital_avg
A159: 테슬라 | B159: TSLA | C159: FY2017 | D159: -0.13668737 | E159: -0.121608 | F159: =E159-D159 -> 0.015079371 | G159: -1632000000 | H159: -1632000000 | I159: 9432327500 | J159: 10601934500 | K159: roic, invested_capital, invested_capital_avg
...

Sheet 경로 검정
A1: 영업이익 소계를 보고하지 않는 기업의 분자를 어떻게 만들지, 주장이 아니라 측정으로 정했습니다. 소계가 보고된 기업-연도에서 각 구성 방식을 보고치와 맞춰본 결과입니다.
A2: 구성 경로 | B2: 검정 건수 | C2: ±2% 일치 | D2: 정확도 | E2: 중위 오차
A3: B 매출총이익 − 영업비용 | B3: 228 | C3: 228 | D3: =IF(B3=0,"",C3/B3) -> 1 | E3: 0
A4: D 매출 − 매출원가 − 영업비용 | B4: 241 | C4: 228 | D4: =IF(B4=0,"",C4/B4) -> 0.94605809 | E4: 0
A5: C 매출 − 총비용 | B5: 176 | C5: 151 | D5: =IF(B5=0,"",C5/B5) -> 0.85795455 | E5: 0
A6: F 세전이익 − 영업외수익 | B6: 478 | C6: 241 | D6: =IF(B6=0,"",C6/B6) -> 0.5041841 | E6: 0.017362902
A7: E 매출총이익 − R&D − 판관비 | B7: 342 | C7: 161 | D7: =IF(B7=0,"",C7/B7) -> 0.47076023 | E7: 0.035024821
A8: G 세전이익 + 이자비용 − 이자·투자수익 | B8: 503 | C8: 212 | D8: =IF(B8=0,"",C8/B8) -> 0.42147117 | E8: 0.028697572
A9: H 세전이익 + 이자비용 (감사에서 기각된 방식) | B9: 503 | C9: 165 | D9: =IF(B9=0,"",C9/B9) -> 0.32803181 | E9: 0.036949846
A12: ±2% 일치율은 이 문제에 맞는 통계가 아닙니다. ROIC를 10% 문턱과 비교하는 것이 목적이므로, 중요한 건 분자를 바꿨을 때 문턱 판정이 뒤집히는지입니다.
A14: 회사별 최종 선택 경로
A15: 기업 | B15: 티커 | C15: 선택 경로 | D15: 역검증 통과 | E15: 중위 역검증 오차 | F15: 우선순위
A16: 버크셔 해서웨이 | B16: BRK-B | C16: pretax_plus_interest_less_investment_income | D16: 미통과 | F16: pretax_plus_interest_less_investment_income → pretax_less_nonoperating
A17: 일라이 릴리 | B17: LLY | C17: pretax_less_nonoperating | D17: 미통과 | F17: pretax_less_nonoperating → pretax_plus_interest_less_investment_income
A18: JP모건 체이스 | B18: JPM | C18: pretax_plus_interest_less_investment_income | D18: 미통과 | F18: pretax_plus_interest_less_investment_income
A19: 엑슨모빌 | B19: XOM | C19: pretax_plus_interest_less_investment_income | D19: 미통과 | F19: pretax_plus_interest_less_investment_income → pretax_less_nonoperating
A20: 존슨앤드존슨 | B20: JNJ | C20: pretax_less_nonoperating | D20: 미통과 | F20: pretax_less_nonoperating → pretax_plus_interest_less_investment_income
A21: 뱅크오브아메리카 | B21: BAC | C21: pretax_plus_interest_less_investment_income | D21: 미통과 | F21: pretax_plus_interest_less_investment_income
A22: 제너럴 일렉트릭 | B22: GE | C22: pretax_less_nonoperating | D22: 미통과 | F22: pretax_less_nonoperating
A23: 셰브론 | B23: CVX | C23: pretax_plus_interest_less_investment_income | D23: 미통과 | F23: pretax_plus_interest_less_investment_income → pretax_less_nonoperating
A24: 모건스탠리 | B24: MS | C24: pretax_plus_interest_less_investment_income | D24: 미통과 | F24: pretax_plus_interest_less_investment_income → pretax_less_nonoperating
A25: 머크 | B25: MRK | C25: pretax_less_nonoperating | D25: 미통과 | F25: pretax_less_nonoperating → pretax_plus_interest_less_investment_income
A26: 웰스파고 | B26: WFC | C26: pretax_plus_interest_less_investment_income | D26: 미통과 | F26: pretax_plus_interest_less_investment_income
A27: KLA | B27: KLAC | C27: verified_line_build | D27: 통과 | E27: 0.03384618 | F27: verified_line_build → pretax_less_nonoperating → pretax_plus_interest_less_investment_income
A28: 아메리칸 익스프레스 | B28: AXP | C28: pretax_plus_interest_less_investment_income | D28: 미통과 | F28: pretax_plus_interest_less_investment_income
A29: 씨티그룹 | B29: C | C29: pretax_plus_interest_less_investment_income | D29: 미통과 | F29: pretax_plus_interest_less_investment_income → pretax_less_nonoperating
A30: IBM | B30: IBM | C30: pretax_plus_interest_less_investment_income | D30: 미통과 | F30: pretax_plus_interest_less_investment_income → pretax_less_nonoperating
