Workbook

Sheet 요약
A1: 버핏 기준 52개 기업 분석
A2: 생성 2026-08-11 08:18 UTC · 미국 50개사 정량 + 한국 2개사 정성
A4: 이 파일 읽는 법
A5: 글자 색 | B5: 파란 글씨는 10-K나 시세에서 그대로 가져온 원천 수치입니다. 검은 글씨는 같은 시트에서 계산한 수식이고, 초록 글씨는 다른 시트를 참조하는 수식입니다. 노란 셀은 바꿔볼 수 있는 가정입니다.
A6: 계산을 따라가는 순서 | B6: 연도별계산 → 품질순위 → DCF계산 → 밸류에이션 순으로 보시면 원천 수치가 비율이 되고, 비율이 점수와 적정가치가 되는 과정이 이어집니다. 각 열의 정의와 산식은 '산식정의' 시트에 정리했습니다.
A7: 가정을 바꾸려면 | B7: '기준표' 시트의 노란 셀을 바꾸면 배점과 적정가치가 함께 움직입니다. 예를 들어 기준 할인율을 10%에서 9%로 낮추면 모든 적정가치가 올라갑니다.
A9: 핵심 결론 | B9: 비금융 41개사 중 36개사가 ROIC로 자본비용을 넘겼지만, 할인율 10% 기준 DCF에서 안전마진 30% 이상인 기업은 0개입니다.
A10: 경계선 | B10: 0개사 (없음). 나머지는 전부 적정가치 추정 범위 밖에서 거래되고 있습니다.
A11: 주주이익 음수 | B11: 2개사 (INTC, AMD). 이익이 없어서가 아니라 설비투자와 운전자본이 순이익을 넘어서기 때문이며, 데이터 공백이 아니라 사업 판정입니다.
A12: 금융업 처리 | B12: 9개사는 ROIC·주주이익을 산출하지 않았습니다. 은행에서 부채는 자금조달이 아니라 원재료라 투하자본이 정의되지 않습니다. SIC 6000~6799 기준.
A13: 한국 2개사 | B13: 삼성전자·SK하이닉스는 정성 분석만 했습니다. DART 접근에 인증키가 필요해 감사받은 1차 출처를 확보할 수 없었고, 기억으로 숫자를 채우지 않았습니다.
A14: 검증 (PHASE 6) | B14: 50/50개사 통과. 각 수치를 해당 10-K 원문의 인라인 XBRL과 대조하고, 인용 접수번호가 EDGAR에 실재하는지 확인하고, 주식수를 재파싱으로 재현했습니다.
A16: 주의 | B16: 이 분석은 '지금 투자 가능 구간 안인가'라는 질문에만 답합니다. 목표주가가 아니며, DCF는 3개 시나리오의 범위로만 읽어야 합니다. 비자의 시가총액은 클래스 B·C 전환분이 빠져 과소평가돼 있어 실제 안전마진은 표시된 값보다 나쁩니다.

Sheet 산식정의
A1: 산식 정의 — 각 열이 어떻게 계산되는가
A2: 시트별로 열 하나하나의 정의와 산식, 그리고 왜 그렇게 계산했는지를 적었습니다.
A4: 시트 | B4: 열 | C4: 산식 | D4: 설명 | E4: 참조 대상
A5: 연도별계산 | B5: 매출 / 세전이익 / 이자비용 / 법인세비용 / 순이익 / 감가상각 / 설비투자 / 자기자본 / 현금 / 단기·장기차입금 / 유동자산 / 유동부채 | C5: 원천 (파란 셀) | D5: 각 회계연도 10-K의 XBRL 태그 값을 그대로 가져온 것. 가공하지 않았습니다. | E5: SEC EDGAR companyfacts, 접수번호 열로 해당 10-K 특정 가능
A6: 연도별계산 | B6: 영업이익(EBIT) | C6: 세전이익 + 이자비용 | D6: 세전이익과 이자비용이 모두 있으면 둘을 더합니다. 릴리·엑슨모빌·IBM·머크·셰브론은 영업이익 소계를 아예 태깅하지 않아, 태그가 있는 회사만 보고된 영업이익을 쓰면 ROIC가 회사마다 다른 것을 뜻하게 됩니다. 그래서 전 종목을 같은 방식으로 맞췄고, 이자비용이 없는 회사만 보고된 영업이익으로 대체합니다. | E6: 같은 행의 원천 셀
A7: 연도별계산 | B7: 실효세율 | C7: 법인세비용 ÷ 세전이익 (5~40%로 제한) | D7: 세전이익이 없거나 음수면 기본 세율 21%를 씁니다. 범위를 벗어나는 값은 일회성 항목의 결과라 한계 세율을 대표하지 못하므로 상·하한을 둡니다. | E7: 기준표의 세율 셀 3개
A8: 연도별계산 | B8: NOPAT | C8: 영업이익(EBIT) × (1 − 실효세율) | D8: 세후 영업이익. ROIC의 분자입니다. | E8: 같은 행
A9: 연도별계산 | B9: 이자부부채 | C9: 단기차입금 + 장기차입금 | D9: 한쪽만 태깅된 경우 나머지는 0으로 봅니다. 잔액이 0이면 태그를 생략하는 것이 관행이기 때문입니다. 양쪽 다 없으면 공란으로 둡니다. | E9: 같은 행
A10: 연도별계산 | B10: 투하자본 | C10: 자기자본 + 이자부부채 − 현금 | D10: 현금을 빼는 이유는 놀고 있는 현금이 사업에 투입된 자본이 아니기 때문입니다. 빼지 않으면 현금이 많은 대형주의 ROIC가 실제보다 낮게 나옵니다. | E10: 같은 행
A11: 연도별계산 | B11: 투하자본(평균) | C11: (당기 투하자본 + 전기 투하자본) ÷ 2 | D11: 기말 잔고를 쓰면 연말에 자본을 조달한 회사가 한 해 내내 그 자본으로 벌어들인 것처럼 보입니다. 전기 값이 없으면 당기 값을 그대로 씁니다. | E11: 같은 행
A12: 연도별계산 | B12: ROIC | C12: NOPAT ÷ 투하자본(평균) | D12: 원칙 1의 핵심 지표. 순위와 배점은 현금을 빼지 않은 '총' 기준을 씁니다 — 현금을 빼는 것이 원칙적으로는 맞지만 보유 현금이 자본 전체에 근접하면 분모가 0에 수렴해 비율이 의미를 잃기 때문입니다. 아리스타의 순ROIC는 96~192%를 오가는 반면 총ROIC는 23~32%입니다. | E12: 같은 행
A13: 연도별계산 | B13: ROE | C13: 순이익 ÷ 자기자본(평균) | D13: 원칙 2에서 ROIC와 비교합니다. | E13: 같은 행
A14: 연도별계산 | B14: ROE−ROIC | C14: ROE − ROIC | D14: 차이가 크면 ROE가 사업의 수익성이 아니라 레버리지에서 나온다는 신호입니다. 다만 자사주 매입으로 자기자본이 줄어도 같은 형태로 벌어지므로 부채 지표를 함께 봐야 합니다. | E14: 같은 행
A15: 연도별계산 | B15: EBITDA | C15: 영업이익(EBIT) + 감가상각 | E15: 같은 행
A16: 연도별계산 | B16: 순부채/EBITDA | C16: (이자부부채 − 현금) ÷ EBITDA | D16: 레버리지 건전성. | E16: 같은 행
A17: 연도별계산 | B17: 이자보상배율 | C17: 영업이익(EBIT) ÷ 이자비용 | D17: 이자를 몇 배로 감당하는지. | E17: 같은 행
A18: 연도별계산 | B18: 운전자본(영업) | C18: 유동자산 − 현금 − (유동부채 − 단기차입금) | D18: 현금과 단기차입금을 빼는 것이 핵심입니다. 유동자산에는 현금이 포함되므로 그대로 두면 현금을 쌓은 회사가 운전자본을 소모한 것처럼 보입니다. 단기차입금은 영업이 아니라 자금조달이라 같은 이유로 뺍니다. | E18: 같은 행
A19: 연도별계산 | B19: 운전자본증감 | C19: 당기 운전자본(영업) − 전기 운전자본(영업) | D19: 양수면 그해 운전자본이 현금을 흡수했다는 뜻입니다. | E19: 같은 행
A20: 연도별계산 | B20: 주주이익 | C20: 순이익 + 감가상각 − 설비투자 − 운전자본증감 | D20: 버핏의 owner earnings 정의입니다. 네 항목이 모두 같은 회계기간이어야 합니다. | E20: 같은 행
A21: 연도별계산 | B21: 주주이익률 / 영업이익률 | C21: 각각 주주이익 ÷ 매출, 영업이익(EBIT) ÷ 매출 | E21: 같은 행
A22: 품질순위 | B22: ROIC 중앙값 · 신규 ROIC · ROIC−WACC · WACC 등 (파란 셀) | C22: 여러 해에 걸친 집계값 | D22: 연도별계산의 여러 행을 걸쳐 계산한 값이라 한 행의 수식으로는 표현되지 않습니다. ROIC 중앙값은 관측된 모든 해의 ROIC 중앙값이고, 신규 ROIC는 (기간말 NOPAT − 기간초 NOPAT) ÷ (기간말 투하자본 − 기간초 투하자본)입니다. | E22: 연도별계산 시트의 해당 기업 행들
A23: 품질순위 | B23: 지속성 비율 | C23: 두자릿수 년수 ÷ 관측 년수 | D23: ROIC가 10%를 넘긴 해의 비율. 높은 평균보다 꾸준함이 해자에 가깝다는 것이 원칙 1의 취지입니다. | E23: 같은 행
A24: 품질순위 | B24: 배점 7개 열 | C24: 각 지표를 기준표의 문턱값과 비교한 조건식 | D24: 셀을 클릭하면 어떤 조건에서 몇 점이 나왔는지 그대로 보입니다. 배점: ROIC 25 · 지속성 20 · 신규 ROIC 20 · 스프레드 15 · 주주이익률 10 · 순부채 5 · 이자보상 5 (합계 100). | E24: 같은 행 + 기준표
A25: 품질순위 | B25: 총점 | C25: 배점 7개 열의 합계 | D25: 백분위가 아니라 절대 기준입니다. | E25: 같은 행
A26: DCF계산 | B26: 적용 성장률 | C26: 과거 주주이익 성장률 × 시나리오 배수, 상한 적용 | D26: 과거 성장률이 없으면 3%를 씁니다. 상한은 보수·기준 10%, 낙관 15%입니다 — 10년을 그보다 빠르게 복리성장한다고 보지 않습니다. | E26: 기준표
A27: DCF계산 | B27: 1~10년차 PV | C27: 기준 주주이익 × (1+성장률)^t ÷ (1+할인율)^t | D27: t년차 주주이익을 현재가치로 할인한 값. | E27: 같은 행
A28: DCF계산 | B28: 영구가치 | C28: 10년차 현금흐름 × (1+영구성장률) ÷ (할인율 − 영구성장률) | D28: 고든 성장 모형. 할인율이 영구성장률 이하면 값이 발산하므로 공란으로 둡니다. | E28: 같은 행
A29: DCF계산 | B29: 적정가치 | C29: 예측기간 PV 합계 + 영구가치 PV | E29: 같은 행
A30: DCF계산 | B30: 안전마진 | C30: (적정가치 − 시가총액) ÷ 적정가치 | D30: 양수면 적정가치보다 싸게 거래된다는 뜻입니다. | E30: 같은 행
A31: DCF계산 | B31: 판정 | C31: 안전마진 ≥ 30% 투자가능 / ≥ 0% 경계선 / 그 외 범위밖 | D31: 목표주가가 아니라 '지금 투자 가능 구간 안인가'에 대한 답입니다. | E31: 기준표
A32: 밸류에이션 | B32: PER / PBR / PSR | C32: 시가총액 ÷ (최근 순이익 / 자기자본 / 매출) | D32: PER은 순이익이 양수일 때만 계산합니다. 적자에서는 의미가 없습니다. | E32: 같은 행
A33: 밸류에이션 | B33: 기준 적정가치 · 안전마진 · 판정 | C33: DCF계산 시트의 기준 시나리오 행 참조 | D33: 초록 글씨는 다른 시트를 가리킵니다. 클릭하면 해당 행으로 따라갈 수 있습니다. | E33: DCF계산
A34: 전체 | B34: 시가총액 | C34: 10-K 표지의 주식수 × 최근 종가 | D34: 표지 주식수는 결산일보다 최신이고 클래스별로 나뉘어 있어 합산했습니다. 버크셔는 A주를 B주 1,500배로 환산했습니다. 비자는 클래스 B·C의 전환비율이 이사회 재량이라 클래스 A만 썼고, 그만큼 시가총액이 과소평가돼 있습니다. | E34: SEC 10-K 표지 인라인 XBRL + 거래소 종가
A35: 전체 | B35: 주식수 시계열 | C35: 액면분할 기준을 통일한 뒤 비교 | D35: 각 연도 주식수는 그해 10-K의 단위로 기록되는데 10-K는 직전 2년까지만 소급 수정하므로, 분할을 가로지르면 신주 발행처럼 보입니다. 조정 전 엔비디아는 연 41% 희석으로 나왔으나 실제로는 4:1과 10:1 분할이었습니다. 정수가 아닌 비율(델 1806:1000, GE 1281:1000)은 스핀오프에 따른 주가 조정이라 적용하지 않았습니다. | E35: 거래소 분할 이력

Sheet 기준표
A1: 기준표 — 가정과 판정 기준
A2: 노란 셀은 바꿀 수 있는 가정입니다. 다른 시트의 수식이 이 셀들을 참조하므로, 값을 바꾸면 점수와 적정가치가 함께 움직입니다.
A4: 항목 | B4: 값 | C4: 설명
A5: 세율
A6: 실효세율 하한 | B6: 0.05 | C6: 이보다 낮은 실효세율은 일회성 항목의 결과로 보고 하한을 적용
A7: 실효세율 상한 | B7: 0.4 | C7: 이보다 높은 실효세율도 마찬가지로 상한을 적용
A8: 기본 세율 | B8: 0.21 | C8: 세전이익이 없거나 음수여서 실효세율을 낼 수 없을 때 쓰는 미국 연방 법정세율
A9: 품질 배점 기준
A10: ROIC 25점 기준 | B10: 0.3 | C10: ROIC 중앙값이 이 이상이면 25점
A11: ROIC 20점 기준 | B11: 0.2
A12: ROIC 15점 기준 | B12: 0.15
A13: ROIC 10점 기준 | B13: 0.1
A14: 신규ROIC 20점 기준 | B14: 0.2 | C14: 증분 ROIC가 이 이상이면 20점
A15: 신규ROIC 15점 기준 | B15: 0.15
A16: 신규ROIC 10점 기준 | B16: 0.1
A17: 스프레드 15점 기준 | B17: 0.15 | C17: ROIC−WACC가 이 이상이면 15점
A18: 스프레드 12점 기준 | B18: 0.1
A19: 스프레드 8점 기준 | B19: 0.05
A20: 주주이익률 10점 기준 | B20: 0.2 | C20: 정규화 주주이익 ÷ 매출이 이 이상이면 10점
A21: 주주이익률 7점 기준 | B21: 0.1
A22: 주주이익률 4점 기준 | B22: 0.05
A23: 순부채 5점 기준 | B23: 1 | C23: 순부채/EBITDA가 이 이하면 5점
A24: 순부채 4점 기준 | B24: 2
A25: 순부채 2점 기준 | B25: 3
A26: 이자보상 5점 기준 | B26: 10 | C26: 이자보상배율이 이 이상이면 5점
A27: 이자보상 3점 기준 | B27: 5
A28: 이자보상 1점 기준 | B28: 2
A29: DCF 가정
A30: 예측기간(년) | B30: 10 | C30: 명시적으로 현금흐름을 추정하는 기간
A31: 보수 할인율 | B31: 0.12
A32: 보수 영구성장률 | B32: 0.02
A33: 보수 성장률 배수 | B33: 0.5 | C33: 과거 주주이익 성장률에 곱하는 배수
A34: 기준 할인율 | B34: 0.1
A35: 기준 영구성장률 | B35: 0.025
A36: 기준 성장률 배수 | B36: 1
A37: 낙관 할인율 | B37: 0.08
A38: 낙관 영구성장률 | B38: 0.03
A39: 낙관 성장률 배수 | B39: 1.25
A40: 성장률 상한(보수·기준) | B40: 0.1 | C40: 10년을 이 속도보다 빠르게 복리성장한다고 보지 않음
A41: 성장률 상한(낙관) | B41: 0.15
A42: 안전마진 투자가능 기준 | B42: 0.3 | C42: 안전마진이 이 이상이면 투자 가능 구간
A43: 매크로
A44: 무위험수익률 | B44: 0.0465 | C44: DGS10 (10-Year Treasury Constant Maturity Rate) · 2026-08-07 · https://fred.stlouisfed.org/graph/fredgraph.csv?id=DGS10
A45: 주식위험프리미엄 | B45: 0.0446 | C45: Damodaran (NYU Stern) · January 5, 2026 · https://pages.stern.nyu.edu/~adamodar/New_Home_Page/datafile/ctryprem.html

Sheet 연도별계산
A1: 연도별 계산 — 원천 수치와 그로부터 나온 모든 비율
A2: 파란 셀은 10-K에서 그대로 가져온 원천 수치이고, 검은 셀은 같은 행의 파란 셀로 계산한 수식입니다. 어떤 비율이든 셀을 클릭하면 수식 입력줄에 계산이 그대로 보입니다. 금액 단위는 십억 USD. 접수번호로 해당 10-K를 특정할 수 있습니다.
A4: 티커 | B4: 기업 | C4: 회계연도 | D4: 결산일 | E4: 업종구분 | F4: 접수번호 | G4: 매출 | H4: 세전이익 | I4: 이자비용 | J4: 법인세비용 | K4: 영업이익(보고) | L4: 순이익 | M4: 감가상각 | N4: 설비투자 | O4: 영업현금흐름 | P4: 자기자본 | Q4: 자기자본(전기) | R4: 현금 | S4: 현금(전기) | T4: 단기차입금 | U4: 단기차입금(전기) | V4: 장기차입금 | W4: 유동자산 | X4: 유동자산(전기) | Y4: 유동부채 | Z4: 유동부채(전기) | AA4: 투하자본(전기) | AB4: 주식수(백만주) | AC4: 영업이익(EBIT) | AD4: 실효세율 | AE4: NOPAT | AF4: 이자부부채 | AG4: 투하자본 | AH4: 투하자본(평균) | AI4: ROIC(순) | AJ4: 투하자본(총) | AK4: ROIC(총) | AL4: 자기자본(평균) | AM4: ROE | AN4: ROE−ROIC | AO4: EBITDA | AP4: 순부채/EBITDA | AQ4: 이자보상배율 | AR4: 운전자본(영업) | AS4: 운전자본(전기) | AT4: 운전자본증감 | AU4: 주주이익 | AV4: 주주이익 산출방식 | AW4: 주주이익률 | AX4: 영업이익률
A5: NVDA | B5: NVIDIA CORP | C5: 2014 | D5: 2015-01-25 | E5: 일반 | F5: 0001045810-17-000027 | G5: 4.682 | J5: 0.124 | K5: 0.759 | L5: 0.631 | M5: 0.143 | O5: 0.906 | P5: 4.418 | R5: 4.623 | V5: 1.384 | W5: 5.713 | Y5: 0.896 | AB5: 21800 | AC5: =IF(AND(ISNUMBER(H5),ISNUMBER(I5)),H5+I5,IF(ISNUMBER(K5),K5,IF(ISNUMBER(H5),H5,""))) | AD5: =IF(OR(NOT(ISNUMBER(J5)),NOT(ISNUMBER(H5)),H5<=0),기준표!$B$8,MIN(MAX(J5/H5,기준표!$B$6),기준표!$B$7)) | AE5: =IF(ISNUMBER(AC5),AC5*(1-AD5),"") | AF5: =IF(AND(NOT(ISNUMBER(T5)),NOT(ISNUMBER(V5))),"",IF(ISNUMBER(T5),T5,0)+IF(ISNUMBER(V5),V5,0)) | AG5: =IF(E5="금융","",IF(AND(ISNUMBER(P5),ISNUMBER(AF5),ISNUMBER(R5)),P5+AF5-R5,"")) | AH5: =IF(E5="금융","",IF(NOT(ISNUMBER(AG5)),"",IF(ISNUMBER(AA5),(AG5+AA5)/2,AG5))) | AI5: =IF(AND(ISNUMBER(AE5),ISNUMBER(AH5),AH5>0),AE5/AH5,"") | AJ5: =IF(E5="금융","",IF(AND(ISNUMBER(P5),ISNUMBER(AF5)),P5+AF5,"")) | AK5: =IF(OR(NOT(ISNUMBER(AE5)),NOT(ISNUMBER(AJ5)),AJ5<=0),"",IF(AND(ISNUMBER(G5),AJ5<0.1*G5),"",AE5/AJ5)) | AL5: =IF(NOT(ISNUMBER(P5)),"",IF(ISNUMBER(Q5),(P5+Q5)/2,P5)) | AM5: =IF(AND(ISNUMBER(L5),ISNUMBER(AL5),AL5>0),L5/AL5,"") | AN5: =IF(AND(ISNUMBER(AM5),ISNUMBER({ROIC})),AM5-{ROIC},"") | AO5: =IF(AND(ISNUMBER(AC5),ISNUMBER(M5)),AC5+M5,"") | AP5: =IF(AND(ISNUMBER(AF5),ISNUMBER(R5),ISNUMBER(AO5),AO5>0),(AF5-R5)/AO5,"") | AQ5: =IF(AND(ISNUMBER(AC5),ISNUMBER(I5),I5<>0,AC5>0),AC5/I5,"") | AR5: =IF(AND(ISNUMBER(W5),ISNUMBER(Y5)),W5-IF(ISNUMBER(R5),R5,0)-(Y5-IF(ISNUMBER(T5),T5,0)),"") | AS5: =IF(AND(ISNUMBER(X5),ISNUMBER(Z5)),X5-IF(ISNUMBER(S5),S5,0)-(Z5-IF(ISNUMBER(U5),U5,0)),"") | AT5: =IF(AND(ISNUMBER(AR5),ISNUMBER(AS5)),AR5-AS5,"") | AU5: =IF(E5="금융","",IF(AND(ISNUMBER(L5),ISNUMBER(M5),ISNUMBER(N5),ISNUMBER(AT5)),L5+M5-N5-AT5,IF(AND(ISNUMBER(O5),ISNUMBER(N5)),O5-N5,""))) | AV5: =IF(E5="금융","금융업 - 정의되지 않음",IF(AND(ISNUMBER(L5),ISNUMBER(M5),ISNUMBER(N5),ISNUMBER(AT5)),"순이익+감가상각-설비투자-운전자본증감",IF(AND(ISNUMBER(O5),ISNUMBER(N5)),"영업현금흐름-설비투자","산출불가"))) | AW5: =IF(AND(ISNUMBER(AU5),ISNUMBER(G5),G5<>0),AU5/G5,"") | AX5: =IF(AND(ISNUMBER(AC5),ISNUMBER(G5),G5<>0),AC5/G5,"")
A6: NVDA | B6: NVIDIA CORP | C6: 2015 | D6: 2016-01-31 | E6: 일반 | F6: 0001045810-18-000010 | G6: 5.01 | J6: 0.129 | K6: 0.747 | L6: 0.614 | M6: 0.124 | O6: 1.175 | P6: 4.469 | Q6: 4.418 | R6: 5.037 | S6: 4.623 | V6: 0 | W6: 6.053 | X6: 5.713 | Y6: 2.351 | Z6: 0.896 | AA6: 1.179 | AB6: 21560 | AC6: =IF(AND(ISNUMBER(H6),ISNUMBER(I6)),H6+I6,IF(ISNUMBER(K6),K6,IF(ISNUMBER(H6),H6,""))) | AD6: =IF(OR(NOT(ISNUMBER(J6)),NOT(ISNUMBER(H6)),H6<=0),기준표!$B$8,MIN(MAX(J6/H6,기준표!$B$6),기준표!$B$7)) | AE6: =IF(ISNUMBER(AC6),AC6*(1-AD6),"") | AF6: =IF(AND(NOT(ISNUMBER(T6)),NOT(ISNUMBER(V6))),"",IF(ISNUMBER(T6),T6,0)+IF(ISNUMBER(V6),V6,0)) | AG6: =IF(E6="금융","",IF(AND(ISNUMBER(P6),ISNUMBER(AF6),ISNUMBER(R6)),P6+AF6-R6,"")) | AH6: =IF(E6="금융","",IF(NOT(ISNUMBER(AG6)),"",IF(ISNUMBER(AA6),(AG6+AA6)/2,AG6))) | AI6: =IF(AND(ISNUMBER(AE6),ISNUMBER(AH6),AH6>0),AE6/AH6,"") | AJ6: =IF(E6="금융","",IF(AND(ISNUMBER(P6),ISNUMBER(AF6)),P6+AF6,"")) | AK6: =IF(OR(NOT(ISNUMBER(AE6)),NOT(ISNUMBER(AJ6)),AJ6<=0),"",IF(AND(ISNUMBER(G6),AJ6<0.1*G6),"",AE6/AJ6)) | AL6: =IF(NOT(ISNUMBER(P6)),"",IF(ISNUMBER(Q6),(P6+Q6)/2,P6)) | AM6: =IF(AND(ISNUMBER(L6),ISNUMBER(AL6),AL6>0),L6/AL6,"") | AN6: =IF(AND(ISNUMBER(AM6),ISNUMBER({ROIC})),AM6-{ROIC},"") | AO6: =IF(AND(ISNUMBER(AC6),ISNUMBER(M6)),AC6+M6,"") | AP6: =IF(AND(ISNUMBER(AF6),ISNUMBER(R6),ISNUMBER(AO6),AO6>0),(AF6-R6)/AO6,"") | AQ6: =IF(AND(ISNUMBER(AC6),ISNUMBER(I6),I6<>0,AC6>0),AC6/I6,"") | AR6: =IF(AND(ISNUMBER(W6),ISNUMBER(Y6)),W6-IF(ISNUMBER(R6),R6,0)-(Y6-IF(ISNUMBER(T6),T6,0)),"") | AS6: =IF(AND(ISNUMBER(X6),ISNUMBER(Z6)),X6-IF(ISNUMBER(S6),S6,0)-(Z6-IF(ISNUMBER(U6),U6,0)),"") | AT6: =IF(AND(ISNUMBER(AR6),ISNUMBER(AS6)),AR6-AS6,"") | AU6: =IF(E6="금융","",IF(AND(ISNUMBER(L6),ISNUMBER(M6),ISNUMBER(N6),ISNUMBER(AT6)),L6+M6-N6-AT6,IF(AND(ISNUMBER(O6),ISNUMBER(N6)),O6-N6,""))) | AV6: =IF(E6="금융","금융업 - 정의되지 않음",IF(AND(ISNUMBER(L6),ISNUMBER(M6),ISNUMBER(N6),ISNUMBER(AT6)),"순이익+감가상각-설비투자-운전자본증감",IF(AND(ISNUMBER(O6),ISNUMBER(N6)),"영업현금흐름-설비투자","산출불가"))) | AW6: =IF(AND(ISNUMBER(AU6),ISNUMBER(G6),G6<>0),AU6/G6,"") | AX6: =IF(AND(ISNUMBER(AC6),ISNUMBER(G6),G6<>0),AC6/G6,"")
A7: NVDA | B7: NVIDIA CORP | C7: 2016 | D7: 2017-01-29 | E7: 일반 | F7: 0001045810-19-000023 | G7: 6.91 | J7: 0.239 | K7: 1.934 | L7: 1.666 | M7: 0.118 | O7: 1.672 | P7: 5.762 | Q7: 4.469 | R7: 6.798 | S7: 5.037 | V7: 1.983 | W7: 8.536 | X7: 6.053 | Y7: 1.788 | Z7: 2.351 | AA7: -0.568 | AB7: 23400 | AC7: =IF(AND(ISNUMBER(H7),ISNUMBER(I7)),H7+I7,IF(ISNUMBER(K7),K7,IF(ISNUMBER(H7),H7,""))) | AD7: =IF(OR(NOT(ISNUMBER(J7)),NOT(ISNUMBER(H7)),H7<=0),기준표!$B$8,MIN(MAX(J7/H7,기준표!$B$6),기준표!$B$7)) | AE7: =IF(ISNUMBER(AC7),AC7*(1-AD7),"") | AF7: =IF(AND(NOT(ISNUMBER(T7)),NOT(ISNUMBER(V7))),"",IF(ISNUMBER(T7),T7,0)+IF(ISNUMBER(V7),V7,0)) | AG7: =IF(E7="금융","",IF(AND(ISNUMBER(P7),ISNUMBER(AF7),ISNUMBER(R7)),P7+AF7-R7,"")) | AH7: =IF(E7="금융","",IF(NOT(ISNUMBER(AG7)),"",IF(ISNUMBER(AA7),(AG7+AA7)/2,AG7))) | AI7: =IF(AND(ISNUMBER(AE7),ISNUMBER(AH7),AH7>0),AE7/AH7,"") | AJ7: =IF(E7="금융","",IF(AND(ISNUMBER(P7),ISNUMBER(AF7)),P7+AF7,"")) | AK7: =IF(OR(NOT(ISNUMBER(AE7)),NOT(ISNUMBER(AJ7)),AJ7<=0),"",IF(AND(ISNUMBER(G7),AJ7<0.1*G7),"",AE7/AJ7)) | AL7: =IF(NOT(ISNUMBER(P7)),"",IF(ISNUMBER(Q7),(P7+Q7)/2,P7)) | AM7: =IF(AND(ISNUMBER(L7),ISNUMBER(AL7),AL7>0),L7/AL7,"") | AN7: =IF(AND(ISNUMBER(AM7),ISNUMBER({ROIC})),AM7-{ROIC},"") | AO7: =IF(AND(ISNUMBER(AC7),ISNUMBER(M7)),AC7+M7,"") | AP7: =IF(AND(ISNUMBER(AF7),ISNUMBER(R7),ISNUMBER(AO7),AO7>0),(AF7-R7)/AO7,"") | AQ7: =IF(AND(ISNUMBER(AC7),ISNUMBER(I7),I7<>0,AC7>0),AC7/I7,"") | AR7: =IF(AND(ISNUMBER(W7),ISNUMBER(Y7)),W7-IF(ISNUMBER(R7),R7,0)-(Y7-IF(ISNUMBER(T7),T7,0)),"") | AS7: =IF(AND(ISNUMBER(X7),ISNUMBER(Z7)),X7-IF(ISNUMBER(S7),S7,0)-(Z7-IF(ISNUMBER(U7),U7,0)),"") | AT7: =IF(AND(ISNUMBER(AR7),ISNUMBER(AS7)),AR7-AS7,"") | AU7: =IF(E7="금융","",IF(AND(ISNUMBER(L7),ISNUMBER(M7),ISNUMBER(N7),ISNUMBER(AT7)),L7+M7-N7-AT7,IF(AND(ISNUMBER(O7),ISNUMBER(N7)),O7-N7,""))) | AV7: =IF(E7="금융","금융업 - 정의되지 않음",IF(AND(ISNUMBER(L7),ISNUMBER(M7),ISNUMBER(N7),ISNUMBER(AT7)),"순이익+감가상각-설비투자-운전자본증감",IF(AND(ISNUMBER(O7),ISNUMBER(N7)),"영업현금흐름-설비투자","산출불가"))) | AW7: =IF(AND(ISNUMBER(AU7),ISNUMBER(G7),G7<>0),AU7/G7,"") | AX7: =IF(AND(ISNUMBER(AC7),ISNUMBER(G7),G7<>0),AC7/G7,"")
A8: NVDA | B8: NVIDIA CORP | C8: 2017 | D8: 2018-01-28 | E8: 일반 | F8: 0001045810-20-000010 | G8: 9.714 | J8: 0.149 | K8: 3.21 | L8: 3.047 | M8: 0.144 | O8: 3.502 | P8: 7.471 | Q8: 5.762 | R8: 7.108 | S8: 6.798 | V8: 1.985 | W8: 9.255 | X8: 8.536 | Y8: 1.153 | Z8: 1.788 | AA8: 0.947 | AB8: 24240 | AC8: =IF(AND(ISNUMBER(H8),ISNUMBER(I8)),H8+I8,IF(ISNUMBER(K8),K8,IF(ISNUMBER(H8),H8,""))) | AD8: =IF(OR(NOT(ISNUMBER(J8)),NOT(ISNUMBER(H8)),H8<=0),기준표!$B$8,MIN(MAX(J8/H8,기준표!$B$6),기준표!$B$7)) | AE8: =IF(ISNUMBER(AC8),AC8*(1-AD8),"") | AF8: =IF(AND(NOT(ISNUMBER(T8)),NOT(ISNUMBER(V8))),"",IF(ISNUMBER(T8),T8,0)+IF(ISNUMBER(V8),V8,0)) | AG8: =IF(E8="금융","",IF(AND(ISNUMBER(P8),ISNUMBER(AF8),ISNUMBER(R8)),P8+AF8-R8,"")) | AH8: =IF(E8="금융","",IF(NOT(ISNUMBER(AG8)),"",IF(ISNUMBER(AA8),(AG8+AA8)/2,AG8))) | AI8: =IF(AND(ISNUMBER(AE8),ISNUMBER(AH8),AH8>0),AE8/AH8,"") | AJ8: =IF(E8="금융","",IF(AND(ISNUMBER(P8),ISNUMBER(AF8)),P8+AF8,"")) | AK8: =IF(OR(NOT(ISNUMBER(AE8)),NOT(ISNUMBER(AJ8)),AJ8<=0),"",IF(AND(ISNUMBER(G8),AJ8<0.1*G8),"",AE8/AJ8)) | AL8: =IF(NOT(ISNUMBER(P8)),"",IF(ISNUMBER(Q8),(P8+Q8)/2,P8)) | AM8: =IF(AND(ISNUMBER(L8),ISNUMBER(AL8),AL8>0),L8/AL8,"") | AN8: =IF(AND(ISNUMBER(AM8),ISNUMBER({ROIC})),AM8-{ROIC},"") | AO8: =IF(AND(ISNUMBER(AC8),ISNUMBER(M8)),AC8+M8,"") | AP8: =IF(AND(ISNUMBER(AF8),ISNUMBER(R8),ISNUMBER(AO8),AO8>0),(AF8-R8)/AO8,"") | AQ8: =IF(AND(ISNUMBER(AC8),ISNUMBER(I8),I8<>0,AC8>0),AC8/I8,"") | AR8: =IF(AND(ISNUMBER(W8),ISNUMBER(Y8)),W8-IF(ISNUMBER(R8),R8,0)-(Y8-IF(ISNUMBER(T8),T8,0)),"") | AS8: =IF(AND(ISNUMBER(X8),ISNUMBER(Z8)),X8-IF(ISNUMBER(S8),S8,0)-(Z8-IF(ISNUMBER(U8),U8,0)),"") | AT8: =IF(AND(ISNUMBER(AR8),ISNUMBER(AS8)),AR8-AS8,"") | AU8: =IF(E8="금융","",IF(AND(ISNUMBER(L8),ISNUMBER(M8),ISNUMBER(N8),ISNUMBER(AT8)),L8+M8-N8-AT8,IF(AND(ISNUMBER(O8),ISNUMBER(N8)),O8-N8,""))) | AV8: =IF(E8="금융","금융업 - 정의되지 않음",IF(AND(ISNUMBER(L8),ISNUMBER(M8),ISNUMBER(N8),ISNUMBER(AT8)),"순이익+감가상각-설비투자-운전자본증감",IF(AND(ISNUMBER(O8),ISNUMBER(N8)),"영업현금흐름-설비투자","산출불가"))) | AW8: =IF(AND(ISNUMBER(AU8),ISNUMBER(G8),G8<>0),AU8/G8,"") | AX8: =IF(AND(ISNUMBER(AC8),ISNUMBER(G8),G8<>0),AC8/G8,"")
A9: NVDA | B9: NVIDIA CORP | C9: 2018 | D9: 2019-01-27 | E9: 일반 | F9: 0001045810-21-000010 | G9: 11.716 | J9: -0.245 | K9: 3.804 | L9: 4.141 | M9: 0.233 | O9: 3.743 | P9: 9.342 | Q9: 7.471 | R9: 7.422 | S9: 7.108 | V9: 1.988 | W9: 10.557 | X9: 9.255 | Y9: 1.329 | Z9: 1.153 | AA9: 2.348 | AB9: 24240 | AC9: =IF(AND(ISNUMBER(H9),ISNUMBER(I9)),H9+I9,IF(ISNUMBER(K9),K9,IF(ISNUMBER(H9),H9,""))) | AD9: =IF(OR(NOT(ISNUMBER(J9)),NOT(ISNUMBER(H9)),H9<=0),기준표!$B$8,MIN(MAX(J9/H9,기준표!$B$6),기준표!$B$7)) | AE9: =IF(ISNUMBER(AC9),AC9*(1-AD9),"") | AF9: =IF(AND(NOT(ISNUMBER(T9)),NOT(ISNUMBER(V9))),"",IF(ISNUMBER(T9),T9,0)+IF(ISNUMBER(V9),V9,0)) | AG9: =IF(E9="금융","",IF(AND(ISNUMBER(P9),ISNUMBER(AF9),ISNUMBER(R9)),P9+AF9-R9,"")) | AH9: =IF(E9="금융","",IF(NOT(ISNUMBER(AG9)),"",IF(ISNUMBER(AA9),(AG9+AA9)/2,AG9))) | AI9: =IF(AND(ISNUMBER(AE9),ISNUMBER(AH9),AH9>0),AE9/AH9,"") | AJ9: =IF(E9="금융","",IF(AND(ISNUMBER(P9),ISNUMBER(AF9)),P9+AF9,"")) | AK9: =IF(OR(NOT(ISNUMBER(AE9)),NOT(ISNUMBER(AJ9)),AJ9<=0),"",IF(AND(ISNUMBER(G9),AJ9<0.1*G9),"",AE9/AJ9)) | AL9: =IF(NOT(ISNUMBER(P9)),"",IF(ISNUMBER(Q9),(P9+Q9)/2,P9)) | AM9: =IF(AND(ISNUMBER(L9),ISNUMBER(AL9),AL9>0),L9/AL9,"") | AN9: =IF(AND(ISNUMBER(AM9),ISNUMBER({ROIC})),AM9-{ROIC},"") | AO9: =IF(AND(ISNUMBER(AC9),ISNUMBER(M9)),AC9+M9,"") | AP9: =IF(AND(ISNUMBER(AF9),ISNUMBER(R9),ISNUMBER(AO9),AO9>0),(AF9-R9)/AO9,"") | AQ9: =IF(AND(ISNUMBER(AC9),ISNUMBER(I9),I9<>0,AC9>0),AC9/I9,"") | AR9: =IF(AND(ISNUMBER(W9),ISNUMBER(Y9)),W9-IF(ISNUMBER(R9),R9,0)-(Y9-IF(ISNUMBER(T9),T9,0)),"") | AS9: =IF(AND(ISNUMBER(X9),ISNUMBER(Z9)),X9-IF(ISNUMBER(S9),S9,0)-(Z9-IF(ISNUMBER(U9),U9,0)),"") | AT9: =IF(AND(ISNUMBER(AR9),ISNUMBER(AS9)),AR9-AS9,"") | AU9: =IF(E9="금융","",IF(AND(ISNUMBER(L9),ISNUMBER(M9),ISNUMBER(N9),ISNUMBER(AT9)),L9+M9-N9-AT9,IF(AND(ISNUMBER(O9),ISNUMBER(N9)),O9-N9,""))) | AV9: =IF(E9="금융","금융업 - 정의되지 않음",IF(AND(ISNUMBER(L9),ISNUMBER(M9),ISNUMBER(N9),ISNUMBER(AT9)),"순이익+감가상각-설비투자-운전자본증감",IF(AND(ISNUMBER(O9),ISNUMBER(N9)),"영업현금흐름-설비투자","산출불가"))) | AW9: =IF(AND(ISNUMBER(AU9),ISNUMBER(G9),G9<>0),AU9/G9,"") | AX9: =IF(AND(ISNUMBER(AC9),ISNUMBER(G9),G9<>0),AC9/G9,"")
A10: NVDA | B10: NVIDIA CORP | C10: 2019 | D10: 2020-01-26 | E10: 일반 | F10: 0001045810-22-000036 | G10: 10.918 | H10: 2.97 | J10: 0.174 | K10: 2.846 | L10: 2.796 | M10: 0.355 | O10: 4.761 | P10: 12.204 | Q10: 9.342 | R10: 10.897 | S10: 7.422 | T10: 0 | V10: 1.991 | W10: 13.69 | X10: 10.557 | Y10: 1.784 | Z10: 1.329 | AA10: 3.908 | AB10: 24480 | AC10: =IF(AND(ISNUMBER(H10),ISNUMBER(I10)),H10+I10,IF(ISNUMBER(K10),K10,IF(ISNUMBER(H10),H10,""))) | AD10: =IF(OR(NOT(ISNUMBER(J10)),NOT(ISNUMBER(H10)),H10<=0),기준표!$B$8,MIN(MAX(J10/H10,기준표!$B$6),기준표!$B$7)) | AE10: =IF(ISNUMBER(AC10),AC10*(1-AD10),"") | AF10: =IF(AND(NOT(ISNUMBER(T10)),NOT(ISNUMBER(V10))),"",IF(ISNUMBER(T10),T10,0)+IF(ISNUMBER(V10),V10,0)) | AG10: =IF(E10="금융","",IF(AND(ISNUMBER(P10),ISNUMBER(AF10),ISNUMBER(R10)),P10+AF10-R10,"")) | AH10: =IF(E10="금융","",IF(NOT(ISNUMBER(AG10)),"",IF(ISNUMBER(AA10),(AG10+AA10)/2,AG10))) | AI10: =IF(AND(ISNUMBER(AE10),ISNUMBER(AH10),AH10>0),AE10/AH10,"") | AJ10: =IF(E10="금융","",IF(AND(ISNUMBER(P10),ISNUMBER(AF10)),P10+AF10,"")) | AK10: =IF(OR(NOT(ISNUMBER(AE10)),NOT(ISNUMBER(AJ10)),AJ10<=0),"",IF(AND(ISNUMBER(G10),AJ10<0.1*G10),"",AE10/AJ10)) | AL10: =IF(NOT(ISNUMBER(P10)),"",IF(ISNUMBER(Q10),(P10+Q10)/2,P10)) | AM10: =IF(AND(ISNUMBER(L10),ISNUMBER(AL10),AL10>0),L10/AL10,"") | AN10: =IF(AND(ISNUMBER(AM10),ISNUMBER({ROIC})),AM10-{ROIC},"") | AO10: =IF(AND(ISNUMBER(AC10),ISNUMBER(M10)),AC10+M10,"") | AP10: =IF(AND(ISNUMBER(AF10),ISNUMBER(R10),ISNUMBER(AO10),AO10>0),(AF10-R10)/AO10,"") | AQ10: =IF(AND(ISNUMBER(AC10),ISNUMBER(I10),I10<>0,AC10>0),AC10/I10,"") | AR10: =IF(AND(ISNUMBER(W10),ISNUMBER(Y10)),W10-IF(ISNUMBER(R10),R10,0)-(Y10-IF(ISNUMBER(T10),T10,0)),"") | AS10: =IF(AND(ISNUMBER(X10),ISNUMBER(Z10)),X10-IF(ISNUMBER(S10),S10,0)-(Z10-IF(ISNUMBER(U10),U10,0)),"") | AT10: =IF(AND(ISNUMBER(AR10),ISNUMBER(AS10)),AR10-AS10,"") | AU10: =IF(E10="금융","",IF(AND(ISNUMBER(L10),ISNUMBER(M10),ISNUMBER(N10),ISNUMBER(AT10)),L10+M10-N10-AT10,IF(AND(ISNUMBER(O10),ISNUMBER(N10)),O10-N10,""))) | AV10: =IF(E10="금융","금융업 - 정의되지 않음",IF(AND(ISNUMBER(L10),ISNUMBER(M10),ISNUMBER(N10),ISNUMBER(AT10)),"순이익+감가상각-설비투자-운전자본증감",IF(AND(ISNUMBER(O10),ISNUMBER(N10)),"영업현금흐름-설비투자","산출불가"))) | AW10: =IF(AND(ISNUMBER(AU10),ISNUMBER(G10),G10<>0),AU10/G10,"") | AX10: =IF(AND(ISNUMBER(AC10),ISNUMBER(G10),G10<>0),AC10/G10,"")
A11: NVDA | B11: NVIDIA CORP | C11: 2020 | D11: 2021-01-31 | E11: 일반 | F11: 0001045810-23-000017 | G11: 16.675 | H11: 4.409 | J11: 0.077 | K11: 4.532 | L11: 4.332 | M11: 0.486 | O11: 5.822 | P11: 16.893 | Q11: 12.204 | R11: 11.561 | S11: 10.897 | T11: 0.999 | U11: 0 | V11: 6.963 | W11: 16.055 | X11: 13.69 | Y11: 3.925 | Z11: 1.784 | AA11: 3.298 | AB11: 24790 | AC11: =IF(AND(ISNUMBER(H11),ISNUMBER(I11)),H11+I11,IF(ISNUMBER(K11),K11,IF(ISNUMBER(H11),H11,""))) | AD11: =IF(OR(NOT(ISNUMBER(J11)),NOT(ISNUMBER(H11)),H11<=0),기준표!$B$8,MIN(MAX(J11/H11,기준표!$B$6),기준표!$B$7)) | AE11: =IF(ISNUMBER(AC11),AC11*(1-AD11),"") | AF11: =IF(AND(NOT(ISNUMBER(T11)),NOT(ISNUMBER(V11))),"",IF(ISNUMBER(T11),T11,0)+IF(ISNUMBER(V11),V11,0)) | AG11: =IF(E11="금융","",IF(AND(ISNUMBER(P11),ISNUMBER(AF11),ISNUMBER(R11)),P11+AF11-R11,"")) | AH11: =IF(E11="금융","",IF(NOT(ISNUMBER(AG11)),"",IF(ISNUMBER(AA11),(AG11+AA11)/2,AG11))) | AI11: =IF(AND(ISNUMBER(AE11),ISNUMBER(AH11),AH11>0),AE11/AH11,"") | AJ11: =IF(E11="금융","",IF(AND(ISNUMBER(P11),ISNUMBER(AF11)),P11+AF11,"")) | AK11: =IF(OR(NOT(ISNUMBER(AE11)),NOT(ISNUMBER(AJ11)),AJ11<=0),"",IF(AND(ISNUMBER(G11),AJ11<0.1*G11),"",AE11/AJ11)) | AL11: =IF(NOT(ISNUMBER(P11)),"",IF(ISNUMBER(Q11),(P11+Q11)/2,P11)) | AM11: =IF(AND(ISNUMBER(L11),ISNUMBER(AL11),AL11>0),L11/AL11,"") | AN11: =IF(AND(ISNUMBER(AM11),ISNUMBER({ROIC})),AM11-{ROIC},"") | AO11: =IF(AND(ISNUMBER(AC11),ISNUMBER(M11)),AC11+M11,"") | AP11: =IF(AND(ISNUMBER(AF11),ISNUMBER(R11),ISNUMBER(AO11),AO11>0),(AF11-R11)/AO11,"") | AQ11: =IF(AND(ISNUMBER(AC11),ISNUMBER(I11),I11<>0,AC11>0),AC11/I11,"") | AR11: =IF(AND(ISNUMBER(W11),ISNUMBER(Y11)),W11-IF(ISNUMBER(R11),R11,0)-(Y11-IF(ISNUMBER(T11),T11,0)),"") | AS11: =IF(AND(ISNUMBER(X11),ISNUMBER(Z11)),X11-IF(ISNUMBER(S11),S11,0)-(Z11-IF(ISNUMBER(U11),U11,0)),"") | AT11: =IF(AND(ISNUMBER(AR11),ISNUMBER(AS11)),AR11-AS11,"") | AU11: =IF(E11="금융","",IF(AND(ISNUMBER(L11),ISNUMBER(M11),ISNUMBER(N11),ISNUMBER(AT11)),L11+M11-N11-AT11,IF(AND(ISNUMBER(O11),ISNUMBER(N11)),O11-N11,""))) | AV11: =IF(E11="금융","금융업 - 정의되지 않음",IF(AND(ISNUMBER(L11),ISNUMBER(M11),ISNUMBER(N11),ISNUMBER(AT11)),"순이익+감가상각-설비투자-운전자본증감",IF(AND(ISNUMBER(O11),ISNUMBER(N11)),"영업현금흐름-설비투자","산출불가"))) | AW11: =IF(AND(ISNUMBER(AU11),ISNUMBER(G11),G11<>0),AU11/G11,"") | AX11: =IF(AND(ISNUMBER(AC11),ISNUMBER(G11),G11<>0),AC11/G11,"")
A12: NVDA | B12: NVIDIA CORP | C12: 2021 | D12: 2022-01-30 | E12: 일반 | F12: 0001045810-24-000029 | G12: 26.914 | H12: 9.941 | J12: 0.189 | K12: 10.041 | L12: 9.752 | M12: 0.611 | N12: 0.976 | O12: 9.108 | P12: 26.612 | Q12: 16.893 | R12: 21.208 | S12: 11.561 | T12: 0 | U12: 0.999 | V12: 10.946 | W12: 28.829 | X12: 16.055 | Y12: 4.335 | Z12: 3.925 | AA12: 13.294 | AB12: 25060 | AC12: =IF(AND(ISNUMBER(H12),ISNUMBER(I12)),H12+I12,IF(ISNUMBER(K12),K12,IF(ISNUMBER(H12),H12,""))) | AD12: =IF(OR(NOT(ISNUMBER(J12)),NOT(ISNUMBER(H12)),H12<=0),기준표!$B$8,MIN(MAX(J12/H12,기준표!$B$6),기준표!$B$7)) | AE12: =IF(ISNUMBER(AC12),AC12*(1-AD12),"") | AF12: =IF(AND(NOT(ISNUMBER(T12)),NOT(ISNUMBER(V12))),"",IF(ISNUMBER(T12),T12,0)+IF(ISNUMBER(V12),V12,0)) | AG12: =IF(E12="금융","",IF(AND(ISNUMBER(P12),ISNUMBER(AF12),ISNUMBER(R12)),P12+AF12-R12,"")) | AH12: =IF(E12="금융","",IF(NOT(ISNUMBER(AG12)),"",IF(ISNUMBER(AA12),(AG12+AA12)/2,AG12))) | AI12: =IF(AND(ISNUMBER(AE12),ISNUMBER(AH12),AH12>0),AE12/AH12,"") | AJ12: =IF(E12="금융","",IF(AND(ISNUMBER(P12),ISNUMBER(AF12)),P12+AF12,"")) | AK12: =IF(OR(NOT(ISNUMBER(AE12)),NOT(ISNUMBER(AJ12)),AJ12<=0),"",IF(AND(ISNUMBER(G12),AJ12<0.1*G12),"",AE12/AJ12)) | AL12: =IF(NOT(ISNUMBER(P12)),"",IF(ISNUMBER(Q12),(P12+Q12)/2,P12)) | AM12: =IF(AND(ISNUMBER(L12),ISNUMBER(AL12),AL12>0),L12/AL12,"") | AN12: =IF(AND(ISNUMBER(AM12),ISNUMBER({ROIC})),AM12-{ROIC},"") | AO12: =IF(AND(ISNUMBER(AC12),ISNUMBER(M12)),AC12+M12,"") | AP12: =IF(AND(ISNUMBER(AF12),ISNUMBER(R12),ISNUMBER(AO12),AO12>0),(AF12-R12)/AO12,"") | AQ12: =IF(AND(ISNUMBER(AC12),ISNUMBER(I12),I12<>0,AC12>0),AC12/I12,"") | AR12: =IF(AND(ISNUMBER(W12),ISNUMBER(Y12)),W12-IF(ISNUMBER(R12),R12,0)-(Y12-IF(ISNUMBER(T12),T12,0)),"") | AS12: =IF(AND(ISNUMBER(X12),ISNUMBER(Z12)),X12-IF(ISNUMBER(S12),S12,0)-(Z12-IF(ISNUMBER(U12),U12,0)),"") | AT12: =IF(AND(ISNUMBER(AR12),ISNUMBER(AS12)),AR12-AS12,"") | AU12: =IF(E12="금융","",IF(AND(ISNUMBER(L12),ISNUMBER(M12),ISNUMBER(N12),ISNUMBER(AT12)),L12+M12-N12-AT12,IF(AND(ISNUMBER(O12),ISNUMBER(N12)),O12-N12,""))) | AV12: =IF(E12="금융","금융업 - 정의되지 않음",IF(AND(ISNUMBER(L12),ISNUMBER(M12),ISNUMBER(N12),ISNUMBER(AT12)),"순이익+감가상각-설비투자-운전자본증감",IF(AND(ISNUMBER(O12),ISNUMBER(N12)),"영업현금흐름-설비투자","산출불가"))) | AW12: =IF(AND(ISNUMBER(AU12),ISNUMBER(G12),G12<>0),AU12/G12,"") | AX12: =IF(AND(ISNUMBER(AC12),ISNUMBER(G12),G12<>0),AC12/G12,"")
A13: NVDA | B13: NVIDIA CORP | C13: 2022 | D13: 2023-01-29 | E13: 일반 | F13: 0001045810-25-000023 | G13: 26.974 | H13: 4.181 | I13: 0.262 | J13: -0.187 | K13: 4.224 | L13: 4.368 | M13: 0.844 | N13: 1.833 | O13: 5.641 | P13: 22.101 | Q13: 26.612 | R13: 13.296 | S13: 21.208 | T13: 1.25 | U13: 0 | V13: 10.953 | W13: 23.073 | X13: 28.829 | Y13: 6.563 | Z13: 4.335 | AA13: 16.35 | AB13: 24660 | AC13: =IF(AND(ISNUMBER(H13),ISNUMBER(I13)),H13+I13,IF(ISNUMBER(K13),K13,IF(ISNUMBER(H13),H13,""))) | AD13: =IF(OR(NOT(ISNUMBER(J13)),NOT(ISNUMBER(H13)),H13<=0),기준표!$B$8,MIN(MAX(J13/H13,기준표!$B$6),기준표!$B$7)) | AE13: =IF(ISNUMBER(AC13),AC13*(1-AD13),"") | AF13: =IF(AND(NOT(ISNUMBER(T13)),NOT(ISNUMBER(V13))),"",IF(ISNUMBER(T13),T13,0)+IF(ISNUMBER(V13),V13,0)) | AG13: =IF(E13="금융","",IF(AND(ISNUMBER(P13),ISNUMBER(AF13),ISNUMBER(R13)),P13+AF13-R13,"")) | AH13: =IF(E13="금융","",IF(NOT(ISNUMBER(AG13)),"",IF(ISNUMBER(AA13),(AG13+AA13)/2,AG13))) | AI13: =IF(AND(ISNUMBER(AE13),ISNUMBER(AH13),AH13>0),AE13/AH13,"") | AJ13: =IF(E13="금융","",IF(AND(ISNUMBER(P13),ISNUMBER(AF13)),P13+AF13,"")) | AK13: =IF(OR(NOT(ISNUMBER(AE13)),NOT(ISNUMBER(AJ13)),AJ13<=0),"",IF(AND(ISNUMBER(G13),AJ13<0.1*G13),"",AE13/AJ13)) | AL13: =IF(NOT(ISNUMBER(P13)),"",IF(ISNUMBER(Q13),(P13+Q13)/2,P13)) | AM13: =IF(AND(ISNUMBER(L13),ISNUMBER(AL13),AL13>0),L13/AL13,"") | AN13: =IF(AND(ISNUMBER(AM13),ISNUMBER({ROIC})),AM13-{ROIC},"") | AO13: =IF(AND(ISNUMBER(AC13),ISNUMBER(M13)),AC13+M13,"") | AP13: =IF(AND(ISNUMBER(AF13),ISNUMBER(R13),ISNUMBER(AO13),AO13>0),(AF13-R13)/AO13,"") | AQ13: =IF(AND(ISNUMBER(AC13),ISNUMBER(I13),I13<>0,AC13>0),AC13/I13,"") | AR13: =IF(AND(ISNUMBER(W13),ISNUMBER(Y13)),W13-IF(ISNUMBER(R13),R13,0)-(Y13-IF(ISNUMBER(T13),T13,0)),"") | AS13: =IF(AND(ISNUMBER(X13),ISNUMBER(Z13)),X13-IF(ISNUMBER(S13),S13,0)-(Z13-IF(ISNUMBER(U13),U13,0)),"") | AT13: =IF(AND(ISNUMBER(AR13),ISNUMBER(AS13)),AR13-AS13,"") | AU13: =IF(E13="금융","",IF(AND(ISNUMBER(L13),ISNUMBER(M13),ISNUMBER(N13),ISNUMBER(AT13)),L13+M13-N13-AT13,IF(AND(ISNUMBER(O13),ISNUMBER(N13)),O13-N13,""))) | AV13: =IF(E13="금융","금융업 - 정의되지 않음",IF(AND(ISNUMBER(L13),ISNUMBER(M13),ISNUMBER(N13),ISNUMBER(AT13)),"순이익+감가상각-설비투자-운전자본증감",IF(AND(ISNUMBER(O13),ISNUMBER(N13)),"영업현금흐름-설비투자","산출불가"))) | AW13: =IF(AND(ISNUMBER(AU13),ISNUMBER(G13),G13<>0),AU13/G13,"") | AX13: =IF(AND(ISNUMBER(AC13),ISNUMBER(G13),G13<>0),AC13/G13,"")
A14: NVDA | B14: NVIDIA CORP | C14: 2023 | D14: 2024-01-28 | E14: 일반 | F14: 0001045810-26-000021 | G14: 60.922 | H14: 33.818 | I14: 0.257 | J14: 4.058 | K14: 32.972 | L14: 29.76 | M14: 0.894 | N14: 1.069 | O14: 28.09 | P14: 42.978 | Q14: 22.101 | R14: 25.984 | S14: 13.296 | T14: 1.25 | U14: 1.25 | V14: 9.709 | W14: 44.345 | X14: 23.073 | Y14: 10.631 | Z14: 6.563 | AA14: 21.008 | AB14: 24643 | AC14: =IF(AND(ISNUMBER(H14),ISNUMBER(I14)),H14+I14,IF(ISNUMBER(K14),K14,IF(ISNUMBER(H14),H14,""))) | AD14: =IF(OR(NOT(ISNUMBER(J14)),NOT(ISNUMBER(H14)),H14<=0),기준표!$B$8,MIN(MAX(J14/H14,기준표!$B$6),기준표!$B$7)) | AE14: =IF(ISNUMBER(AC14),AC14*(1-AD14),"") | AF14: =IF(AND(NOT(ISNUMBER(T14)),NOT(ISNUMBER(V14))),"",IF(ISNUMBER(T14),T14,0)+IF(ISNUMBER(V14),V14,0)) | AG14: =IF(E14="금융","",IF(AND(ISNUMBER(P14),ISNUMBER(AF14),ISNUMBER(R14)),P14+AF14-R14,"")) | AH14: =IF(E14="금융","",IF(NOT(ISNUMBER(AG14)),"",IF(ISNUMBER(AA14),(AG14+AA14)/2,AG14))) | AI14: =IF(AND(ISNUMBER(AE14),ISNUMBER(AH14),AH14>0),AE14/AH14,"") | AJ14: =IF(E14="금융","",IF(AND(ISNUMBER(P14),ISNUMBER(AF14)),P14+AF14,"")) | AK14: =IF(OR(NOT(ISNUMBER(AE14)),NOT(ISNUMBER(AJ14)),AJ14<=0),"",IF(AND(ISNUMBER(G14),AJ14<0.1*G14),"",AE14/AJ14)) | AL14: =IF(NOT(ISNUMBER(P14)),"",IF(ISNUMBER(Q14),(P14+Q14)/2,P14)) | AM14: =IF(AND(ISNUMBER(L14),ISNUMBER(AL14),AL14>0),L14/AL14,"") | AN14: =IF(AND(ISNUMBER(AM14),ISNUMBER({ROIC})),AM14-{ROIC},"") | AO14: =IF(AND(ISNUMBER(AC14),ISNUMBER(M14)),AC14+M14,"") | AP14: =IF(AND(ISNUMBER(AF14),ISNUMBER(R14),ISNUMBER(AO14),AO14>0),(AF14-R14)/AO14,"") | AQ14: =IF(AND(ISNUMBER(AC14),ISNUMBER(I14),I14<>0,AC14>0),AC14/I14,"") | AR14: =IF(AND(ISNUMBER(W14),ISNUMBER(Y14)),W14-IF(ISNUMBER(R14),R14,0)-(Y14-IF(ISNUMBER(T14),T14,0)),"") | AS14: =IF(AND(ISNUMBER(X14),ISNUMBER(Z14)),X14-IF(ISNUMBER(S14),S14,0)-(Z14-IF(ISNUMBER(U14),U14,0)),"") | AT14: =IF(AND(ISNUMBER(AR14),ISNUMBER(AS14)),AR14-AS14,"") | AU14: =IF(E14="금융","",IF(AND(ISNUMBER(L14),ISNUMBER(M14),ISNUMBER(N14),ISNUMBER(AT14)),L14+M14-N14-AT14,IF(AND(ISNUMBER(O14),ISNUMBER(N14)),O14-N14,""))) | AV14: =IF(E14="금융","금융업 - 정의되지 않음",IF(AND(ISNUMBER(L14),ISNUMBER(M14),ISNUMBER(N14),ISNUMBER(AT14)),"순이익+감가상각-설비투자-운전자본증감",IF(AND(ISNUMBER(O14),ISNUMBER(N14)),"영업현금흐름-설비투자","산출불가"))) | AW14: =IF(AND(ISNUMBER(AU14),ISNUMBER(G14),G14<>0),AU14/G14,"") | AX14: =IF(AND(ISNUMBER(AC14),ISNUMBER(G14),G14<>0),AC14/G14,"")
A15: NVDA | B15: NVIDIA CORP | C15: 2024 | D15: 2025-01-26 | E15: 일반 | F15: 0001045810-26-000021 | G15: 130.497 | H15: 84.026 | I15: 0.247 | J15: 11.146 | K15: 81.453 | L15: 72.88 | M15: 1.3 | N15: 3.236 | O15: 64.089 | P15: 79.327 | Q15: 42.978 | R15: 43.21 | S15: 25.984 | T15: 0 | U15: 1.25 | V15: 8.463 | W15: 80.126 | X15: 44.345 | Y15: 18.047 | Z15: 10.631 | AA15: 27.953 | AB15: 24477 | AC15: =IF(AND(ISNUMBER(H15),ISNUMBER(I15)),H15+I15,IF(ISNUMBER(K15),K15,IF(ISNUMBER(H15),H15,""))) | AD15: =IF(OR(NOT(ISNUMBER(J15)),NOT(ISNUMBER(H15)),H15<=0),기준표!$B$8,MIN(MAX(J15/H15,기준표!$B$6),기준표!$B$7)) | AE15: =IF(ISNUMBER(AC15),AC15*(1-AD15),"") | AF15: =IF(AND(NOT(ISNUMBER(T15)),NOT(ISNUMBER(V15))),"",IF(ISNUMBER(T15),T15,0)+IF(ISNUMBER(V15),V15,0)) | AG15: =IF(E15="금융","",IF(AND(ISNUMBER(P15),ISNUMBER(AF15),ISNUMBER(R15)),P15+AF15-R15,"")) | AH15: =IF(E15="금융","",IF(NOT(ISNUMBER(AG15)),"",IF(ISNUMBER(AA15),(AG15+AA15)/2,AG15))) | AI15: =IF(AND(ISNUMBER(AE15),ISNUMBER(AH15),AH15>0),AE15/AH15,"") | AJ15: =IF(E15="금융","",IF(AND(ISNUMBER(P15),ISNUMBER(AF15)),P15+AF15,"")) | AK15: =IF(OR(NOT(ISNUMBER(AE15)),NOT(ISNUMBER(AJ15)),AJ15<=0),"",IF(AND(ISNUMBER(G15),AJ15<0.1*G15),"",AE15/AJ15)) | AL15: =IF(NOT(ISNUMBER(P15)),"",IF(ISNUMBER(Q15),(P15+Q15)/2,P15)) | AM15: =IF(AND(ISNUMBER(L15),ISNUMBER(AL15),AL15>0),L15/AL15,"") | AN15: =IF(AND(ISNUMBER(AM15),ISNUMBER({ROIC})),AM15-{ROIC},"") | AO15: =IF(AND(ISNUMBER(AC15),ISNUMBER(M15)),AC15+M15,"") | AP15: =IF(AND(ISNUMBER(AF15),ISNUMBER(R15),ISNUMBER(AO15),AO15>0),(AF15-R15)/AO15,"") | AQ15: =IF(AND(ISNUMBER(AC15),ISNUMBER(I15),I15<>0,AC15>0),AC15/I15,"") | AR15: =IF(AND(ISNUMBER(W15),ISNUMBER(Y15)),W15-IF(ISNUMBER(R15),R15,0)-(Y15-IF(ISNUMBER(T15),T15,0)),"") | AS15: =IF(AND(ISNUMBER(X15),ISNUMBER(Z15)),X15-IF(ISNUMBER(S15),S15,0)-(Z15-IF(ISNUMBER(U15),U15,0)),"") | AT15: =IF(AND(ISNUMBER(AR15),ISNUMBER(AS15)),AR15-AS15,"") | AU15: =IF(E15="금융","",IF(AND(ISNUMBER(L15),ISNUMBER(M15),ISNUMBER(N15),ISNUMBER(AT15)),L15+M15-N15-AT15,IF(AND(ISNUMBER(O15),ISNUMBER(N15)),O15-N15,""))) | AV15: =IF(E15="금융","금융업 - 정의되지 않음",IF(AND(ISNUMBER(L15),ISNUMBER(M15),ISNUMBER(N15),ISNUMBER(AT15)),"순이익+감가상각-설비투자-운전자본증감",IF(AND(ISNUMBER(O15),ISNUMBER(N15)),"영업현금흐름-설비투자","산출불가"))) | AW15: =IF(AND(ISNUMBER(AU15),ISNUMBER(G15),G15<>0),AU15/G15,"") | AX15: =IF(AND(ISNUMBER(AC15),ISNUMBER(G15),G15<>0),AC15/G15,"")
A16: NVDA | B16: NVIDIA CORP | C16: 2025 | D16: 2026-01-25 | E16: 일반 | F16: 0001045810-26-000021 | G16: 215.938 | H16: 141.45 | I16: 0.259 | J16: 21.383 | K16: 130.387 | L16: 120.067 | M16: 2.4 | N16: 6.042 | O16: 102.718 | P16: 157.293 | Q16: 79.327 | R16: 10.605 | S16: 43.21 | T16: 0.999 | U16: 0 | V16: 8.468 | W16: 125.605 | X16: 80.126 | Y16: 32.163 | Z16: 18.047 | AA16: 44.58 | AB16: 24304 | AC16: =IF(AND(ISNUMBER(H16),ISNUMBER(I16)),H16+I16,IF(ISNUMBER(K16),K16,IF(ISNUMBER(H16),H16,""))) | AD16: =IF(OR(NOT(ISNUMBER(J16)),NOT(ISNUMBER(H16)),H16<=0),기준표!$B$8,MIN(MAX(J16/H16,기준표!$B$6),기준표!$B$7)) | AE16: =IF(ISNUMBER(AC16),AC16*(1-AD16),"") | AF16: =IF(AND(NOT(ISNUMBER(T16)),NOT(ISNUMBER(V16))),"",IF(ISNUMBER(T16),T16,0)+IF(ISNUMBER(V16),V16,0)) | AG16: =IF(E16="금융","",IF(AND(ISNUMBER(P16),ISNUMBER(AF16),ISNUMBER(R16)),P16+AF16-R16,"")) | AH16: =IF(E16="금융","",IF(NOT(ISNUMBER(AG16)),"",IF(ISNUMBER(AA16),(AG16+AA16)/2,AG16))) | AI16: =IF(AND(ISNUMBER(AE16),ISNUMBER(AH16),AH16>0),AE16/AH16,"") | AJ16: =IF(E16="금융","",IF(AND(ISNUMBER(P16),ISNUMBER(AF16)),P16+AF16,"")) | AK16: =IF(OR(NOT(ISNUMBER(AE16)),NOT(ISNUMBER(AJ16)),AJ16<=0),"",IF(AND(ISNUMBER(G16),AJ16<0.1*G16),"",AE16/AJ16)) | AL16: =IF(NOT(ISNUMBER(P16)),"",IF(ISNUMBER(Q16),(P16+Q16)/2,P16)) | AM16: =IF(AND(ISNUMBER(L16),ISNUMBER(AL16),AL16>0),L16/AL16,"") | AN16: =IF(AND(ISNUMBER(AM16),ISNUMBER({ROIC})),AM16-{ROIC},"") | AO16: =IF(AND(ISNUMBER(AC16),ISNUMBER(M16)),AC16+M16,"") | AP16: =IF(AND(ISNUMBER(AF16),ISNUMBER(R16),ISNUMBER(AO16),AO16>0),(AF16-R16)/AO16,"") | AQ16: =IF(AND(ISNUMBER(AC16),ISNUMBER(I16),I16<>0,AC16>0),AC16/I16,"") | AR16: =IF(AND(ISNUMBER(W16),ISNUMBER(Y16)),W16-IF(ISNUMBER(R16),R16,0)-(Y16-IF(ISNUMBER(T16),T16,0)),"") | AS16: =IF(AND(ISNUMBER(X16),ISNUMBER(Z16)),X16-IF(ISNUMBER(S16),S16,0)-(Z16-IF(ISNUMBER(U16),U16,0)),"") | AT16: =IF(AND(ISNUMBER(AR16),ISNUMBER(AS16)),AR16-AS16,"") | AU16: =IF(E16="금융","",IF(AND(ISNUMBER(L16),ISNUMBER(M16),ISNUMBER(N16),ISNUMBER(AT16)),L16+M16-N16-AT16,IF(AND(ISNUMBER(O16),ISNUMBER(N16)),O16-N16,""))) | AV16: =IF(E16="금융","금융업 - 정의되지 않음",IF(AND(ISNUMBER(L16),ISNUMBER(M16),ISNUMBER(N16),ISNUMBER(AT16)),"순이익+감가상각-설비투자-운전자본증감",IF(AND(ISNUMBER(O16),ISNUMBER(N16)),"영업현금흐름-설비투자","산출불가"))) | AW16: =IF(AND(ISNUMBER(AU16),ISNUMBER(G16),G16<>0),AU16/G16,"") | AX16: =IF(AND(ISNUMBER(AC16),ISNUMBER(G16),G16<>0),AC16/G16,"")
A17: AAPL | B17: Apple Inc. | C17: 2014 | D17: 2014-09-27 | E17: 일반 | F17: 0001628280-16-020309 | H17: 53.483 | I17: 0.384 | J17: 13.973 | K17: 52.503 | L17: 39.51 | N17: 9.571 | P17: 111.547 | R17: 13.844 | T17: 0 | V17: 28.987 | W17: 68.531 | Y17: 63.448 | AB17: 23464.644 | AC17: =IF(AND(ISNUMBER(H17),ISNUMBER(I17)),H17+I17,IF(ISNUMBER(K17),K17,IF(ISNUMBER(H17),H17,""))) | AD17: =IF(OR(NOT(ISNUMBER(J17)),NOT(ISNUMBER(H17)),H17<=0),기준표!$B$8,MIN(MAX(J17/H17,기준표!$B$6),기준표!$B$7)) | AE17: =IF(ISNUMBER(AC17),AC17*(1-AD17),"") | AF17: =IF(AND(NOT(ISNUMBER(T17)),NOT(ISNUMBER(V17))),"",IF(ISNUMBER(T17),T17,0)+IF(ISNUMBER(V17),V17,0)) | AG17: =IF(E17="금융","",IF(AND(ISNUMBER(P17),ISNUMBER(AF17),ISNUMBER(R17)),P17+AF17-R17,"")) | AH17: =IF(E17="금융","",IF(NOT(ISNUMBER(AG17)),"",IF(ISNUMBER(AA17),(AG17+AA17)/2,AG17))) | AI17: =IF(AND(ISNUMBER(AE17),ISNUMBER(AH17),AH17>0),AE17/AH17,"") | AJ17: =IF(E17="금융","",IF(AND(ISNUMBER(P17),ISNUMBER(AF17)),P17+AF17,"")) | AK17: =IF(OR(NOT(ISNUMBER(AE17)),NOT(ISNUMBER(AJ17)),AJ17<=0),"",IF(AND(ISNUMBER(G17),AJ17<0.1*G17),"",AE17/AJ17)) | AL17: =IF(NOT(ISNUMBER(P17)),"",IF(ISNUMBER(Q17),(P17+Q17)/2,P17)) | AM17: =IF(AND(ISNUMBER(L17),ISNUMBER(AL17),AL17>0),L17/AL17,"") | AN17: =IF(AND(ISNUMBER(AM17),ISNUMBER({ROIC})),AM17-{ROIC},"") | AO17: =IF(AND(ISNUMBER(AC17),ISNUMBER(M17)),AC17+M17,"") | AP17: =IF(AND(ISNUMBER(AF17),ISNUMBER(R17),ISNUMBER(AO17),AO17>0),(AF17-R17)/AO17,"") | AQ17: =IF(AND(ISNUMBER(AC17),ISNUMBER(I17),I17<>0,AC17>0),AC17/I17,"") | AR17: =IF(AND(ISNUMBER(W17),ISNUMBER(Y17)),W17-IF(ISNUMBER(R17),R17,0)-(Y17-IF(ISNUMBER(T17),T17,0)),"") | AS17: =IF(AND(ISNUMBER(X17),ISNUMBER(Z17)),X17-IF(ISNUMBER(S17),S17,0)-(Z17-IF(ISNUMBER(U17),U17,0)),"") | AT17: =IF(AND(ISNUMBER(AR17),ISNUMBER(AS17)),AR17-AS17,"") | AU17: =IF(E17="금융","",IF(AND(ISNUMBER(L17),ISNUMBER(M17),ISNUMBER(N17),ISNUMBER(AT17)),L17+M17-N17-AT17,IF(AND(ISNUMBER(O17),ISNUMBER(N17)),O17-N17,""))) | AV17: =IF(E17="금융","금융업 - 정의되지 않음",IF(AND(ISNUMBER(L17),ISNUMBER(M17),ISNUMBER(N17),ISNUMBER(AT17)),"순이익+감가상각-설비투자-운전자본증감",IF(AND(ISNUMBER(O17),ISNUMBER(N17)),"영업현금흐름-설비투자","산출불가"))) | AW17: =IF(AND(ISNUMBER(AU17),ISNUMBER(G17),G17<>0),AU17/G17,"") | AX17: =IF(AND(ISNUMBER(AC17),ISNUMBER(G17),G17<>0),AC17/G17,"")
A18: AAPL | B18: Apple Inc. | C18: 2015 | D18: 2015-09-26 | E18: 일반 | F18: 0000320193-17-000070 | H18: 72.515 | I18: 0.733 | J18: 19.121 | K18: 71.23 | L18: 53.394 | M18: 9.2 | N18: 11.247 | O18: 81.266 | P18: 119.355 | Q18: 111.547 | R18: 21.12 | S18: 13.844 | T18: 2.5 | U18: 0 | V18: 53.329 | W18: 89.378 | X18: 68.531 | Y18: 80.61 | Z18: 63.448 | AA18: 126.69 | AB18: 22315.012 | AC18: =IF(AND(ISNUMBER(H18),ISNUMBER(I18)),H18+I18,IF(ISNUMBER(K18),K18,IF(ISNUMBER(H18),H18,""))) | AD18: =IF(OR(NOT(ISNUMBER(J18)),NOT(ISNUMBER(H18)),H18<=0),기준표!$B$8,MIN(MAX(J18/H18,기준표!$B$6),기준표!$B$7)) | AE18: =IF(ISNUMBER(AC18),AC18*(1-AD18),"") | AF18: =IF(AND(NOT(ISNUMBER(T18)),NOT(ISNUMBER(V18))),"",IF(ISNUMBER(T18),T18,0)+IF(ISNUMBER(V18),V18,0)) | AG18: =IF(E18="금융","",IF(AND(ISNUMBER(P18),ISNUMBER(AF18),ISNUMBER(R18)),P18+AF18-R18,"")) | AH18: =IF(E18="금융","",IF(NOT(ISNUMBER(AG18)),"",IF(ISNUMBER(AA18),(AG18+AA18)/2,AG18))) | AI18: =IF(AND(ISNUMBER(AE18),ISNUMBER(AH18),AH18>0),AE18/AH18,"") | AJ18: =IF(E18="금융","",IF(AND(ISNUMBER(P18),ISNUMBER(AF18)),P18+AF18,"")) | AK18: =IF(OR(NOT(ISNUMBER(AE18)),NOT(ISNUMBER(AJ18)),AJ18<=0),"",IF(AND(ISNUMBER(G18),AJ18<0.1*G18),"",AE18/AJ18)) | AL18: =IF(NOT(ISNUMBER(P18)),"",IF(ISNUMBER(Q18),(P18+Q18)/2,P18)) | AM18: =IF(AND(ISNUMBER(L18),ISNUMBER(AL18),AL18>0),L18/AL18,"") | AN18: =IF(AND(ISNUMBER(AM18),ISNUMBER({ROIC})),AM18-{ROIC},"") | AO18: =IF(AND(ISNUMBER(AC18),ISNUMBER(M18)),AC18+M18,"") | AP18: =IF(AND(ISNUMBER(AF18),ISNUMBER(R18),ISNUMBER(AO18),AO18>0),(AF18-R18)/AO18,"") | AQ18: =IF(AND(ISNUMBER(AC18),ISNUMBER(I18),I18<>0,AC18>0),AC18/I18,"") | AR18: =IF(AND(ISNUMBER(W18),ISNUMBER(Y18)),W18-IF(ISNUMBER(R18),R18,0)-(Y18-IF(ISNUMBER(T18),T18,0)),"") | AS18: =IF(AND(ISNUMBER(X18),ISNUMBER(Z18)),X18-IF(ISNUMBER(S18),S18,0)-(Z18-IF(ISNUMBER(U18),U18,0)),"") | AT18: =IF(AND(ISNUMBER(AR18),ISNUMBER(AS18)),AR18-AS18,"") | AU18: =IF(E18="금융","",IF(AND(ISNUMBER(L18),ISNUMBER(M18),ISNUMBER(N18),ISNUMBER(AT18)),L18+M18-N18-AT18,IF(AND(ISNUMBER(O18),ISNUMBER(N18)),O18-N18,""))) | AV18: =IF(E18="금융","금융업 - 정의되지 않음",IF(AND(ISNUMBER(L18),ISNUMBER(M18),ISNUMBER(N18),ISNUMBER(AT18)),"순이익+감가상각-설비투자-운전자본증감",IF(AND(ISNUMBER(O18),ISNUMBER(N18)),"영업현금흐름-설비투자","산출불가"))) | AW18: =IF(AND(ISNUMBER(AU18),ISNUMBER(G18),G18<>0),AU18/G18,"") | AX18: =IF(AND(ISNUMBER(AC18),ISNUMBER(G18),G18<>0),AC18/G18,"")
A19: AAPL | B19: Apple Inc. | C19: 2016 | D19: 2016-09-24 | E19: 일반 | F19: 0000320193-18-000145 | H19: 61.372 | I19: 1.456 | J19: 15.685 | K19: 60.024 | L19: 45.687 | M19: 10.505 | N19: 12.734 | O19: 66.231 | P19: 128.249 | Q19: 119.355 | R19: 20.484 | S19: 21.12 | T19: 3.5 | U19: 2.5 | V19: 75.427 | W19: 106.869 | X19: 89.378 | Y19: 79.006 | Z19: 80.61 | AA19: 154.064 | AB19: 21344.664 | AC19: =IF(AND(ISNUMBER(H19),ISNUMBER(I19)),H19+I19,IF(ISNUMBER(K19),K19,IF(ISNUMBER(H19),H19,""))) | AD19: =IF(OR(NOT(ISNUMBER(J19)),NOT(ISNUMBER(H19)),H19<=0),기준표!$B$8,MIN(MAX(J19/H19,기준표!$B$6),기준표!$B$7)) | AE19: =IF(ISNUMBER(AC19),AC19*(1-AD19),"") | AF19: =IF(AND(NOT(ISNUMBER(T19)),NOT(ISNUMBER(V19))),"",IF(ISNUMBER(T19),T19,0)+IF(ISNUMBER(V19),V19,0)) | AG19: =IF(E19="금융","",IF(AND(ISNUMBER(P19),ISNUMBER(AF19),ISNUMBER(R19)),P19+AF19-R19,"")) | AH19: =IF(E19="금융","",IF(NOT(ISNUMBER(AG19)),"",IF(ISNUMBER(AA19),(AG19+AA19)/2,AG19))) | AI19: =IF(AND(ISNUMBER(AE19),ISNUMBER(AH19),AH19>0),AE19/AH19,"") | AJ19: =IF(E19="금융","",IF(AND(ISNUMBER(P19),ISNUMBER(AF19)),P19+AF19,"")) | AK19: =IF(OR(NOT(ISNUMBER(AE19)),NOT(ISNUMBER(AJ19)),AJ19<=0),"",IF(AND(ISNUMBER(G19),AJ19<0.1*G19),"",AE19/AJ19)) | AL19: =IF(NOT(ISNUMBER(P19)),"",IF(ISNUMBER(Q19),(P19+Q19)/2,P19)) | AM19: =IF(AND(ISNUMBER(L19),ISNUMBER(AL19),AL19>0),L19/AL19,"") | AN19: =IF(AND(ISNUMBER(AM19),ISNUMBER({ROIC})),AM19-{ROIC},"") | AO19: =IF(AND(ISNUMBER(AC19),ISNUMBER(M19)),AC19+M19,"") | AP19: =IF(AND(ISNUMBER(AF19),ISNUMBER(R19),ISNUMBER(AO19),AO19>0),(AF19-R19)/AO19,"") | AQ19: =IF(AND(ISNUMBER(AC19),ISNUMBER(I19),I19<>0,AC19>0),AC19/I19,"") | AR19: =IF(AND(ISNUMBER(W19),ISNUMBER(Y19)),W19-IF(ISNUMBER(R19),R19,0)-(Y19-IF(ISNUMBER(T19),T19,0)),"") | AS19: =IF(AND(ISNUMBER(X19),ISNUMBER(Z19)),X19-IF(ISNUMBER(S19),S19,0)-(Z19-IF(ISNUMBER(U19),U19,0)),"") | AT19: =IF(AND(ISNUMBER(AR19),ISNUMBER(AS19)),AR19-AS19,"") | AU19: =IF(E19="금융","",IF(AND(ISNUMBER(L19),ISNUMBER(M19),ISNUMBER(N19),ISNUMBER(AT19)),L19+M19-N19-AT19,IF(AND(ISNUMBER(O19),ISNUMBER(N19)),O19-N19,""))) | AV19: =IF(E19="금융","금융업 - 정의되지 않음",IF(AND(ISNUMBER(L19),ISNUMBER(M19),ISNUMBER(N19),ISNUMBER(AT19)),"순이익+감가상각-설비투자-운전자본증감",IF(AND(ISNUMBER(O19),ISNUMBER(N19)),"영업현금흐름-설비투자","산출불가"))) | AW19: =IF(AND(ISNUMBER(AU19),ISNUMBER(G19),G19<>0),AU19/G19,"") | AX19: =IF(AND(ISNUMBER(AC19),ISNUMBER(G19),G19<>0),AC19/G19,"")
A20: AAPL | B20: Apple Inc. | C20: 2017 | D20: 2017-09-30 | E20: 일반 | F20: 0000320193-19-000119 | G20: 229.234 | H20: 64.089 | I20: 2.323 | J20: 15.738 | K20: 61.344 | L20: 48.351 | M20: 10.157 | N20: 12.451 | O20: 64.225 | P20: 134.047 | Q20: 128.249 | R20: 20.289 | S20: 20.484 | T20: 6.496 | U20: 3.5 | V20: 97.207 | W20: 128.645 | X20: 106.869 | Y20: 100.814 | Z20: 79.006 | AA20: 186.692 | AB20: 20504.804 | AC20: =IF(AND(ISNUMBER(H20),ISNUMBER(I20)),H20+I20,IF(ISNUMBER(K20),K20,IF(ISNUMBER(H20),H20,""))) | AD20: =IF(OR(NOT(ISNUMBER(J20)),NOT(ISNUMBER(H20)),H20<=0),기준표!$B$8,MIN(MAX(J20/H20,기준표!$B$6),기준표!$B$7)) | AE20: =IF(ISNUMBER(AC20),AC20*(1-AD20),"") | AF20: =IF(AND(NOT(ISNUMBER(T20)),NOT(ISNUMBER(V20))),"",IF(ISNUMBER(T20),T20,0)+IF(ISNUMBER(V20),V20,0)) | AG20: =IF(E20="금융","",IF(AND(ISNUMBER(P20),ISNUMBER(AF20),ISNUMBER(R20)),P20+AF20-R20,"")) | AH20: =IF(E20="금융","",IF(NOT(ISNUMBER(AG20)),"",IF(ISNUMBER(AA20),(AG20+AA20)/2,AG20))) | AI20: =IF(AND(ISNUMBER(AE20),ISNUMBER(AH20),AH20>0),AE20/AH20,"") | AJ20: =IF(E20="금융","",IF(AND(ISNUMBER(P20),ISNUMBER(AF20)),P20+AF20,"")) | AK20: =IF(OR(NOT(ISNUMBER(AE20)),NOT(ISNUMBER(AJ20)),AJ20<=0),"",IF(AND(ISNUMBER(G20),AJ20<0.1*G20),"",AE20/AJ20)) | AL20: =IF(NOT(ISNUMBER(P20)),"",IF(ISNUMBER(Q20),(P20+Q20)/2,P20)) | AM20: =IF(AND(ISNUMBER(L20),ISNUMBER(AL20),AL20>0),L20/AL20,"") | AN20: =IF(AND(ISNUMBER(AM20),ISNUMBER({ROIC})),AM20-{ROIC},"") | AO20: =IF(AND(ISNUMBER(AC20),ISNUMBER(M20)),AC20+M20,"") | AP20: =IF(AND(ISNUMBER(AF20),ISNUMBER(R20),ISNUMBER(AO20),AO20>0),(AF20-R20)/AO20,"") | AQ20: =IF(AND(ISNUMBER(AC20),ISNUMBER(I20),I20<>0,AC20>0),AC20/I20,"") | AR20: =IF(AND(ISNUMBER(W20),ISNUMBER(Y20)),W20-IF(ISNUMBER(R20),R20,0)-(Y20-IF(ISNUMBER(T20),T20,0)),"") | AS20: =IF(AND(ISNUMBER(X20),ISNUMBER(Z20)),X20-IF(ISNUMBER(S20),S20,0)-(Z20-IF(ISNUMBER(U20),U20,0)),"") | AT20: =IF(AND(ISNUMBER(AR20),ISNUMBER(AS20)),AR20-AS20,"") | AU20: =IF(E20="금융","",IF(AND(ISNUMBER(L20),ISNUMBER(M20),ISNUMBER(N20),ISNUMBER(AT20)),L20+M20-N20-AT20,IF(AND(ISNUMBER(O20),ISNUMBER(N20)),O20-N20,""))) | AV20: =IF(E20="금융","금융업 - 정의되지 않음",IF(AND(ISNUMBER(L20),ISNUMBER(M20),ISNUMBER(N20),ISNUMBER(AT20)),"순이익+감가상각-설비투자-운전자본증감",IF(AND(ISNUMBER(O20),ISNUMBER(N20)),"영업현금흐름-설비투자","산출불가"))) | AW20: =IF(AND(ISNUMBER(AU20),ISNUMBER(G20),G20<>0),AU20/G20,"") | AX20: =IF(AND(ISNUMBER(AC20),ISNUMBER(G20),G20<>0),AC20/G20,"")
A21: AAPL | B21: Apple Inc. | C21: 2018 | D21: 2018-09-29 | E21: 일반 | F21: 0000320193-20-000096 | G21: 265.595 | H21: 72.903 | I21: 3.24 | J21: 13.372 | K21: 70.898 | L21: 59.531 | M21: 10.903 | N21: 13.313 | O21: 77.434 | P21: 107.147 | Q21: 134.047 | R21: 66.301 | S21: 20.289 | T21: 8.784 | U21: 6.496 | V21: 93.735 | W21: 131.339 | X21: 128.645 | Y21: 115.929 | Z21: 100.814 | AA21: 217.461 | AB21: 19019.944 | AC21: =IF(AND(ISNUMBER(H21),ISNUMBER(I21)),H21+I21,IF(ISNUMBER(K21),K21,IF(ISNUMBER(H21),H21,""))) | AD21: =IF(OR(NOT(ISNUMBER(J21)),NOT(ISNUMBER(H21)),H21<=0),기준표!$B$8,MIN(MAX(J21/H21,기준표!$B$6),기준표!$B$7)) | AE21: =IF(ISNUMBER(AC21),AC21*(1-AD21),"") | AF21: =IF(AND(NOT(ISNUMBER(T21)),NOT(ISNUMBER(V21))),"",IF(ISNUMBER(T21),T21,0)+IF(ISNUMBER(V21),V21,0)) | AG21: =IF(E21="금융","",IF(AND(ISNUMBER(P21),ISNUMBER(AF21),ISNUMBER(R21)),P21+AF21-R21,"")) | AH21: =IF(E21="금융","",IF(NOT(ISNUMBER(AG21)),"",IF(ISNUMBER(AA21),(AG21+AA21)/2,AG21))) | AI21: =IF(AND(ISNUMBER(AE21),ISNUMBER(AH21),AH21>0),AE21/AH21,"") | AJ21: =IF(E21="금융","",IF(AND(ISNUMBER(P21),ISNUMBER(AF21)),P21+AF21,"")) | AK21: =IF(OR(NOT(ISNUMBER(AE21)),NOT(ISNUMBER(AJ21)),AJ21<=0),"",IF(AND(ISNUMBER(G21),AJ21<0.1*G21),"",AE21/AJ21)) | AL21: =IF(NOT(ISNUMBER(P21)),"",IF(ISNUMBER(Q21),(P21+Q21)/2,P21)) | AM21: =IF(AND(ISNUMBER(L21),ISNUMBER(AL21),AL21>0),L21/AL21,"") | AN21: =IF(AND(ISNUMBER(AM21),ISNUMBER({ROIC})),AM21-{ROIC},"") | AO21: =IF(AND(ISNUMBER(AC21),ISNUMBER(M21)),AC21+M21,"") | AP21: =IF(AND(ISNUMBER(AF21),ISNUMBER(R21),ISNUMBER(AO21),AO21>0),(AF21-R21)/AO21,"") | AQ21: =IF(AND(ISNUMBER(AC21),ISNUMBER(I21),I21<>0,AC21>0),AC21/I21,"") | AR21: =IF(AND(ISNUMBER(W21),ISNUMBER(Y21)),W21-IF(ISNUMBER(R21),R21,0)-(Y21-IF(ISNUMBER(T21),T21,0)),"") | AS21: =IF(AND(ISNUMBER(X21),ISNUMBER(Z21)),X21-IF(ISNUMBER(S21),S21,0)-(Z21-IF(ISNUMBER(U21),U21,0)),"") | AT21: =IF(AND(ISNUMBER(AR21),ISNUMBER(AS21)),AR21-AS21,"") | AU21: =IF(E21="금융","",IF(AND(ISNUMBER(L21),ISNUMBER(M21),ISNUMBER(N21),ISNUMBER(AT21)),L21+M21-N21-AT21,IF(AND(ISNUMBER(O21),ISNUMBER(N21)),O21-N21,""))) | AV21: =IF(E21="금융","금융업 - 정의되지 않음",IF(AND(ISNUMBER(L21),ISNUMBER(M21),ISNUMBER(N21),ISNUMBER(AT21)),"순이익+감가상각-설비투자-운전자본증감",IF(AND(ISNUMBER(O21),ISNUMBER(N21)),"영업현금흐름-설비투자","산출불가"))) | AW21: =IF(AND(ISNUMBER(AU21),ISNUMBER(G21),G21<>0),AU21/G21,"") | AX21: =IF(AND(ISNUMBER(AC21),ISNUMBER(G21),G21<>0),AC21/G21,"")
A22: AAPL | B22: Apple Inc. | C22: 2019 | D22: 2019-09-28 | E22: 일반 | F22: 0000320193-21-000105 | G22: 260.174 | H22: 65.737 | I22: 3.576 | J22: 10.481 | K22: 63.93 | L22: 55.256 | M22: 12.547 | N22: 10.495 | O22: 69.391 | P22: 90.488 | Q22: 107.147 | R22: 100.557 | S22: 66.301 | T22: 10.26 | U22: 8.784 | V22: 91.807 | W22: 162.819 | X22: 131.339 | Y22: 105.718 | Z22: 115.929 | AA22: 143.365 | AB22: 17772.945 | AC22: =IF(AND(ISNUMBER(H22),ISNUMBER(I22)),H22+I22,IF(ISNUMBER(K22),K22,IF(ISNUMBER(H22),H22,""))) | AD22: =IF(OR(NOT(ISNUMBER(J22)),NOT(ISNUMBER(H22)),H22<=0),기준표!$B$8,MIN(MAX(J22/H22,기준표!$B$6),기준표!$B$7)) | AE22: =IF(ISNUMBER(AC22),AC22*(1-AD22),"") | AF22: =IF(AND(NOT(ISNUMBER(T22)),NOT(ISNUMBER(V22))),"",IF(ISNUMBER(T22),T22,0)+IF(ISNUMBER(V22),V22,0)) | AG22: =IF(E22="금융","",IF(AND(ISNUMBER(P22),ISNUMBER(AF22),ISNUMBER(R22)),P22+AF22-R22,"")) | AH22: =IF(E22="금융","",IF(NOT(ISNUMBER(AG22)),"",IF(ISNUMBER(AA22),(AG22+AA22)/2,AG22))) | AI22: =IF(AND(ISNUMBER(AE22),ISNUMBER(AH22),AH22>0),AE22/AH22,"") | AJ22: =IF(E22="금융","",IF(AND(ISNUMBER(P22),ISNUMBER(AF22)),P22+AF22,"")) | AK22: =IF(OR(NOT(ISNUMBER(AE22)),NOT(ISNUMBER(AJ22)),AJ22<=0),"",IF(AND(ISNUMBER(G22),AJ22<0.1*G22),"",AE22/AJ22)) | AL22: =IF(NOT(ISNUMBER(P22)),"",IF(ISNUMBER(Q22),(P22+Q22)/2,P22)) | AM22: =IF(AND(ISNUMBER(L22),ISNUMBER(AL22),AL22>0),L22/AL22,"") | AN22: =IF(AND(ISNUMBER(AM22),ISNUMBER({ROIC})),AM22-{ROIC},"") | AO22: =IF(AND(ISNUMBER(AC22),ISNUMBER(M22)),AC22+M22,"") | AP22: =IF(AND(ISNUMBER(AF22),ISNUMBER(R22),ISNUMBER(AO22),AO22>0),(AF22-R22)/AO22,"") | AQ22: =IF(AND(ISNUMBER(AC22),ISNUMBER(I22),I22<>0,AC22>0),AC22/I22,"") | AR22: =IF(AND(ISNUMBER(W22),ISNUMBER(Y22)),W22-IF(ISNUMBER(R22),R22,0)-(Y22-IF(ISNUMBER(T22),T22,0)),"") | AS22: =IF(AND(ISNUMBER(X22),ISNUMBER(Z22)),X22-IF(ISNUMBER(S22),S22,0)-(Z22-IF(ISNUMBER(U22),U22,0)),"") | AT22: =IF(AND(ISNUMBER(AR22),ISNUMBER(AS22)),AR22-AS22,"") | AU22: =IF(E22="금융","",IF(AND(ISNUMBER(L22),ISNUMBER(M22),ISNUMBER(N22),ISNUMBER(AT22)),L22+M22-N22-AT22,IF(AND(ISNUMBER(O22),ISNUMBER(N22)),O22-N22,""))) | AV22: =IF(E22="금융","금융업 - 정의되지 않음",IF(AND(ISNUMBER(L22),ISNUMBER(M22),ISNUMBER(N22),ISNUMBER(AT22)),"순이익+감가상각-설비투자-운전자본증감",IF(AND(ISNUMBER(O22),ISNUMBER(N22)),"영업현금흐름-설비투자","산출불가"))) | AW22: =IF(AND(ISNUMBER(AU22),ISNUMBER(G22),G22<>0),AU22/G22,"") | AX22: =IF(AND(ISNUMBER(AC22),ISNUMBER(G22),G22<>0),AC22/G22,"")
A23: AAPL | B23: Apple Inc. | C23: 2020 | D23: 2020-09-26 | E23: 일반 | F23: 0000320193-22-000108 | G23: 274.515 | H23: 67.091 | I23: 2.873 | J23: 9.68 | K23: 66.288 | L23: 57.411 | M23: 11.056 | N23: 7.309 | O23: 80.674 | P23: 65.339 | Q23: 90.488 | R23: 90.943 | S23: 100.557 | T23: 8.773 | U23: 10.26 | V23: 98.667 | W23: 143.713 | X23: 162.819 | Y23: 105.392 | Z23: 105.718 | AA23: 91.998 | AB23: 16976.763 | AC23: =IF(AND(ISNUMBER(H23),ISNUMBER(I23)),H23+I23,IF(ISNUMBER(K23),K23,IF(ISNUMBER(H23),H23,""))) | AD23: =IF(OR(NOT(ISNUMBER(J23)),NOT(ISNUMBER(H23)),H23<=0),기준표!$B$8,MIN(MAX(J23/H23,기준표!$B$6),기준표!$B$7)) | AE23: =IF(ISNUMBER(AC23),AC23*(1-AD23),"") | AF23: =IF(AND(NOT(ISNUMBER(T23)),NOT(ISNUMBER(V23))),"",IF(ISNUMBER(T23),T23,0)+IF(ISNUMBER(V23),V23,0)) | AG23: =IF(E23="금융","",IF(AND(ISNUMBER(P23),ISNUMBER(AF23),ISNUMBER(R23)),P23+AF23-R23,"")) | AH23: =IF(E23="금융","",IF(NOT(ISNUMBER(AG23)),"",IF(ISNUMBER(AA23),(AG23+AA23)/2,AG23))) | AI23: =IF(AND(ISNUMBER(AE23),ISNUMBER(AH23),AH23>0),AE23/AH23,"") | AJ23: =IF(E23="금융","",IF(AND(ISNUMBER(P23),ISNUMBER(AF23)),P23+AF23,"")) | AK23: =IF(OR(NOT(ISNUMBER(AE23)),NOT(ISNUMBER(AJ23)),AJ23<=0),"",IF(AND(ISNUMBER(G23),AJ23<0.1*G23),"",AE23/AJ23)) | AL23: =IF(NOT(ISNUMBER(P23)),"",IF(ISNUMBER(Q23),(P23+Q23)/2,P23)) | AM23: =IF(AND(ISNUMBER(L23),ISNUMBER(AL23),AL23>0),L23/AL23,"") | AN23: =IF(AND(ISNUMBER(AM23),ISNUMBER({ROIC})),AM23-{ROIC},"") | AO23: =IF(AND(ISNUMBER(AC23),ISNUMBER(M23)),AC23+M23,"") | AP23: =IF(AND(ISNUMBER(AF23),ISNUMBER(R23),ISNUMBER(AO23),AO23>0),(AF23-R23)/AO23,"") | AQ23: =IF(AND(ISNUMBER(AC23),ISNUMBER(I23),I23<>0,AC23>0),AC23/I23,"") | AR23: =IF(AND(ISNUMBER(W23),ISNUMBER(Y23)),W23-IF(ISNUMBER(R23),R23,0)-(Y23-IF(ISNUMBER(T23),T23,0)),"") | AS23: =IF(AND(ISNUMBER(X23),ISNUMBER(Z23)),X23-IF(ISNUMBER(S23),S23,0)-(Z23-IF(ISNUMBER(U23),U23,0)),"") | AT23: =IF(AND(ISNUMBER(AR23),ISNUMBER(AS23)),AR23-AS23,"") | AU23: =IF(E23="금융","",IF(AND(ISNUMBER(L23),ISNUMBER(M23),ISNUMBER(N23),ISNUMBER(AT23)),L23+M23-N23-AT23,IF(AND(ISNUMBER(O23),ISNUMBER(N23)),O23-N23,""))) | AV23: =IF(E23="금융","금융업 - 정의되지 않음",IF(AND(ISNUMBER(L23),ISNUMBER(M23),ISNUMBER(N23),ISNUMBER(AT23)),"순이익+감가상각-설비투자-운전자본증감",IF(AND(ISNUMBER(O23),ISNUMBER(N23)),"영업현금흐름-설비투자","산출불가"))) | AW23: =IF(AND(ISNUMBER(AU23),ISNUMBER(G23),G23<>0),AU23/G23,"") | AX23: =IF(AND(ISNUMBER(AC23),ISNUMBER(G23),G23<>0),AC23/G23,"")
A24: AAPL | B24: Apple Inc. | C24: 2021 | D24: 2021-09-25 | E24: 일반 | F24: 0000320193-23-000106 | G24: 365.817 | H24: 109.207 | I24: 2.645 | J24: 14.527 | K24: 108.949 | L24: 94.68 | M24: 11.284 | N24: 11.085 | O24: 104.038 | P24: 63.09 | Q24: 65.339 | R24: 62.639 | S24: 90.943 | T24: 9.613 | U24: 8.773 | V24: 109.106 | W24: 134.836 | X24: 143.713 | Y24: 125.481 | Z24: 105.392 | AA24: 81.836 | AB24: 16426.786 | AC24: =IF(AND(ISNUMBER(H24),ISNUMBER(I24)),H24+I24,IF(ISNUMBER(K24),K24,IF(ISNUMBER(H24),H24,""))) | AD24: =IF(OR(NOT(ISNUMBER(J24)),NOT(ISNUMBER(H24)),H24<=0),기준표!$B$8,MIN(MAX(J24/H24,기준표!$B$6),기준표!$B$7)) | AE24: =IF(ISNUMBER(AC24),AC24*(1-AD24),"") | AF24: =IF(AND(NOT(ISNUMBER(T24)),NOT(ISNUMBER(V24))),"",IF(ISNUMBER(T24),T24,0)+IF(ISNUMBER(V24),V24,0)) | AG24: =IF(E24="금융","",IF(AND(ISNUMBER(P24),ISNUMBER(AF24),ISNUMBER(R24)),P24+AF24-R24,"")) | AH24: =IF(E24="금융","",IF(NOT(ISNUMBER(AG24)),"",IF(ISNUMBER(AA24),(AG24+AA24)/2,AG24))) | AI24: =IF(AND(ISNUMBER(AE24),ISNUMBER(AH24),AH24>0),AE24/AH24,"") | AJ24: =IF(E24="금융","",IF(AND(ISNUMBER(P24),ISNUMBER(AF24)),P24+AF24,"")) | AK24: =IF(OR(NOT(ISNUMBER(AE24)),NOT(ISNUMBER(AJ24)),AJ24<=0),"",IF(AND(ISNUMBER(G24),AJ24<0.1*G24),"",AE24/AJ24)) | AL24: =IF(NOT(ISNUMBER(P24)),"",IF(ISNUMBER(Q24),(P24+Q24)/2,P24)) | AM24: =IF(AND(ISNUMBER(L24),ISNUMBER(AL24),AL24>0),L24/AL24,"") | AN24: =IF(AND(ISNUMBER(AM24),ISNUMBER({ROIC})),AM24-{ROIC},"") | AO24: =IF(AND(ISNUMBER(AC24),ISNUMBER(M24)),AC24+M24,"") | AP24: =IF(AND(ISNUMBER(AF24),ISNUMBER(R24),ISNUMBER(AO24),AO24>0),(AF24-R24)/AO24,"") | AQ24: =IF(AND(ISNUMBER(AC24),ISNUMBER(I24),I24<>0,AC24>0),AC24/I24,"") | AR24: =IF(AND(ISNUMBER(W24),ISNUMBER(Y24)),W24-IF(ISNUMBER(R24),R24,0)-(Y24-IF(ISNUMBER(T24),T24,0)),"") | AS24: =IF(AND(ISNUMBER(X24),ISNUMBER(Z24)),X24-IF(ISNUMBER(S24),S24,0)-(Z24-IF(ISNUMBER(U24),U24,0)),"") | AT24: =IF(AND(ISNUMBER(AR24),ISNUMBER(AS24)),AR24-AS24,"") | AU24: =IF(E24="금융","",IF(AND(ISNUMBER(L24),ISNUMBER(M24),ISNUMBER(N24),ISNUMBER(AT24)),L24+M24-N24-AT24,IF(AND(ISNUMBER(O24),ISNUMBER(N24)),O24-N24,""))) | AV24: =IF(E24="금융","금융업 - 정의되지 않음",IF(AND(ISNUMBER(L24),ISNUMBER(M24),ISNUMBER(N24),ISNUMBER(AT24)),"순이익+감가상각-설비투자-운전자본증감",IF(AND(ISNUMBER(O24),ISNUMBER(N24)),"영업현금흐름-설비투자","산출불가"))) | AW24: =IF(AND(ISNUMBER(AU24),ISNUMBER(G24),G24<>0),AU24/G24,"") | AX24: =IF(AND(ISNUMBER(AC24),ISNUMBER(G24),G24<>0),AC24/G24,"")
A25: AAPL | B25: Apple Inc. | C25: 2022 | D25: 2022-09-24 | E25: 일반 | F25: 0000320193-24-000123 | G25: 394.328 | H25: 119.103 | I25: 2.931 | J25: 19.3 | K25: 119.437 | L25: 99.803 | M25: 11.104 | N25: 10.708 | O25: 122.151 | P25: 50.672 | Q25: 63.09 | R25: 48.304 | S25: 62.639 | T25: 11.128 | U25: 9.613 | V25: 98.959 | W25: 135.405 | X25: 134.836 | Y25: 153.982 | Z25: 125.481 | AA25: 119.17 | AB25: 15943.425 | AC25: =IF(AND(ISNUMBER(H25),ISNUMBER(I25)),H25+I25,IF(ISNUMBER(K25),K25,IF(ISNUMBER(H25),H25,""))) | AD25: =IF(OR(NOT(ISNUMBER(J25)),NOT(ISNUMBER(H25)),H25<=0),기준표!$B$8,MIN(MAX(J25/H25,기준표!$B$6),기준표!$B$7)) | AE25: =IF(ISNUMBER(AC25),AC25*(1-AD25),"") | AF25: =IF(AND(NOT(ISNUMBER(T25)),NOT(ISNUMBER(V25))),"",IF(ISNUMBER(T25),T25,0)+IF(ISNUMBER(V25),V25,0)) | AG25: =IF(E25="금융","",IF(AND(ISNUMBER(P25),ISNUMBER(AF25),ISNUMBER(R25)),P25+AF25-R25,"")) | AH25: =IF(E25="금융","",IF(NOT(ISNUMBER(AG25)),"",IF(ISNUMBER(AA25),(AG25+AA25)/2,AG25))) | AI25: =IF(AND(ISNUMBER(AE25),ISNUMBER(AH25),AH25>0),AE25/AH25,"") | AJ25: =IF(E25="금융","",IF(AND(ISNUMBER(P25),ISNUMBER(AF25)),P25+AF25,"")) | AK25: =IF(OR(NOT(ISNUMBER(AE25)),NOT(ISNUMBER(AJ25)),AJ25<=0),"",IF(AND(ISNUMBER(G25),AJ25<0.1*G25),"",AE25/AJ25)) | AL25: =IF(NOT(ISNUMBER(P25)),"",IF(ISNUMBER(Q25),(P25+Q25)/2,P25)) | AM25: =IF(AND(ISNUMBER(L25),ISNUMBER(AL25),AL25>0),L25/AL25,"") | AN25: =IF(AND(ISNUMBER(AM25),ISNUMBER({ROIC})),AM25-{ROIC},"") | AO25: =IF(AND(ISNUMBER(AC25),ISNUMBER(M25)),AC25+M25,"") | AP25: =IF(AND(ISNUMBER(AF25),ISNUMBER(R25),ISNUMBER(AO25),AO25>0),(AF25-R25)/AO25,"") | AQ25: =IF(AND(ISNUMBER(AC25),ISNUMBER(I25),I25<>0,AC25>0),AC25/I25,"") | AR25: =IF(AND(ISNUMBER(W25),ISNUMBER(Y25)),W25-IF(ISNUMBER(R25),R25,0)-(Y25-IF(ISNUMBER(T25),T25,0)),"") | AS25: =IF(AND(ISNUMBER(X25),ISNUMBER(Z25)),X25-IF(ISNUMBER(S25),S25,0)-(Z25-IF(ISNUMBER(U25),U25,0)),"") | AT25: =IF(AND(ISNUMBER(AR25),ISNUMBER(AS25)),AR25-AS25,"") | AU25: =IF(E25="금융","",IF(AND(ISNUMBER(L25),ISNUMBER(M25),ISNUMBER(N25),ISNUMBER(AT25)),L25+M25-N25-AT25,IF(AND(ISNUMBER(O25),ISNUMBER(N25)),O25-N25,""))) | AV25: =IF(E25="금융","금융업 - 정의되지 않음",IF(AND(ISNUMBER(L25),ISNUMBER(M25),ISNUMBER(N25),ISNUMBER(AT25)),"순이익+감가상각-설비투자-운전자본증감",IF(AND(ISNUMBER(O25),ISNUMBER(N25)),"영업현금흐름-설비투자","산출불가"))) | AW25: =IF(AND(ISNUMBER(AU25),ISNUMBER(G25),G25<>0),AU25/G25,"") | AX25: =IF(AND(ISNUMBER(AC25),ISNUMBER(G25),G25<>0),AC25/G25,"")
A26: AAPL | B26: Apple Inc. | C26: 2023 | D26: 2023-09-30 | E26: 일반 | F26: 0000320193-25-000079 | G26: 383.285 | H26: 113.736 | I26: 3.933 | J26: 16.741 | K26: 114.301 | L26: 96.995 | M26: 11.519 | N26: 10.959 | O26: 110.543 | P26: 62.146 | Q26: 50.672 | R26: 61.555 | S26: 48.304 | T26: 9.822 | U26: 11.128 | V26: 95.281 | W26: 143.566 | X26: 135.405 | Y26: 145.308 | Z26: 153.982 | AA26: 112.455 | AB26: 15550.061 | AC26: =IF(AND(ISNUMBER(H26),ISNUMBER(I26)),H26+I26,IF(ISNUMBER(K26),K26,IF(ISNUMBER(H26),H26,""))) | AD26: =IF(OR(NOT(ISNUMBER(J26)),NOT(ISNUMBER(H26)),H26<=0),기준표!$B$8,MIN(MAX(J26/H26,기준표!$B$6),기준표!$B$7)) | AE26: =IF(ISNUMBER(AC26),AC26*(1-AD26),"") | AF26: =IF(AND(NOT(ISNUMBER(T26)),NOT(ISNUMBER(V26))),"",IF(ISNUMBER(T26),T26,0)+IF(ISNUMBER(V26),V26,0)) | AG26: =IF(E26="금융","",IF(AND(ISNUMBER(P26),ISNUMBER(AF26),ISNUMBER(R26)),P26+AF26-R26,"")) | AH26: =IF(E26="금융","",IF(NOT(ISNUMBER(AG26)),"",IF(ISNUMBER(AA26),(AG26+AA26)/2,AG26))) | AI26: =IF(AND(ISNUMBER(AE26),ISNUMBER(AH26),AH26>0),AE26/AH26,"") | AJ26: =IF(E26="금융","",IF(AND(ISNUMBER(P26),ISNUMBER(AF26)),P26+AF26,"")) | AK26: =IF(OR(NOT(ISNUMBER(AE26)),NOT(ISNUMBER(AJ26)),AJ26<=0),"",IF(AND(ISNUMBER(G26),AJ26<0.1*G26),"",AE26/AJ26)) | AL26: =IF(NOT(ISNUMBER(P26)),"",IF(ISNUMBER(Q26),(P26+Q26)/2,P26)) | AM26: =IF(AND(ISNUMBER(L26),ISNUMBER(AL26),AL26>0),L26/AL26,"") | AN26: =IF(AND(ISNUMBER(AM26),ISNUMBER({ROIC})),AM26-{ROIC},"") | AO26: =IF(AND(ISNUMBER(AC26),ISNUMBER(M26)),AC26+M26,"") | AP26: =IF(AND(ISNUMBER(AF26),ISNUMBER(R26),ISNUMBER(AO26),AO26>0),(AF26-R26)/AO26,"") | AQ26: =IF(AND(ISNUMBER(AC26),ISNUMBER(I26),I26<>0,AC26>0),AC26/I26,"") | AR26: =IF(AND(ISNUMBER(W26),ISNUMBER(Y26)),W26-IF(ISNUMBER(R26),R26,0)-(Y26-IF(ISNUMBER(T26),T26,0)),"") | AS26: =IF(AND(ISNUMBER(X26),ISNUMBER(Z26)),X26-IF(ISNUMBER(S26),S26,0)-(Z26-IF(ISNUMBER(U26),U26,0)),"") | AT26: =IF(AND(ISNUMBER(AR26),ISNUMBER(AS26)),AR26-AS26,"") | AU26: =IF(E26="금융","",IF(AND(ISNUMBER(L26),ISNUMBER(M26),ISNUMBER(N26),ISNUMBER(AT26)),L26+M26-N26-AT26,IF(AND(ISNUMBER(O26),ISNUMBER(N26)),O26-N26,""))) | AV26: =IF(E26="금융","금융업 - 정의되지 않음",IF(AND(ISNUMBER(L26),ISNUMBER(M26),ISNUMBER(N26),ISNUMBER(AT26)),"순이익+감가상각-설비투자-운전자본증감",IF(AND(ISNUMBER(O26),ISNUMBER(N26)),"영업현금흐름-설비투자","산출불가"))) | AW26: =IF(AND(ISNUMBER(AU26),ISNUMBER(G26),G26<>0),AU26/G26,"") | AX26: =IF(AND(ISNUMBER(AC26),ISNUMBER(G26),G26<>0),AC26/G26,"")
A27: AAPL | B27: Apple Inc. | C27: 2024 | D27: 2024-09-28 | E27: 일반 | F27: 0000320193-25-000079 | G27: 391.035 | H27: 123.485 | J27: 29.749 | K27: 123.216 | L27: 93.736 | M27: 11.445 | N27: 9.447 | O27: 118.254 | P27: 56.95 | Q27: 62.146 | R27: 65.171 | S27: 61.555 | T27: 10.912 | U27: 9.822 | V27: 85.75 | W27: 152.987 | X27: 143.566 | Y27: 176.392 | Z27: 145.308 | AA27: 105.694 | AB27: 15116.786 | AC27: =IF(AND(ISNUMBER(H27),ISNUMBER(I27)),H27+I27,IF(ISNUMBER(K27),K27,IF(ISNUMBER(H27),H27,""))) | AD27: =IF(OR(NOT(ISNUMBER(J27)),NOT(ISNUMBER(H27)),H27<=0),기준표!$B$8,MIN(MAX(J27/H27,기준표!$B$6),기준표!$B$7)) | AE27: =IF(ISNUMBER(AC27),AC27*(1-AD27),"") | AF27: =IF(AND(NOT(ISNUMBER(T27)),NOT(ISNUMBER(V27))),"",IF(ISNUMBER(T27),T27,0)+IF(ISNUMBER(V27),V27,0)) | AG27: =IF(E27="금융","",IF(AND(ISNUMBER(P27),ISNUMBER(AF27),ISNUMBER(R27)),P27+AF27-R27,"")) | AH27: =IF(E27="금융","",IF(NOT(ISNUMBER(AG27)),"",IF(ISNUMBER(AA27),(AG27+AA27)/2,AG27))) | AI27: =IF(AND(ISNUMBER(AE27),ISNUMBER(AH27),AH27>0),AE27/AH27,"") | AJ27: =IF(E27="금융","",IF(AND(ISNUMBER(P27),ISNUMBER(AF27)),P27+AF27,"")) | AK27: =IF(OR(NOT(ISNUMBER(AE27)),NOT(ISNUMBER(AJ27)),AJ27<=0),"",IF(AND(ISNUMBER(G27),AJ27<0.1*G27),"",AE27/AJ27)) | AL27: =IF(NOT(ISNUMBER(P27)),"",IF(ISNUMBER(Q27),(P27+Q27)/2,P27)) | AM27: =IF(AND(ISNUMBER(L27),ISNUMBER(AL27),AL27>0),L27/AL27,"") | AN27: =IF(AND(ISNUMBER(AM27),ISNUMBER({ROIC})),AM27-{ROIC},"") | AO27: =IF(AND(ISNUMBER(AC27),ISNUMBER(M27)),AC27+M27,"") | AP27: =IF(AND(ISNUMBER(AF27),ISNUMBER(R27),ISNUMBER(AO27),AO27>0),(AF27-R27)/AO27,"") | AQ27: =IF(AND(ISNUMBER(AC27),ISNUMBER(I27),I27<>0,AC27>0),AC27/I27,"") | AR27: =IF(AND(ISNUMBER(W27),ISNUMBER(Y27)),W27-IF(ISNUMBER(R27),R27,0)-(Y27-IF(ISNUMBER(T27),T27,0)),"") | AS27: =IF(AND(ISNUMBER(X27),ISNUMBER(Z27)),X27-IF(ISNUMBER(S27),S27,0)-(Z27-IF(ISNUMBER(U27),U27,0)),"") | AT27: =IF(AND(ISNUMBER(AR27),ISNUMBER(AS27)),AR27-AS27,"") | AU27: =IF(E27="금융","",IF(AND(ISNUMBER(L27),ISNUMBER(M27),ISNUMBER(N27),ISNUMBER(AT27)),L27+M27-N27-AT27,IF(AND(ISNUMBER(O27),ISNUMBER(N27)),O27-N27,""))) | AV27: =IF(E27="금융","금융업 - 정의되지 않음",IF(AND(ISNUMBER(L27),ISNUMBER(M27),ISNUMBER(N27),ISNUMBER(AT27)),"순이익+감가상각-설비투자-운전자본증감",IF(AND(ISNUMBER(O27),ISNUMBER(N27)),"영업현금흐름-설비투자","산출불가"))) | AW27: =IF(AND(ISNUMBER(AU27),ISNUMBER(G27),G27<>0),AU27/G27,"") | AX27: =IF(AND(ISNUMBER(AC27),ISNUMBER(G27),G27<>0),AC27/G27,"")
A28: AAPL | B28: Apple Inc. | C28: 2025 | D28: 2025-09-27 | E28: 일반 | F28: 0000320193-25-000079 | G28: 416.161 | H28: 132.729 | J28: 20.719 | K28: 133.05 | L28: 112.01 | M28: 11.698 | N28: 12.715 | O28: 111.482 | P28: 73.733 | Q28: 56.95 | R28: 54.697 | S28: 65.171 | T28: 12.35 | U28: 10.912 | V28: 78.328 | W28: 147.957 | X28: 152.987 | Y28: 165.631 | Z28: 176.392 | AA28: 88.441 | AB28: 14773.26 | AC28: =IF(AND(ISNUMBER(H28),ISNUMBER(I28)),H28+I28,IF(ISNUMBER(K28),K28,IF(ISNUMBER(H28),H28,""))) | AD28: =IF(OR(NOT(ISNUMBER(J28)),NOT(ISNUMBER(H28)),H28<=0),기준표!$B$8,MIN(MAX(J28/H28,기준표!$B$6),기준표!$B$7)) | AE28: =IF(ISNUMBER(AC28),AC28*(1-AD28),"") | AF28: =IF(AND(NOT(ISNUMBER(T28)),NOT(ISNUMBER(V28))),"",IF(ISNUMBER(T28),T28,0)+IF(ISNUMBER(V28),V28,0)) | AG28: =IF(E28="금융","",IF(AND(ISNUMBER(P28),ISNUMBER(AF28),ISNUMBER(R28)),P28+AF28-R28,"")) | AH28: =IF(E28="금융","",IF(NOT(ISNUMBER(AG28)),"",IF(ISNUMBER(AA28),(AG28+AA28)/2,AG28))) | AI28: =IF(AND(ISNUMBER(AE28),ISNUMBER(AH28),AH28>0),AE28/AH28,"") | AJ28: =IF(E28="금융","",IF(AND(ISNUMBER(P28),ISNUMBER(AF28)),P28+AF28,"")) | AK28: =IF(OR(NOT(ISNUMBER(AE28)),NOT(ISNUMBER(AJ28)),AJ28<=0),"",IF(AND(ISNUMBER(G28),AJ28<0.1*G28),"",AE28/AJ28)) | AL28: =IF(NOT(ISNUMBER(P28)),"",IF(ISNUMBER(Q28),(P28+Q28)/2,P28)) | AM28: =IF(AND(ISNUMBER(L28),ISNUMBER(AL28),AL28>0),L28/AL28,"") | AN28: =IF(AND(ISNUMBER(AM28),ISNUMBER({ROIC})),AM28-{ROIC},"") | AO28: =IF(AND(ISNUMBER(AC28),ISNUMBER(M28)),AC28+M28,"") | AP28: =IF(AND(ISNUMBER(AF28),ISNUMBER(R28),ISNUMBER(AO28),AO28>0),(AF28-R28)/AO28,"") | AQ28: =IF(AND(ISNUMBER(AC28),ISNUMBER(I28),I28<>0,AC28>0),AC28/I28,"") | AR28: =IF(AND(ISNUMBER(W28),ISNUMBER(Y28)),W28-IF(ISNUMBER(R28),R28,0)-(Y28-IF(ISNUMBER(T28),T28,0)),"") | AS28: =IF(AND(ISNUMBER(X28),ISNUMBER(Z28)),X28-IF(ISNUMBER(S28),S28,0)-(Z28-IF(ISNUMBER(U28),U28,0)),"") | AT28: =IF(AND(ISNUMBER(AR28),ISNUMBER(AS28)),AR28-AS28,"") | AU28: =IF(E28="금융","",IF(AND(ISNUMBER(L28),ISNUMBER(M28),ISNUMBER(N28),ISNUMBER(AT28)),L28+M28-N28-AT28,IF(AND(ISNUMBER(O28),ISNUMBER(N28)),O28-N28,""))) | AV28: =IF(E28="금융","금융업 - 정의되지 않음",IF(AND(ISNUMBER(L28),ISNUMBER(M28),ISNUMBER(N28),ISNUMBER(AT28)),"순이익+감가상각-설비투자-운전자본증감",IF(AND(ISNUMBER(O28),ISNUMBER(N28)),"영업현금흐름-설비투자","산출불가"))) | AW28: =IF(AND(ISNUMBER(AU28),ISNUMBER(G28),G28<>0),AU28/G28,"") | AX28: =IF(AND(ISNUMBER(AC28),ISNUMBER(G28),G28<>0),AC28/G28,"")
A29: GOOG | B29: Alphabet Inc. | C29: 2014 | D29: 2014-12-31 | E29: 일반 | F29: 0001652044-17-000008 | G29: 66.001 | J29: 3.639 | K29: 16.496 | L29: 14.136 | N29: 11.014 | O29: 23.024 | P29: 103.86 | R29: 64.395 | T29: 2 | W29: 78.656 | Y29: 16.779 | AB29: 13603.44 | AC29: =IF(AND(ISNUMBER(H29),ISNUMBER(I29)),H29+I29,IF(ISNUMBER(K29),K29,IF(ISNUMBER(H29),H29,""))) | AD29: =IF(OR(NOT(ISNUMBER(J29)),NOT(ISNUMBER(H29)),H29<=0),기준표!$B$8,MIN(MAX(J29/H29,기준표!$B$6),기준표!$B$7)) | AE29: =IF(ISNUMBER(AC29),AC29*(1-AD29),"") | AF29: =IF(AND(NOT(ISNUMBER(T29)),NOT(ISNUMBER(V29))),"",IF(ISNUMBER(T29),T29,0)+IF(ISNUMBER(V29),V29,0)) | AG29: =IF(E29="금융","",IF(AND(ISNUMBER(P29),ISNUMBER(AF29),ISNUMBER(R29)),P29+AF29-R29,"")) | AH29: =IF(E29="금융","",IF(NOT(ISNUMBER(AG29)),"",IF(ISNUMBER(AA29),(AG29+AA29)/2,AG29))) | AI29: =IF(AND(ISNUMBER(AE29),ISNUMBER(AH29),AH29>0),AE29/AH29,"") | AJ29: =IF(E29="금융","",IF(AND(ISNUMBER(P29),ISNUMBER(AF29)),P29+AF29,"")) | AK29: =IF(OR(NOT(ISNUMBER(AE29)),NOT(ISNUMBER(AJ29)),AJ29<=0),"",IF(AND(ISNUMBER(G29),AJ29<0.1*G29),"",AE29/AJ29)) | AL29: =IF(NOT(ISNUMBER(P29)),"",IF(ISNUMBER(Q29),(P29+Q29)/2,P29)) | AM29: =IF(AND(ISNUMBER(L29),ISNUMBER(AL29),AL29>0),L29/AL29,"") | AN29: =IF(AND(ISNUMBER(AM29),ISNUMBER({ROIC})),AM29-{ROIC},"") | AO29: =IF(AND(ISNUMBER(AC29),ISNUMBER(M29)),AC29+M29,"") | AP29: =IF(AND(ISNUMBER(AF29),ISNUMBER(R29),ISNUMBER(AO29),AO29>0),(AF29-R29)/AO29,"") | AQ29: =IF(AND(ISNUMBER(AC29),ISNUMBER(I29),I29<>0,AC29>0),AC29/I29,"") | AR29: =IF(AND(ISNUMBER(W29),ISNUMBER(Y29)),W29-IF(ISNUMBER(R29),R29,0)-(Y29-IF(ISNUMBER(T29),T29,0)),"") | AS29: =IF(AND(ISNUMBER(X29),ISNUMBER(Z29)),X29-IF(ISNUMBER(S29),S29,0)-(Z29-IF(ISNUMBER(U29),U29,0)),"") | AT29: =IF(AND(ISNUMBER(AR29),ISNUMBER(AS29)),AR29-AS29,"") | AU29: =IF(E29="금융","",IF(AND(ISNUMBER(L29),ISNUMBER(M29),ISNUMBER(N29),ISNUMBER(AT29)),L29+M29-N29-AT29,IF(AND(ISNUMBER(O29),ISNUMBER(N29)),O29-N29,""))) | AV29: =IF(E29="금융","금융업 - 정의되지 않음",IF(AND(ISNUMBER(L29),ISNUMBER(M29),ISNUMBER(N29),ISNUMBER(AT29)),"순이익+감가상각-설비투자-운전자본증감",IF(AND(ISNUMBER(O29),ISNUMBER(N29)),"영업현금흐름-설비투자","산출불가"))) | AW29: =IF(AND(ISNUMBER(AU29),ISNUMBER(G29),G29<>0),AU29/G29,"") | AX29: =IF(AND(ISNUMBER(AC29),ISNUMBER(G29),G29<>0),AC29/G29,"")
A30: GOOG | B30: Alphabet Inc. | C30: 2015 | D30: 2015-12-31 | E30: 일반 | F30: 0001652044-18-000007 | G30: 74.989 | J30: 3.303 | K30: 19.36 | L30: 16.348 | N30: 9.95 | O30: 26.572 | P30: 120.331 | Q30: 103.86 | R30: 73.066 | S30: 64.395 | T30: 2 | U30: 2 | V30: 3.225 | W30: 90.114 | X30: 78.656 | Y30: 19.31 | Z30: 16.779 | AA30: 41.465 | AB30: 13746.96 | AC30: =IF(AND(ISNUMBER(H30),ISNUMBER(I30)),H30+I30,IF(ISNUMBER(K30),K30,IF(ISNUMBER(H30),H30,""))) | AD30: =IF(OR(NOT(ISNUMBER(J30)),NOT(ISNUMBER(H30)),H30<=0),기준표!$B$8,MIN(MAX(J30/H30,기준표!$B$6),기준표!$B$7)) | AE30: =IF(ISNUMBER(AC30),AC30*(1-AD30),"") | AF30: =IF(AND(NOT(ISNUMBER(T30)),NOT(ISNUMBER(V30))),"",IF(ISNUMBER(T30),T30,0)+IF(ISNUMBER(V30),V30,0)) | AG30: =IF(E30="금융","",IF(AND(ISNUMBER(P30),ISNUMBER(AF30),ISNUMBER(R30)),P30+AF30-R30,"")) | AH30: =IF(E30="금융","",IF(NOT(ISNUMBER(AG30)),"",IF(ISNUMBER(AA30),(AG30+AA30)/2,AG30))) | AI30: =IF(AND(ISNUMBER(AE30),ISNUMBER(AH30),AH30>0),AE30/AH30,"") | AJ30: =IF(E30="금융","",IF(AND(ISNUMBER(P30),ISNUMBER(AF30)),P30+AF30,"")) | AK30: =IF(OR(NOT(ISNUMBER(AE30)),NOT(ISNUMBER(AJ30)),AJ30<=0),"",IF(AND(ISNUMBER(G30),AJ30<0.1*G30),"",AE30/AJ30)) | AL30: =IF(NOT(ISNUMBER(P30)),"",IF(ISNUMBER(Q30),(P30+Q30)/2,P30)) | AM30: =IF(AND(ISNUMBER(L30),ISNUMBER(AL30),AL30>0),L30/AL30,"") | AN30: =IF(AND(ISNUMBER(AM30),ISNUMBER({ROIC})),AM30-{ROIC},"") | AO30: =IF(AND(ISNUMBER(AC30),ISNUMBER(M30)),AC30+M30,"") | AP30: =IF(AND(ISNUMBER(AF30),ISNUMBER(R30),ISNUMBER(AO30),AO30>0),(AF30-R30)/AO30,"") | AQ30: =IF(AND(ISNUMBER(AC30),ISNUMBER(I30),I30<>0,AC30>0),AC30/I30,"") | AR30: =IF(AND(ISNUMBER(W30),ISNUMBER(Y30)),W30-IF(ISNUMBER(R30),R30,0)-(Y30-IF(ISNUMBER(T30),T30,0)),"") | AS30: =IF(AND(ISNUMBER(X30),ISNUMBER(Z30)),X30-IF(ISNUMBER(S30),S30,0)-(Z30-IF(ISNUMBER(U30),U30,0)),"") | AT30: =IF(AND(ISNUMBER(AR30),ISNUMBER(AS30)),AR30-AS30,"") | AU30: =IF(E30="금융","",IF(AND(ISNUMBER(L30),ISNUMBER(M30),ISNUMBER(N30),ISNUMBER(AT30)),L30+M30-N30-AT30,IF(AND(ISNUMBER(O30),ISNUMBER(N30)),O30-N30,""))) | AV30: =IF(E30="금융","금융업 - 정의되지 않음",IF(AND(ISNUMBER(L30),ISNUMBER(M30),ISNUMBER(N30),ISNUMBER(AT30)),"순이익+감가상각-설비투자-운전자본증감",IF(AND(ISNUMBER(O30),ISNUMBER(N30)),"영업현금흐름-설비투자","산출불가"))) | AW30: =IF(AND(ISNUMBER(AU30),ISNUMBER(G30),G30<>0),AU30/G30,"") | AX30: =IF(AND(ISNUMBER(AC30),ISNUMBER(G30),G30<>0),AC30/G30,"")
A31: GOOG | B31: Alphabet Inc. | C31: 2016 | D31: 2016-12-31 | E31: 일반 | F31: 0001652044-19-000004 | G31: 90.272 | J31: 4.672 | K31: 23.716 | L31: 19.478 | N31: 10.212 | O31: 36.036 | P31: 139.036 | Q31: 120.331 | R31: 86.333 | S31: 73.066 | T31: 0 | U31: 2 | V31: 4 | W31: 105.408 | X31: 90.114 | Y31: 16.756 | Z31: 19.31 | AA31: 52.49 | AB31: 13825.86 | AC31: =IF(AND(ISNUMBER(H31),ISNUMBER(I31)),H31+I31,IF(ISNUMBER(K31),K31,IF(ISNUMBER(H31),H31,""))) | AD31: =IF(OR(NOT(ISNUMBER(J31)),NOT(ISNUMBER(H31)),H31<=0),기준표!$B$8,MIN(MAX(J31/H31,기준표!$B$6),기준표!$B$7)) | AE31: =IF(ISNUMBER(AC31),AC31*(1-AD31),"") | AF31: =IF(AND(NOT(ISNUMBER(T31)),NOT(ISNUMBER(V31))),"",IF(ISNUMBER(T31),T31,0)+IF(ISNUMBER(V31),V31,0)) | AG31: =IF(E31="금융","",IF(AND(ISNUMBER(P31),ISNUMBER(AF31),ISNUMBER(R31)),P31+AF31-R31,"")) | AH31: =IF(E31="금융","",IF(NOT(ISNUMBER(AG31)),"",IF(ISNUMBER(AA31),(AG31+AA31)/2,AG31))) | AI31: =IF(AND(ISNUMBER(AE31),ISNUMBER(AH31),AH31>0),AE31/AH31,"") | AJ31: =IF(E31="금융","",IF(AND(ISNUMBER(P31),ISNUMBER(AF31)),P31+AF31,"")) | AK31: =IF(OR(NOT(ISNUMBER(AE31)),NOT(ISNUMBER(AJ31)),AJ31<=0),"",IF(AND(ISNUMBER(G31),AJ31<0.1*G31),"",AE31/AJ31)) | AL31: =IF(NOT(ISNUMBER(P31)),"",IF(ISNUMBER(Q31),(P31+Q31)/2,P31)) | AM31: =IF(AND(ISNUMBER(L31),ISNUMBER(AL31),AL31>0),L31/AL31,"") | AN31: =IF(AND(ISNUMBER(AM31),ISNUMBER({ROIC})),AM31-{ROIC},"") | AO31: =IF(AND(ISNUMBER(AC31),ISNUMBER(M31)),AC31+M31,"") | AP31: =IF(AND(ISNUMBER(AF31),ISNUMBER(R31),ISNUMBER(AO31),AO31>0),(AF31-R31)/AO31,"") | AQ31: =IF(AND(ISNUMBER(AC31),ISNUMBER(I31),I31<>0,AC31>0),AC31/I31,"") | AR31: =IF(AND(ISNUMBER(W31),ISNUMBER(Y31)),W31-IF(ISNUMBER(R31),R31,0)-(Y31-IF(ISNUMBER(T31),T31,0)),"") | AS31: =IF(AND(ISNUMBER(X31),ISNUMBER(Z31)),X31-IF(ISNUMBER(S31),S31,0)-(Z31-IF(ISNUMBER(U31),U31,0)),"") | AT31: =IF(AND(ISNUMBER(AR31),ISNUMBER(AS31)),AR31-AS31,"") | AU31: =IF(E31="금융","",IF(AND(ISNUMBER(L31),ISNUMBER(M31),ISNUMBER(N31),ISNUMBER(AT31)),L31+M31-N31-AT31,IF(AND(ISNUMBER(O31),ISNUMBER(N31)),O31-N31,""))) | AV31: =IF(E31="금융","금융업 - 정의되지 않음",IF(AND(ISNUMBER(L31),ISNUMBER(M31),ISNUMBER(N31),ISNUMBER(AT31)),"순이익+감가상각-설비투자-운전자본증감",IF(AND(ISNUMBER(O31),ISNUMBER(N31)),"영업현금흐름-설비투자","산출불가"))) | AW31: =IF(AND(ISNUMBER(AU31),ISNUMBER(G31),G31<>0),AU31/G31,"") | AX31: =IF(AND(ISNUMBER(AC31),ISNUMBER(G31),G31<>0),AC31/G31,"")
A32: GOOG | B32: Alphabet Inc. | C32: 2017 | D32: 2017-12-31 | E32: 일반 | F32: 0001652044-20-000008 | G32: 110.855 | H32: 27.193 | J32: 14.531 | K32: 26.178 | L32: 12.662 | N32: 13.184 | O32: 37.091 | P32: 152.502 | Q32: 139.036 | R32: 101.871 | S32: 86.333 | T32: 0 | U32: 0 | V32: 4.026 | W32: 124.308 | X32: 105.408 | Y32: 24.183 | Z32: 16.756 | AA32: 56.703 | AB32: 13895.66 | AC32: =IF(AND(ISNUMBER(H32),ISNUMBER(I32)),H32+I32,IF(ISNUMBER(K32),K32,IF(ISNUMBER(H32),H32,""))) | AD32: =IF(OR(NOT(ISNUMBER(J32)),NOT(ISNUMBER(H32)),H32<=0),기준표!$B$8,MIN(MAX(J32/H32,기준표!$B$6),기준표!$B$7)) | AE32: =IF(ISNUMBER(AC32),AC32*(1-AD32),"") | AF32: =IF(AND(NOT(ISNUMBER(T32)),NOT(ISNUMBER(V32))),"",IF(ISNUMBER(T32),T32,0)+IF(ISNUMBER(V32),V32,0)) | AG32: =IF(E32="금융","",IF(AND(ISNUMBER(P32),ISNUMBER(AF32),ISNUMBER(R32)),P32+AF32-R32,"")) | AH32: =IF(E32="금융","",IF(NOT(ISNUMBER(AG32)),"",IF(ISNUMBER(AA32),(AG32+AA32)/2,AG32))) | AI32: =IF(AND(ISNUMBER(AE32),ISNUMBER(AH32),AH32>0),AE32/AH32,"") | AJ32: =IF(E32="금융","",IF(AND(ISNUMBER(P32),ISNUMBER(AF32)),P32+AF32,"")) | AK32: =IF(OR(NOT(ISNUMBER(AE32)),NOT(ISNUMBER(AJ32)),AJ32<=0),"",IF(AND(ISNUMBER(G32),AJ32<0.1*G32),"",AE32/AJ32)) | AL32: =IF(NOT(ISNUMBER(P32)),"",IF(ISNUMBER(Q32),(P32+Q32)/2,P32)) | AM32: =IF(AND(ISNUMBER(L32),ISNUMBER(AL32),AL32>0),L32/AL32,"") | AN32: =IF(AND(ISNUMBER(AM32),ISNUMBER({ROIC})),AM32-{ROIC},"") | AO32: =IF(AND(ISNUMBER(AC32),ISNUMBER(M32)),AC32+M32,"") | AP32: =IF(AND(ISNUMBER(AF32),ISNUMBER(R32),ISNUMBER(AO32),AO32>0),(AF32-R32)/AO32,"") | AQ32: =IF(AND(ISNUMBER(AC32),ISNUMBER(I32),I32<>0,AC32>0),AC32/I32,"") | AR32: =IF(AND(ISNUMBER(W32),ISNUMBER(Y32)),W32-IF(ISNUMBER(R32),R32,0)-(Y32-IF(ISNUMBER(T32),T32,0)),"") | AS32: =IF(AND(ISNUMBER(X32),ISNUMBER(Z32)),X32-IF(ISNUMBER(S32),S32,0)-(Z32-IF(ISNUMBER(U32),U32,0)),"") | AT32: =IF(AND(ISNUMBER(AR32),ISNUMBER(AS32)),AR32-AS32,"") | AU32: =IF(E32="금융","",IF(AND(ISNUMBER(L32),ISNUMBER(M32),ISNUMBER(N32),ISNUMBER(AT32)),L32+M32-N32-AT32,IF(AND(ISNUMBER(O32),ISNUMBER(N32)),O32-N32,""))) | AV32: =IF(E32="금융","금융업 - 정의되지 않음",IF(AND(ISNUMBER(L32),ISNUMBER(M32),ISNUMBER(N32),ISNUMBER(AT32)),"순이익+감가상각-설비투자-운전자본증감",IF(AND(ISNUMBER(O32),ISNUMBER(N32)),"영업현금흐름-설비투자","산출불가"))) | AW32: =IF(AND(ISNUMBER(AU32),ISNUMBER(G32),G32<>0),AU32/G32,"") | AX32: =IF(AND(ISNUMBER(AC32),ISNUMBER(G32),G32<>0),AC32/G32,"")
A33: GOOG | B33: Alphabet Inc. | C33: 2018 | D33: 2018-12-31 | E33: 일반 | F33: 0001652044-21-000010 | G33: 136.819 | H33: 34.913 | J33: 4.177 | K33: 27.524 | L33: 30.736 | N33: 25.139 | O33: 47.971 | P33: 177.628 | Q33: 152.502 | R33: 109.14 | S33: 101.871 | T33: 0 | U33: 0 | V33: 4.062 | W33: 135.676 | X33: 124.308 | Y33: 34.62 | Z33: 24.183 | AA33: 54.657 | AB33: 13911.12 | AC33: =IF(AND(ISNUMBER(H33),ISNUMBER(I33)),H33+I33,IF(ISNUMBER(K33),K33,IF(ISNUMBER(H33),H33,""))) | AD33: =IF(OR(NOT(ISNUMBER(J33)),NOT(ISNUMBER(H33)),H33<=0),기준표!$B$8,MIN(MAX(J33/H33,기준표!$B$6),기준표!$B$7)) | AE33: =IF(ISNUMBER(AC33),AC33*(1-AD33),"") | AF33: =IF(AND(NOT(ISNUMBER(T33)),NOT(ISNUMBER(V33))),"",IF(ISNUMBER(T33),T33,0)+IF(ISNUMBER(V33),V33,0)) | AG33: =IF(E33="금융","",IF(AND(ISNUMBER(P33),ISNUMBER(AF33),ISNUMBER(R33)),P33+AF33-R33,"")) | AH33: =IF(E33="금융","",IF(NOT(ISNUMBER(AG33)),"",IF(ISNUMBER(AA33),(AG33+AA33)/2,AG33))) | AI33: =IF(AND(ISNUMBER(AE33),ISNUMBER(AH33),AH33>0),AE33/AH33,"") | AJ33: =IF(E33="금융","",IF(AND(ISNUMBER(P33),ISNUMBER(AF33)),P33+AF33,"")) | AK33: =IF(OR(NOT(ISNUMBER(AE33)),NOT(ISNUMBER(AJ33)),AJ33<=0),"",IF(AND(ISNUMBER(G33),AJ33<0.1*G33),"",AE33/AJ33)) | AL33: =IF(NOT(ISNUMBER(P33)),"",IF(ISNUMBER(Q33),(P33+Q33)/2,P33)) | AM33: =IF(AND(ISNUMBER(L33),ISNUMBER(AL33),AL33>0),L33/AL33,"") | AN33: =IF(AND(ISNUMBER(AM33),ISNUMBER({ROIC})),AM33-{ROIC},"") | AO33: =IF(AND(ISNUMBER(AC33),ISNUMBER(M33)),AC33+M33,"") | AP33: =IF(AND(ISNUMBER(AF33),ISNUMBER(R33),ISNUMBER(AO33),AO33>0),(AF33-R33)/AO33,"") | AQ33: =IF(AND(ISNUMBER(AC33),ISNUMBER(I33),I33<>0,AC33>0),AC33/I33,"") | AR33: =IF(AND(ISNUMBER(W33),ISNUMBER(Y33)),W33-IF(ISNUMBER(R33),R33,0)-(Y33-IF(ISNUMBER(T33),T33,0)),"") | AS33: =IF(AND(ISNUMBER(X33),ISNUMBER(Z33)),X33-IF(ISNUMBER(S33),S33,0)-(Z33-IF(ISNUMBER(U33),U33,0)),"") | AT33: =IF(AND(ISNUMBER(AR33),ISNUMBER(AS33)),AR33-AS33,"") | AU33: =IF(E33="금융","",IF(AND(ISNUMBER(L33),ISNUMBER(M33),ISNUMBER(N33),ISNUMBER(AT33)),L33+M33-N33-AT33,IF(AND(ISNUMBER(O33),ISNUMBER(N33)),O33-N33,""))) | AV33: =IF(E33="금융","금융업 - 정의되지 않음",IF(AND(ISNUMBER(L33),ISNUMBER(M33),ISNUMBER(N33),ISNUMBER(AT33)),"순이익+감가상각-설비투자-운전자본증감",IF(AND(ISNUMBER(O33),ISNUMBER(N33)),"영업현금흐름-설비투자","산출불가"))) | AW33: =IF(AND(ISNUMBER(AU33),ISNUMBER(G33),G33<>0),AU33/G33,"") | AX33: =IF(AND(ISNUMBER(AC33),ISNUMBER(G33),G33<>0),AC33/G33,"")
A34: GOOG | B34: Alphabet Inc. | C34: 2019 | D34: 2019-12-31 | E34: 일반 | F34: 0001652044-22-000019 | G34: 161.857 | H34: 39.625 | J34: 5.282 | K34: 34.231 | L34: 34.343 | N34: 23.548 | O34: 54.52 | P34: 201.442 | Q34: 177.628 | R34: 119.675 | S34: 109.14 | T34: 0 | U34: 0 | V34: 4.685 | W34: 152.578 | X34: 135.676 | Y34: 45.221 | Z34: 34.62 | AA34: 72.55 | AB34: 13766.7 | AC34: =IF(AND(ISNUMBER(H34),ISNUMBER(I34)),H34+I34,IF(ISNUMBER(K34),K34,IF(ISNUMBER(H34),H34,""))) | AD34: =IF(OR(NOT(ISNUMBER(J34)),NOT(ISNUMBER(H34)),H34<=0),기준표!$B$8,MIN(MAX(J34/H34,기준표!$B$6),기준표!$B$7)) | AE34: =IF(ISNUMBER(AC34),AC34*(1-AD34),"") | AF34: =IF(AND(NOT(ISNUMBER(T34)),NOT(ISNUMBER(V34))),"",IF(ISNUMBER(T34),T34,0)+IF(ISNUMBER(V34),V34,0)) | AG34: =IF(E34="금융","",IF(AND(ISNUMBER(P34),ISNUMBER(AF34),ISNUMBER(R34)),P34+AF34-R34,"")) | AH34: =IF(E34="금융","",IF(NOT(ISNUMBER(AG34)),"",IF(ISNUMBER(AA34),(AG34+AA34)/2,AG34))) | AI34: =IF(AND(ISNUMBER(AE34),ISNUMBER(AH34),AH34>0),AE34/AH34,"") | AJ34: =IF(E34="금융","",IF(AND(ISNUMBER(P34),ISNUMBER(AF34)),P34+AF34,"")) | AK34: =IF(OR(NOT(ISNUMBER(AE34)),NOT(ISNUMBER(AJ34)),AJ34<=0),"",IF(AND(ISNUMBER(G34),AJ34<0.1*G34),"",AE34/AJ34)) | AL34: =IF(NOT(ISNUMBER(P34)),"",IF(ISNUMBER(Q34),(P34+Q34)/2,P34)) | AM34: =IF(AND(ISNUMBER(L34),ISNUMBER(AL34),AL34>0),L34/AL34,"") | AN34: =IF(AND(ISNUMBER(AM34),ISNUMBER({ROIC})),AM34-{ROIC},"") | AO34: =IF(AND(ISNUMBER(AC34),ISNUMBER(M34)),AC34+M34,"") | AP34: =IF(AND(ISNUMBER(AF34),ISNUMBER(R34),ISNUMBER(AO34),AO34>0),(AF34-R34)/AO34,"") | AQ34: =IF(AND(ISNUMBER(AC34),ISNUMBER(I34),I34<>0,AC34>0),AC34/I34,"") | AR34: =IF(AND(ISNUMBER(W34),ISNUMBER(Y34)),W34-IF(ISNUMBER(R34),R34,0)-(Y34-IF(ISNUMBER(T34),T34,0)),"") | AS34: =IF(AND(ISNUMBER(X34),ISNUMBER(Z34)),X34-IF(ISNUMBER(S34),S34,0)-(Z34-IF(ISNUMBER(U34),U34,0)),"") | AT34: =IF(AND(ISNUMBER(AR34),ISNUMBER(AS34)),AR34-AS34,"") | AU34: =IF(E34="금융","",IF(AND(ISNUMBER(L34),ISNUMBER(M34),ISNUMBER(N34),ISNUMBER(AT34)),L34+M34-N34-AT34,IF(AND(ISNUMBER(O34),ISNUMBER(N34)),O34-N34,""))) | AV34: =IF(E34="금융","금융업 - 정의되지 않음",IF(AND(ISNUMBER(L34),ISNUMBER(M34),ISNUMBER(N34),ISNUMBER(AT34)),"순이익+감가상각-설비투자-운전자본증감",IF(AND(ISNUMBER(O34),ISNUMBER(N34)),"영업현금흐름-설비투자","산출불가"))) | AW34: =IF(AND(ISNUMBER(AU34),ISNUMBER(G34),G34<>0),AU34/G34,"") | AX34: =IF(AND(ISNUMBER(AC34),ISNUMBER(G34),G34<>0),AC34/G34,"")
A35: GOOG | B35: Alphabet Inc. | C35: 2020 | D35: 2020-12-31 | E35: 일반 | F35: 0001652044-23-000016 | G35: 182.527 | H35: 48.082 | J35: 7.813 | K35: 41.224 | L35: 40.269 | N35: 22.281 | O35: 65.124 | P35: 222.544 | Q35: 201.442 | R35: 136.694 | S35: 119.675 | T35: 0 | U35: 0 | V35: 15.319 | W35: 174.296 | X35: 152.578 | Y35: 56.834 | Z35: 45.221 | AA35: 86.452 | AB35: 13504.44 | AC35: =IF(AND(ISNUMBER(H35),ISNUMBER(I35)),H35+I35,IF(ISNUMBER(K35),K35,IF(ISNUMBER(H35),H35,""))) | AD35: =IF(OR(NOT(ISNUMBER(J35)),NOT(ISNUMBER(H35)),H35<=0),기준표!$B$8,MIN(MAX(J35/H35,기준표!$B$6),기준표!$B$7)) | AE35: =IF(ISNUMBER(AC35),AC35*(1-AD35),"") | AF35: =IF(AND(NOT(ISNUMBER(T35)),NOT(ISNUMBER(V35))),"",IF(ISNUMBER(T35),T35,0)+IF(ISNUMBER(V35),V35,0)) | AG35: =IF(E35="금융","",IF(AND(ISNUMBER(P35),ISNUMBER(AF35),ISNUMBER(R35)),P35+AF35-R35,"")) | AH35: =IF(E35="금융","",IF(NOT(ISNUMBER(AG35)),"",IF(ISNUMBER(AA35),(AG35+AA35)/2,AG35))) | AI35: =IF(AND(ISNUMBER(AE35),ISNUMBER(AH35),AH35>0),AE35/AH35,"") | AJ35: =IF(E35="금융","",IF(AND(ISNUMBER(P35),ISNUMBER(AF35)),P35+AF35,"")) | AK35: =IF(OR(NOT(ISNUMBER(AE35)),NOT(ISNUMBER(AJ35)),AJ35<=0),"",IF(AND(ISNUMBER(G35),AJ35<0.1*G35),"",AE35/AJ35)) | AL35: =IF(NOT(ISNUMBER(P35)),"",IF(ISNUMBER(Q35),(P35+Q35)/2,P35)) | AM35: =IF(AND(ISNUMBER(L35),ISNUMBER(AL35),AL35>0),L35/AL35,"") | AN35: =IF(AND(ISNUMBER(AM35),ISNUMBER({ROIC})),AM35-{ROIC},"") | AO35: =IF(AND(ISNUMBER(AC35),ISNUMBER(M35)),AC35+M35,"") | AP35: =IF(AND(ISNUMBER(AF35),ISNUMBER(R35),ISNUMBER(AO35),AO35>0),(AF35-R35)/AO35,"") | AQ35: =IF(AND(ISNUMBER(AC35),ISNUMBER(I35),I35<>0,AC35>0),AC35/I35,"") | AR35: =IF(AND(ISNUMBER(W35),ISNUMBER(Y35)),W35-IF(ISNUMBER(R35),R35,0)-(Y35-IF(ISNUMBER(T35),T35,0)),"") | AS35: =IF(AND(ISNUMBER(X35),ISNUMBER(Z35)),X35-IF(ISNUMBER(S35),S35,0)-(Z35-IF(ISNUMBER(U35),U35,0)),"") | AT35: =IF(AND(ISNUMBER(AR35),ISNUMBER(AS35)),AR35-AS35,"") | AU35: =IF(E35="금융","",IF(AND(ISNUMBER(L35),ISNUMBER(M35),ISNUMBER(N35),ISNUMBER(AT35)),L35+M35-N35-AT35,IF(AND(ISNUMBER(O35),ISNUMBER(N35)),O35-N35,""))) | AV35: =IF(E35="금융","금융업 - 정의되지 않음",IF(AND(ISNUMBER(L35),ISNUMBER(M35),ISNUMBER(N35),ISNUMBER(AT35)),"순이익+감가상각-설비투자-운전자본증감",IF(AND(ISNUMBER(O35),ISNUMBER(N35)),"영업현금흐름-설비투자","산출불가"))) | AW35: =IF(AND(ISNUMBER(AU35),ISNUMBER(G35),G35<>0),AU35/G35,"") | AX35: =IF(AND(ISNUMBER(AC35),ISNUMBER(G35),G35<>0),AC35/G35,"")
A36: GOOG | B36: Alphabet Inc. | C36: 2021 | D36: 2021-12-31 | E36: 일반 | F36: 0001652044-24-000022 | G36: 257.637 | H36: 90.734 | J36: 14.701 | K36: 78.714 | L36: 76.033 | M36: 10.273 | N36: 24.64 | O36: 91.652 | P36: 251.635 | Q36: 222.544 | R36: 139.649 | S36: 136.694 | T36: 0 | U36: 0 | V36: 15.44 | W36: 188.143 | X36: 174.296 | Y36: 64.254 | Z36: 56.834 | AA36: 101.169 | AB36: 13242 | AC36: =IF(AND(ISNUMBER(H36),ISNUMBER(I36)),H36+I36,IF(ISNUMBER(K36),K36,IF(ISNUMBER(H36),H36,""))) | AD36: =IF(OR(NOT(ISNUMBER(J36)),NOT(ISNUMBER(H36)),H36<=0),기준표!$B$8,MIN(MAX(J36/H36,기준표!$B$6),기준표!$B$7)) | AE36: =IF(ISNUMBER(AC36),AC36*(1-AD36),"") | AF36: =IF(AND(NOT(ISNUMBER(T36)),NOT(ISNUMBER(V36))),"",IF(ISNUMBER(T36),T36,0)+IF(ISNUMBER(V36),V36,0)) | AG36: =IF(E36="금융","",IF(AND(ISNUMBER(P36),ISNUMBER(AF36),ISNUMBER(R36)),P36+AF36-R36,"")) | AH36: =IF(E36="금융","",IF(NOT(ISNUMBER(AG36)),"",IF(ISNUMBER(AA36),(AG36+AA36)/2,AG36))) | AI36: =IF(AND(ISNUMBER(AE36),ISNUMBER(AH36),AH36>0),AE36/AH36,"") | AJ36: =IF(E36="금융","",IF(AND(ISNUMBER(P36),ISNUMBER(AF36)),P36+AF36,"")) | AK36: =IF(OR(NOT(ISNUMBER(AE36)),NOT(ISNUMBER(AJ36)),AJ36<=0),"",IF(AND(ISNUMBER(G36),AJ36<0.1*G36),"",AE36/AJ36)) | AL36: =IF(NOT(ISNUMBER(P36)),"",IF(ISNUMBER(Q36),(P36+Q36)/2,P36)) | AM36: =IF(AND(ISNUMBER(L36),ISNUMBER(AL36),AL36>0),L36/AL36,"") | AN36: =IF(AND(ISNUMBER(AM36),ISNUMBER({ROIC})),AM36-{ROIC},"") | AO36: =IF(AND(ISNUMBER(AC36),ISNUMBER(M36)),AC36+M36,"") | AP36: =IF(AND(ISNUMBER(AF36),ISNUMBER(R36),ISNUMBER(AO36),AO36>0),(AF36-R36)/AO36,"") | AQ36: =IF(AND(ISNUMBER(AC36),ISNUMBER(I36),I36<>0,AC36>0),AC36/I36,"") | AR36: =IF(AND(ISNUMBER(W36),ISNUMBER(Y36)),W36-IF(ISNUMBER(R36),R36,0)-(Y36-IF(ISNUMBER(T36),T36,0)),"") | AS36: =IF(AND(ISNUMBER(X36),ISNUMBER(Z36)),X36-IF(ISNUMBER(S36),S36,0)-(Z36-IF(ISNUMBER(U36),U36,0)),"") | AT36: =IF(AND(ISNUMBER(AR36),ISNUMBER(AS36)),AR36-AS36,"") | AU36: =IF(E36="금융","",IF(AND(ISNUMBER(L36),ISNUMBER(M36),ISNUMBER(N36),ISNUMBER(AT36)),L36+M36-N36-AT36,IF(AND(ISNUMBER(O36),ISNUMBER(N36)),O36-N36,""))) | AV36: =IF(E36="금융","금융업 - 정의되지 않음",IF(AND(ISNUMBER(L36),ISNUMBER(M36),ISNUMBER(N36),ISNUMBER(AT36)),"순이익+감가상각-설비투자-운전자본증감",IF(AND(ISNUMBER(O36),ISNUMBER(N36)),"영업현금흐름-설비투자","산출불가"))) | AW36: =IF(AND(ISNUMBER(AU36),ISNUMBER(G36),G36<>0),AU36/G36,"") | AX36: =IF(AND(ISNUMBER(AC36),ISNUMBER(G36),G36<>0),AC36/G36,"")
A37: GOOG | B37: Alphabet Inc. | C37: 2022 | D37: 2022-12-31 | E37: 일반 | F37: 0001652044-25-000014 | G37: 282.836 | H37: 71.328 | I37: 0.357 | J37: 11.356 | K37: 74.842 | L37: 59.972 | M37: 13.475 | N37: 31.485 | O37: 91.495 | P37: 256.144 | Q37: 251.635 | R37: 113.762 | S37: 139.649 | T37: 0 | U37: 0 | V37: 15.312 | W37: 164.795 | X37: 188.143 | Y37: 69.3 | Z37: 64.254 | AA37: 127.426 | AB37: 12849 | AC37: =IF(AND(ISNUMBER(H37),ISNUMBER(I37)),H37+I37,IF(ISNUMBER(K37),K37,IF(ISNUMBER(H37),H37,""))) | AD37: =IF(OR(NOT(ISNUMBER(J37)),NOT(ISNUMBER(H37)),H37<=0),기준표!$B$8,MIN(MAX(J37/H37,기준표!$B$6),기준표!$B$7)) | AE37: =IF(ISNUMBER(AC37),AC37*(1-AD37),"") | AF37: =IF(AND(NOT(ISNUMBER(T37)),NOT(ISNUMBER(V37))),"",IF(ISNUMBER(T37),T37,0)+IF(ISNUMBER(V37),V37,0)) | AG37: =IF(E37="금융","",IF(AND(ISNUMBER(P37),ISNUMBER(AF37),ISNUMBER(R37)),P37+AF37-R37,"")) | AH37: =IF(E37="금융","",IF(NOT(ISNUMBER(AG37)),"",IF(ISNUMBER(AA37),(AG37+AA37)/2,AG37))) | AI37: =IF(AND(ISNUMBER(AE37),ISNUMBER(AH37),AH37>0),AE37/AH37,"") | AJ37: =IF(E37="금융","",IF(AND(ISNUMBER(P37),ISNUMBER(AF37)),P37+AF37,"")) | AK37: =IF(OR(NOT(ISNUMBER(AE37)),NOT(ISNUMBER(AJ37)),AJ37<=0),"",IF(AND(ISNUMBER(G37),AJ37<0.1*G37),"",AE37/AJ37)) | AL37: =IF(NOT(ISNUMBER(P37)),"",IF(ISNUMBER(Q37),(P37+Q37)/2,P37)) | AM37: =IF(AND(ISNUMBER(L37),ISNUMBER(AL37),AL37>0),L37/AL37,"") | AN37: =IF(AND(ISNUMBER(AM37),ISNUMBER({ROIC})),AM37-{ROIC},"") | AO37: =IF(AND(ISNUMBER(AC37),ISNUMBER(M37)),AC37+M37,"") | AP37: =IF(AND(ISNUMBER(AF37),ISNUMBER(R37),ISNUMBER(AO37),AO37>0),(AF37-R37)/AO37,"") | AQ37: =IF(AND(ISNUMBER(AC37),ISNUMBER(I37),I37<>0,AC37>0),AC37/I37,"") | AR37: =IF(AND(ISNUMBER(W37),ISNUMBER(Y37)),W37-IF(ISNUMBER(R37),R37,0)-(Y37-IF(ISNUMBER(T37),T37,0)),"") | AS37: =IF(AND(ISNUMBER(X37),ISNUMBER(Z37)),X37-IF(ISNUMBER(S37),S37,0)-(Z37-IF(ISNUMBER(U37),U37,0)),"") | AT37: =IF(AND(ISNUMBER(AR37),ISNUMBER(AS37)),AR37-AS37,"") | AU37: =IF(E37="금융","",IF(AND(ISNUMBER(L37),ISNUMBER(M37),ISNUMBER(N37),ISNUMBER(AT37)),L37+M37-N37-AT37,IF(AND(ISNUMBER(O37),ISNUMBER(N37)),O37-N37,""))) | AV37: =IF(E37="금융","금융업 - 정의되지 않음",IF(AND(ISNUMBER(L37),ISNUMBER(M37),ISNUMBER(N37),ISNUMBER(AT37)),"순이익+감가상각-설비투자-운전자본증감",IF(AND(ISNUMBER(O37),ISNUMBER(N37)),"영업현금흐름-설비투자","산출불가"))) | AW37: =IF(AND(ISNUMBER(AU37),ISNUMBER(G37),G37<>0),AU37/G37,"") | AX37: =IF(AND(ISNUMBER(AC37),ISNUMBER(G37),G37<>0),AC37/G37,"")
A38: GOOG | B38: Alphabet Inc. | C38: 2023 | D38: 2023-12-31 | E38: 일반 | F38: 0001652044-26-000018 | G38: 307.394 | H38: 85.717 | I38: 0.308 | J38: 11.922 | K38: 84.293 | L38: 73.795 | M38: 11.946 | N38: 32.251 | O38: 101.746 | P38: 283.379 | Q38: 256.144 | R38: 110.916 | S38: 113.762 | T38: 0 | U38: 0 | V38: 13 | W38: 171.53 | X38: 164.795 | Y38: 81.814 | Z38: 69.3 | AA38: 157.694 | AB38: 12460 | AC38: =IF(AND(ISNUMBER(H38),ISNUMBER(I38)),H38+I38,IF(ISNUMBER(K38),K38,IF(ISNUMBER(H38),H38,""))) | AD38: =IF(OR(NOT(ISNUMBER(J38)),NOT(ISNUMBER(H38)),H38<=0),기준표!$B$8,MIN(MAX(J38/H38,기준표!$B$6),기준표!$B$7)) | AE38: =IF(ISNUMBER(AC38),AC38*(1-AD38),"") | AF38: =IF(AND(NOT(ISNUMBER(T38)),NOT(ISNUMBER(V38))),"",IF(ISNUMBER(T38),T38,0)+IF(ISNUMBER(V38),V38,0)) | AG38: =IF(E38="금융","",IF(AND(ISNUMBER(P38),ISNUMBER(AF38),ISNUMBER(R38)),P38+AF38-R38,"")) | AH38: =IF(E38="금융","",IF(NOT(ISNUMBER(AG38)),"",IF(ISNUMBER(AA38),(AG38+AA38)/2,AG38))) | AI38: =IF(AND(ISNUMBER(AE38),ISNUMBER(AH38),AH38>0),AE38/AH38,"") | AJ38: =IF(E38="금융","",IF(AND(ISNUMBER(P38),ISNUMBER(AF38)),P38+AF38,"")) | AK38: =IF(OR(NOT(ISNUMBER(AE38)),NOT(ISNUMBER(AJ38)),AJ38<=0),"",IF(AND(ISNUMBER(G38),AJ38<0.1*G38),"",AE38/AJ38)) | AL38: =IF(NOT(ISNUMBER(P38)),"",IF(ISNUMBER(Q38),(P38+Q38)/2,P38)) | AM38: =IF(AND(ISNUMBER(L38),ISNUMBER(AL38),AL38>0),L38/AL38,"") | AN38: =IF(AND(ISNUMBER(AM38),ISNUMBER({ROIC})),AM38-{ROIC},"") | AO38: =IF(AND(ISNUMBER(AC38),ISNUMBER(M38)),AC38+M38,"") | AP38: =IF(AND(ISNUMBER(AF38),ISNUMBER(R38),ISNUMBER(AO38),AO38>0),(AF38-R38)/AO38,"") | AQ38: =IF(AND(ISNUMBER(AC38),ISNUMBER(I38),I38<>0,AC38>0),AC38/I38,"") | AR38: =IF(AND(ISNUMBER(W38),ISNUMBER(Y38)),W38-IF(ISNUMBER(R38),R38,0)-(Y38-IF(ISNUMBER(T38),T38,0)),"") | AS38: =IF(AND(ISNUMBER(X38),ISNUMBER(Z38)),X38-IF(ISNUMBER(S38),S38,0)-(Z38-IF(ISNUMBER(U38),U38,0)),"") | AT38: =IF(AND(ISNUMBER(AR38),ISNUMBER(AS38)),AR38-AS38,"") | AU38: =IF(E38="금융","",IF(AND(ISNUMBER(L38),ISNUMBER(M38),ISNUMBER(N38),ISNUMBER(AT38)),L38+M38-N38-AT38,IF(AND(ISNUMBER(O38),ISNUMBER(N38)),O38-N38,""))) | AV38: =IF(E38="금융","금융업 - 정의되지 않음",IF(AND(ISNUMBER(L38),ISNUMBER(M38),ISNUMBER(N38),ISNUMBER(AT38)),"순이익+감가상각-설비투자-운전자본증감",IF(AND(ISNUMBER(O38),ISNUMBER(N38)),"영업현금흐름-설비투자","산출불가"))) | AW38: =IF(AND(ISNUMBER(AU38),ISNUMBER(G38),G38<>0),AU38/G38,"") | AX38: =IF(AND(ISNUMBER(AC38),ISNUMBER(G38),G38<>0),AC38/G38,"")
A39: GOOG | B39: Alphabet Inc. | C39: 2024 | D39: 2024-12-31 | E39: 일반 | F39: 0001652044-26-000018 | G39: 350.018 | H39: 119.815 | I39: 0.268 | J39: 19.697 | K39: 112.39 | L39: 100.118 | M39: 15.311 | N39: 52.535 | O39: 125.299 | P39: 325.084 | Q39: 283.379 | R39: 95.657 | S39: 110.916 | T39: 2.3 | U39: 0 | V39: 12 | W39: 163.711 | X39: 171.53 | Y39: 89.122 | Z39: 81.814 | AA39: 185.463 | AB39: 12211 | AC39: =IF(AND(ISNUMBER(H39),ISNUMBER(I39)),H39+I39,IF(ISNUMBER(K39),K39,IF(ISNUMBER(H39),H39,""))) | AD39: =IF(OR(NOT(ISNUMBER(J39)),NOT(ISNUMBER(H39)),H39<=0),기준표!$B$8,MIN(MAX(J39/H39,기준표!$B$6),기준표!$B$7)) | AE39: =IF(ISNUMBER(AC39),AC39*(1-AD39),"") | AF39: =IF(AND(NOT(ISNUMBER(T39)),NOT(ISNUMBER(V39))),"",IF(ISNUMBER(T39),T39,0)+IF(ISNUMBER(V39),V39,0)) | AG39: =IF(E39="금융","",IF(AND(ISNUMBER(P39),ISNUMBER(AF39),ISNUMBER(R39)),P39+AF39-R39,"")) | AH39: =IF(E39="금융","",IF(NOT(ISNUMBER(AG39)),"",IF(ISNUMBER(AA39),(AG39+AA39)/2,AG39))) | AI39: =IF(AND(ISNUMBER(AE39),ISNUMBER(AH39),AH39>0),AE39/AH39,"") | AJ39: =IF(E39="금융","",IF(AND(ISNUMBER(P39),ISNUMBER(AF39)),P39+AF39,"")) | AK39: =IF(OR(NOT(ISNUMBER(AE39)),NOT(ISNUMBER(AJ39)),AJ39<=0),"",IF(AND(ISNUMBER(G39),AJ39<0.1*G39),"",AE39/AJ39)) | AL39: =IF(NOT(ISNUMBER(P39)),"",IF(ISNUMBER(Q39),(P39+Q39)/2,P39)) | AM39: =IF(AND(ISNUMBER(L39),ISNUMBER(AL39),AL39>0),L39/AL39,"") | AN39: =IF(AND(ISNUMBER(AM39),ISNUMBER({ROIC})),AM39-{ROIC},"") | AO39: =IF(AND(ISNUMBER(AC39),ISNUMBER(M39)),AC39+M39,"") | AP39: =IF(AND(ISNUMBER(AF39),ISNUMBER(R39),ISNUMBER(AO39),AO39>0),(AF39-R39)/AO39,"") | AQ39: =IF(AND(ISNUMBER(AC39),ISNUMBER(I39),I39<>0,AC39>0),AC39/I39,"") | AR39: =IF(AND(ISNUMBER(W39),ISNUMBER(Y39)),W39-IF(ISNUMBER(R39),R39,0)-(Y39-IF(ISNUMBER(T39),T39,0)),"") | AS39: =IF(AND(ISNUMBER(X39),ISNUMBER(Z39)),X39-IF(ISNUMBER(S39),S39,0)-(Z39-IF(ISNUMBER(U39),U39,0)),"") | AT39: =IF(AND(ISNUMBER(AR39),ISNUMBER(AS39)),AR39-AS39,"") | AU39: =IF(E39="금융","",IF(AND(ISNUMBER(L39),ISNUMBER(M39),ISNUMBER(N39),ISNUMBER(AT39)),L39+M39-N39-AT39,IF(AND(ISNUMBER(O39),ISNUMBER(N39)),O39-N39,""))) | AV39: =IF(E39="금융","금융업 - 정의되지 않음",IF(AND(ISNUMBER(L39),ISNUMBER(M39),ISNUMBER(N39),ISNUMBER(AT39)),"순이익+감가상각-설비투자-운전자본증감",IF(AND(ISNUMBER(O39),ISNUMBER(N39)),"영업현금흐름-설비투자","산출불가"))) | AW39: =IF(AND(ISNUMBER(AU39),ISNUMBER(G39),G39<>0),AU39/G39,"") | AX39: =IF(AND(ISNUMBER(AC39),ISNUMBER(G39),G39<>0),AC39/G39,"")
A40: GOOG | B40: Alphabet Inc. | C40: 2025 | D40: 2025-12-31 | E40: 일반 | F40: 0001652044-26-000018 | G40: 402.836 | H40: 158.826 | I40: 0.736 | J40: 26.656 | K40: 129.039 | L40: 132.17 | M40: 21.136 | N40: 91.447 | O40: 164.713 | P40: 415.265 | Q40: 325.084 | R40: 126.843 | S40: 95.657 | T40: 0 | U40: 2.3 | V40: 49.085 | W40: 206.038 | X40: 163.711 | Y40: 102.745 | Z40: 89.122 | AA40: 243.727 | AB40: 12088 | AC40: =IF(AND(ISNUMBER(H40),ISNUMBER(I40)),H40+I40,IF(ISNUMBER(K40),K40,IF(ISNUMBER(H40),H40,""))) | AD40: =IF(OR(NOT(ISNUMBER(J40)),NOT(ISNUMBER(H40)),H40<=0),기준표!$B$8,MIN(MAX(J40/H40,기준표!$B$6),기준표!$B$7)) | AE40: =IF(ISNUMBER(AC40),AC40*(1-AD40),"") | AF40: =IF(AND(NOT(ISNUMBER(T40)),NOT(ISNUMBER(V40))),"",IF(ISNUMBER(T40),T40,0)+IF(ISNUMBER(V40),V40,0)) | AG40: =IF(E40="금융","",IF(AND(ISNUMBER(P40),ISNUMBER(AF40),ISNUMBER(R40)),P40+AF40-R40,"")) | AH40: =IF(E40="금융","",IF(NOT(ISNUMBER(AG40)),"",IF(ISNUMBER(AA40),(AG40+AA40)/2,AG40))) | AI40: =IF(AND(ISNUMBER(AE40),ISNUMBER(AH40),AH40>0),AE40/AH40,"") | AJ40: =IF(E40="금융","",IF(AND(ISNUMBER(P40),ISNUMBER(AF40)),P40+AF40,"")) | AK40: =IF(OR(NOT(ISNUMBER(AE40)),NOT(ISNUMBER(AJ40)),AJ40<=0),"",IF(AND(ISNUMBER(G40),AJ40<0.1*G40),"",AE40/AJ40)) | AL40: =IF(NOT(ISNUMBER(P40)),"",IF(ISNUMBER(Q40),(P40+Q40)/2,P40)) | AM40: =IF(AND(ISNUMBER(L40),ISNUMBER(AL40),AL40>0),L40/AL40,"") | AN40: =IF(AND(ISNUMBER(AM40),ISNUMBER({ROIC})),AM40-{ROIC},"") | AO40: =IF(AND(ISNUMBER(AC40),ISNUMBER(M40)),AC40+M40,"") | AP40: =IF(AND(ISNUMBER(AF40),ISNUMBER(R40),ISNUMBER(AO40),AO40>0),(AF40-R40)/AO40,"") | AQ40: =IF(AND(ISNUMBER(AC40),ISNUMBER(I40),I40<>0,AC40>0),AC40/I40,"") | AR40: =IF(AND(ISNUMBER(W40),ISNUMBER(Y40)),W40-IF(ISNUMBER(R40),R40,0)-(Y40-IF(ISNUMBER(T40),T40,0)),"") | AS40: =IF(AND(ISNUMBER(X40),ISNUMBER(Z40)),X40-IF(ISNUMBER(S40),S40,0)-(Z40-IF(ISNUMBER(U40),U40,0)),"") | AT40: =IF(AND(ISNUMBER(AR40),ISNUMBER(AS40)),AR40-AS40,"") | AU40: =IF(E40="금융","",IF(AND(ISNUMBER(L40),ISNUMBER(M40),ISNUMBER(N40),ISNUMBER(AT40)),L40+M40-N40-AT40,IF(AND(ISNUMBER(O40),ISNUMBER(N40)),O40-N40,""))) | AV40: =IF(E40="금융","금융업 - 정의되지 않음",IF(AND(ISNUMBER(L40),ISNUMBER(M40),ISNUMBER(N40),ISNUMBER(AT40)),"순이익+감가상각-설비투자-운전자본증감",IF(AND(ISNUMBER(O40),ISNUMBER(N40)),"영업현금흐름-설비투자","산출불가"))) | AW40: =IF(AND(ISNUMBER(AU40),ISNUMBER(G40),G40<>0),AU40/G40,"") | AX40: =IF(AND(ISNUMBER(AC40),ISNUMBER(G40),G40<>0),AC40/G40,"")
A41: MSFT | B41: MICROSOFT CORP | C41: 2015 | D41: 2015-06-30 | E41: 일반 | F41: 0001564590-17-014900 | J41: 6.314 | K41: 18.161 | L41: 12.193 | M41: 4.1 | N41: 5.944 | O41: 29.668 | P41: 80.083 | R41: 96.526 | T41: 2.499 | V41: 27.808 | W41: 122.797 | Y41: 49.647 | AB41: 8027 | AC41: =IF(AND(ISNUMBER(H41),ISNUMBER(I41)),H41+I41,IF(ISNUMBER(K41),K41,IF(ISNUMBER(H41),H41,""))) | AD41: =IF(OR(NOT(ISNUMBER(J41)),NOT(ISNUMBER(H41)),H41<=0),기준표!$B$8,MIN(MAX(J41/H41,기준표!$B$6),기준표!$B$7)) | AE41: =IF(ISNUMBER(AC41),AC41*(1-AD41),"") | AF41: =IF(AND(NOT(ISNUMBER(T41)),NOT(ISNUMBER(V41))),"",IF(ISNUMBER(T41),T41,0)+IF(ISNUMBER(V41),V41,0)) | AG41: =IF(E41="금융","",IF(AND(ISNUMBER(P41),ISNUMBER(AF41),ISNUMBER(R41)),P41+AF41-R41,"")) | AH41: =IF(E41="금융","",IF(NOT(ISNUMBER(AG41)),"",IF(ISNUMBER(AA41),(AG41+AA41)/2,AG41))) | AI41: =IF(AND(ISNUMBER(AE41),ISNUMBER(AH41),AH41>0),AE41/AH41,"") | AJ41: =IF(E41="금융","",IF(AND(ISNUMBER(P41),ISNUMBER(AF41)),P41+AF41,"")) | AK41: =IF(OR(NOT(ISNUMBER(AE41)),NOT(ISNUMBER(AJ41)),AJ41<=0),"",IF(AND(ISNUMBER(G41),AJ41<0.1*G41),"",AE41/AJ41)) | AL41: =IF(NOT(ISNUMBER(P41)),"",IF(ISNUMBER(Q41),(P41+Q41)/2,P41)) | AM41: =IF(AND(ISNUMBER(L41),ISNUMBER(AL41),AL41>0),L41/AL41,"") | AN41: =IF(AND(ISNUMBER(AM41),ISNUMBER({ROIC})),AM41-{ROIC},"") | AO41: =IF(AND(ISNUMBER(AC41),ISNUMBER(M41)),AC41+M41,"") | AP41: =IF(AND(ISNUMBER(AF41),ISNUMBER(R41),ISNUMBER(AO41),AO41>0),(AF41-R41)/AO41,"") | AQ41: =IF(AND(ISNUMBER(AC41),ISNUMBER(I41),I41<>0,AC41>0),AC41/I41,"") | AR41: =IF(AND(ISNUMBER(W41),ISNUMBER(Y41)),W41-IF(ISNUMBER(R41),R41,0)-(Y41-IF(ISNUMBER(T41),T41,0)),"") | AS41: =IF(AND(ISNUMBER(X41),ISNUMBER(Z41)),X41-IF(ISNUMBER(S41),S41,0)-(Z41-IF(ISNUMBER(U41),U41,0)),"") | AT41: =IF(AND(ISNUMBER(AR41),ISNUMBER(AS41)),AR41-AS41,"") | AU41: =IF(E41="금융","",IF(AND(ISNUMBER(L41),ISNUMBER(M41),ISNUMBER(N41),ISNUMBER(AT41)),L41+M41-N41-AT41,IF(AND(ISNUMBER(O41),ISNUMBER(N41)),O41-N41,""))) | AV41: =IF(E41="금융","금융업 - 정의되지 않음",IF(AND(ISNUMBER(L41),ISNUMBER(M41),ISNUMBER(N41),ISNUMBER(AT41)),"순이익+감가상각-설비투자-운전자본증감",IF(AND(ISNUMBER(O41),ISNUMBER(N41)),"영업현금흐름-설비투자","산출불가"))) | AW41: =IF(AND(ISNUMBER(AU41),ISNUMBER(G41),G41<>0),AU41/G41,"") | AX41: =IF(AND(ISNUMBER(AC41),ISNUMBER(G41),G41<>0),AC41/G41,"")
A42: MSFT | B42: MICROSOFT CORP | C42: 2016 | D42: 2016-06-30 | E42: 일반 | F42: 0001564590-18-019062 | G42: 91.154 | J42: 5.1 | K42: 26.078 | L42: 20.539 | M42: 4.9 | N42: 8.343 | O42: 33.325 | P42: 83.09 | Q42: 80.083 | R42: 113.24 | S42: 96.526 | T42: 0 | U42: 2.499 | V42: 40.557 | W42: 139.66 | X42: 122.797 | Y42: 59.357 | Z42: 49.647 | AA42: 13.864 | AB42: 7808 | AC42: =IF(AND(ISNUMBER(H42),ISNUMBER(I42)),H42+I42,IF(ISNUMBER(K42),K42,IF(ISNUMBER(H42),H42,""))) | AD42: =IF(OR(NOT(ISNUMBER(J42)),NOT(ISNUMBER(H42)),H42<=0),기준표!$B$8,MIN(MAX(J42/H42,기준표!$B$6),기준표!$B$7)) | AE42: =IF(ISNUMBER(AC42),AC42*(1-AD42),"") | AF42: =IF(AND(NOT(ISNUMBER(T42)),NOT(ISNUMBER(V42))),"",IF(ISNUMBER(T42),T42,0)+IF(ISNUMBER(V42),V42,0)) | AG42: =IF(E42="금융","",IF(AND(ISNUMBER(P42),ISNUMBER(AF42),ISNUMBER(R42)),P42+AF42-R42,"")) | AH42: =IF(E42="금융","",IF(NOT(ISNUMBER(AG42)),"",IF(ISNUMBER(AA42),(AG42+AA42)/2,AG42))) | AI42: =IF(AND(ISNUMBER(AE42),ISNUMBER(AH42),AH42>0),AE42/AH42,"") | AJ42: =IF(E42="금융","",IF(AND(ISNUMBER(P42),ISNUMBER(AF42)),P42+AF42,"")) | AK42: =IF(OR(NOT(ISNUMBER(AE42)),NOT(ISNUMBER(AJ42)),AJ42<=0),"",IF(AND(ISNUMBER(G42),AJ42<0.1*G42),"",AE42/AJ42)) | AL42: =IF(NOT(ISNUMBER(P42)),"",IF(ISNUMBER(Q42),(P42+Q42)/2,P42)) | AM42: =IF(AND(ISNUMBER(L42),ISNUMBER(AL42),AL42>0),L42/AL42,"") | AN42: =IF(AND(ISNUMBER(AM42),ISNUMBER({ROIC})),AM42-{ROIC},"") | AO42: =IF(AND(ISNUMBER(AC42),ISNUMBER(M42)),AC42+M42,"") | AP42: =IF(AND(ISNUMBER(AF42),ISNUMBER(R42),ISNUMBER(AO42),AO42>0),(AF42-R42)/AO42,"") | AQ42: =IF(AND(ISNUMBER(AC42),ISNUMBER(I42),I42<>0,AC42>0),AC42/I42,"") | AR42: =IF(AND(ISNUMBER(W42),ISNUMBER(Y42)),W42-IF(ISNUMBER(R42),R42,0)-(Y42-IF(ISNUMBER(T42),T42,0)),"") | AS42: =IF(AND(ISNUMBER(X42),ISNUMBER(Z42)),X42-IF(ISNUMBER(S42),S42,0)-(Z42-IF(ISNUMBER(U42),U42,0)),"") | AT42: =IF(AND(ISNUMBER(AR42),ISNUMBER(AS42)),AR42-AS42,"") | AU42: =IF(E42="금융","",IF(AND(ISNUMBER(L42),ISNUMBER(M42),ISNUMBER(N42),ISNUMBER(AT42)),L42+M42-N42-AT42,IF(AND(ISNUMBER(O42),ISNUMBER(N42)),O42-N42,""))) | AV42: =IF(E42="금융","금융업 - 정의되지 않음",IF(AND(ISNUMBER(L42),ISNUMBER(M42),ISNUMBER(N42),ISNUMBER(AT42)),"순이익+감가상각-설비투자-운전자본증감",IF(AND(ISNUMBER(O42),ISNUMBER(N42)),"영업현금흐름-설비투자","산출불가"))) | AW42: =IF(AND(ISNUMBER(AU42),ISNUMBER(G42),G42<>0),AU42/G42,"") | AX42: =IF(AND(ISNUMBER(AC42),ISNUMBER(G42),G42<>0),AC42/G42,"")
A43: MSFT | B43: MICROSOFT CORP | C43: 2017 | D43: 2017-06-30 | E43: 일반 | F43: 0001564590-19-027952 | G43: 96.571 | J43: 4.412 | K43: 29.025 | L43: 25.489 | M43: 6.1 | N43: 8.129 | O43: 39.507 | P43: 87.711 | Q43: 83.09 | R43: 132.981 | S43: 113.24 | T43: 1.049 | U43: 0 | V43: 76.073 | W43: 162.696 | X43: 139.66 | Y43: 55.745 | Z43: 59.357 | AA43: 10.407 | AB43: 7708 | AC43: =IF(AND(ISNUMBER(H43),ISNUMBER(I43)),H43+I43,IF(ISNUMBER(K43),K43,IF(ISNUMBER(H43),H43,""))) | AD43: =IF(OR(NOT(ISNUMBER(J43)),NOT(ISNUMBER(H43)),H43<=0),기준표!$B$8,MIN(MAX(J43/H43,기준표!$B$6),기준표!$B$7)) | AE43: =IF(ISNUMBER(AC43),AC43*(1-AD43),"") | AF43: =IF(AND(NOT(ISNUMBER(T43)),NOT(ISNUMBER(V43))),"",IF(ISNUMBER(T43),T43,0)+IF(ISNUMBER(V43),V43,0)) | AG43: =IF(E43="금융","",IF(AND(ISNUMBER(P43),ISNUMBER(AF43),ISNUMBER(R43)),P43+AF43-R43,"")) | AH43: =IF(E43="금융","",IF(NOT(ISNUMBER(AG43)),"",IF(ISNUMBER(AA43),(AG43+AA43)/2,AG43))) | AI43: =IF(AND(ISNUMBER(AE43),ISNUMBER(AH43),AH43>0),AE43/AH43,"") | AJ43: =IF(E43="금융","",IF(AND(ISNUMBER(P43),ISNUMBER(AF43)),P43+AF43,"")) | AK43: =IF(OR(NOT(ISNUMBER(AE43)),NOT(ISNUMBER(AJ43)),AJ43<=0),"",IF(AND(ISNUMBER(G43),AJ43<0.1*G43),"",AE43/AJ43)) | AL43: =IF(NOT(ISNUMBER(P43)),"",IF(ISNUMBER(Q43),(P43+Q43)/2,P43)) | AM43: =IF(AND(ISNUMBER(L43),ISNUMBER(AL43),AL43>0),L43/AL43,"") | AN43: =IF(AND(ISNUMBER(AM43),ISNUMBER({ROIC})),AM43-{ROIC},"") | AO43: =IF(AND(ISNUMBER(AC43),ISNUMBER(M43)),AC43+M43,"") | AP43: =IF(AND(ISNUMBER(AF43),ISNUMBER(R43),ISNUMBER(AO43),AO43>0),(AF43-R43)/AO43,"") | AQ43: =IF(AND(ISNUMBER(AC43),ISNUMBER(I43),I43<>0,AC43>0),AC43/I43,"") | AR43: =IF(AND(ISNUMBER(W43),ISNUMBER(Y43)),W43-IF(ISNUMBER(R43),R43,0)-(Y43-IF(ISNUMBER(T43),T43,0)),"") | AS43: =IF(AND(ISNUMBER(X43),ISNUMBER(Z43)),X43-IF(ISNUMBER(S43),S43,0)-(Z43-IF(ISNUMBER(U43),U43,0)),"") | AT43: =IF(AND(ISNUMBER(AR43),ISNUMBER(AS43)),AR43-AS43,"") | AU43: =IF(E43="금융","",IF(AND(ISNUMBER(L43),ISNUMBER(M43),ISNUMBER(N43),ISNUMBER(AT43)),L43+M43-N43-AT43,IF(AND(ISNUMBER(O43),ISNUMBER(N43)),O43-N43,""))) | AV43: =IF(E43="금융","금융업 - 정의되지 않음",IF(AND(ISNUMBER(L43),ISNUMBER(M43),ISNUMBER(N43),ISNUMBER(AT43)),"순이익+감가상각-설비투자-운전자본증감",IF(AND(ISNUMBER(O43),ISNUMBER(N43)),"영업현금흐름-설비투자","산출불가"))) | AW43: =IF(AND(ISNUMBER(AU43),ISNUMBER(G43),G43<>0),AU43/G43,"") | AX43: =IF(AND(ISNUMBER(AC43),ISNUMBER(G43),G43<>0),AC43/G43,"")
A44: MSFT | B44: MICROSOFT CORP | C44: 2018 | D44: 2018-06-30 | E44: 일반 | F44: 0001564590-20-034944 | G44: 110.36 | J44: 19.903 | K44: 35.058 | L44: 16.571 | M44: 7.7 | N44: 11.632 | O44: 43.884 | P44: 82.718 | Q44: 87.711 | R44: 133.768 | S44: 132.981 | T44: 3.998 | U44: 1.049 | V44: 72.242 | W44: 169.662 | X44: 162.696 | Y44: 58.488 | Z44: 55.745 | AA44: 31.852 | AB44: 7677 | AC44: =IF(AND(ISNUMBER(H44),ISNUMBER(I44)),H44+I44,IF(ISNUMBER(K44),K44,IF(ISNUMBER(H44),H44,""))) | AD44: =IF(OR(NOT(ISNUMBER(J44)),NOT(ISNUMBER(H44)),H44<=0),기준표!$B$8,MIN(MAX(J44/H44,기준표!$B$6),기준표!$B$7)) | AE44: =IF(ISNUMBER(AC44),AC44*(1-AD44),"") | AF44: =IF(AND(NOT(ISNUMBER(T44)),NOT(ISNUMBER(V44))),"",IF(ISNUMBER(T44),T44,0)+IF(ISNUMBER(V44),V44,0)) | AG44: =IF(E44="금융","",IF(AND(ISNUMBER(P44),ISNUMBER(AF44),ISNUMBER(R44)),P44+AF44-R44,"")) | AH44: =IF(E44="금융","",IF(NOT(ISNUMBER(AG44)),"",IF(ISNUMBER(AA44),(AG44+AA44)/2,AG44))) | AI44: =IF(AND(ISNUMBER(AE44),ISNUMBER(AH44),AH44>0),AE44/AH44,"") | AJ44: =IF(E44="금융","",IF(AND(ISNUMBER(P44),ISNUMBER(AF44)),P44+AF44,"")) | AK44: =IF(OR(NOT(ISNUMBER(AE44)),NOT(ISNUMBER(AJ44)),AJ44<=0),"",IF(AND(ISNUMBER(G44),AJ44<0.1*G44),"",AE44/AJ44)) | AL44: =IF(NOT(ISNUMBER(P44)),"",IF(ISNUMBER(Q44),(P44+Q44)/2,P44)) | AM44: =IF(AND(ISNUMBER(L44),ISNUMBER(AL44),AL44>0),L44/AL44,"") | AN44: =IF(AND(ISNUMBER(AM44),ISNUMBER({ROIC})),AM44-{ROIC},"") | AO44: =IF(AND(ISNUMBER(AC44),ISNUMBER(M44)),AC44+M44,"") | AP44: =IF(AND(ISNUMBER(AF44),ISNUMBER(R44),ISNUMBER(AO44),AO44>0),(AF44-R44)/AO44,"") | AQ44: =IF(AND(ISNUMBER(AC44),ISNUMBER(I44),I44<>0,AC44>0),AC44/I44,"") | AR44: =IF(AND(ISNUMBER(W44),ISNUMBER(Y44)),W44-IF(ISNUMBER(R44),R44,0)-(Y44-IF(ISNUMBER(T44),T44,0)),"") | AS44: =IF(AND(ISNUMBER(X44),ISNUMBER(Z44)),X44-IF(ISNUMBER(S44),S44,0)-(Z44-IF(ISNUMBER(U44),U44,0)),"") | AT44: =IF(AND(ISNUMBER(AR44),ISNUMBER(AS44)),AR44-AS44,"") | AU44: =IF(E44="금융","",IF(AND(ISNUMBER(L44),ISNUMBER(M44),ISNUMBER(N44),ISNUMBER(AT44)),L44+M44-N44-AT44,IF(AND(ISNUMBER(O44),ISNUMBER(N44)),O44-N44,""))) | AV44: =IF(E44="금융","금융업 - 정의되지 않음",IF(AND(ISNUMBER(L44),ISNUMBER(M44),ISNUMBER(N44),ISNUMBER(AT44)),"순이익+감가상각-설비투자-운전자본증감",IF(AND(ISNUMBER(O44),ISNUMBER(N44)),"영업현금흐름-설비투자","산출불가"))) | AW44: =IF(AND(ISNUMBER(AU44),ISNUMBER(G44),G44<>0),AU44/G44,"") | AX44: =IF(AND(ISNUMBER(AC44),ISNUMBER(G44),G44<>0),AC44/G44,"")
A45: MSFT | B45: MICROSOFT CORP | C45: 2019 | D45: 2019-06-30 | E45: 일반 | F45: 0001564590-21-039151 | G45: 125.843 | J45: 4.448 | K45: 42.959 | L45: 39.24 | M45: 9.7 | N45: 13.925 | O45: 52.185 | P45: 102.33 | Q45: 82.718 | R45: 133.819 | S45: 133.768 | T45: 5.516 | U45: 3.998 | V45: 66.662 | W45: 175.552 | X45: 169.662 | Y45: 69.42 | Z45: 58.488 | AA45: 25.19 | AB45: 7643 | AC45: =IF(AND(ISNUMBER(H45),ISNUMBER(I45)),H45+I45,IF(ISNUMBER(K45),K45,IF(ISNUMBER(H45),H45,""))) | AD45: =IF(OR(NOT(ISNUMBER(J45)),NOT(ISNUMBER(H45)),H45<=0),기준표!$B$8,MIN(MAX(J45/H45,기준표!$B$6),기준표!$B$7)) | AE45: =IF(ISNUMBER(AC45),AC45*(1-AD45),"") | AF45: =IF(AND(NOT(ISNUMBER(T45)),NOT(ISNUMBER(V45))),"",IF(ISNUMBER(T45),T45,0)+IF(ISNUMBER(V45),V45,0)) | AG45: =IF(E45="금융","",IF(AND(ISNUMBER(P45),ISNUMBER(AF45),ISNUMBER(R45)),P45+AF45-R45,"")) | AH45: =IF(E45="금융","",IF(NOT(ISNUMBER(AG45)),"",IF(ISNUMBER(AA45),(AG45+AA45)/2,AG45))) | AI45: =IF(AND(ISNUMBER(AE45),ISNUMBER(AH45),AH45>0),AE45/AH45,"") | AJ45: =IF(E45="금융","",IF(AND(ISNUMBER(P45),ISNUMBER(AF45)),P45+AF45,"")) | AK45: =IF(OR(NOT(ISNUMBER(AE45)),NOT(ISNUMBER(AJ45)),AJ45<=0),"",IF(AND(ISNUMBER(G45),AJ45<0.1*G45),"",AE45/AJ45)) | AL45: =IF(NOT(ISNUMBER(P45)),"",IF(ISNUMBER(Q45),(P45+Q45)/2,P45)) | AM45: =IF(AND(ISNUMBER(L45),ISNUMBER(AL45),AL45>0),L45/AL45,"") | AN45: =IF(AND(ISNUMBER(AM45),ISNUMBER({ROIC})),AM45-{ROIC},"") | AO45: =IF(AND(ISNUMBER(AC45),ISNUMBER(M45)),AC45+M45,"") | AP45: =IF(AND(ISNUMBER(AF45),ISNUMBER(R45),ISNUMBER(AO45),AO45>0),(AF45-R45)/AO45,"") | AQ45: =IF(AND(ISNUMBER(AC45),ISNUMBER(I45),I45<>0,AC45>0),AC45/I45,"") | AR45: =IF(AND(ISNUMBER(W45),ISNUMBER(Y45)),W45-IF(ISNUMBER(R45),R45,0)-(Y45-IF(ISNUMBER(T45),T45,0)),"") | AS45: =IF(AND(ISNUMBER(X45),ISNUMBER(Z45)),X45-IF(ISNUMBER(S45),S45,0)-(Z45-IF(ISNUMBER(U45),U45,0)),"") | AT45: =IF(AND(ISNUMBER(AR45),ISNUMBER(AS45)),AR45-AS45,"") | AU45: =IF(E45="금융","",IF(AND(ISNUMBER(L45),ISNUMBER(M45),ISNUMBER(N45),ISNUMBER(AT45)),L45+M45-N45-AT45,IF(AND(ISNUMBER(O45),ISNUMBER(N45)),O45-N45,""))) | AV45: =IF(E45="금융","금융업 - 정의되지 않음",IF(AND(ISNUMBER(L45),ISNUMBER(M45),ISNUMBER(N45),ISNUMBER(AT45)),"순이익+감가상각-설비투자-운전자본증감",IF(AND(ISNUMBER(O45),ISNUMBER(N45)),"영업현금흐름-설비투자","산출불가"))) | AW45: =IF(AND(ISNUMBER(AU45),ISNUMBER(G45),G45<>0),AU45/G45,"") | AX45: =IF(AND(ISNUMBER(AC45),ISNUMBER(G45),G45<>0),AC45/G45,"")
A46: MSFT | B46: MICROSOFT CORP | C46: 2020 | D46: 2020-06-30 | E46: 일반 | F46: 0001564590-22-026876 | G46: 143.015 | H46: 53.036 | J46: 8.755 | K46: 52.959 | L46: 44.281 | M46: 10.7 | N46: 15.441 | O46: 60.675 | P46: 118.304 | Q46: 102.33 | R46: 136.527 | S46: 133.819 | T46: 3.749 | U46: 5.516 | V46: 59.578 | W46: 181.915 | X46: 175.552 | Y46: 72.31 | Z46: 69.42 | AA46: 40.689 | AB46: 7571 | AC46: =IF(AND(ISNUMBER(H46),ISNUMBER(I46)),H46+I46,IF(ISNUMBER(K46),K46,IF(ISNUMBER(H46),H46,""))) | AD46: =IF(OR(NOT(ISNUMBER(J46)),NOT(ISNUMBER(H46)),H46<=0),기준표!$B$8,MIN(MAX(J46/H46,기준표!$B$6),기준표!$B$7)) | AE46: =IF(ISNUMBER(AC46),AC46*(1-AD46),"") | AF46: =IF(AND(NOT(ISNUMBER(T46)),NOT(ISNUMBER(V46))),"",IF(ISNUMBER(T46),T46,0)+IF(ISNUMBER(V46),V46,0)) | AG46: =IF(E46="금융","",IF(AND(ISNUMBER(P46),ISNUMBER(AF46),ISNUMBER(R46)),P46+AF46-R46,"")) | AH46: =IF(E46="금융","",IF(NOT(ISNUMBER(AG46)),"",IF(ISNUMBER(AA46),(AG46+AA46)/2,AG46))) | AI46: =IF(AND(ISNUMBER(AE46),ISNUMBER(AH46),AH46>0),AE46/AH46,"") | AJ46: =IF(E46="금융","",IF(AND(ISNUMBER(P46),ISNUMBER(AF46)),P46+AF46,"")) | AK46: =IF(OR(NOT(ISNUMBER(AE46)),NOT(ISNUMBER(AJ46)),AJ46<=0),"",IF(AND(ISNUMBER(G46),AJ46<0.1*G46),"",AE46/AJ46)) | AL46: =IF(NOT(ISNUMBER(P46)),"",IF(ISNUMBER(Q46),(P46+Q46)/2,P46)) | AM46: =IF(AND(ISNUMBER(L46),ISNUMBER(AL46),AL46>0),L46/AL46,"") | AN46: =IF(AND(ISNUMBER(AM46),ISNUMBER({ROIC})),AM46-{ROIC},"") | AO46: =IF(AND(ISNUMBER(AC46),ISNUMBER(M46)),AC46+M46,"") | AP46: =IF(AND(ISNUMBER(AF46),ISNUMBER(R46),ISNUMBER(AO46),AO46>0),(AF46-R46)/AO46,"") | AQ46: =IF(AND(ISNUMBER(AC46),ISNUMBER(I46),I46<>0,AC46>0),AC46/I46,"") | AR46: =IF(AND(ISNUMBER(W46),ISNUMBER(Y46)),W46-IF(ISNUMBER(R46),R46,0)-(Y46-IF(ISNUMBER(T46),T46,0)),"") | AS46: =IF(AND(ISNUMBER(X46),ISNUMBER(Z46)),X46-IF(ISNUMBER(S46),S46,0)-(Z46-IF(ISNUMBER(U46),U46,0)),"") | AT46: =IF(AND(ISNUMBER(AR46),ISNUMBER(AS46)),AR46-AS46,"") | AU46: =IF(E46="금융","",IF(AND(ISNUMBER(L46),ISNUMBER(M46),ISNUMBER(N46),ISNUMBER(AT46)),L46+M46-N46-AT46,IF(AND(ISNUMBER(O46),ISNUMBER(N46)),O46-N46,""))) | AV46: =IF(E46="금융","금융업 - 정의되지 않음",IF(AND(ISNUMBER(L46),ISNUMBER(M46),ISNUMBER(N46),ISNUMBER(AT46)),"순이익+감가상각-설비투자-운전자본증감",IF(AND(ISNUMBER(O46),ISNUMBER(N46)),"영업현금흐름-설비투자","산출불가"))) | AW46: =IF(AND(ISNUMBER(AU46),ISNUMBER(G46),G46<>0),AU46/G46,"") | AX46: =IF(AND(ISNUMBER(AC46),ISNUMBER(G46),G46<>0),AC46/G46,"")
A47: MSFT | B47: MICROSOFT CORP | C47: 2021 | D47: 2021-06-30 | E47: 일반 | F47: 0000950170-23-035122 | G47: 168.088 | H47: 71.102 | J47: 9.831 | K47: 69.916 | L47: 61.271 | M47: 9.3 | N47: 20.622 | O47: 76.74 | P47: 141.988 | Q47: 118.304 | R47: 130.334 | S47: 136.527 | T47: 8.072 | U47: 3.749 | V47: 50.074 | W47: 184.406 | X47: 181.915 | Y47: 88.657 | Z47: 72.31 | AA47: 45.104 | AB47: 7519 | AC47: =IF(AND(ISNUMBER(H47),ISNUMBER(I47)),H47+I47,IF(ISNUMBER(K47),K47,IF(ISNUMBER(H47),H47,""))) | AD47: =IF(OR(NOT(ISNUMBER(J47)),NOT(ISNUMBER(H47)),H47<=0),기준표!$B$8,MIN(MAX(J47/H47,기준표!$B$6),기준표!$B$7)) | AE47: =IF(ISNUMBER(AC47),AC47*(1-AD47),"") | AF47: =IF(AND(NOT(ISNUMBER(T47)),NOT(ISNUMBER(V47))),"",IF(ISNUMBER(T47),T47,0)+IF(ISNUMBER(V47),V47,0)) | AG47: =IF(E47="금융","",IF(AND(ISNUMBER(P47),ISNUMBER(AF47),ISNUMBER(R47)),P47+AF47-R47,"")) | AH47: =IF(E47="금융","",IF(NOT(ISNUMBER(AG47)),"",IF(ISNUMBER(AA47),(AG47+AA47)/2,AG47))) | AI47: =IF(AND(ISNUMBER(AE47),ISNUMBER(AH47),AH47>0),AE47/AH47,"") | AJ47: =IF(E47="금융","",IF(AND(ISNUMBER(P47),ISNUMBER(AF47)),P47+AF47,"")) | AK47: =IF(OR(NOT(ISNUMBER(AE47)),NOT(ISNUMBER(AJ47)),AJ47<=0),"",IF(AND(ISNUMBER(G47),AJ47<0.1*G47),"",AE47/AJ47)) | AL47: =IF(NOT(ISNUMBER(P47)),"",IF(ISNUMBER(Q47),(P47+Q47)/2,P47)) | AM47: =IF(AND(ISNUMBER(L47),ISNUMBER(AL47),AL47>0),L47/AL47,"") | AN47: =IF(AND(ISNUMBER(AM47),ISNUMBER({ROIC})),AM47-{ROIC},"") | AO47: =IF(AND(ISNUMBER(AC47),ISNUMBER(M47)),AC47+M47,"") | AP47: =IF(AND(ISNUMBER(AF47),ISNUMBER(R47),ISNUMBER(AO47),AO47>0),(AF47-R47)/AO47,"") | AQ47: =IF(AND(ISNUMBER(AC47),ISNUMBER(I47),I47<>0,AC47>0),AC47/I47,"") | AR47: =IF(AND(ISNUMBER(W47),ISNUMBER(Y47)),W47-IF(ISNUMBER(R47),R47,0)-(Y47-IF(ISNUMBER(T47),T47,0)),"") | AS47: =IF(AND(ISNUMBER(X47),ISNUMBER(Z47)),X47-IF(ISNUMBER(S47),S47,0)-(Z47-IF(ISNUMBER(U47),U47,0)),"") | AT47: =IF(AND(ISNUMBER(AR47),ISNUMBER(AS47)),AR47-AS47,"") | AU47: =IF(E47="금융","",IF(AND(ISNUMBER(L47),ISNUMBER(M47),ISNUMBER(N47),ISNUMBER(AT47)),L47+M47-N47-AT47,IF(AND(ISNUMBER(O47),ISNUMBER(N47)),O47-N47,""))) | AV47: =IF(E47="금융","금융업 - 정의되지 않음",IF(AND(ISNUMBER(L47),ISNUMBER(M47),ISNUMBER(N47),ISNUMBER(AT47)),"순이익+감가상각-설비투자-운전자본증감",IF(AND(ISNUMBER(O47),ISNUMBER(N47)),"영업현금흐름-설비투자","산출불가"))) | AW47: =IF(AND(ISNUMBER(AU47),ISNUMBER(G47),G47<>0),AU47/G47,"") | AX47: =IF(AND(ISNUMBER(AC47),ISNUMBER(G47),G47<>0),AC47/G47,"")
A48: MSFT | B48: MICROSOFT CORP | C48: 2022 | D48: 2022-06-30 | E48: 일반 | F48: 0000950170-24-087843 | G48: 198.27 | H48: 83.716 | J48: 10.978 | K48: 83.383 | L48: 72.738 | M48: 12.6 | N48: 23.886 | O48: 89.035 | P48: 166.542 | Q48: 141.988 | R48: 104.757 | S48: 130.334 | T48: 2.749 | U48: 8.072 | V48: 47.032 | W48: 169.684 | X48: 184.406 | Y48: 95.082 | Z48: 88.657 | AA48: 69.8 | AB48: 7464 | AC48: =IF(AND(ISNUMBER(H48),ISNUMBER(I48)),H48+I48,IF(ISNUMBER(K48),K48,IF(ISNUMBER(H48),H48,""))) | AD48: =IF(OR(NOT(ISNUMBER(J48)),NOT(ISNUMBER(H48)),H48<=0),기준표!$B$8,MIN(MAX(J48/H48,기준표!$B$6),기준표!$B$7)) | AE48: =IF(ISNUMBER(AC48),AC48*(1-AD48),"") | AF48: =IF(AND(NOT(ISNUMBER(T48)),NOT(ISNUMBER(V48))),"",IF(ISNUMBER(T48),T48,0)+IF(ISNUMBER(V48),V48,0)) | AG48: =IF(E48="금융","",IF(AND(ISNUMBER(P48),ISNUMBER(AF48),ISNUMBER(R48)),P48+AF48-R48,"")) | AH48: =IF(E48="금융","",IF(NOT(ISNUMBER(AG48)),"",IF(ISNUMBER(AA48),(AG48+AA48)/2,AG48))) | AI48: =IF(AND(ISNUMBER(AE48),ISNUMBER(AH48),AH48>0),AE48/AH48,"") | AJ48: =IF(E48="금융","",IF(AND(ISNUMBER(P48),ISNUMBER(AF48)),P48+AF48,"")) | AK48: =IF(OR(NOT(ISNUMBER(AE48)),NOT(ISNUMBER(AJ48)),AJ48<=0),"",IF(AND(ISNUMBER(G48),AJ48<0.1*G48),"",AE48/AJ48)) | AL48: =IF(NOT(ISNUMBER(P48)),"",IF(ISNUMBER(Q48),(P48+Q48)/2,P48)) | AM48: =IF(AND(ISNUMBER(L48),ISNUMBER(AL48),AL48>0),L48/AL48,"") | AN48: =IF(AND(ISNUMBER(AM48),ISNUMBER({ROIC})),AM48-{ROIC},"") | AO48: =IF(AND(ISNUMBER(AC48),ISNUMBER(M48)),AC48+M48,"") | AP48: =IF(AND(ISNUMBER(AF48),ISNUMBER(R48),ISNUMBER(AO48),AO48>0),(AF48-R48)/AO48,"") | AQ48: =IF(AND(ISNUMBER(AC48),ISNUMBER(I48),I48<>0,AC48>0),AC48/I48,"") | AR48: =IF(AND(ISNUMBER(W48),ISNUMBER(Y48)),W48-IF(ISNUMBER(R48),R48,0)-(Y48-IF(ISNUMBER(T48),T48,0)),"") | AS48: =IF(AND(ISNUMBER(X48),ISNUMBER(Z48)),X48-IF(ISNUMBER(S48),S48,0)-(Z48-IF(ISNUMBER(U48),U48,0)),"") | AT48: =IF(AND(ISNUMBER(AR48),ISNUMBER(AS48)),AR48-AS48,"") | AU48: =IF(E48="금융","",IF(AND(ISNUMBER(L48),ISNUMBER(M48),ISNUMBER(N48),ISNUMBER(AT48)),L48+M48-N48-AT48,IF(AND(ISNUMBER(O48),ISNUMBER(N48)),O48-N48,""))) | AV48: =IF(E48="금융","금융업 - 정의되지 않음",IF(AND(ISNUMBER(L48),ISNUMBER(M48),ISNUMBER(N48),ISNUMBER(AT48)),"순이익+감가상각-설비투자-운전자본증감",IF(AND(ISNUMBER(O48),ISNUMBER(N48)),"영업현금흐름-설비투자","산출불가"))) | AW48: =IF(AND(ISNUMBER(AU48),ISNUMBER(G48),G48<>0),AU48/G48,"") | AX48: =IF(AND(ISNUMBER(AC48),ISNUMBER(G48),G48<>0),AC48/G48,"")
A49: MSFT | B49: MICROSOFT CORP | C49: 2023 | D49: 2023-06-30 | E49: 일반 | F49: 0000950170-25-100235 | G49: 211.915 | H49: 89.311 | I49: 1.968 | J49: 16.95 | K49: 88.523 | L49: 72.361 | M49: 11 | N49: 28.107 | O49: 87.582 | P49: 206.223 | Q49: 166.542 | R49: 111.262 | S49: 104.757 | T49: 5.247 | U49: 2.749 | V49: 41.99 | W49: 184.257 | X49: 169.684 | Y49: 104.149 | Z49: 95.082 | AA49: 111.566 | AB49: 7432 | AC49: =IF(AND(ISNUMBER(H49),ISNUMBER(I49)),H49+I49,IF(ISNUMBER(K49),K49,IF(ISNUMBER(H49),H49,""))) | AD49: =IF(OR(NOT(ISNUMBER(J49)),NOT(ISNUMBER(H49)),H49<=0),기준표!$B$8,MIN(MAX(J49/H49,기준표!$B$6),기준표!$B$7)) | AE49: =IF(ISNUMBER(AC49),AC49*(1-AD49),"") | AF49: =IF(AND(NOT(ISNUMBER(T49)),NOT(ISNUMBER(V49))),"",IF(ISNUMBER(T49),T49,0)+IF(ISNUMBER(V49),V49,0)) | AG49: =IF(E49="금융","",IF(AND(ISNUMBER(P49),ISNUMBER(AF49),ISNUMBER(R49)),P49+AF49-R49,"")) | AH49: =IF(E49="금융","",IF(NOT(ISNUMBER(AG49)),"",IF(ISNUMBER(AA49),(AG49+AA49)/2,AG49))) | AI49: =IF(AND(ISNUMBER(AE49),ISNUMBER(AH49),AH49>0),AE49/AH49,"") | AJ49: =IF(E49="금융","",IF(AND(ISNUMBER(P49),ISNUMBER(AF49)),P49+AF49,"")) | AK49: =IF(OR(NOT(ISNUMBER(AE49)),NOT(ISNUMBER(AJ49)),AJ49<=0),"",IF(AND(ISNUMBER(G49),AJ49<0.1*G49),"",AE49/AJ49)) | AL49: =IF(NOT(ISNUMBER(P49)),"",IF(ISNUMBER(Q49),(P49+Q49)/2,P49)) | AM49: =IF(AND(ISNUMBER(L49),ISNUMBER(AL49),AL49>0),L49/AL49,"") | AN49: =IF(AND(ISNUMBER(AM49),ISNUMBER({ROIC})),AM49-{ROIC},"") | AO49: =IF(AND(ISNUMBER(AC49),ISNUMBER(M49)),AC49+M49,"") | AP49: =IF(AND(ISNUMBER(AF49),ISNUMBER(R49),ISNUMBER(AO49),AO49>0),(AF49-R49)/AO49,"") | AQ49: =IF(AND(ISNUMBER(AC49),ISNUMBER(I49),I49<>0,AC49>0),AC49/I49,"") | AR49: =IF(AND(ISNUMBER(W49),ISNUMBER(Y49)),W49-IF(ISNUMBER(R49),R49,0)-(Y49-IF(ISNUMBER(T49),T49,0)),"") | AS49: =IF(AND(ISNUMBER(X49),ISNUMBER(Z49)),X49-IF(ISNUMBER(S49),S49,0)-(Z49-IF(ISNUMBER(U49),U49,0)),"") | AT49: =IF(AND(ISNUMBER(AR49),ISNUMBER(AS49)),AR49-AS49,"") | AU49: =IF(E49="금융","",IF(AND(ISNUMBER(L49),ISNUMBER(M49),ISNUMBER(N49),ISNUMBER(AT49)),L49+M49-N49-AT49,IF(AND(ISNUMBER(O49),ISNUMBER(N49)),O49-N49,""))) | AV49: =IF(E49="금융","금융업 - 정의되지 않음",IF(AND(ISNUMBER(L49),ISNUMBER(M49),ISNUMBER(N49),ISNUMBER(AT49)),"순이익+감가상각-설비투자-운전자본증감",IF(AND(ISNUMBER(O49),ISNUMBER(N49)),"영업현금흐름-설비투자","산출불가"))) | AW49: =IF(AND(ISNUMBER(AU49),ISNUMBER(G49),G49<>0),AU49/G49,"") | AX49: =IF(AND(ISNUMBER(AC49),ISNUMBER(G49),G49<>0),AC49/G49,"")
A50: MSFT | B50: MICROSOFT CORP | C50: 2024 | D50: 2024-06-30 | E50: 일반 | F50: 0001193125-26-323660 | G50: 245.122 | H50: 107.787 | I50: 2.935 | J50: 19.651 | K50: 109.433 | L50: 88.136 | M50: 15.2 | N50: 44.477 | O50: 118.548 | P50: 268.477 | Q50: 206.223 | R50: 75.543 | S50: 111.262 | T50: 2.249 | U50: 5.247 | V50: 42.688 | W50: 159.734 | X50: 184.257 | Y50: 125.286 | Z50: 104.149 | AA50: 142.198 | AB50: 7434 | AC50: =IF(AND(ISNUMBER(H50),ISNUMBER(I50)),H50+I50,IF(ISNUMBER(K50),K50,IF(ISNUMBER(H50),H50,""))) | AD50: =IF(OR(NOT(ISNUMBER(J50)),NOT(ISNUMBER(H50)),H50<=0),기준표!$B$8,MIN(MAX(J50/H50,기준표!$B$6),기준표!$B$7)) | AE50: =IF(ISNUMBER(AC50),AC50*(1-AD50),"") | AF50: =IF(AND(NOT(ISNUMBER(T50)),NOT(ISNUMBER(V50))),"",IF(ISNUMBER(T50),T50,0)+IF(ISNUMBER(V50),V50,0)) | AG50: =IF(E50="금융","",IF(AND(ISNUMBER(P50),ISNUMBER(AF50),ISNUMBER(R50)),P50+AF50-R50,"")) | AH50: =IF(E50="금융","",IF(NOT(ISNUMBER(AG50)),"",IF(ISNUMBER(AA50),(AG50+AA50)/2,AG50))) | AI50: =IF(AND(ISNUMBER(AE50),ISNUMBER(AH50),AH50>0),AE50/AH50,"") | AJ50: =IF(E50="금융","",IF(AND(ISNUMBER(P50),ISNUMBER(AF50)),P50+AF50,"")) | AK50: =IF(OR(NOT(ISNUMBER(AE50)),NOT(ISNUMBER(AJ50)),AJ50<=0),"",IF(AND(ISNUMBER(G50),AJ50<0.1*G50),"",AE50/AJ50)) | AL50: =IF(NOT(ISNUMBER(P50)),"",IF(ISNUMBER(Q50),(P50+Q50)/2,P50)) | AM50: =IF(AND(ISNUMBER(L50),ISNUMBER(AL50),AL50>0),L50/AL50,"") | AN50: =IF(AND(ISNUMBER(AM50),ISNUMBER({ROIC})),AM50-{ROIC},"") | AO50: =IF(AND(ISNUMBER(AC50),ISNUMBER(M50)),AC50+M50,"") | AP50: =IF(AND(ISNUMBER(AF50),ISNUMBER(R50),ISNUMBER(AO50),AO50>0),(AF50-R50)/AO50,"") | AQ50: =IF(AND(ISNUMBER(AC50),ISNUMBER(I50),I50<>0,AC50>0),AC50/I50,"") | AR50: =IF(AND(ISNUMBER(W50),ISNUMBER(Y50)),W50-IF(ISNUMBER(R50),R50,0)-(Y50-IF(ISNUMBER(T50),T50,0)),"") | AS50: =IF(AND(ISNUMBER(X50),ISNUMBER(Z50)),X50-IF(ISNUMBER(S50),S50,0)-(Z50-IF(ISNUMBER(U50),U50,0)),"") | AT50: =IF(AND(ISNUMBER(AR50),ISNUMBER(AS50)),AR50-AS50,"") | AU50: =IF(E50="금융","",IF(AND(ISNUMBER(L50),ISNUMBER(M50),ISNUMBER(N50),ISNUMBER(AT50)),L50+M50-N50-AT50,IF(AND(ISNUMBER(O50),ISNUMBER(N50)),O50-N50,""))) | AV50: =IF(E50="금융","금융업 - 정의되지 않음",IF(AND(ISNUMBER(L50),ISNUMBER(M50),ISNUMBER(N50),ISNUMBER(AT50)),"순이익+감가상각-설비투자-운전자본증감",IF(AND(ISNUMBER(O50),ISNUMBER(N50)),"영업현금흐름-설비투자","산출불가"))) | AW50: =IF(AND(ISNUMBER(AU50),ISNUMBER(G50),G50<>0),AU50/G50,"") | AX50: =IF(AND(ISNUMBER(AC50),ISNUMBER(G50),G50<>0),AC50/G50,"")
A51: MSFT | B51: MICROSOFT CORP | C51: 2025 | D51: 2025-06-30 | E51: 일반 | F51: 0001193125-26-323660 | G51: 281.724 | H51: 123.627 | I51: 2.385 | J51: 21.795 | K51: 128.528 | L51: 101.832 | M51: 22 | N51: 64.551 | O51: 136.162 | P51: 343.479 | Q51: 268.477 | R51: 94.565 | S51: 75.543 | T51: 2.999 | U51: 2.249 | V51: 40.152 | W51: 191.131 | X51: 159.734 | Y51: 141.218 | Z51: 125.286 | AA51: 237.871 | AB51: 7434 | AC51: =IF(AND(ISNUMBER(H51),ISNUMBER(I51)),H51+I51,IF(ISNUMBER(K51),K51,IF(ISNUMBER(H51),H51,""))) | AD51: =IF(OR(NOT(ISNUMBER(J51)),NOT(ISNUMBER(H51)),H51<=0),기준표!$B$8,MIN(MAX(J51/H51,기준표!$B$6),기준표!$B$7)) | AE51: =IF(ISNUMBER(AC51),AC51*(1-AD51),"") | AF51: =IF(AND(NOT(ISNUMBER(T51)),NOT(ISNUMBER(V51))),"",IF(ISNUMBER(T51),T51,0)+IF(ISNUMBER(V51),V51,0)) | AG51: =IF(E51="금융","",IF(AND(ISNUMBER(P51),ISNUMBER(AF51),ISNUMBER(R51)),P51+AF51-R51,"")) | AH51: =IF(E51="금융","",IF(NOT(ISNUMBER(AG51)),"",IF(ISNUMBER(AA51),(AG51+AA51)/2,AG51))) | AI51: =IF(AND(ISNUMBER(AE51),ISNUMBER(AH51),AH51>0),AE51/AH51,"") | AJ51: =IF(E51="금융","",IF(AND(ISNUMBER(P51),ISNUMBER(AF51)),P51+AF51,"")) | AK51: =IF(OR(NOT(ISNUMBER(AE51)),NOT(ISNUMBER(AJ51)),AJ51<=0),"",IF(AND(ISNUMBER(G51),AJ51<0.1*G51),"",AE51/AJ51)) | AL51: =IF(NOT(ISNUMBER(P51)),"",IF(ISNUMBER(Q51),(P51+Q51)/2,P51)) | AM51: =IF(AND(ISNUMBER(L51),ISNUMBER(AL51),AL51>0),L51/AL51,"") | AN51: =IF(AND(ISNUMBER(AM51),ISNUMBER({ROIC})),AM51-{ROIC},"") | AO51: =IF(AND(ISNUMBER(AC51),ISNUMBER(M51)),AC51+M51,"") | AP51: =IF(AND(ISNUMBER(AF51),ISNUMBER(R51),ISNUMBER(AO51),AO51>0),(AF51-R51)/AO51,"") | AQ51: =IF(AND(ISNUMBER(AC51),ISNUMBER(I51),I51<>0,AC51>0),AC51/I51,"") | AR51: =IF(AND(ISNUMBER(W51),ISNUMBER(Y51)),W51-IF(ISNUMBER(R51),R51,0)-(Y51-IF(ISNUMBER(T51),T51,0)),"") | AS51: =IF(AND(ISNUMBER(X51),ISNUMBER(Z51)),X51-IF(ISNUMBER(S51),S51,0)-(Z51-IF(ISNUMBER(U51),U51,0)),"") | AT51: =IF(AND(ISNUMBER(AR51),ISNUMBER(AS51)),AR51-AS51,"") | AU51: =IF(E51="금융","",IF(AND(ISNUMBER(L51),ISNUMBER(M51),ISNUMBER(N51),ISNUMBER(AT51)),L51+M51-N51-AT51,IF(AND(ISNUMBER(O51),ISNUMBER(N51)),O51-N51,""))) | AV51: =IF(E51="금융","금융업 - 정의되지 않음",IF(AND(ISNUMBER(L51),ISNUMBER(M51),ISNUMBER(N51),ISNUMBER(AT51)),"순이익+감가상각-설비투자-운전자본증감",IF(AND(ISNUMBER(O51),ISNUMBER(N51)),"영업현금흐름-설비투자","산출불가"))) | AW51: =IF(AND(ISNUMBER(AU51),ISNUMBER(G51),G51<>0),AU51/G51,"") | AX51: =IF(AND(ISNUMBER(AC51),ISNUMBER(G51),G51<>0),AC51/G51,"")
A52: MSFT | B52: MICROSOFT CORP | C52: 2026 | D52: 2026-06-30 | E52: 일반 | F52: 0001193125-26-323660 | G52: 331.839 | H52: 165.934 | I52: 3.051 | J52: 32.185 | K52: 155.237 | L52: 133.749 | M52: 34.3 | N52: 115.948 | O52: 182.935 | P52: 442.387 | Q52: 343.479 | R52: 76.843 | S52: 94.565 | T52: 9.227 | U52: 2.999 | V52: 31.067 | W52: 207.71 | X52: 191.131 | Y52: 168.825 | Z52: 141.218 | AA52: 292.065 | AB52: 7427 | AC52: =IF(AND(ISNUMBER(H52),ISNUMBER(I52)),H52+I52,IF(ISNUMBER(K52),K52,IF(ISNUMBER(H52),H52,""))) | AD52: =IF(OR(NOT(ISNUMBER(J52)),NOT(ISNUMBER(H52)),H52<=0),기준표!$B$8,MIN(MAX(J52/H52,기준표!$B$6),기준표!$B$7)) | AE52: =IF(ISNUMBER(AC52),AC52*(1-AD52),"") | AF52: =IF(AND(NOT(ISNUMBER(T52)),NOT(ISNUMBER(V52))),"",IF(ISNUMBER(T52),T52,0)+IF(ISNUMBER(V52),V52,0)) | AG52: =IF(E52="금융","",IF(AND(ISNUMBER(P52),ISNUMBER(AF52),ISNUMBER(R52)),P52+AF52-R52,"")) | AH52: =IF(E52="금융","",IF(NOT(ISNUMBER(AG52)),"",IF(ISNUMBER(AA52),(AG52+AA52)/2,AG52))) | AI52: =IF(AND(ISNUMBER(AE52),ISNUMBER(AH52),AH52>0),AE52/AH52,"") | AJ52: =IF(E52="금융","",IF(AND(ISNUMBER(P52),ISNUMBER(AF52)),P52+AF52,"")) | AK52: =IF(OR(NOT(ISNUMBER(AE52)),NOT(ISNUMBER(AJ52)),AJ52<=0),"",IF(AND(ISNUMBER(G52),AJ52<0.1*G52),"",AE52/AJ52)) | AL52: =IF(NOT(ISNUMBER(P52)),"",IF(ISNUMBER(Q52),(P52+Q52)/2,P52)) | AM52: =IF(AND(ISNUMBER(L52),ISNUMBER(AL52),AL52>0),L52/AL52,"") | AN52: =IF(AND(ISNUMBER(AM52),ISNUMBER({ROIC})),AM52-{ROIC},"") | AO52: =IF(AND(ISNUMBER(AC52),ISNUMBER(M52)),AC52+M52,"") | AP52: =IF(AND(ISNUMBER(AF52),ISNUMBER(R52),ISNUMBER(AO52),AO52>0),(AF52-R52)/AO52,"") | AQ52: =IF(AND(ISNUMBER(AC52),ISNUMBER(I52),I52<>0,AC52>0),AC52/I52,"") | AR52: =IF(AND(ISNUMBER(W52),ISNUMBER(Y52)),W52-IF(ISNUMBER(R52),R52,0)-(Y52-IF(ISNUMBER(T52),T52,0)),"") | AS52: =IF(AND(ISNUMBER(X52),ISNUMBER(Z52)),X52-IF(ISNUMBER(S52),S52,0)-(Z52-IF(ISNUMBER(U52),U52,0)),"") | AT52: =IF(AND(ISNUMBER(AR52),ISNUMBER(AS52)),AR52-AS52,"") | AU52: =IF(E52="금융","",IF(AND(ISNUMBER(L52),ISNUMBER(M52),ISNUMBER(N52),ISNUMBER(AT52)),L52+M52-N52-AT52,IF(AND(ISNUMBER(O52),ISNUMBER(N52)),O52-N52,""))) | AV52: =IF(E52="금융","금융업 - 정의되지 않음",IF(AND(ISNUMBER(L52),ISNUMBER(M52),ISNUMBER(N52),ISNUMBER(AT52)),"순이익+감가상각-설비투자-운전자본증감",IF(AND(ISNUMBER(O52),ISNUMBER(N52)),"영업현금흐름-설비투자","산출불가"))) | AW52: =IF(AND(ISNUMBER(AU52),ISNUMBER(G52),G52<>0),AU52/G52,"") | AX52: =IF(AND(ISNUMBER(AC52),ISNUMBER(G52),G52<>0),AC52/G52,"")
A53: AMZN | B53: AMAZON COM INC | C53: 2014 | D53: 2014-12-31 | E53: 일반 | F53: 0001018724-17-000011 | H53: -0.111 | J53: 0.167 | K53: 0.178 | L53: -0.241 | M53: 3.616 | O53: 6.842 | P53: 10.741 | R53: 17.416 | T53: 1.52 | V53: 8.265 | W53: 31.327 | Y53: 28.089 | AB53: 9300 | AC53: =IF(AND(ISNUMBER(H53),ISNUMBER(I53)),H53+I53,IF(ISNUMBER(K53),K53,IF(ISNUMBER(H53),H53,""))) | AD53: =IF(OR(NOT(ISNUMBER(J53)),NOT(ISNUMBER(H53)),H53<=0),기준표!$B$8,MIN(MAX(J53/H53,기준표!$B$6),기준표!$B$7)) | AE53: =IF(ISNUMBER(AC53),AC53*(1-AD53),"") | AF53: =IF(AND(NOT(ISNUMBER(T53)),NOT(ISNUMBER(V53))),"",IF(ISNUMBER(T53),T53,0)+IF(ISNUMBER(V53),V53,0)) | AG53: =IF(E53="금융","",IF(AND(ISNUMBER(P53),ISNUMBER(AF53),ISNUMBER(R53)),P53+AF53-R53,"")) | AH53: =IF(E53="금융","",IF(NOT(ISNUMBER(AG53)),"",IF(ISNUMBER(AA53),(AG53+AA53)/2,AG53))) | AI53: =IF(AND(ISNUMBER(AE53),ISNUMBER(AH53),AH53>0),AE53/AH53,"") | AJ53: =IF(E53="금융","",IF(AND(ISNUMBER(P53),ISNUMBER(AF53)),P53+AF53,"")) | AK53: =IF(OR(NOT(ISNUMBER(AE53)),NOT(ISNUMBER(AJ53)),AJ53<=0),"",IF(AND(ISNUMBER(G53),AJ53<0.1*G53),"",AE53/AJ53)) | AL53: =IF(NOT(ISNUMBER(P53)),"",IF(ISNUMBER(Q53),(P53+Q53)/2,P53)) | AM53: =IF(AND(ISNUMBER(L53),ISNUMBER(AL53),AL53>0),L53/AL53,"") | AN53: =IF(AND(ISNUMBER(AM53),ISNUMBER({ROIC})),AM53-{ROIC},"") | AO53: =IF(AND(ISNUMBER(AC53),ISNUMBER(M53)),AC53+M53,"") | AP53: =IF(AND(ISNUMBER(AF53),ISNUMBER(R53),ISNUMBER(AO53),AO53>0),(AF53-R53)/AO53,"") | AQ53: =IF(AND(ISNUMBER(AC53),ISNUMBER(I53),I53<>0,AC53>0),AC53/I53,"") | AR53: =IF(AND(ISNUMBER(W53),ISNUMBER(Y53)),W53-IF(ISNUMBER(R53),R53,0)-(Y53-IF(ISNUMBER(T53),T53,0)),"") | AS53: =IF(AND(ISNUMBER(X53),ISNUMBER(Z53)),X53-IF(ISNUMBER(S53),S53,0)-(Z53-IF(ISNUMBER(U53),U53,0)),"") | AT53: =IF(AND(ISNUMBER(AR53),ISNUMBER(AS53)),AR53-AS53,"") | AU53: =IF(E53="금융","",IF(AND(ISNUMBER(L53),ISNUMBER(M53),ISNUMBER(N53),ISNUMBER(AT53)),L53+M53-N53-AT53,IF(AND(ISNUMBER(O53),ISNUMBER(N53)),O53-N53,""))) | AV53: =IF(E53="금융","금융업 - 정의되지 않음",IF(AND(ISNUMBER(L53),ISNUMBER(M53),ISNUMBER(N53),ISNUMBER(AT53)),"순이익+감가상각-설비투자-운전자본증감",IF(AND(ISNUMBER(O53),ISNUMBER(N53)),"영업현금흐름-설비투자","산출불가"))) | AW53: =IF(AND(ISNUMBER(AU53),ISNUMBER(G53),G53<>0),AU53/G53,"") | AX53: =IF(AND(ISNUMBER(AC53),ISNUMBER(G53),G53<>0),AC53/G53,"")
A54: AMZN | B54: AMAZON COM INC | C54: 2015 | D54: 2015-12-31 | E54: 일반 | F54: 0001018724-18-000005 | H54: 1.568 | J54: 0.95 | K54: 2.233 | L54: 0.596 | M54: 6.281 | O54: 12.039 | P54: 13.384 | Q54: 10.741 | R54: 19.808 | S54: 17.416 | T54: 0.238 | U54: 1.52 | V54: 8.227 | W54: 35.705 | X54: 31.327 | Y54: 33.887 | Z54: 28.089 | AA54: 3.11 | AB54: 9420 | AC54: =IF(AND(ISNUMBER(H54),ISNUMBER(I54)),H54+I54,IF(ISNUMBER(K54),K54,IF(ISNUMBER(H54),H54,""))) | AD54: =IF(OR(NOT(ISNUMBER(J54)),NOT(ISNUMBER(H54)),H54<=0),기준표!$B$8,MIN(MAX(J54/H54,기준표!$B$6),기준표!$B$7)) | AE54: =IF(ISNUMBER(AC54),AC54*(1-AD54),"") | AF54: =IF(AND(NOT(ISNUMBER(T54)),NOT(ISNUMBER(V54))),"",IF(ISNUMBER(T54),T54,0)+IF(ISNUMBER(V54),V54,0)) | AG54: =IF(E54="금융","",IF(AND(ISNUMBER(P54),ISNUMBER(AF54),ISNUMBER(R54)),P54+AF54-R54,"")) | AH54: =IF(E54="금융","",IF(NOT(ISNUMBER(AG54)),"",IF(ISNUMBER(AA54),(AG54+AA54)/2,AG54))) | AI54: =IF(AND(ISNUMBER(AE54),ISNUMBER(AH54),AH54>0),AE54/AH54,"") | AJ54: =IF(E54="금융","",IF(AND(ISNUMBER(P54),ISNUMBER(AF54)),P54+AF54,"")) | AK54: =IF(OR(NOT(ISNUMBER(AE54)),NOT(ISNUMBER(AJ54)),AJ54<=0),"",IF(AND(ISNUMBER(G54),AJ54<0.1*G54),"",AE54/AJ54)) | AL54: =IF(NOT(ISNUMBER(P54)),"",IF(ISNUMBER(Q54),(P54+Q54)/2,P54)) | AM54: =IF(AND(ISNUMBER(L54),ISNUMBER(AL54),AL54>0),L54/AL54,"") | AN54: =IF(AND(ISNUMBER(AM54),ISNUMBER({ROIC})),AM54-{ROIC},"") | AO54: =IF(AND(ISNUMBER(AC54),ISNUMBER(M54)),AC54+M54,"") | AP54: =IF(AND(ISNUMBER(AF54),ISNUMBER(R54),ISNUMBER(AO54),AO54>0),(AF54-R54)/AO54,"") | AQ54: =IF(AND(ISNUMBER(AC54),ISNUMBER(I54),I54<>0,AC54>0),AC54/I54,"") | AR54: =IF(AND(ISNUMBER(W54),ISNUMBER(Y54)),W54-IF(ISNUMBER(R54),R54,0)-(Y54-IF(ISNUMBER(T54),T54,0)),"") | AS54: =IF(AND(ISNUMBER(X54),ISNUMBER(Z54)),X54-IF(ISNUMBER(S54),S54,0)-(Z54-IF(ISNUMBER(U54),U54,0)),"") | AT54: =IF(AND(ISNUMBER(AR54),ISNUMBER(AS54)),AR54-AS54,"") | AU54: =IF(E54="금융","",IF(AND(ISNUMBER(L54),ISNUMBER(M54),ISNUMBER(N54),ISNUMBER(AT54)),L54+M54-N54-AT54,IF(AND(ISNUMBER(O54),ISNUMBER(N54)),O54-N54,""))) | AV54: =IF(E54="금융","금융업 - 정의되지 않음",IF(AND(ISNUMBER(L54),ISNUMBER(M54),ISNUMBER(N54),ISNUMBER(AT54)),"순이익+감가상각-설비투자-운전자본증감",IF(AND(ISNUMBER(O54),ISNUMBER(N54)),"영업현금흐름-설비투자","산출불가"))) | AW54: =IF(AND(ISNUMBER(AU54),ISNUMBER(G54),G54<>0),AU54/G54,"") | AX54: =IF(AND(ISNUMBER(AC54),ISNUMBER(G54),G54<>0),AC54/G54,"")
A55: AMZN | B55: AMAZON COM INC | C55: 2016 | D55: 2016-12-31 | E55: 일반 | F55: 0001018724-19-000004 | G55: 135.987 | H55: 3.892 | J55: 1.425 | K55: 4.186 | L55: 2.371 | M55: 8.116 | N55: 7.804 | O55: 17.203 | P55: 19.285 | Q55: 13.384 | R55: 25.981 | S55: 19.808 | T55: 1.056 | U55: 0.238 | V55: 7.694 | W55: 45.781 | X55: 35.705 | Y55: 43.816 | Z55: 33.887 | AA55: 2.041 | AB55: 9540 | AC55: =IF(AND(ISNUMBER(H55),ISNUMBER(I55)),H55+I55,IF(ISNUMBER(K55),K55,IF(ISNUMBER(H55),H55,""))) | AD55: =IF(OR(NOT(ISNUMBER(J55)),NOT(ISNUMBER(H55)),H55<=0),기준표!$B$8,MIN(MAX(J55/H55,기준표!$B$6),기준표!$B$7)) | AE55: =IF(ISNUMBER(AC55),AC55*(1-AD55),"") | AF55: =IF(AND(NOT(ISNUMBER(T55)),NOT(ISNUMBER(V55))),"",IF(ISNUMBER(T55),T55,0)+IF(ISNUMBER(V55),V55,0)) | AG55: =IF(E55="금융","",IF(AND(ISNUMBER(P55),ISNUMBER(AF55),ISNUMBER(R55)),P55+AF55-R55,"")) | AH55: =IF(E55="금융","",IF(NOT(ISNUMBER(AG55)),"",IF(ISNUMBER(AA55),(AG55+AA55)/2,AG55))) | AI55: =IF(AND(ISNUMBER(AE55),ISNUMBER(AH55),AH55>0),AE55/AH55,"") | AJ55: =IF(E55="금융","",IF(AND(ISNUMBER(P55),ISNUMBER(AF55)),P55+AF55,"")) | AK55: =IF(OR(NOT(ISNUMBER(AE55)),NOT(ISNUMBER(AJ55)),AJ55<=0),"",IF(AND(ISNUMBER(G55),AJ55<0.1*G55),"",AE55/AJ55)) | AL55: =IF(NOT(ISNUMBER(P55)),"",IF(ISNUMBER(Q55),(P55+Q55)/2,P55)) | AM55: =IF(AND(ISNUMBER(L55),ISNUMBER(AL55),AL55>0),L55/AL55,"") | AN55: =IF(AND(ISNUMBER(AM55),ISNUMBER({ROIC})),AM55-{ROIC},"") | AO55: =IF(AND(ISNUMBER(AC55),ISNUMBER(M55)),AC55+M55,"") | AP55: =IF(AND(ISNUMBER(AF55),ISNUMBER(R55),ISNUMBER(AO55),AO55>0),(AF55-R55)/AO55,"") | AQ55: =IF(AND(ISNUMBER(AC55),ISNUMBER(I55),I55<>0,AC55>0),AC55/I55,"") | AR55: =IF(AND(ISNUMBER(W55),ISNUMBER(Y55)),W55-IF(ISNUMBER(R55),R55,0)-(Y55-IF(ISNUMBER(T55),T55,0)),"") | AS55: =IF(AND(ISNUMBER(X55),ISNUMBER(Z55)),X55-IF(ISNUMBER(S55),S55,0)-(Z55-IF(ISNUMBER(U55),U55,0)),"") | AT55: =IF(AND(ISNUMBER(AR55),ISNUMBER(AS55)),AR55-AS55,"") | AU55: =IF(E55="금융","",IF(AND(ISNUMBER(L55),ISNUMBER(M55),ISNUMBER(N55),ISNUMBER(AT55)),L55+M55-N55-AT55,IF(AND(ISNUMBER(O55),ISNUMBER(N55)),O55-N55,""))) | AV55: =IF(E55="금융","금융업 - 정의되지 않음",IF(AND(ISNUMBER(L55),ISNUMBER(M55),ISNUMBER(N55),ISNUMBER(AT55)),"순이익+감가상각-설비투자-운전자본증감",IF(AND(ISNUMBER(O55),ISNUMBER(N55)),"영업현금흐름-설비투자","산출불가"))) | AW55: =IF(AND(ISNUMBER(AU55),ISNUMBER(G55),G55<>0),AU55/G55,"") | AX55: =IF(AND(ISNUMBER(AC55),ISNUMBER(G55),G55<>0),AC55/G55,"")
A56: AMZN | B56: AMAZON COM INC | C56: 2017 | D56: 2017-12-31 | E56: 일반 | F56: 0001018724-20-000004 | G56: 177.866 | H56: 3.806 | J56: 0.769 | K56: 4.106 | L56: 3.033 | M56: 11.478 | N56: 11.955 | O56: 18.365 | P56: 27.709 | Q56: 19.285 | R56: 30.986 | S56: 25.981 | T56: 0.1 | U56: 1.056 | V56: 24.743 | W56: 60.197 | X56: 45.781 | Y56: 57.883 | Z56: 43.816 | AA56: 2.054 | AB56: 9680 | AC56: =IF(AND(ISNUMBER(H56),ISNUMBER(I56)),H56+I56,IF(ISNUMBER(K56),K56,IF(ISNUMBER(H56),H56,""))) | AD56: =IF(OR(NOT(ISNUMBER(J56)),NOT(ISNUMBER(H56)),H56<=0),기준표!$B$8,MIN(MAX(J56/H56,기준표!$B$6),기준표!$B$7)) | AE56: =IF(ISNUMBER(AC56),AC56*(1-AD56),"") | AF56: =IF(AND(NOT(ISNUMBER(T56)),NOT(ISNUMBER(V56))),"",IF(ISNUMBER(T56),T56,0)+IF(ISNUMBER(V56),V56,0)) | AG56: =IF(E56="금융","",IF(AND(ISNUMBER(P56),ISNUMBER(AF56),ISNUMBER(R56)),P56+AF56-R56,"")) | AH56: =IF(E56="금융","",IF(NOT(ISNUMBER(AG56)),"",IF(ISNUMBER(AA56),(AG56+AA56)/2,AG56))) | AI56: =IF(AND(ISNUMBER(AE56),ISNUMBER(AH56),AH56>0),AE56/AH56,"") | AJ56: =IF(E56="금융","",IF(AND(ISNUMBER(P56),ISNUMBER(AF56)),P56+AF56,"")) | AK56: =IF(OR(NOT(ISNUMBER(AE56)),NOT(ISNUMBER(AJ56)),AJ56<=0),"",IF(AND(ISNUMBER(G56),AJ56<0.1*G56),"",AE56/AJ56)) | AL56: =IF(NOT(ISNUMBER(P56)),"",IF(ISNUMBER(Q56),(P56+Q56)/2,P56)) | AM56: =IF(AND(ISNUMBER(L56),ISNUMBER(AL56),AL56>0),L56/AL56,"") | AN56: =IF(AND(ISNUMBER(AM56),ISNUMBER({ROIC})),AM56-{ROIC},"") | AO56: =IF(AND(ISNUMBER(AC56),ISNUMBER(M56)),AC56+M56,"") | AP56: =IF(AND(ISNUMBER(AF56),ISNUMBER(R56),ISNUMBER(AO56),AO56>0),(AF56-R56)/AO56,"") | AQ56: =IF(AND(ISNUMBER(AC56),ISNUMBER(I56),I56<>0,AC56>0),AC56/I56,"") | AR56: =IF(AND(ISNUMBER(W56),ISNUMBER(Y56)),W56-IF(ISNUMBER(R56),R56,0)-(Y56-IF(ISNUMBER(T56),T56,0)),"") | AS56: =IF(AND(ISNUMBER(X56),ISNUMBER(Z56)),X56-IF(ISNUMBER(S56),S56,0)-(Z56-IF(ISNUMBER(U56),U56,0)),"") | AT56: =IF(AND(ISNUMBER(AR56),ISNUMBER(AS56)),AR56-AS56,"") | AU56: =IF(E56="금융","",IF(AND(ISNUMBER(L56),ISNUMBER(M56),ISNUMBER(N56),ISNUMBER(AT56)),L56+M56-N56-AT56,IF(AND(ISNUMBER(O56),ISNUMBER(N56)),O56-N56,""))) | AV56: =IF(E56="금융","금융업 - 정의되지 않음",IF(AND(ISNUMBER(L56),ISNUMBER(M56),ISNUMBER(N56),ISNUMBER(AT56)),"순이익+감가상각-설비투자-운전자본증감",IF(AND(ISNUMBER(O56),ISNUMBER(N56)),"영업현금흐름-설비투자","산출불가"))) | AW56: =IF(AND(ISNUMBER(AU56),ISNUMBER(G56),G56<>0),AU56/G56,"") | AX56: =IF(AND(ISNUMBER(AC56),ISNUMBER(G56),G56<>0),AC56/G56,"")
A57: AMZN | B57: AMAZON COM INC | C57: 2018 | D57: 2018-12-31 | E57: 일반 | F57: 0001018724-21-000004 | G57: 232.887 | H57: 11.261 | J57: 1.197 | K57: 12.421 | L57: 10.073 | M57: 15.341 | N57: 13.427 | O57: 30.723 | P57: 43.549 | Q57: 27.709 | R57: 41.25 | S57: 30.986 | T57: 1.371 | U57: 0.1 | V57: 23.495 | W57: 75.101 | X57: 60.197 | Y57: 68.391 | Z57: 57.883 | AA57: 21.566 | AB57: 9820 | AC57: =IF(AND(ISNUMBER(H57),ISNUMBER(I57)),H57+I57,IF(ISNUMBER(K57),K57,IF(ISNUMBER(H57),H57,""))) | AD57: =IF(OR(NOT(ISNUMBER(J57)),NOT(ISNUMBER(H57)),H57<=0),기준표!$B$8,MIN(MAX(J57/H57,기준표!$B$6),기준표!$B$7)) | AE57: =IF(ISNUMBER(AC57),AC57*(1-AD57),"") | AF57: =IF(AND(NOT(ISNUMBER(T57)),NOT(ISNUMBER(V57))),"",IF(ISNUMBER(T57),T57,0)+IF(ISNUMBER(V57),V57,0)) | AG57: =IF(E57="금융","",IF(AND(ISNUMBER(P57),ISNUMBER(AF57),ISNUMBER(R57)),P57+AF57-R57,"")) | AH57: =IF(E57="금융","",IF(NOT(ISNUMBER(AG57)),"",IF(ISNUMBER(AA57),(AG57+AA57)/2,AG57))) | AI57: =IF(AND(ISNUMBER(AE57),ISNUMBER(AH57),AH57>0),AE57/AH57,"") | AJ57: =IF(E57="금융","",IF(AND(ISNUMBER(P57),ISNUMBER(AF57)),P57+AF57,"")) | AK57: =IF(OR(NOT(ISNUMBER(AE57)),NOT(ISNUMBER(AJ57)),AJ57<=0),"",IF(AND(ISNUMBER(G57),AJ57<0.1*G57),"",AE57/AJ57)) | AL57: =IF(NOT(ISNUMBER(P57)),"",IF(ISNUMBER(Q57),(P57+Q57)/2,P57)) | AM57: =IF(AND(ISNUMBER(L57),ISNUMBER(AL57),AL57>0),L57/AL57,"") | AN57: =IF(AND(ISNUMBER(AM57),ISNUMBER({ROIC})),AM57-{ROIC},"") | AO57: =IF(AND(ISNUMBER(AC57),ISNUMBER(M57)),AC57+M57,"") | AP57: =IF(AND(ISNUMBER(AF57),ISNUMBER(R57),ISNUMBER(AO57),AO57>0),(AF57-R57)/AO57,"") | AQ57: =IF(AND(ISNUMBER(AC57),ISNUMBER(I57),I57<>0,AC57>0),AC57/I57,"") | AR57: =IF(AND(ISNUMBER(W57),ISNUMBER(Y57)),W57-IF(ISNUMBER(R57),R57,0)-(Y57-IF(ISNUMBER(T57),T57,0)),"") | AS57: =IF(AND(ISNUMBER(X57),ISNUMBER(Z57)),X57-IF(ISNUMBER(S57),S57,0)-(Z57-IF(ISNUMBER(U57),U57,0)),"") | AT57: =IF(AND(ISNUMBER(AR57),ISNUMBER(AS57)),AR57-AS57,"") | AU57: =IF(E57="금융","",IF(AND(ISNUMBER(L57),ISNUMBER(M57),ISNUMBER(N57),ISNUMBER(AT57)),L57+M57-N57-AT57,IF(AND(ISNUMBER(O57),ISNUMBER(N57)),O57-N57,""))) | AV57: =IF(E57="금융","금융업 - 정의되지 않음",IF(AND(ISNUMBER(L57),ISNUMBER(M57),ISNUMBER(N57),ISNUMBER(AT57)),"순이익+감가상각-설비투자-운전자본증감",IF(AND(ISNUMBER(O57),ISNUMBER(N57)),"영업현금흐름-설비투자","산출불가"))) | AW57: =IF(AND(ISNUMBER(AU57),ISNUMBER(G57),G57<>0),AU57/G57,"") | AX57: =IF(AND(ISNUMBER(AC57),ISNUMBER(G57),G57<>0),AC57/G57,"")
A58: AMZN | B58: AMAZON COM INC | C58: 2019 | D58: 2019-12-31 | E58: 일반 | F58: 0001018724-22-000005 | G58: 280.522 | H58: 13.976 | J58: 2.374 | K58: 14.541 | L58: 11.588 | M58: 21.789 | N58: 16.861 | O58: 38.514 | P58: 62.06 | Q58: 43.549 | R58: 55.021 | S58: 41.25 | T58: 1.305 | U58: 1.371 | V58: 23.414 | W58: 96.334 | X58: 75.101 | Y58: 87.812 | Z58: 68.391 | AA58: 27.165 | AB58: 9960 | AC58: =IF(AND(ISNUMBER(H58),ISNUMBER(I58)),H58+I58,IF(ISNUMBER(K58),K58,IF(ISNUMBER(H58),H58,""))) | AD58: =IF(OR(NOT(ISNUMBER(J58)),NOT(ISNUMBER(H58)),H58<=0),기준표!$B$8,MIN(MAX(J58/H58,기준표!$B$6),기준표!$B$7)) | AE58: =IF(ISNUMBER(AC58),AC58*(1-AD58),"") | AF58: =IF(AND(NOT(ISNUMBER(T58)),NOT(ISNUMBER(V58))),"",IF(ISNUMBER(T58),T58,0)+IF(ISNUMBER(V58),V58,0)) | AG58: =IF(E58="금융","",IF(AND(ISNUMBER(P58),ISNUMBER(AF58),ISNUMBER(R58)),P58+AF58-R58,"")) | AH58: =IF(E58="금융","",IF(NOT(ISNUMBER(AG58)),"",IF(ISNUMBER(AA58),(AG58+AA58)/2,AG58))) | AI58: =IF(AND(ISNUMBER(AE58),ISNUMBER(AH58),AH58>0),AE58/AH58,"") | AJ58: =IF(E58="금융","",IF(AND(ISNUMBER(P58),ISNUMBER(AF58)),P58+AF58,"")) | AK58: =IF(OR(NOT(ISNUMBER(AE58)),NOT(ISNUMBER(AJ58)),AJ58<=0),"",IF(AND(ISNUMBER(G58),AJ58<0.1*G58),"",AE58/AJ58)) | AL58: =IF(NOT(ISNUMBER(P58)),"",IF(ISNUMBER(Q58),(P58+Q58)/2,P58)) | AM58: =IF(AND(ISNUMBER(L58),ISNUMBER(AL58),AL58>0),L58/AL58,"") | AN58: =IF(AND(ISNUMBER(AM58),ISNUMBER({ROIC})),AM58-{ROIC},"") | AO58: =IF(AND(ISNUMBER(AC58),ISNUMBER(M58)),AC58+M58,"") | AP58: =IF(AND(ISNUMBER(AF58),ISNUMBER(R58),ISNUMBER(AO58),AO58>0),(AF58-R58)/AO58,"") | AQ58: =IF(AND(ISNUMBER(AC58),ISNUMBER(I58),I58<>0,AC58>0),AC58/I58,"") | AR58: =IF(AND(ISNUMBER(W58),ISNUMBER(Y58)),W58-IF(ISNUMBER(R58),R58,0)-(Y58-IF(ISNUMBER(T58),T58,0)),"") | AS58: =IF(AND(ISNUMBER(X58),ISNUMBER(Z58)),X58-IF(ISNUMBER(S58),S58,0)-(Z58-IF(ISNUMBER(U58),U58,0)),"") | AT58: =IF(AND(ISNUMBER(AR58),ISNUMBER(AS58)),AR58-AS58,"") | AU58: =IF(E58="금융","",IF(AND(ISNUMBER(L58),ISNUMBER(M58),ISNUMBER(N58),ISNUMBER(AT58)),L58+M58-N58-AT58,IF(AND(ISNUMBER(O58),ISNUMBER(N58)),O58-N58,""))) | AV58: =IF(E58="금융","금융업 - 정의되지 않음",IF(AND(ISNUMBER(L58),ISNUMBER(M58),ISNUMBER(N58),ISNUMBER(AT58)),"순이익+감가상각-설비투자-운전자본증감",IF(AND(ISNUMBER(O58),ISNUMBER(N58)),"영업현금흐름-설비투자","산출불가"))) | AW58: =IF(AND(ISNUMBER(AU58),ISNUMBER(G58),G58<>0),AU58/G58,"") | AX58: =IF(AND(ISNUMBER(AC58),ISNUMBER(G58),G58<>0),AC58/G58,"")
A59: AMZN | B59: AMAZON COM INC | C59: 2020 | D59: 2020-12-31 | E59: 일반 | F59: 0001018724-23-000004 | G59: 386.064 | H59: 24.178 | J59: 2.863 | K59: 22.899 | L59: 21.331 | M59: 25.18 | N59: 40.14 | O59: 66.064 | P59: 93.404 | Q59: 62.06 | R59: 84.396 | S59: 55.021 | T59: 1.155 | U59: 1.305 | V59: 31.816 | W59: 132.733 | X59: 96.334 | Y59: 126.385 | Z59: 87.812 | AA59: 31.758 | AB59: 10060 | AC59: =IF(AND(ISNUMBER(H59),ISNUMBER(I59)),H59+I59,IF(ISNUMBER(K59),K59,IF(ISNUMBER(H59),H59,""))) | AD59: =IF(OR(NOT(ISNUMBER(J59)),NOT(ISNUMBER(H59)),H59<=0),기준표!$B$8,MIN(MAX(J59/H59,기준표!$B$6),기준표!$B$7)) | AE59: =IF(ISNUMBER(AC59),AC59*(1-AD59),"") | AF59: =IF(AND(NOT(ISNUMBER(T59)),NOT(ISNUMBER(V59))),"",IF(ISNUMBER(T59),T59,0)+IF(ISNUMBER(V59),V59,0)) | AG59: =IF(E59="금융","",IF(AND(ISNUMBER(P59),ISNUMBER(AF59),ISNUMBER(R59)),P59+AF59-R59,"")) | AH59: =IF(E59="금융","",IF(NOT(ISNUMBER(AG59)),"",IF(ISNUMBER(AA59),(AG59+AA59)/2,AG59))) | AI59: =IF(AND(ISNUMBER(AE59),ISNUMBER(AH59),AH59>0),AE59/AH59,"") | AJ59: =IF(E59="금융","",IF(AND(ISNUMBER(P59),ISNUMBER(AF59)),P59+AF59,"")) | AK59: =IF(OR(NOT(ISNUMBER(AE59)),NOT(ISNUMBER(AJ59)),AJ59<=0),"",IF(AND(ISNUMBER(G59),AJ59<0.1*G59),"",AE59/AJ59)) | AL59: =IF(NOT(ISNUMBER(P59)),"",IF(ISNUMBER(Q59),(P59+Q59)/2,P59)) | AM59: =IF(AND(ISNUMBER(L59),ISNUMBER(AL59),AL59>0),L59/AL59,"") | AN59: =IF(AND(ISNUMBER(AM59),ISNUMBER({ROIC})),AM59-{ROIC},"") | AO59: =IF(AND(ISNUMBER(AC59),ISNUMBER(M59)),AC59+M59,"") | AP59: =IF(AND(ISNUMBER(AF59),ISNUMBER(R59),ISNUMBER(AO59),AO59>0),(AF59-R59)/AO59,"") | AQ59: =IF(AND(ISNUMBER(AC59),ISNUMBER(I59),I59<>0,AC59>0),AC59/I59,"") | AR59: =IF(AND(ISNUMBER(W59),ISNUMBER(Y59)),W59-IF(ISNUMBER(R59),R59,0)-(Y59-IF(ISNUMBER(T59),T59,0)),"") | AS59: =IF(AND(ISNUMBER(X59),ISNUMBER(Z59)),X59-IF(ISNUMBER(S59),S59,0)-(Z59-IF(ISNUMBER(U59),U59,0)),"") | AT59: =IF(AND(ISNUMBER(AR59),ISNUMBER(AS59)),AR59-AS59,"") | AU59: =IF(E59="금융","",IF(AND(ISNUMBER(L59),ISNUMBER(M59),ISNUMBER(N59),ISNUMBER(AT59)),L59+M59-N59-AT59,IF(AND(ISNUMBER(O59),ISNUMBER(N59)),O59-N59,""))) | AV59: =IF(E59="금융","금융업 - 정의되지 않음",IF(AND(ISNUMBER(L59),ISNUMBER(M59),ISNUMBER(N59),ISNUMBER(AT59)),"순이익+감가상각-설비투자-운전자본증감",IF(AND(ISNUMBER(O59),ISNUMBER(N59)),"영업현금흐름-설비투자","산출불가"))) | AW59: =IF(AND(ISNUMBER(AU59),ISNUMBER(G59),G59<>0),AU59/G59,"") | AX59: =IF(AND(ISNUMBER(AC59),ISNUMBER(G59),G59<>0),AC59/G59,"")
A60: AMZN | B60: AMAZON COM INC | C60: 2021 | D60: 2021-12-31 | E60: 일반 | F60: 0001018724-24-000008 | G60: 469.822 | H60: 38.151 | J60: 4.791 | K60: 24.879 | L60: 33.364 | M60: 34.433 | N60: 61.053 | O60: 46.327 | P60: 138.245 | Q60: 93.404 | R60: 96.049 | S60: 84.396 | T60: 1.491 | U60: 1.155 | V60: 48.744 | W60: 161.58 | X60: 132.733 | Y60: 142.266 | Z60: 126.385 | AA60: 41.979 | AB60: 10175 | AC60: =IF(AND(ISNUMBER(H60),ISNUMBER(I60)),H60+I60,IF(ISNUMBER(K60),K60,IF(ISNUMBER(H60),H60,""))) | AD60: =IF(OR(NOT(ISNUMBER(J60)),NOT(ISNUMBER(H60)),H60<=0),기준표!$B$8,MIN(MAX(J60/H60,기준표!$B$6),기준표!$B$7)) | AE60: =IF(ISNUMBER(AC60),AC60*(1-AD60),"") | AF60: =IF(AND(NOT(ISNUMBER(T60)),NOT(ISNUMBER(V60))),"",IF(ISNUMBER(T60),T60,0)+IF(ISNUMBER(V60),V60,0)) | AG60: =IF(E60="금융","",IF(AND(ISNUMBER(P60),ISNUMBER(AF60),ISNUMBER(R60)),P60+AF60-R60,"")) | AH60: =IF(E60="금융","",IF(NOT(ISNUMBER(AG60)),"",IF(ISNUMBER(AA60),(AG60+AA60)/2,AG60))) | AI60: =IF(AND(ISNUMBER(AE60),ISNUMBER(AH60),AH60>0),AE60/AH60,"") | AJ60: =IF(E60="금융","",IF(AND(ISNUMBER(P60),ISNUMBER(AF60)),P60+AF60,"")) | AK60: =IF(OR(NOT(ISNUMBER(AE60)),NOT(ISNUMBER(AJ60)),AJ60<=0),"",IF(AND(ISNUMBER(G60),AJ60<0.1*G60),"",AE60/AJ60)) | AL60: =IF(NOT(ISNUMBER(P60)),"",IF(ISNUMBER(Q60),(P60+Q60)/2,P60)) | AM60: =IF(AND(ISNUMBER(L60),ISNUMBER(AL60),AL60>0),L60/AL60,"") | AN60: =IF(AND(ISNUMBER(AM60),ISNUMBER({ROIC})),AM60-{ROIC},"") | AO60: =IF(AND(ISNUMBER(AC60),ISNUMBER(M60)),AC60+M60,"") | AP60: =IF(AND(ISNUMBER(AF60),ISNUMBER(R60),ISNUMBER(AO60),AO60>0),(AF60-R60)/AO60,"") | AQ60: =IF(AND(ISNUMBER(AC60),ISNUMBER(I60),I60<>0,AC60>0),AC60/I60,"") | AR60: =IF(AND(ISNUMBER(W60),ISNUMBER(Y60)),W60-IF(ISNUMBER(R60),R60,0)-(Y60-IF(ISNUMBER(T60),T60,0)),"") | AS60: =IF(AND(ISNUMBER(X60),ISNUMBER(Z60)),X60-IF(ISNUMBER(S60),S60,0)-(Z60-IF(ISNUMBER(U60),U60,0)),"") | AT60: =IF(AND(ISNUMBER(AR60),ISNUMBER(AS60)),AR60-AS60,"") | AU60: =IF(E60="금융","",IF(AND(ISNUMBER(L60),ISNUMBER(M60),ISNUMBER(N60),ISNUMBER(AT60)),L60+M60-N60-AT60,IF(AND(ISNUMBER(O60),ISNUMBER(N60)),O60-N60,""))) | AV60: =IF(E60="금융","금융업 - 정의되지 않음",IF(AND(ISNUMBER(L60),ISNUMBER(M60),ISNUMBER(N60),ISNUMBER(AT60)),"순이익+감가상각-설비투자-운전자본증감",IF(AND(ISNUMBER(O60),ISNUMBER(N60)),"영업현금흐름-설비투자","산출불가"))) | AW60: =IF(AND(ISNUMBER(AU60),ISNUMBER(G60),G60<>0),AU60/G60,"") | AX60: =IF(AND(ISNUMBER(AC60),ISNUMBER(G60),G60<>0),AC60/G60,"")
A61: AMZN | B61: AMAZON COM INC | C61: 2022 | D61: 2022-12-31 | E61: 일반 | F61: 0001018724-25-000004 | G61: 513.983 | H61: -5.936 | I61: 2.367 | J61: -3.217 | K61: 12.248 | L61: -2.722 | M61: 41.921 | N61: 63.645 | O61: 46.752 | P61: 146.043 | Q61: 138.245 | R61: 70.026 | S61: 96.049 | T61: 2.999 | U61: 1.491 | V61: 67.15 | W61: 146.791 | X61: 161.58 | Y61: 155.393 | Z61: 142.266 | AA61: 92.431 | AB61: 10242 | AC61: =IF(AND(ISNUMBER(H61),ISNUMBER(I61)),H61+I61,IF(ISNUMBER(K61),K61,IF(ISNUMBER(H61),H61,""))) | AD61: =IF(OR(NOT(ISNUMBER(J61)),NOT(ISNUMBER(H61)),H61<=0),기준표!$B$8,MIN(MAX(J61/H61,기준표!$B$6),기준표!$B$7)) | AE61: =IF(ISNUMBER(AC61),AC61*(1-AD61),"") | AF61: =IF(AND(NOT(ISNUMBER(T61)),NOT(ISNUMBER(V61))),"",IF(ISNUMBER(T61),T61,0)+IF(ISNUMBER(V61),V61,0)) | AG61: =IF(E61="금융","",IF(AND(ISNUMBER(P61),ISNUMBER(AF61),ISNUMBER(R61)),P61+AF61-R61,"")) | AH61: =IF(E61="금융","",IF(NOT(ISNUMBER(AG61)),"",IF(ISNUMBER(AA61),(AG61+AA61)/2,AG61))) | AI61: =IF(AND(ISNUMBER(AE61),ISNUMBER(AH61),AH61>0),AE61/AH61,"") | AJ61: =IF(E61="금융","",IF(AND(ISNUMBER(P61),ISNUMBER(AF61)),P61+AF61,"")) | AK61: =IF(OR(NOT(ISNUMBER(AE61)),NOT(ISNUMBER(AJ61)),AJ61<=0),"",IF(AND(ISNUMBER(G61),AJ61<0.1*G61),"",AE61/AJ61)) | AL61: =IF(NOT(ISNUMBER(P61)),"",IF(ISNUMBER(Q61),(P61+Q61)/2,P61)) | AM61: =IF(AND(ISNUMBER(L61),ISNUMBER(AL61),AL61>0),L61/AL61,"") | AN61: =IF(AND(ISNUMBER(AM61),ISNUMBER({ROIC})),AM61-{ROIC},"") | AO61: =IF(AND(ISNUMBER(AC61),ISNUMBER(M61)),AC61+M61,"") | AP61: =IF(AND(ISNUMBER(AF61),ISNUMBER(R61),ISNUMBER(AO61),AO61>0),(AF61-R61)/AO61,"") | AQ61: =IF(AND(ISNUMBER(AC61),ISNUMBER(I61),I61<>0,AC61>0),AC61/I61,"") | AR61: =IF(AND(ISNUMBER(W61),ISNUMBER(Y61)),W61-IF(ISNUMBER(R61),R61,0)-(Y61-IF(ISNUMBER(T61),T61,0)),"") | AS61: =IF(AND(ISNUMBER(X61),ISNUMBER(Z61)),X61-IF(ISNUMBER(S61),S61,0)-(Z61-IF(ISNUMBER(U61),U61,0)),"") | AT61: =IF(AND(ISNUMBER(AR61),ISNUMBER(AS61)),AR61-AS61,"") | AU61: =IF(E61="금융","",IF(AND(ISNUMBER(L61),ISNUMBER(M61),ISNUMBER(N61),ISNUMBER(AT61)),L61+M61-N61-AT61,IF(AND(ISNUMBER(O61),ISNUMBER(N61)),O61-N61,""))) | AV61: =IF(E61="금융","금융업 - 정의되지 않음",IF(AND(ISNUMBER(L61),ISNUMBER(M61),ISNUMBER(N61),ISNUMBER(AT61)),"순이익+감가상각-설비투자-운전자본증감",IF(AND(ISNUMBER(O61),ISNUMBER(N61)),"영업현금흐름-설비투자","산출불가"))) | AW61: =IF(AND(ISNUMBER(AU61),ISNUMBER(G61),G61<>0),AU61/G61,"") | AX61: =IF(AND(ISNUMBER(AC61),ISNUMBER(G61),G61<>0),AC61/G61,"")
A62: AMZN | B62: AMAZON COM INC | C62: 2023 | D62: 2023-12-31 | E62: 일반 | F62: 0001018724-26-000004 | G62: 574.785 | H62: 37.557 | I62: 3.182 | J62: 7.12 | K62: 36.852 | L62: 30.425 | M62: 48.663 | N62: 52.729 | O62: 84.946 | P62: 201.875 | Q62: 146.043 | R62: 86.78 | S62: 70.026 | T62: 8.494 | U62: 2.999 | V62: 58.314 | W62: 172.351 | X62: 146.791 | Y62: 164.917 | Z62: 155.393 | AA62: 146.166 | AB62: 10383 | AC62: =IF(AND(ISNUMBER(H62),ISNUMBER(I62)),H62+I62,IF(ISNUMBER(K62),K62,IF(ISNUMBER(H62),H62,""))) | AD62: =IF(OR(NOT(ISNUMBER(J62)),NOT(ISNUMBER(H62)),H62<=0),기준표!$B$8,MIN(MAX(J62/H62,기준표!$B$6),기준표!$B$7)) | AE62: =IF(ISNUMBER(AC62),AC62*(1-AD62),"") | AF62: =IF(AND(NOT(ISNUMBER(T62)),NOT(ISNUMBER(V62))),"",IF(ISNUMBER(T62),T62,0)+IF(ISNUMBER(V62),V62,0)) | AG62: =IF(E62="금융","",IF(AND(ISNUMBER(P62),ISNUMBER(AF62),ISNUMBER(R62)),P62+AF62-R62,"")) | AH62: =IF(E62="금융","",IF(NOT(ISNUMBER(AG62)),"",IF(ISNUMBER(AA62),(AG62+AA62)/2,AG62))) | AI62: =IF(AND(ISNUMBER(AE62),ISNUMBER(AH62),AH62>0),AE62/AH62,"") | AJ62: =IF(E62="금융","",IF(AND(ISNUMBER(P62),ISNUMBER(AF62)),P62+AF62,"")) | AK62: =IF(OR(NOT(ISNUMBER(AE62)),NOT(ISNUMBER(AJ62)),AJ62<=0),"",IF(AND(ISNUMBER(G62),AJ62<0.1*G62),"",AE62/AJ62)) | AL62: =IF(NOT(ISNUMBER(P62)),"",IF(ISNUMBER(Q62),(P62+Q62)/2,P62)) | AM62: =IF(AND(ISNUMBER(L62),ISNUMBER(AL62),AL62>0),L62/AL62,"") | AN62: =IF(AND(ISNUMBER(AM62),ISNUMBER({ROIC})),AM62-{ROIC},"") | AO62: =IF(AND(ISNUMBER(AC62),ISNUMBER(M62)),AC62+M62,"") | AP62: =IF(AND(ISNUMBER(AF62),ISNUMBER(R62),ISNUMBER(AO62),AO62>0),(AF62-R62)/AO62,"") | AQ62: =IF(AND(ISNUMBER(AC62),ISNUMBER(I62),I62<>0,AC62>0),AC62/I62,"") | AR62: =IF(AND(ISNUMBER(W62),ISNUMBER(Y62)),W62-IF(ISNUMBER(R62),R62,0)-(Y62-IF(ISNUMBER(T62),T62,0)),"") | AS62: =IF(AND(ISNUMBER(X62),ISNUMBER(Z62)),X62-IF(ISNUMBER(S62),S62,0)-(Z62-IF(ISNUMBER(U62),U62,0)),"") | AT62: =IF(AND(ISNUMBER(AR62),ISNUMBER(AS62)),AR62-AS62,"") | AU62: =IF(E62="금융","",IF(AND(ISNUMBER(L62),ISNUMBER(M62),ISNUMBER(N62),ISNUMBER(AT62)),L62+M62-N62-AT62,IF(AND(ISNUMBER(O62),ISNUMBER(N62)),O62-N62,""))) | AV62: =IF(E62="금융","금융업 - 정의되지 않음",IF(AND(ISNUMBER(L62),ISNUMBER(M62),ISNUMBER(N62),ISNUMBER(AT62)),"순이익+감가상각-설비투자-운전자본증감",IF(AND(ISNUMBER(O62),ISNUMBER(N62)),"영업현금흐름-설비투자","산출불가"))) | AW62: =IF(AND(ISNUMBER(AU62),ISNUMBER(G62),G62<>0),AU62/G62,"") | AX62: =IF(AND(ISNUMBER(AC62),ISNUMBER(G62),G62<>0),AC62/G62,"")
A63: AMZN | B63: AMAZON COM INC | C63: 2024 | D63: 2024-12-31 | E63: 일반 | F63: 0001018724-26-000004 | G63: 637.959 | H63: 68.614 | I63: 2.406 | J63: 9.265 | K63: 68.593 | L63: 59.248 | M63: 52.795 | N63: 82.999 | O63: 115.877 | P63: 285.97 | Q63: 201.875 | R63: 101.202 | S63: 86.78 | T63: 5.017 | U63: 8.494 | V63: 52.623 | W63: 190.867 | X63: 172.351 | Y63: 179.431 | Z63: 164.917 | AA63: 181.903 | AB63: 10593 | AC63: =IF(AND(ISNUMBER(H63),ISNUMBER(I63)),H63+I63,IF(ISNUMBER(K63),K63,IF(ISNUMBER(H63),H63,""))) | AD63: =IF(OR(NOT(ISNUMBER(J63)),NOT(ISNUMBER(H63)),H63<=0),기준표!$B$8,MIN(MAX(J63/H63,기준표!$B$6),기준표!$B$7)) | AE63: =IF(ISNUMBER(AC63),AC63*(1-AD63),"") | AF63: =IF(AND(NOT(ISNUMBER(T63)),NOT(ISNUMBER(V63))),"",IF(ISNUMBER(T63),T63,0)+IF(ISNUMBER(V63),V63,0)) | AG63: =IF(E63="금융","",IF(AND(ISNUMBER(P63),ISNUMBER(AF63),ISNUMBER(R63)),P63+AF63-R63,"")) | AH63: =IF(E63="금융","",IF(NOT(ISNUMBER(AG63)),"",IF(ISNUMBER(AA63),(AG63+AA63)/2,AG63))) | AI63: =IF(AND(ISNUMBER(AE63),ISNUMBER(AH63),AH63>0),AE63/AH63,"") | AJ63: =IF(E63="금융","",IF(AND(ISNUMBER(P63),ISNUMBER(AF63)),P63+AF63,"")) | AK63: =IF(OR(NOT(ISNUMBER(AE63)),NOT(ISNUMBER(AJ63)),AJ63<=0),"",IF(AND(ISNUMBER(G63),AJ63<0.1*G63),"",AE63/AJ63)) | AL63: =IF(NOT(ISNUMBER(P63)),"",IF(ISNUMBER(Q63),(P63+Q63)/2,P63)) | AM63: =IF(AND(ISNUMBER(L63),ISNUMBER(AL63),AL63>0),L63/AL63,"") | AN63: =IF(AND(ISNUMBER(AM63),ISNUMBER({ROIC})),AM63-{ROIC},"") | AO63: =IF(AND(ISNUMBER(AC63),ISNUMBER(M63)),AC63+M63,"") | AP63: =IF(AND(ISNUMBER(AF63),ISNUMBER(R63),ISNUMBER(AO63),AO63>0),(AF63-R63)/AO63,"") | AQ63: =IF(AND(ISNUMBER(AC63),ISNUMBER(I63),I63<>0,AC63>0),AC63/I63,"") | AR63: =IF(AND(ISNUMBER(W63),ISNUMBER(Y63)),W63-IF(ISNUMBER(R63),R63,0)-(Y63-IF(ISNUMBER(T63),T63,0)),"") | AS63: =IF(AND(ISNUMBER(X63),ISNUMBER(Z63)),X63-IF(ISNUMBER(S63),S63,0)-(Z63-IF(ISNUMBER(U63),U63,0)),"") | AT63: =IF(AND(ISNUMBER(AR63),ISNUMBER(AS63)),AR63-AS63,"") | AU63: =IF(E63="금융","",IF(AND(ISNUMBER(L63),ISNUMBER(M63),ISNUMBER(N63),ISNUMBER(AT63)),L63+M63-N63-AT63,IF(AND(ISNUMBER(O63),ISNUMBER(N63)),O63-N63,""))) | AV63: =IF(E63="금융","금융업 - 정의되지 않음",IF(AND(ISNUMBER(L63),ISNUMBER(M63),ISNUMBER(N63),ISNUMBER(AT63)),"순이익+감가상각-설비투자-운전자본증감",IF(AND(ISNUMBER(O63),ISNUMBER(N63)),"영업현금흐름-설비투자","산출불가"))) | AW63: =IF(AND(ISNUMBER(AU63),ISNUMBER(G63),G63<>0),AU63/G63,"") | AX63: =IF(AND(ISNUMBER(AC63),ISNUMBER(G63),G63<>0),AC63/G63,"")
A64: AMZN | B64: AMAZON COM INC | C64: 2025 | D64: 2025-12-31 | E64: 일반 | F64: 0001018724-26-000004 | G64: 716.924 | H64: 97.311 | I64: 2.274 | J64: 19.087 | K64: 79.975 | L64: 77.67 | M64: 65.756 | N64: 131.819 | O64: 139.514 | P64: 411.065 | Q64: 285.97 | R64: 123.029 | S64: 101.202 | T64: 2.748 | U64: 5.017 | V64: 65.648 | W64: 229.083 | X64: 190.867 | Y64: 218.005 | Z64: 179.431 | AA64: 242.408 | AB64: 10731 | AC64: =IF(AND(ISNUMBER(H64),ISNUMBER(I64)),H64+I64,IF(ISNUMBER(K64),K64,IF(ISNUMBER(H64),H64,""))) | AD64: =IF(OR(NOT(ISNUMBER(J64)),NOT(ISNUMBER(H64)),H64<=0),기준표!$B$8,MIN(MAX(J64/H64,기준표!$B$6),기준표!$B$7)) | AE64: =IF(ISNUMBER(AC64),AC64*(1-AD64),"") | AF64: =IF(AND(NOT(ISNUMBER(T64)),NOT(ISNUMBER(V64))),"",IF(ISNUMBER(T64),T64,0)+IF(ISNUMBER(V64),V64,0)) | AG64: =IF(E64="금융","",IF(AND(ISNUMBER(P64),ISNUMBER(AF64),ISNUMBER(R64)),P64+AF64-R64,"")) | AH64: =IF(E64="금융","",IF(NOT(ISNUMBER(AG64)),"",IF(ISNUMBER(AA64),(AG64+AA64)/2,AG64))) | AI64: =IF(AND(ISNUMBER(AE64),ISNUMBER(AH64),AH64>0),AE64/AH64,"") | AJ64: =IF(E64="금융","",IF(AND(ISNUMBER(P64),ISNUMBER(AF64)),P64+AF64,"")) | AK64: =IF(OR(NOT(ISNUMBER(AE64)),NOT(ISNUMBER(AJ64)),AJ64<=0),"",IF(AND(ISNUMBER(G64),AJ64<0.1*G64),"",AE64/AJ64)) | AL64: =IF(NOT(ISNUMBER(P64)),"",IF(ISNUMBER(Q64),(P64+Q64)/2,P64)) | AM64: =IF(AND(ISNUMBER(L64),ISNUMBER(AL64),AL64>0),L64/AL64,"") | AN64: =IF(AND(ISNUMBER(AM64),ISNUMBER({ROIC})),AM64-{ROIC},"") | AO64: =IF(AND(ISNUMBER(AC64),ISNUMBER(M64)),AC64+M64,"") | AP64: =IF(AND(ISNUMBER(AF64),ISNUMBER(R64),ISNUMBER(AO64),AO64>0),(AF64-R64)/AO64,"") | AQ64: =IF(AND(ISNUMBER(AC64),ISNUMBER(I64),I64<>0,AC64>0),AC64/I64,"") | AR64: =IF(AND(ISNUMBER(W64),ISNUMBER(Y64)),W64-IF(ISNUMBER(R64),R64,0)-(Y64-IF(ISNUMBER(T64),T64,0)),"") | AS64: =IF(AND(ISNUMBER(X64),ISNUMBER(Z64)),X64-IF(ISNUMBER(S64),S64,0)-(Z64-IF(ISNUMBER(U64),U64,0)),"") | AT64: =IF(AND(ISNUMBER(AR64),ISNUMBER(AS64)),AR64-AS64,"") | AU64: =IF(E64="금융","",IF(AND(ISNUMBER(L64),ISNUMBER(M64),ISNUMBER(N64),ISNUMBER(AT64)),L64+M64-N64-AT64,IF(AND(ISNUMBER(O64),ISNUMBER(N64)),O64-N64,""))) | AV64: =IF(E64="금융","금융업 - 정의되지 않음",IF(AND(ISNUMBER(L64),ISNUMBER(M64),ISNUMBER(N64),ISNUMBER(AT64)),"순이익+감가상각-설비투자-운전자본증감",IF(AND(ISNUMBER(O64),ISNUMBER(N64)),"영업현금흐름-설비투자","산출불가"))) | AW64: =IF(AND(ISNUMBER(AU64),ISNUMBER(G64),G64<>0),AU64/G64,"") | AX64: =IF(AND(ISNUMBER(AC64),ISNUMBER(G64),G64<>0),AC64/G64,"")
A65: AVGO | B65: Broadcom Inc. | C65: 2016 | D65: 2016-10-30 | E65: 일반 | F65: 0001730168-18-000084 | H65: -1.107 | J65: 0.642 | K65: -0.409 | L65: -1.861 | M65: 0.402 | N65: 0.723 | O65: 3.411 | P65: 21.876 | R65: 3.097 | AB65: 3830 | AC65: =IF(AND(ISNUMBER(H65),ISNUMBER(I65)),H65+I65,IF(ISNUMBER(K65),K65,IF(ISNUMBER(H65),H65,""))) | AD65: =IF(OR(NOT(ISNUMBER(J65)),NOT(ISNUMBER(H65)),H65<=0),기준표!$B$8,MIN(MAX(J65/H65,기준표!$B$6),기준표!$B$7)) | AE65: =IF(ISNUMBER(AC65),AC65*(1-AD65),"") | AF65: =IF(AND(NOT(ISNUMBER(T65)),NOT(ISNUMBER(V65))),"",IF(ISNUMBER(T65),T65,0)+IF(ISNUMBER(V65),V65,0)) | AG65: =IF(E65="금융","",IF(AND(ISNUMBER(P65),ISNUMBER(AF65),ISNUMBER(R65)),P65+AF65-R65,"")) | AH65: =IF(E65="금융","",IF(NOT(ISNUMBER(AG65)),"",IF(ISNUMBER(AA65),(AG65+AA65)/2,AG65))) | AI65: =IF(AND(ISNUMBER(AE65),ISNUMBER(AH65),AH65>0),AE65/AH65,"") | AJ65: =IF(E65="금융","",IF(AND(ISNUMBER(P65),ISNUMBER(AF65)),P65+AF65,"")) | AK65: =IF(OR(NOT(ISNUMBER(AE65)),NOT(ISNUMBER(AJ65)),AJ65<=0),"",IF(AND(ISNUMBER(G65),AJ65<0.1*G65),"",AE65/AJ65)) | AL65: =IF(NOT(ISNUMBER(P65)),"",IF(ISNUMBER(Q65),(P65+Q65)/2,P65)) | AM65: =IF(AND(ISNUMBER(L65),ISNUMBER(AL65),AL65>0),L65/AL65,"") | AN65: =IF(AND(ISNUMBER(AM65),ISNUMBER({ROIC})),AM65-{ROIC},"") | AO65: =IF(AND(ISNUMBER(AC65),ISNUMBER(M65)),AC65+M65,"") | AP65: =IF(AND(ISNUMBER(AF65),ISNUMBER(R65),ISNUMBER(AO65),AO65>0),(AF65-R65)/AO65,"") | AQ65: =IF(AND(ISNUMBER(AC65),ISNUMBER(I65),I65<>0,AC65>0),AC65/I65,"") | AR65: =IF(AND(ISNUMBER(W65),ISNUMBER(Y65)),W65-IF(ISNUMBER(R65),R65,0)-(Y65-IF(ISNUMBER(T65),T65,0)),"") | AS65: =IF(AND(ISNUMBER(X65),ISNUMBER(Z65)),X65-IF(ISNUMBER(S65),S65,0)-(Z65-IF(ISNUMBER(U65),U65,0)),"") | AT65: =IF(AND(ISNUMBER(AR65),ISNUMBER(AS65)),AR65-AS65,"") | AU65: =IF(E65="금융","",IF(AND(ISNUMBER(L65),ISNUMBER(M65),ISNUMBER(N65),ISNUMBER(AT65)),L65+M65-N65-AT65,IF(AND(ISNUMBER(O65),ISNUMBER(N65)),O65-N65,""))) | AV65: =IF(E65="금융","금융업 - 정의되지 않음",IF(AND(ISNUMBER(L65),ISNUMBER(M65),ISNUMBER(N65),ISNUMBER(AT65)),"순이익+감가상각-설비투자-운전자본증감",IF(AND(ISNUMBER(O65),ISNUMBER(N65)),"영업현금흐름-설비투자","산출불가"))) | AW65: =IF(AND(ISNUMBER(AU65),ISNUMBER(G65),G65<>0),AU65/G65,"") | AX65: =IF(AND(ISNUMBER(AC65),ISNUMBER(G65),G65<>0),AC65/G65,"")
A66: AVGO | B66: Broadcom Inc. | C66: 2017 | D66: 2017-10-29 | E66: 일반 | F66: 0001730168-19-000144 | G66: 17.636 | H66: 1.825 | J66: 0.035 | K66: 2.371 | L66: 1.784 | M66: 0.451 | N66: 1.069 | O66: 6.551 | P66: 23.186 | Q66: 21.876 | R66: 11.204 | S66: 3.097 | T66: 0.117 | W66: 15.823 | Y66: 2.529 | AB66: 4210 | AC66: =IF(AND(ISNUMBER(H66),ISNUMBER(I66)),H66+I66,IF(ISNUMBER(K66),K66,IF(ISNUMBER(H66),H66,""))) | AD66: =IF(OR(NOT(ISNUMBER(J66)),NOT(ISNUMBER(H66)),H66<=0),기준표!$B$8,MIN(MAX(J66/H66,기준표!$B$6),기준표!$B$7)) | AE66: =IF(ISNUMBER(AC66),AC66*(1-AD66),"") | AF66: =IF(AND(NOT(ISNUMBER(T66)),NOT(ISNUMBER(V66))),"",IF(ISNUMBER(T66),T66,0)+IF(ISNUMBER(V66),V66,0)) | AG66: =IF(E66="금융","",IF(AND(ISNUMBER(P66),ISNUMBER(AF66),ISNUMBER(R66)),P66+AF66-R66,"")) | AH66: =IF(E66="금융","",IF(NOT(ISNUMBER(AG66)),"",IF(ISNUMBER(AA66),(AG66+AA66)/2,AG66))) | AI66: =IF(AND(ISNUMBER(AE66),ISNUMBER(AH66),AH66>0),AE66/AH66,"") | AJ66: =IF(E66="금융","",IF(AND(ISNUMBER(P66),ISNUMBER(AF66)),P66+AF66,"")) | AK66: =IF(OR(NOT(ISNUMBER(AE66)),NOT(ISNUMBER(AJ66)),AJ66<=0),"",IF(AND(ISNUMBER(G66),AJ66<0.1*G66),"",AE66/AJ66)) | AL66: =IF(NOT(ISNUMBER(P66)),"",IF(ISNUMBER(Q66),(P66+Q66)/2,P66)) | AM66: =IF(AND(ISNUMBER(L66),ISNUMBER(AL66),AL66>0),L66/AL66,"") | AN66: =IF(AND(ISNUMBER(AM66),ISNUMBER({ROIC})),AM66-{ROIC},"") | AO66: =IF(AND(ISNUMBER(AC66),ISNUMBER(M66)),AC66+M66,"") | AP66: =IF(AND(ISNUMBER(AF66),ISNUMBER(R66),ISNUMBER(AO66),AO66>0),(AF66-R66)/AO66,"") | AQ66: =IF(AND(ISNUMBER(AC66),ISNUMBER(I66),I66<>0,AC66>0),AC66/I66,"") | AR66: =IF(AND(ISNUMBER(W66),ISNUMBER(Y66)),W66-IF(ISNUMBER(R66),R66,0)-(Y66-IF(ISNUMBER(T66),T66,0)),"") | AS66: =IF(AND(ISNUMBER(X66),ISNUMBER(Z66)),X66-IF(ISNUMBER(S66),S66,0)-(Z66-IF(ISNUMBER(U66),U66,0)),"") | AT66: =IF(AND(ISNUMBER(AR66),ISNUMBER(AS66)),AR66-AS66,"") | AU66: =IF(E66="금융","",IF(AND(ISNUMBER(L66),ISNUMBER(M66),ISNUMBER(N66),ISNUMBER(AT66)),L66+M66-N66-AT66,IF(AND(ISNUMBER(O66),ISNUMBER(N66)),O66-N66,""))) | AV66: =IF(E66="금융","금융업 - 정의되지 않음",IF(AND(ISNUMBER(L66),ISNUMBER(M66),ISNUMBER(N66),ISNUMBER(AT66)),"순이익+감가상각-설비투자-운전자본증감",IF(AND(ISNUMBER(O66),ISNUMBER(N66)),"영업현금흐름-설비투자","산출불가"))) | AW66: =IF(AND(ISNUMBER(AU66),ISNUMBER(G66),G66<>0),AU66/G66,"") | AX66: =IF(AND(ISNUMBER(AC66),ISNUMBER(G66),G66<>0),AC66/G66,"")
A67: AVGO | B67: Broadcom Inc. | C67: 2018 | D67: 2018-11-04 | E67: 일반 | F67: 0001730168-20-000226 | G67: 20.848 | H67: 4.545 | J67: -8.084 | K67: 5.135 | L67: 12.61 | M67: 0.515 | N67: 0.635 | O67: 8.88 | P67: 26.657 | Q67: 23.186 | R67: 4.292 | S67: 11.204 | T67: 0 | U67: 0.117 | W67: 9.107 | X67: 15.823 | Y67: 2.338 | Z67: 2.529 | AA67: 12.099 | AB67: 4310 | AC67: =IF(AND(ISNUMBER(H67),ISNUMBER(I67)),H67+I67,IF(ISNUMBER(K67),K67,IF(ISNUMBER(H67),H67,""))) | AD67: =IF(OR(NOT(ISNUMBER(J67)),NOT(ISNUMBER(H67)),H67<=0),기준표!$B$8,MIN(MAX(J67/H67,기준표!$B$6),기준표!$B$7)) | AE67: =IF(ISNUMBER(AC67),AC67*(1-AD67),"") | AF67: =IF(AND(NOT(ISNUMBER(T67)),NOT(ISNUMBER(V67))),"",IF(ISNUMBER(T67),T67,0)+IF(ISNUMBER(V67),V67,0)) | AG67: =IF(E67="금융","",IF(AND(ISNUMBER(P67),ISNUMBER(AF67),ISNUMBER(R67)),P67+AF67-R67,"")) | AH67: =IF(E67="금융","",IF(NOT(ISNUMBER(AG67)),"",IF(ISNUMBER(AA67),(AG67+AA67)/2,AG67))) | AI67: =IF(AND(ISNUMBER(AE67),ISNUMBER(AH67),AH67>0),AE67/AH67,"") | AJ67: =IF(E67="금융","",IF(AND(ISNUMBER(P67),ISNUMBER(AF67)),P67+AF67,"")) | AK67: =IF(OR(NOT(ISNUMBER(AE67)),NOT(ISNUMBER(AJ67)),AJ67<=0),"",IF(AND(ISNUMBER(G67),AJ67<0.1*G67),"",AE67/AJ67)) | AL67: =IF(NOT(ISNUMBER(P67)),"",IF(ISNUMBER(Q67),(P67+Q67)/2,P67)) | AM67: =IF(AND(ISNUMBER(L67),ISNUMBER(AL67),AL67>0),L67/AL67,"") | AN67: =IF(AND(ISNUMBER(AM67),ISNUMBER({ROIC})),AM67-{ROIC},"") | AO67: =IF(AND(ISNUMBER(AC67),ISNUMBER(M67)),AC67+M67,"") | AP67: =IF(AND(ISNUMBER(AF67),ISNUMBER(R67),ISNUMBER(AO67),AO67>0),(AF67-R67)/AO67,"") | AQ67: =IF(AND(ISNUMBER(AC67),ISNUMBER(I67),I67<>0,AC67>0),AC67/I67,"") | AR67: =IF(AND(ISNUMBER(W67),ISNUMBER(Y67)),W67-IF(ISNUMBER(R67),R67,0)-(Y67-IF(ISNUMBER(T67),T67,0)),"") | AS67: =IF(AND(ISNUMBER(X67),ISNUMBER(Z67)),X67-IF(ISNUMBER(S67),S67,0)-(Z67-IF(ISNUMBER(U67),U67,0)),"") | AT67: =IF(AND(ISNUMBER(AR67),ISNUMBER(AS67)),AR67-AS67,"") | AU67: =IF(E67="금융","",IF(AND(ISNUMBER(L67),ISNUMBER(M67),ISNUMBER(N67),ISNUMBER(AT67)),L67+M67-N67-AT67,IF(AND(ISNUMBER(O67),ISNUMBER(N67)),O67-N67,""))) | AV67: =IF(E67="금융","금융업 - 정의되지 않음",IF(AND(ISNUMBER(L67),ISNUMBER(M67),ISNUMBER(N67),ISNUMBER(AT67)),"순이익+감가상각-설비투자-운전자본증감",IF(AND(ISNUMBER(O67),ISNUMBER(N67)),"영업현금흐름-설비투자","산출불가"))) | AW67: =IF(AND(ISNUMBER(AU67),ISNUMBER(G67),G67<>0),AU67/G67,"") | AX67: =IF(AND(ISNUMBER(AC67),ISNUMBER(G67),G67<>0),AC67/G67,"")
A68: AVGO | B68: Broadcom Inc. | C68: 2019 | D68: 2019-11-03 | E68: 일반 | F68: 0001730168-21-000153 | G68: 22.597 | H68: 2.226 | J68: -0.51 | K68: 3.444 | L68: 2.724 | M68: 0.569 | N68: 0.432 | O68: 9.697 | P68: 24.941 | Q68: 26.657 | R68: 5.055 | S68: 4.292 | T68: 2.787 | U68: 0 | W68: 9.917 | X68: 9.107 | Y68: 6.899 | Z68: 2.338 | AA68: 22.365 | AB68: 4190 | AC68: =IF(AND(ISNUMBER(H68),ISNUMBER(I68)),H68+I68,IF(ISNUMBER(K68),K68,IF(ISNUMBER(H68),H68,""))) | AD68: =IF(OR(NOT(ISNUMBER(J68)),NOT(ISNUMBER(H68)),H68<=0),기준표!$B$8,MIN(MAX(J68/H68,기준표!$B$6),기준표!$B$7)) | AE68: =IF(ISNUMBER(AC68),AC68*(1-AD68),"") | AF68: =IF(AND(NOT(ISNUMBER(T68)),NOT(ISNUMBER(V68))),"",IF(ISNUMBER(T68),T68,0)+IF(ISNUMBER(V68),V68,0)) | AG68: =IF(E68="금융","",IF(AND(ISNUMBER(P68),ISNUMBER(AF68),ISNUMBER(R68)),P68+AF68-R68,"")) | AH68: =IF(E68="금융","",IF(NOT(ISNUMBER(AG68)),"",IF(ISNUMBER(AA68),(AG68+AA68)/2,AG68))) | AI68: =IF(AND(ISNUMBER(AE68),ISNUMBER(AH68),AH68>0),AE68/AH68,"") | AJ68: =IF(E68="금융","",IF(AND(ISNUMBER(P68),ISNUMBER(AF68)),P68+AF68,"")) | AK68: =IF(OR(NOT(ISNUMBER(AE68)),NOT(ISNUMBER(AJ68)),AJ68<=0),"",IF(AND(ISNUMBER(G68),AJ68<0.1*G68),"",AE68/AJ68)) | AL68: =IF(NOT(ISNUMBER(P68)),"",IF(ISNUMBER(Q68),(P68+Q68)/2,P68)) | AM68: =IF(AND(ISNUMBER(L68),ISNUMBER(AL68),AL68>0),L68/AL68,"") | AN68: =IF(AND(ISNUMBER(AM68),ISNUMBER({ROIC})),AM68-{ROIC},"") | AO68: =IF(AND(ISNUMBER(AC68),ISNUMBER(M68)),AC68+M68,"") | AP68: =IF(AND(ISNUMBER(AF68),ISNUMBER(R68),ISNUMBER(AO68),AO68>0),(AF68-R68)/AO68,"") | AQ68: =IF(AND(ISNUMBER(AC68),ISNUMBER(I68),I68<>0,AC68>0),AC68/I68,"") | AR68: =IF(AND(ISNUMBER(W68),ISNUMBER(Y68)),W68-IF(ISNUMBER(R68),R68,0)-(Y68-IF(ISNUMBER(T68),T68,0)),"") | AS68: =IF(AND(ISNUMBER(X68),ISNUMBER(Z68)),X68-IF(ISNUMBER(S68),S68,0)-(Z68-IF(ISNUMBER(U68),U68,0)),"") | AT68: =IF(AND(ISNUMBER(AR68),ISNUMBER(AS68)),AR68-AS68,"") | AU68: =IF(E68="금융","",IF(AND(ISNUMBER(L68),ISNUMBER(M68),ISNUMBER(N68),ISNUMBER(AT68)),L68+M68-N68-AT68,IF(AND(ISNUMBER(O68),ISNUMBER(N68)),O68-N68,""))) | AV68: =IF(E68="금융","금융업 - 정의되지 않음",IF(AND(ISNUMBER(L68),ISNUMBER(M68),ISNUMBER(N68),ISNUMBER(AT68)),"순이익+감가상각-설비투자-운전자본증감",IF(AND(ISNUMBER(O68),ISNUMBER(N68)),"영업현금흐름-설비투자","산출불가"))) | AW68: =IF(AND(ISNUMBER(AU68),ISNUMBER(G68),G68<>0),AU68/G68,"") | AX68: =IF(AND(ISNUMBER(AC68),ISNUMBER(G68),G68<>0),AC68/G68,"")
A69: AVGO | B69: Broadcom Inc. | C69: 2020 | D69: 2020-11-01 | E69: 일반 | F69: 0001730168-22-000118 | G69: 23.888 | H69: 2.443 | J69: -0.518 | K69: 4.014 | L69: 2.96 | M69: 0.57 | N69: 0.463 | O69: 12.061 | P69: 23.874 | Q69: 24.941 | R69: 7.618 | S69: 5.055 | T69: 0.827 | U69: 2.787 | W69: 11.895 | X69: 9.917 | Y69: 6.371 | Z69: 6.899 | AA69: 22.673 | AB69: 4210 | AC69: =IF(AND(ISNUMBER(H69),ISNUMBER(I69)),H69+I69,IF(ISNUMBER(K69),K69,IF(ISNUMBER(H69),H69,""))) | AD69: =IF(OR(NOT(ISNUMBER(J69)),NOT(ISNUMBER(H69)),H69<=0),기준표!$B$8,MIN(MAX(J69/H69,기준표!$B$6),기준표!$B$7)) | AE69: =IF(ISNUMBER(AC69),AC69*(1-AD69),"") | AF69: =IF(AND(NOT(ISNUMBER(T69)),NOT(ISNUMBER(V69))),"",IF(ISNUMBER(T69),T69,0)+IF(ISNUMBER(V69),V69,0)) | AG69: =IF(E69="금융","",IF(AND(ISNUMBER(P69),ISNUMBER(AF69),ISNUMBER(R69)),P69+AF69-R69,"")) | AH69: =IF(E69="금융","",IF(NOT(ISNUMBER(AG69)),"",IF(ISNUMBER(AA69),(AG69+AA69)/2,AG69))) | AI69: =IF(AND(ISNUMBER(AE69),ISNUMBER(AH69),AH69>0),AE69/AH69,"") | AJ69: =IF(E69="금융","",IF(AND(ISNUMBER(P69),ISNUMBER(AF69)),P69+AF69,"")) | AK69: =IF(OR(NOT(ISNUMBER(AE69)),NOT(ISNUMBER(AJ69)),AJ69<=0),"",IF(AND(ISNUMBER(G69),AJ69<0.1*G69),"",AE69/AJ69)) | AL69: =IF(NOT(ISNUMBER(P69)),"",IF(ISNUMBER(Q69),(P69+Q69)/2,P69)) | AM69: =IF(AND(ISNUMBER(L69),ISNUMBER(AL69),AL69>0),L69/AL69,"") | AN69: =IF(AND(ISNUMBER(AM69),ISNUMBER({ROIC})),AM69-{ROIC},"") | AO69: =IF(AND(ISNUMBER(AC69),ISNUMBER(M69)),AC69+M69,"") | AP69: =IF(AND(ISNUMBER(AF69),ISNUMBER(R69),ISNUMBER(AO69),AO69>0),(AF69-R69)/AO69,"") | AQ69: =IF(AND(ISNUMBER(AC69),ISNUMBER(I69),I69<>0,AC69>0),AC69/I69,"") | AR69: =IF(AND(ISNUMBER(W69),ISNUMBER(Y69)),W69-IF(ISNUMBER(R69),R69,0)-(Y69-IF(ISNUMBER(T69),T69,0)),"") | AS69: =IF(AND(ISNUMBER(X69),ISNUMBER(Z69)),X69-IF(ISNUMBER(S69),S69,0)-(Z69-IF(ISNUMBER(U69),U69,0)),"") | AT69: =IF(AND(ISNUMBER(AR69),ISNUMBER(AS69)),AR69-AS69,"") | AU69: =IF(E69="금융","",IF(AND(ISNUMBER(L69),ISNUMBER(M69),ISNUMBER(N69),ISNUMBER(AT69)),L69+M69-N69-AT69,IF(AND(ISNUMBER(O69),ISNUMBER(N69)),O69-N69,""))) | AV69: =IF(E69="금융","금융업 - 정의되지 않음",IF(AND(ISNUMBER(L69),ISNUMBER(M69),ISNUMBER(N69),ISNUMBER(AT69)),"순이익+감가상각-설비투자-운전자본증감",IF(AND(ISNUMBER(O69),ISNUMBER(N69)),"영업현금흐름-설비투자","산출불가"))) | AW69: =IF(AND(ISNUMBER(AU69),ISNUMBER(G69),G69<>0),AU69/G69,"") | AX69: =IF(AND(ISNUMBER(AC69),ISNUMBER(G69),G69<>0),AC69/G69,"")
A70: AVGO | B70: Broadcom Inc. | C70: 2021 | D70: 2021-10-31 | E70: 일반 | F70: 0001730168-23-000096 | G70: 27.45 | H70: 6.765 | J70: 0.029 | K70: 8.519 | L70: 6.736 | M70: 0.539 | N70: 0.443 | O70: 13.764 | P70: 24.962 | Q70: 23.874 | R70: 12.163 | S70: 7.618 | T70: 0.264 | U70: 0.827 | V70: 39.44 | W70: 16.586 | X70: 11.895 | Y70: 6.281 | Z70: 6.371 | AA70: 17.083 | AB70: 4290 | AC70: =IF(AND(ISNUMBER(H70),ISNUMBER(I70)),H70+I70,IF(ISNUMBER(K70),K70,IF(ISNUMBER(H70),H70,""))) | AD70: =IF(OR(NOT(ISNUMBER(J70)),NOT(ISNUMBER(H70)),H70<=0),기준표!$B$8,MIN(MAX(J70/H70,기준표!$B$6),기준표!$B$7)) | AE70: =IF(ISNUMBER(AC70),AC70*(1-AD70),"") | AF70: =IF(AND(NOT(ISNUMBER(T70)),NOT(ISNUMBER(V70))),"",IF(ISNUMBER(T70),T70,0)+IF(ISNUMBER(V70),V70,0)) | AG70: =IF(E70="금융","",IF(AND(ISNUMBER(P70),ISNUMBER(AF70),ISNUMBER(R70)),P70+AF70-R70,"")) | AH70: =IF(E70="금융","",IF(NOT(ISNUMBER(AG70)),"",IF(ISNUMBER(AA70),(AG70+AA70)/2,AG70))) | AI70: =IF(AND(ISNUMBER(AE70),ISNUMBER(AH70),AH70>0),AE70/AH70,"") | AJ70: =IF(E70="금융","",IF(AND(ISNUMBER(P70),ISNUMBER(AF70)),P70+AF70,"")) | AK70: =IF(OR(NOT(ISNUMBER(AE70)),NOT(ISNUMBER(AJ70)),AJ70<=0),"",IF(AND(ISNUMBER(G70),AJ70<0.1*G70),"",AE70/AJ70)) | AL70: =IF(NOT(ISNUMBER(P70)),"",IF(ISNUMBER(Q70),(P70+Q70)/2,P70)) | AM70: =IF(AND(ISNUMBER(L70),ISNUMBER(AL70),AL70>0),L70/AL70,"") | AN70: =IF(AND(ISNUMBER(AM70),ISNUMBER({ROIC})),AM70-{ROIC},"") | AO70: =IF(AND(ISNUMBER(AC70),ISNUMBER(M70)),AC70+M70,"") | AP70: =IF(AND(ISNUMBER(AF70),ISNUMBER(R70),ISNUMBER(AO70),AO70>0),(AF70-R70)/AO70,"") | AQ70: =IF(AND(ISNUMBER(AC70),ISNUMBER(I70),I70<>0,AC70>0),AC70/I70,"") | AR70: =IF(AND(ISNUMBER(W70),ISNUMBER(Y70)),W70-IF(ISNUMBER(R70),R70,0)-(Y70-IF(ISNUMBER(T70),T70,0)),"") | AS70: =IF(AND(ISNUMBER(X70),ISNUMBER(Z70)),X70-IF(ISNUMBER(S70),S70,0)-(Z70-IF(ISNUMBER(U70),U70,0)),"") | AT70: =IF(AND(ISNUMBER(AR70),ISNUMBER(AS70)),AR70-AS70,"") | AU70: =IF(E70="금융","",IF(AND(ISNUMBER(L70),ISNUMBER(M70),ISNUMBER(N70),ISNUMBER(AT70)),L70+M70-N70-AT70,IF(AND(ISNUMBER(O70),ISNUMBER(N70)),O70-N70,""))) | AV70: =IF(E70="금융","금융업 - 정의되지 않음",IF(AND(ISNUMBER(L70),ISNUMBER(M70),ISNUMBER(N70),ISNUMBER(AT70)),"순이익+감가상각-설비투자-운전자본증감",IF(AND(ISNUMBER(O70),ISNUMBER(N70)),"영업현금흐름-설비투자","산출불가"))) | AW70: =IF(AND(ISNUMBER(AU70),ISNUMBER(G70),G70<>0),AU70/G70,"") | AX70: =IF(AND(ISNUMBER(AC70),ISNUMBER(G70),G70<>0),AC70/G70,"")
A71: AVGO | B71: Broadcom Inc. | C71: 2022 | D71: 2022-10-30 | E71: 일반 | F71: 0001730168-24-000139 | G71: 33.203 | H71: 12.434 | J71: 0.939 | K71: 14.225 | L71: 11.495 | M71: 0.529 | N71: 0.424 | O71: 16.736 | P71: 22.709 | Q71: 24.962 | R71: 12.416 | S71: 12.163 | T71: 0.403 | U71: 0.264 | V71: 39.075 | W71: 18.504 | X71: 16.586 | Y71: 7.052 | Z71: 6.281 | AA71: 52.503 | AB71: 4232 | AC71: =IF(AND(ISNUMBER(H71),ISNUMBER(I71)),H71+I71,IF(ISNUMBER(K71),K71,IF(ISNUMBER(H71),H71,""))) | AD71: =IF(OR(NOT(ISNUMBER(J71)),NOT(ISNUMBER(H71)),H71<=0),기준표!$B$8,MIN(MAX(J71/H71,기준표!$B$6),기준표!$B$7)) | AE71: =IF(ISNUMBER(AC71),AC71*(1-AD71),"") | AF71: =IF(AND(NOT(ISNUMBER(T71)),NOT(ISNUMBER(V71))),"",IF(ISNUMBER(T71),T71,0)+IF(ISNUMBER(V71),V71,0)) | AG71: =IF(E71="금융","",IF(AND(ISNUMBER(P71),ISNUMBER(AF71),ISNUMBER(R71)),P71+AF71-R71,"")) | AH71: =IF(E71="금융","",IF(NOT(ISNUMBER(AG71)),"",IF(ISNUMBER(AA71),(AG71+AA71)/2,AG71))) | AI71: =IF(AND(ISNUMBER(AE71),ISNUMBER(AH71),AH71>0),AE71/AH71,"") | AJ71: =IF(E71="금융","",IF(AND(ISNUMBER(P71),ISNUMBER(AF71)),P71+AF71,"")) | AK71: =IF(OR(NOT(ISNUMBER(AE71)),NOT(ISNUMBER(AJ71)),AJ71<=0),"",IF(AND(ISNUMBER(G71),AJ71<0.1*G71),"",AE71/AJ71)) | AL71: =IF(NOT(ISNUMBER(P71)),"",IF(ISNUMBER(Q71),(P71+Q71)/2,P71)) | AM71: =IF(AND(ISNUMBER(L71),ISNUMBER(AL71),AL71>0),L71/AL71,"") | AN71: =IF(AND(ISNUMBER(AM71),ISNUMBER({ROIC})),AM71-{ROIC},"") | AO71: =IF(AND(ISNUMBER(AC71),ISNUMBER(M71)),AC71+M71,"") | AP71: =IF(AND(ISNUMBER(AF71),ISNUMBER(R71),ISNUMBER(AO71),AO71>0),(AF71-R71)/AO71,"") | AQ71: =IF(AND(ISNUMBER(AC71),ISNUMBER(I71),I71<>0,AC71>0),AC71/I71,"") | AR71: =IF(AND(ISNUMBER(W71),ISNUMBER(Y71)),W71-IF(ISNUMBER(R71),R71,0)-(Y71-IF(ISNUMBER(T71),T71,0)),"") | AS71: =IF(AND(ISNUMBER(X71),ISNUMBER(Z71)),X71-IF(ISNUMBER(S71),S71,0)-(Z71-IF(ISNUMBER(U71),U71,0)),"") | AT71: =IF(AND(ISNUMBER(AR71),ISNUMBER(AS71)),AR71-AS71,"") | AU71: =IF(E71="금융","",IF(AND(ISNUMBER(L71),ISNUMBER(M71),ISNUMBER(N71),ISNUMBER(AT71)),L71+M71-N71-AT71,IF(AND(ISNUMBER(O71),ISNUMBER(N71)),O71-N71,""))) | AV71: =IF(E71="금융","금융업 - 정의되지 않음",IF(AND(ISNUMBER(L71),ISNUMBER(M71),ISNUMBER(N71),ISNUMBER(AT71)),"순이익+감가상각-설비투자-운전자본증감",IF(AND(ISNUMBER(O71),ISNUMBER(N71)),"영업현금흐름-설비투자","산출불가"))) | AW71: =IF(AND(ISNUMBER(AU71),ISNUMBER(G71),G71<>0),AU71/G71,"") | AX71: =IF(AND(ISNUMBER(AC71),ISNUMBER(G71),G71<>0),AC71/G71,"")
A72: AVGO | B72: Broadcom Inc. | C72: 2023 | D72: 2023-10-29 | E72: 일반 | F72: 0001730168-25-000121 | G72: 35.819 | H72: 15.097 | I72: 1.622 | J72: 1.015 | K72: 16.207 | L72: 14.082 | M72: 0.502 | N72: 0.452 | O72: 18.085 | P72: 23.988 | Q72: 22.709 | R72: 14.189 | S72: 12.416 | T72: 1.563 | U72: 0.403 | V72: 37.621 | W72: 20.847 | X72: 18.504 | Y72: 7.405 | Z72: 7.052 | AA72: 49.771 | AB72: 4272 | AC72: =IF(AND(ISNUMBER(H72),ISNUMBER(I72)),H72+I72,IF(ISNUMBER(K72),K72,IF(ISNUMBER(H72),H72,""))) | AD72: =IF(OR(NOT(ISNUMBER(J72)),NOT(ISNUMBER(H72)),H72<=0),기준표!$B$8,MIN(MAX(J72/H72,기준표!$B$6),기준표!$B$7)) | AE72: =IF(ISNUMBER(AC72),AC72*(1-AD72),"") | AF72: =IF(AND(NOT(ISNUMBER(T72)),NOT(ISNUMBER(V72))),"",IF(ISNUMBER(T72),T72,0)+IF(ISNUMBER(V72),V72,0)) | AG72: =IF(E72="금융","",IF(AND(ISNUMBER(P72),ISNUMBER(AF72),ISNUMBER(R72)),P72+AF72-R72,"")) | AH72: =IF(E72="금융","",IF(NOT(ISNUMBER(AG72)),"",IF(ISNUMBER(AA72),(AG72+AA72)/2,AG72))) | AI72: =IF(AND(ISNUMBER(AE72),ISNUMBER(AH72),AH72>0),AE72/AH72,"") | AJ72: =IF(E72="금융","",IF(AND(ISNUMBER(P72),ISNUMBER(AF72)),P72+AF72,"")) | AK72: =IF(OR(NOT(ISNUMBER(AE72)),NOT(ISNUMBER(AJ72)),AJ72<=0),"",IF(AND(ISNUMBER(G72),AJ72<0.1*G72),"",AE72/AJ72)) | AL72: =IF(NOT(ISNUMBER(P72)),"",IF(ISNUMBER(Q72),(P72+Q72)/2,P72)) | AM72: =IF(AND(ISNUMBER(L72),ISNUMBER(AL72),AL72>0),L72/AL72,"") | AN72: =IF(AND(ISNUMBER(AM72),ISNUMBER({ROIC})),AM72-{ROIC},"") | AO72: =IF(AND(ISNUMBER(AC72),ISNUMBER(M72)),AC72+M72,"") | AP72: =IF(AND(ISNUMBER(AF72),ISNUMBER(R72),ISNUMBER(AO72),AO72>0),(AF72-R72)/AO72,"") | AQ72: =IF(AND(ISNUMBER(AC72),ISNUMBER(I72),I72<>0,AC72>0),AC72/I72,"") | AR72: =IF(AND(ISNUMBER(W72),ISNUMBER(Y72)),W72-IF(ISNUMBER(R72),R72,0)-(Y72-IF(ISNUMBER(T72),T72,0)),"") | AS72: =IF(AND(ISNUMBER(X72),ISNUMBER(Z72)),X72-IF(ISNUMBER(S72),S72,0)-(Z72-IF(ISNUMBER(U72),U72,0)),"") | AT72: =IF(AND(ISNUMBER(AR72),ISNUMBER(AS72)),AR72-AS72,"") | AU72: =IF(E72="금융","",IF(AND(ISNUMBER(L72),ISNUMBER(M72),ISNUMBER(N72),ISNUMBER(AT72)),L72+M72-N72-AT72,IF(AND(ISNUMBER(O72),ISNUMBER(N72)),O72-N72,""))) | AV72: =IF(E72="금융","금융업 - 정의되지 않음",IF(AND(ISNUMBER(L72),ISNUMBER(M72),ISNUMBER(N72),ISNUMBER(AT72)),"순이익+감가상각-설비투자-운전자본증감",IF(AND(ISNUMBER(O72),ISNUMBER(N72)),"영업현금흐름-설비투자","산출불가"))) | AW72: =IF(AND(ISNUMBER(AU72),ISNUMBER(G72),G72<>0),AU72/G72,"") | AX72: =IF(AND(ISNUMBER(AC72),ISNUMBER(G72),G72<>0),AC72/G72,"")
A73: AVGO | B73: Broadcom Inc. | C73: 2024 | D73: 2024-11-03 | E73: 일반 | F73: 0001730168-25-000121 | G73: 51.574 | H73: 9.916 | I73: 3.953 | J73: 3.748 | K73: 13.463 | L73: 5.895 | M73: 0.593 | N73: 0.548 | O73: 19.962 | P73: 67.678 | Q73: 23.988 | R73: 9.348 | S73: 14.189 | T73: 1.245 | U73: 1.563 | V73: 66.295 | W73: 19.595 | X73: 20.847 | Y73: 16.697 | Z73: 7.405 | AA73: 48.983 | AB73: 4778 | AC73: =IF(AND(ISNUMBER(H73),ISNUMBER(I73)),H73+I73,IF(ISNUMBER(K73),K73,IF(ISNUMBER(H73),H73,""))) | AD73: =IF(OR(NOT(ISNUMBER(J73)),NOT(ISNUMBER(H73)),H73<=0),기준표!$B$8,MIN(MAX(J73/H73,기준표!$B$6),기준표!$B$7)) | AE73: =IF(ISNUMBER(AC73),AC73*(1-AD73),"") | AF73: =IF(AND(NOT(ISNUMBER(T73)),NOT(ISNUMBER(V73))),"",IF(ISNUMBER(T73),T73,0)+IF(ISNUMBER(V73),V73,0)) | AG73: =IF(E73="금융","",IF(AND(ISNUMBER(P73),ISNUMBER(AF73),ISNUMBER(R73)),P73+AF73-R73,"")) | AH73: =IF(E73="금융","",IF(NOT(ISNUMBER(AG73)),"",IF(ISNUMBER(AA73),(AG73+AA73)/2,AG73))) | AI73: =IF(AND(ISNUMBER(AE73),ISNUMBER(AH73),AH73>0),AE73/AH73,"") | AJ73: =IF(E73="금융","",IF(AND(ISNUMBER(P73),ISNUMBER(AF73)),P73+AF73,"")) | AK73: =IF(OR(NOT(ISNUMBER(AE73)),NOT(ISNUMBER(AJ73)),AJ73<=0),"",IF(AND(ISNUMBER(G73),AJ73<0.1*G73),"",AE73/AJ73)) | AL73: =IF(NOT(ISNUMBER(P73)),"",IF(ISNUMBER(Q73),(P73+Q73)/2,P73)) | AM73: =IF(AND(ISNUMBER(L73),ISNUMBER(AL73),AL73>0),L73/AL73,"") | AN73: =IF(AND(ISNUMBER(AM73),ISNUMBER({ROIC})),AM73-{ROIC},"") | AO73: =IF(AND(ISNUMBER(AC73),ISNUMBER(M73)),AC73+M73,"") | AP73: =IF(AND(ISNUMBER(AF73),ISNUMBER(R73),ISNUMBER(AO73),AO73>0),(AF73-R73)/AO73,"") | AQ73: =IF(AND(ISNUMBER(AC73),ISNUMBER(I73),I73<>0,AC73>0),AC73/I73,"") | AR73: =IF(AND(ISNUMBER(W73),ISNUMBER(Y73)),W73-IF(ISNUMBER(R73),R73,0)-(Y73-IF(ISNUMBER(T73),T73,0)),"") | AS73: =IF(AND(ISNUMBER(X73),ISNUMBER(Z73)),X73-IF(ISNUMBER(S73),S73,0)-(Z73-IF(ISNUMBER(U73),U73,0)),"") | AT73: =IF(AND(ISNUMBER(AR73),ISNUMBER(AS73)),AR73-AS73,"") | AU73: =IF(E73="금융","",IF(AND(ISNUMBER(L73),ISNUMBER(M73),ISNUMBER(N73),ISNUMBER(AT73)),L73+M73-N73-AT73,IF(AND(ISNUMBER(O73),ISNUMBER(N73)),O73-N73,""))) | AV73: =IF(E73="금융","금융업 - 정의되지 않음",IF(AND(ISNUMBER(L73),ISNUMBER(M73),ISNUMBER(N73),ISNUMBER(AT73)),"순이익+감가상각-설비투자-운전자본증감",IF(AND(ISNUMBER(O73),ISNUMBER(N73)),"영업현금흐름-설비투자","산출불가"))) | AW73: =IF(AND(ISNUMBER(AU73),ISNUMBER(G73),G73<>0),AU73/G73,"") | AX73: =IF(AND(ISNUMBER(AC73),ISNUMBER(G73),G73<>0),AC73/G73,"")
A74: AVGO | B74: Broadcom Inc. | C74: 2025 | D74: 2025-11-02 | E74: 일반 | F74: 0001730168-25-000121 | G74: 63.887 | H74: 22.729 | I74: 3.21 | J74: -0.397 | K74: 25.484 | L74: 23.126 | M74: 0.574 | N74: 0.623 | O74: 27.537 | P74: 81.292 | Q74: 67.678 | R74: 16.178 | S74: 9.348 | T74: 3.152 | U74: 1.245 | V74: 61.984 | W74: 31.573 | X74: 19.595 | Y74: 18.514 | Z74: 16.697 | AA74: 125.87 | AB74: 4853 | AC74: =IF(AND(ISNUMBER(H74),ISNUMBER(I74)),H74+I74,IF(ISNUMBER(K74),K74,IF(ISNUMBER(H74),H74,""))) | AD74: =IF(OR(NOT(ISNUMBER(J74)),NOT(ISNUMBER(H74)),H74<=0),기준표!$B$8,MIN(MAX(J74/H74,기준표!$B$6),기준표!$B$7)) | AE74: =IF(ISNUMBER(AC74),AC74*(1-AD74),"") | AF74: =IF(AND(NOT(ISNUMBER(T74)),NOT(ISNUMBER(V74))),"",IF(ISNUMBER(T74),T74,0)+IF(ISNUMBER(V74),V74,0)) | AG74: =IF(E74="금융","",IF(AND(ISNUMBER(P74),ISNUMBER(AF74),ISNUMBER(R74)),P74+AF74-R74,"")) | AH74: =IF(E74="금융","",IF(NOT(ISNUMBER(AG74)),"",IF(ISNUMBER(AA74),(AG74+AA74)/2,AG74))) | AI74: =IF(AND(ISNUMBER(AE74),ISNUMBER(AH74),AH74>0),AE74/AH74,"") | AJ74: =IF(E74="금융","",IF(AND(ISNUMBER(P74),ISNUMBER(AF74)),P74+AF74,"")) | AK74: =IF(OR(NOT(ISNUMBER(AE74)),NOT(ISNUMBER(AJ74)),AJ74<=0),"",IF(AND(ISNUMBER(G74),AJ74<0.1*G74),"",AE74/AJ74)) | AL74: =IF(NOT(ISNUMBER(P74)),"",IF(ISNUMBER(Q74),(P74+Q74)/2,P74)) | AM74: =IF(AND(ISNUMBER(L74),ISNUMBER(AL74),AL74>0),L74/AL74,"") | AN74: =IF(AND(ISNUMBER(AM74),ISNUMBER({ROIC})),AM74-{ROIC},"") | AO74: =IF(AND(ISNUMBER(AC74),ISNUMBER(M74)),AC74+M74,"") | AP74: =IF(AND(ISNUMBER(AF74),ISNUMBER(R74),ISNUMBER(AO74),AO74>0),(AF74-R74)/AO74,"") | AQ74: =IF(AND(ISNUMBER(AC74),ISNUMBER(I74),I74<>0,AC74>0),AC74/I74,"") | AR74: =IF(AND(ISNUMBER(W74),ISNUMBER(Y74)),W74-IF(ISNUMBER(R74),R74,0)-(Y74-IF(ISNUMBER(T74),T74,0)),"") | AS74: =IF(AND(ISNUMBER(X74),ISNUMBER(Z74)),X74-IF(ISNUMBER(S74),S74,0)-(Z74-IF(ISNUMBER(U74),U74,0)),"") | AT74: =IF(AND(ISNUMBER(AR74),ISNUMBER(AS74)),AR74-AS74,"") | AU74: =IF(E74="금융","",IF(AND(ISNUMBER(L74),ISNUMBER(M74),ISNUMBER(N74),ISNUMBER(AT74)),L74+M74-N74-AT74,IF(AND(ISNUMBER(O74),ISNUMBER(N74)),O74-N74,""))) | AV74: =IF(E74="금융","금융업 - 정의되지 않음",IF(AND(ISNUMBER(L74),ISNUMBER(M74),ISNUMBER(N74),ISNUMBER(AT74)),"순이익+감가상각-설비투자-운전자본증감",IF(AND(ISNUMBER(O74),ISNUMBER(N74)),"영업현금흐름-설비투자","산출불가"))) | AW74: =IF(AND(ISNUMBER(AU74),ISNUMBER(G74),G74<>0),AU74/G74,"") | AX74: =IF(AND(ISNUMBER(AC74),ISNUMBER(G74),G74<>0),AC74/G74,"")
A75: META | B75: Meta Platforms, Inc. | C75: 2014 | D75: 2014-12-31 | E75: 일반 | F75: 0001326801-17-000007 | H75: 4.91 | J75: 1.97 | K75: 4.994 | L75: 2.94 | M75: 1.243 | N75: 1.831 | O75: 7.326 | P75: 36.096 | R75: 11.199 | T75: 0 | W75: 13.39 | Y75: 1.424 | AB75: 2664 | AC75: =IF(AND(ISNUMBER(H75),ISNUMBER(I75)),H75+I75,IF(ISNUMBER(K75),K75,IF(ISNUMBER(H75),H75,""))) | AD75: =IF(OR(NOT(ISNUMBER(J75)),NOT(ISNUMBER(H75)),H75<=0),기준표!$B$8,MIN(MAX(J75/H75,기준표!$B$6),기준표!$B$7)) | AE75: =IF(ISNUMBER(AC75),AC75*(1-AD75),"") | AF75: =IF(AND(NOT(ISNUMBER(T75)),NOT(ISNUMBER(V75))),"",IF(ISNUMBER(T75),T75,0)+IF(ISNUMBER(V75),V75,0)) | AG75: =IF(E75="금융","",IF(AND(ISNUMBER(P75),ISNUMBER(AF75),ISNUMBER(R75)),P75+AF75-R75,"")) | AH75: =IF(E75="금융","",IF(NOT(ISNUMBER(AG75)),"",IF(ISNUMBER(AA75),(AG75+AA75)/2,AG75))) | AI75: =IF(AND(ISNUMBER(AE75),ISNUMBER(AH75),AH75>0),AE75/AH75,"") | AJ75: =IF(E75="금융","",IF(AND(ISNUMBER(P75),ISNUMBER(AF75)),P75+AF75,"")) | AK75: =IF(OR(NOT(ISNUMBER(AE75)),NOT(ISNUMBER(AJ75)),AJ75<=0),"",IF(AND(ISNUMBER(G75),AJ75<0.1*G75),"",AE75/AJ75)) | AL75: =IF(NOT(ISNUMBER(P75)),"",IF(ISNUMBER(Q75),(P75+Q75)/2,P75)) | AM75: =IF(AND(ISNUMBER(L75),ISNUMBER(AL75),AL75>0),L75/AL75,"") | AN75: =IF(AND(ISNUMBER(AM75),ISNUMBER({ROIC})),AM75-{ROIC},"") | AO75: =IF(AND(ISNUMBER(AC75),ISNUMBER(M75)),AC75+M75,"") | AP75: =IF(AND(ISNUMBER(AF75),ISNUMBER(R75),ISNUMBER(AO75),AO75>0),(AF75-R75)/AO75,"") | AQ75: =IF(AND(ISNUMBER(AC75),ISNUMBER(I75),I75<>0,AC75>0),AC75/I75,"") | AR75: =IF(AND(ISNUMBER(W75),ISNUMBER(Y75)),W75-IF(ISNUMBER(R75),R75,0)-(Y75-IF(ISNUMBER(T75),T75,0)),"") | AS75: =IF(AND(ISNUMBER(X75),ISNUMBER(Z75)),X75-IF(ISNUMBER(S75),S75,0)-(Z75-IF(ISNUMBER(U75),U75,0)),"") | AT75: =IF(AND(ISNUMBER(AR75),ISNUMBER(AS75)),AR75-AS75,"") | AU75: =IF(E75="금융","",IF(AND(ISNUMBER(L75),ISNUMBER(M75),ISNUMBER(N75),ISNUMBER(AT75)),L75+M75-N75-AT75,IF(AND(ISNUMBER(O75),ISNUMBER(N75)),O75-N75,""))) | AV75: =IF(E75="금융","금융업 - 정의되지 않음",IF(AND(ISNUMBER(L75),ISNUMBER(M75),ISNUMBER(N75),ISNUMBER(AT75)),"순이익+감가상각-설비투자-운전자본증감",IF(AND(ISNUMBER(O75),ISNUMBER(N75)),"영업현금흐름-설비투자","산출불가"))) | AW75: =IF(AND(ISNUMBER(AU75),ISNUMBER(G75),G75<>0),AU75/G75,"") | AX75: =IF(AND(ISNUMBER(AC75),ISNUMBER(G75),G75<>0),AC75/G75,"")
A76: META | B76: Meta Platforms, Inc. | C76: 2015 | D76: 2015-12-31 | E76: 일반 | F76: 0001326801-18-000009 | H76: 6.194 | J76: 2.506 | K76: 6.225 | L76: 3.688 | M76: 1.945 | N76: 2.523 | O76: 10.32 | P76: 44.218 | Q76: 36.096 | R76: 18.434 | S76: 11.199 | T76: 0.201 | U76: 0 | W76: 21.652 | X76: 13.39 | Y76: 1.925 | Z76: 1.424 | AA76: 24.897 | AB76: 2905 | AC76: =IF(AND(ISNUMBER(H76),ISNUMBER(I76)),H76+I76,IF(ISNUMBER(K76),K76,IF(ISNUMBER(H76),H76,""))) | AD76: =IF(OR(NOT(ISNUMBER(J76)),NOT(ISNUMBER(H76)),H76<=0),기준표!$B$8,MIN(MAX(J76/H76,기준표!$B$6),기준표!$B$7)) | AE76: =IF(ISNUMBER(AC76),AC76*(1-AD76),"") | AF76: =IF(AND(NOT(ISNUMBER(T76)),NOT(ISNUMBER(V76))),"",IF(ISNUMBER(T76),T76,0)+IF(ISNUMBER(V76),V76,0)) | AG76: =IF(E76="금융","",IF(AND(ISNUMBER(P76),ISNUMBER(AF76),ISNUMBER(R76)),P76+AF76-R76,"")) | AH76: =IF(E76="금융","",IF(NOT(ISNUMBER(AG76)),"",IF(ISNUMBER(AA76),(AG76+AA76)/2,AG76))) | AI76: =IF(AND(ISNUMBER(AE76),ISNUMBER(AH76),AH76>0),AE76/AH76,"") | AJ76: =IF(E76="금융","",IF(AND(ISNUMBER(P76),ISNUMBER(AF76)),P76+AF76,"")) | AK76: =IF(OR(NOT(ISNUMBER(AE76)),NOT(ISNUMBER(AJ76)),AJ76<=0),"",IF(AND(ISNUMBER(G76),AJ76<0.1*G76),"",AE76/AJ76)) | AL76: =IF(NOT(ISNUMBER(P76)),"",IF(ISNUMBER(Q76),(P76+Q76)/2,P76)) | AM76: =IF(AND(ISNUMBER(L76),ISNUMBER(AL76),AL76>0),L76/AL76,"") | AN76: =IF(AND(ISNUMBER(AM76),ISNUMBER({ROIC})),AM76-{ROIC},"") | AO76: =IF(AND(ISNUMBER(AC76),ISNUMBER(M76)),AC76+M76,"") | AP76: =IF(AND(ISNUMBER(AF76),ISNUMBER(R76),ISNUMBER(AO76),AO76>0),(AF76-R76)/AO76,"") | AQ76: =IF(AND(ISNUMBER(AC76),ISNUMBER(I76),I76<>0,AC76>0),AC76/I76,"") | AR76: =IF(AND(ISNUMBER(W76),ISNUMBER(Y76)),W76-IF(ISNUMBER(R76),R76,0)-(Y76-IF(ISNUMBER(T76),T76,0)),"") | AS76: =IF(AND(ISNUMBER(X76),ISNUMBER(Z76)),X76-IF(ISNUMBER(S76),S76,0)-(Z76-IF(ISNUMBER(U76),U76,0)),"") | AT76: =IF(AND(ISNUMBER(AR76),ISNUMBER(AS76)),AR76-AS76,"") | AU76: =IF(E76="금융","",IF(AND(ISNUMBER(L76),ISNUMBER(M76),ISNUMBER(N76),ISNUMBER(AT76)),L76+M76-N76-AT76,IF(AND(ISNUMBER(O76),ISNUMBER(N76)),O76-N76,""))) | AV76: =IF(E76="금융","금융업 - 정의되지 않음",IF(AND(ISNUMBER(L76),ISNUMBER(M76),ISNUMBER(N76),ISNUMBER(AT76)),"순이익+감가상각-설비투자-운전자본증감",IF(AND(ISNUMBER(O76),ISNUMBER(N76)),"영업현금흐름-설비투자","산출불가"))) | AW76: =IF(AND(ISNUMBER(AU76),ISNUMBER(G76),G76<>0),AU76/G76,"") | AX76: =IF(AND(ISNUMBER(AC76),ISNUMBER(G76),G76<>0),AC76/G76,"")
A77: META | B77: Meta Platforms, Inc. | C77: 2016 | D77: 2016-12-31 | E77: 일반 | F77: 0001326801-19-000009 | G77: 27.638 | H77: 12.518 | J77: 2.301 | K77: 12.427 | L77: 10.217 | M77: 2.342 | N77: 4.491 | O77: 16.108 | P77: 59.194 | Q77: 44.218 | R77: 29.449 | S77: 18.434 | T77: 0 | U77: 0.201 | W77: 34.401 | X77: 21.652 | Y77: 2.875 | Z77: 1.925 | AA77: 25.985 | AB77: 2925 | AC77: =IF(AND(ISNUMBER(H77),ISNUMBER(I77)),H77+I77,IF(ISNUMBER(K77),K77,IF(ISNUMBER(H77),H77,""))) | AD77: =IF(OR(NOT(ISNUMBER(J77)),NOT(ISNUMBER(H77)),H77<=0),기준표!$B$8,MIN(MAX(J77/H77,기준표!$B$6),기준표!$B$7)) | AE77: =IF(ISNUMBER(AC77),AC77*(1-AD77),"") | AF77: =IF(AND(NOT(ISNUMBER(T77)),NOT(ISNUMBER(V77))),"",IF(ISNUMBER(T77),T77,0)+IF(ISNUMBER(V77),V77,0)) | AG77: =IF(E77="금융","",IF(AND(ISNUMBER(P77),ISNUMBER(AF77),ISNUMBER(R77)),P77+AF77-R77,"")) | AH77: =IF(E77="금융","",IF(NOT(ISNUMBER(AG77)),"",IF(ISNUMBER(AA77),(AG77+AA77)/2,AG77))) | AI77: =IF(AND(ISNUMBER(AE77),ISNUMBER(AH77),AH77>0),AE77/AH77,"") | AJ77: =IF(E77="금융","",IF(AND(ISNUMBER(P77),ISNUMBER(AF77)),P77+AF77,"")) | AK77: =IF(OR(NOT(ISNUMBER(AE77)),NOT(ISNUMBER(AJ77)),AJ77<=0),"",IF(AND(ISNUMBER(G77),AJ77<0.1*G77),"",AE77/AJ77)) | AL77: =IF(NOT(ISNUMBER(P77)),"",IF(ISNUMBER(Q77),(P77+Q77)/2,P77)) | AM77: =IF(AND(ISNUMBER(L77),ISNUMBER(AL77),AL77>0),L77/AL77,"") | AN77: =IF(AND(ISNUMBER(AM77),ISNUMBER({ROIC})),AM77-{ROIC},"") | AO77: =IF(AND(ISNUMBER(AC77),ISNUMBER(M77)),AC77+M77,"") | AP77: =IF(AND(ISNUMBER(AF77),ISNUMBER(R77),ISNUMBER(AO77),AO77>0),(AF77-R77)/AO77,"") | AQ77: =IF(AND(ISNUMBER(AC77),ISNUMBER(I77),I77<>0,AC77>0),AC77/I77,"") | AR77: =IF(AND(ISNUMBER(W77),ISNUMBER(Y77)),W77-IF(ISNUMBER(R77),R77,0)-(Y77-IF(ISNUMBER(T77),T77,0)),"") | AS77: =IF(AND(ISNUMBER(X77),ISNUMBER(Z77)),X77-IF(ISNUMBER(S77),S77,0)-(Z77-IF(ISNUMBER(U77),U77,0)),"") | AT77: =IF(AND(ISNUMBER(AR77),ISNUMBER(AS77)),AR77-AS77,"") | AU77: =IF(E77="금융","",IF(AND(ISNUMBER(L77),ISNUMBER(M77),ISNUMBER(N77),ISNUMBER(AT77)),L77+M77-N77-AT77,IF(AND(ISNUMBER(O77),ISNUMBER(N77)),O77-N77,""))) | AV77: =IF(E77="금융","금융업 - 정의되지 않음",IF(AND(ISNUMBER(L77),ISNUMBER(M77),ISNUMBER(N77),ISNUMBER(AT77)),"순이익+감가상각-설비투자-운전자본증감",IF(AND(ISNUMBER(O77),ISNUMBER(N77)),"영업현금흐름-설비투자","산출불가"))) | AW77: =IF(AND(ISNUMBER(AU77),ISNUMBER(G77),G77<>0),AU77/G77,"") | AX77: =IF(AND(ISNUMBER(AC77),ISNUMBER(G77),G77<>0),AC77/G77,"")
A78: META | B78: Meta Platforms, Inc. | C78: 2017 | D78: 2017-12-31 | E78: 일반 | F78: 0001326801-20-000013 | G78: 40.653 | H78: 20.594 | J78: 4.66 | K78: 20.203 | L78: 15.934 | M78: 3.025 | N78: 6.733 | O78: 24.216 | P78: 74.347 | Q78: 59.194 | R78: 41.711 | S78: 29.449 | U78: 0 | W78: 48.563 | X78: 34.401 | Y78: 3.76 | Z78: 2.875 | AA78: 29.745 | AB78: 2956 | AC78: =IF(AND(ISNUMBER(H78),ISNUMBER(I78)),H78+I78,IF(ISNUMBER(K78),K78,IF(ISNUMBER(H78),H78,""))) | AD78: =IF(OR(NOT(ISNUMBER(J78)),NOT(ISNUMBER(H78)),H78<=0),기준표!$B$8,MIN(MAX(J78/H78,기준표!$B$6),기준표!$B$7)) | AE78: =IF(ISNUMBER(AC78),AC78*(1-AD78),"") | AF78: =IF(AND(NOT(ISNUMBER(T78)),NOT(ISNUMBER(V78))),"",IF(ISNUMBER(T78),T78,0)+IF(ISNUMBER(V78),V78,0)) | AG78: =IF(E78="금융","",IF(AND(ISNUMBER(P78),ISNUMBER(AF78),ISNUMBER(R78)),P78+AF78-R78,"")) | AH78: =IF(E78="금융","",IF(NOT(ISNUMBER(AG78)),"",IF(ISNUMBER(AA78),(AG78+AA78)/2,AG78))) | AI78: =IF(AND(ISNUMBER(AE78),ISNUMBER(AH78),AH78>0),AE78/AH78,"") | AJ78: =IF(E78="금융","",IF(AND(ISNUMBER(P78),ISNUMBER(AF78)),P78+AF78,"")) | AK78: =IF(OR(NOT(ISNUMBER(AE78)),NOT(ISNUMBER(AJ78)),AJ78<=0),"",IF(AND(ISNUMBER(G78),AJ78<0.1*G78),"",AE78/AJ78)) | AL78: =IF(NOT(ISNUMBER(P78)),"",IF(ISNUMBER(Q78),(P78+Q78)/2,P78)) | AM78: =IF(AND(ISNUMBER(L78),ISNUMBER(AL78),AL78>0),L78/AL78,"") | AN78: =IF(AND(ISNUMBER(AM78),ISNUMBER({ROIC})),AM78-{ROIC},"") | AO78: =IF(AND(ISNUMBER(AC78),ISNUMBER(M78)),AC78+M78,"") | AP78: =IF(AND(ISNUMBER(AF78),ISNUMBER(R78),ISNUMBER(AO78),AO78>0),(AF78-R78)/AO78,"") | AQ78: =IF(AND(ISNUMBER(AC78),ISNUMBER(I78),I78<>0,AC78>0),AC78/I78,"") | AR78: =IF(AND(ISNUMBER(W78),ISNUMBER(Y78)),W78-IF(ISNUMBER(R78),R78,0)-(Y78-IF(ISNUMBER(T78),T78,0)),"") | AS78: =IF(AND(ISNUMBER(X78),ISNUMBER(Z78)),X78-IF(ISNUMBER(S78),S78,0)-(Z78-IF(ISNUMBER(U78),U78,0)),"") | AT78: =IF(AND(ISNUMBER(AR78),ISNUMBER(AS78)),AR78-AS78,"") | AU78: =IF(E78="금융","",IF(AND(ISNUMBER(L78),ISNUMBER(M78),ISNUMBER(N78),ISNUMBER(AT78)),L78+M78-N78-AT78,IF(AND(ISNUMBER(O78),ISNUMBER(N78)),O78-N78,""))) | AV78: =IF(E78="금융","금융업 - 정의되지 않음",IF(AND(ISNUMBER(L78),ISNUMBER(M78),ISNUMBER(N78),ISNUMBER(AT78)),"순이익+감가상각-설비투자-운전자본증감",IF(AND(ISNUMBER(O78),ISNUMBER(N78)),"영업현금흐름-설비투자","산출불가"))) | AW78: =IF(AND(ISNUMBER(AU78),ISNUMBER(G78),G78<>0),AU78/G78,"") | AX78: =IF(AND(ISNUMBER(AC78),ISNUMBER(G78),G78<>0),AC78/G78,"")
A79: META | B79: Meta Platforms, Inc. | C79: 2018 | D79: 2018-12-31 | E79: 일반 | F79: 0001326801-21-000014 | G79: 55.838 | H79: 25.361 | J79: 3.249 | K79: 24.913 | L79: 22.112 | M79: 4.315 | N79: 13.915 | O79: 29.274 | P79: 84.127 | Q79: 74.347 | R79: 41.114 | S79: 41.711 | W79: 50.48 | X79: 48.563 | Y79: 7.017 | Z79: 3.76 | AB79: 2921 | AC79: =IF(AND(ISNUMBER(H79),ISNUMBER(I79)),H79+I79,IF(ISNUMBER(K79),K79,IF(ISNUMBER(H79),H79,""))) | AD79: =IF(OR(NOT(ISNUMBER(J79)),NOT(ISNUMBER(H79)),H79<=0),기준표!$B$8,MIN(MAX(J79/H79,기준표!$B$6),기준표!$B$7)) | AE79: =IF(ISNUMBER(AC79),AC79*(1-AD79),"") | AF79: =IF(AND(NOT(ISNUMBER(T79)),NOT(ISNUMBER(V79))),"",IF(ISNUMBER(T79),T79,0)+IF(ISNUMBER(V79),V79,0)) | AG79: =IF(E79="금융","",IF(AND(ISNUMBER(P79),ISNUMBER(AF79),ISNUMBER(R79)),P79+AF79-R79,"")) | AH79: =IF(E79="금융","",IF(NOT(ISNUMBER(AG79)),"",IF(ISNUMBER(AA79),(AG79+AA79)/2,AG79))) | AI79: =IF(AND(ISNUMBER(AE79),ISNUMBER(AH79),AH79>0),AE79/AH79,"") | AJ79: =IF(E79="금융","",IF(AND(ISNUMBER(P79),ISNUMBER(AF79)),P79+AF79,"")) | AK79: =IF(OR(NOT(ISNUMBER(AE79)),NOT(ISNUMBER(AJ79)),AJ79<=0),"",IF(AND(ISNUMBER(G79),AJ79<0.1*G79),"",AE79/AJ79)) | AL79: =IF(NOT(ISNUMBER(P79)),"",IF(ISNUMBER(Q79),(P79+Q79)/2,P79)) | AM79: =IF(AND(ISNUMBER(L79),ISNUMBER(AL79),AL79>0),L79/AL79,"") | AN79: =IF(AND(ISNUMBER(AM79),ISNUMBER({ROIC})),AM79-{ROIC},"") | AO79: =IF(AND(ISNUMBER(AC79),ISNUMBER(M79)),AC79+M79,"") | AP79: =IF(AND(ISNUMBER(AF79),ISNUMBER(R79),ISNUMBER(AO79),AO79>0),(AF79-R79)/AO79,"") | AQ79: =IF(AND(ISNUMBER(AC79),ISNUMBER(I79),I79<>0,AC79>0),AC79/I79,"") | AR79: =IF(AND(ISNUMBER(W79),ISNUMBER(Y79)),W79-IF(ISNUMBER(R79),R79,0)-(Y79-IF(ISNUMBER(T79),T79,0)),"") | AS79: =IF(AND(ISNUMBER(X79),ISNUMBER(Z79)),X79-IF(ISNUMBER(S79),S79,0)-(Z79-IF(ISNUMBER(U79),U79,0)),"") | AT79: =IF(AND(ISNUMBER(AR79),ISNUMBER(AS79)),AR79-AS79,"") | AU79: =IF(E79="금융","",IF(AND(ISNUMBER(L79),ISNUMBER(M79),ISNUMBER(N79),ISNUMBER(AT79)),L79+M79-N79-AT79,IF(AND(ISNUMBER(O79),ISNUMBER(N79)),O79-N79,""))) | AV79: =IF(E79="금융","금융업 - 정의되지 않음",IF(AND(ISNUMBER(L79),ISNUMBER(M79),ISNUMBER(N79),ISNUMBER(AT79)),"순이익+감가상각-설비투자-운전자본증감",IF(AND(ISNUMBER(O79),ISNUMBER(N79)),"영업현금흐름-설비투자","산출불가"))) | AW79: =IF(AND(ISNUMBER(AU79),ISNUMBER(G79),G79<>0),AU79/G79,"") | AX79: =IF(AND(ISNUMBER(AC79),ISNUMBER(G79),G79<>0),AC79/G79,"")
A80: META | B80: Meta Platforms, Inc. | C80: 2019 | D80: 2019-12-31 | E80: 일반 | F80: 0001326801-22-000018 | G80: 70.697 | H80: 24.812 | J80: 6.327 | K80: 23.986 | L80: 18.485 | M80: 5.741 | N80: 15.102 | O80: 36.314 | P80: 101.054 | Q80: 84.127 | R80: 54.855 | S80: 41.114 | W80: 66.225 | X80: 50.48 | Y80: 15.053 | Z80: 7.017 | AB80: 2876 | AC80: =IF(AND(ISNUMBER(H80),ISNUMBER(I80)),H80+I80,IF(ISNUMBER(K80),K80,IF(ISNUMBER(H80),H80,""))) | AD80: =IF(OR(NOT(ISNUMBER(J80)),NOT(ISNUMBER(H80)),H80<=0),기준표!$B$8,MIN(MAX(J80/H80,기준표!$B$6),기준표!$B$7)) | AE80: =IF(ISNUMBER(AC80),AC80*(1-AD80),"") | AF80: =IF(AND(NOT(ISNUMBER(T80)),NOT(ISNUMBER(V80))),"",IF(ISNUMBER(T80),T80,0)+IF(ISNUMBER(V80),V80,0)) | AG80: =IF(E80="금융","",IF(AND(ISNUMBER(P80),ISNUMBER(AF80),ISNUMBER(R80)),P80+AF80-R80,"")) | AH80: =IF(E80="금융","",IF(NOT(ISNUMBER(AG80)),"",IF(ISNUMBER(AA80),(AG80+AA80)/2,AG80))) | AI80: =IF(AND(ISNUMBER(AE80),ISNUMBER(AH80),AH80>0),AE80/AH80,"") | AJ80: =IF(E80="금융","",IF(AND(ISNUMBER(P80),ISNUMBER(AF80)),P80+AF80,"")) | AK80: =IF(OR(NOT(ISNUMBER(AE80)),NOT(ISNUMBER(AJ80)),AJ80<=0),"",IF(AND(ISNUMBER(G80),AJ80<0.1*G80),"",AE80/AJ80)) | AL80: =IF(NOT(ISNUMBER(P80)),"",IF(ISNUMBER(Q80),(P80+Q80)/2,P80)) | AM80: =IF(AND(ISNUMBER(L80),ISNUMBER(AL80),AL80>0),L80/AL80,"") | AN80: =IF(AND(ISNUMBER(AM80),ISNUMBER({ROIC})),AM80-{ROIC},"") | AO80: =IF(AND(ISNUMBER(AC80),ISNUMBER(M80)),AC80+M80,"") | AP80: =IF(AND(ISNUMBER(AF80),ISNUMBER(R80),ISNUMBER(AO80),AO80>0),(AF80-R80)/AO80,"") | AQ80: =IF(AND(ISNUMBER(AC80),ISNUMBER(I80),I80<>0,AC80>0),AC80/I80,"") | AR80: =IF(AND(ISNUMBER(W80),ISNUMBER(Y80)),W80-IF(ISNUMBER(R80),R80,0)-(Y80-IF(ISNUMBER(T80),T80,0)),"") | AS80: =IF(AND(ISNUMBER(X80),ISNUMBER(Z80)),X80-IF(ISNUMBER(S80),S80,0)-(Z80-IF(ISNUMBER(U80),U80,0)),"") | AT80: =IF(AND(ISNUMBER(AR80),ISNUMBER(AS80)),AR80-AS80,"") | AU80: =IF(E80="금융","",IF(AND(ISNUMBER(L80),ISNUMBER(M80),ISNUMBER(N80),ISNUMBER(AT80)),L80+M80-N80-AT80,IF(AND(ISNUMBER(O80),ISNUMBER(N80)),O80-N80,""))) | AV80: =IF(E80="금융","금융업 - 정의되지 않음",IF(AND(ISNUMBER(L80),ISNUMBER(M80),ISNUMBER(N80),ISNUMBER(AT80)),"순이익+감가상각-설비투자-운전자본증감",IF(AND(ISNUMBER(O80),ISNUMBER(N80)),"영업현금흐름-설비투자","산출불가"))) | AW80: =IF(AND(ISNUMBER(AU80),ISNUMBER(G80),G80<>0),AU80/G80,"") | AX80: =IF(AND(ISNUMBER(AC80),ISNUMBER(G80),G80<>0),AC80/G80,"")
A81: META | B81: Meta Platforms, Inc. | C81: 2020 | D81: 2020-12-31 | E81: 일반 | F81: 0001326801-23-000013 | G81: 85.965 | H81: 33.18 | J81: 4.034 | K81: 32.671 | L81: 29.146 | M81: 6.862 | N81: 15.163 | O81: 38.747 | P81: 128.29 | Q81: 101.054 | R81: 61.954 | S81: 54.855 | W81: 75.67 | X81: 66.225 | Y81: 14.981 | Z81: 15.053 | AB81: 2888 | AC81: =IF(AND(ISNUMBER(H81),ISNUMBER(I81)),H81+I81,IF(ISNUMBER(K81),K81,IF(ISNUMBER(H81),H81,""))) | AD81: =IF(OR(NOT(ISNUMBER(J81)),NOT(ISNUMBER(H81)),H81<=0),기준표!$B$8,MIN(MAX(J81/H81,기준표!$B$6),기준표!$B$7)) | AE81: =IF(ISNUMBER(AC81),AC81*(1-AD81),"") | AF81: =IF(AND(NOT(ISNUMBER(T81)),NOT(ISNUMBER(V81))),"",IF(ISNUMBER(T81),T81,0)+IF(ISNUMBER(V81),V81,0)) | AG81: =IF(E81="금융","",IF(AND(ISNUMBER(P81),ISNUMBER(AF81),ISNUMBER(R81)),P81+AF81-R81,"")) | AH81: =IF(E81="금융","",IF(NOT(ISNUMBER(AG81)),"",IF(ISNUMBER(AA81),(AG81+AA81)/2,AG81))) | AI81: =IF(AND(ISNUMBER(AE81),ISNUMBER(AH81),AH81>0),AE81/AH81,"") | AJ81: =IF(E81="금융","",IF(AND(ISNUMBER(P81),ISNUMBER(AF81)),P81+AF81,"")) | AK81: =IF(OR(NOT(ISNUMBER(AE81)),NOT(ISNUMBER(AJ81)),AJ81<=0),"",IF(AND(ISNUMBER(G81),AJ81<0.1*G81),"",AE81/AJ81)) | AL81: =IF(NOT(ISNUMBER(P81)),"",IF(ISNUMBER(Q81),(P81+Q81)/2,P81)) | AM81: =IF(AND(ISNUMBER(L81),ISNUMBER(AL81),AL81>0),L81/AL81,"") | AN81: =IF(AND(ISNUMBER(AM81),ISNUMBER({ROIC})),AM81-{ROIC},"") | AO81: =IF(AND(ISNUMBER(AC81),ISNUMBER(M81)),AC81+M81,"") | AP81: =IF(AND(ISNUMBER(AF81),ISNUMBER(R81),ISNUMBER(AO81),AO81>0),(AF81-R81)/AO81,"") | AQ81: =IF(AND(ISNUMBER(AC81),ISNUMBER(I81),I81<>0,AC81>0),AC81/I81,"") | AR81: =IF(AND(ISNUMBER(W81),ISNUMBER(Y81)),W81-IF(ISNUMBER(R81),R81,0)-(Y81-IF(ISNUMBER(T81),T81,0)),"") | AS81: =IF(AND(ISNUMBER(X81),ISNUMBER(Z81)),X81-IF(ISNUMBER(S81),S81,0)-(Z81-IF(ISNUMBER(U81),U81,0)),"") | AT81: =IF(AND(ISNUMBER(AR81),ISNUMBER(AS81)),AR81-AS81,"") | AU81: =IF(E81="금융","",IF(AND(ISNUMBER(L81),ISNUMBER(M81),ISNUMBER(N81),ISNUMBER(AT81)),L81+M81-N81-AT81,IF(AND(ISNUMBER(O81),ISNUMBER(N81)),O81-N81,""))) | AV81: =IF(E81="금융","금융업 - 정의되지 않음",IF(AND(ISNUMBER(L81),ISNUMBER(M81),ISNUMBER(N81),ISNUMBER(AT81)),"순이익+감가상각-설비투자-운전자본증감",IF(AND(ISNUMBER(O81),ISNUMBER(N81)),"영업현금흐름-설비투자","산출불가"))) | AW81: =IF(AND(ISNUMBER(AU81),ISNUMBER(G81),G81<>0),AU81/G81,"") | AX81: =IF(AND(ISNUMBER(AC81),ISNUMBER(G81),G81<>0),AC81/G81,"")
A82: META | B82: Meta Platforms, Inc. | C82: 2021 | D82: 2021-12-31 | E82: 일반 | F82: 0001326801-24-000012 | G82: 117.929 | H82: 47.284 | J82: 7.914 | K82: 46.753 | L82: 39.37 | M82: 7.967 | N82: 18.69 | O82: 57.683 | P82: 124.879 | Q82: 128.29 | R82: 47.998 | S82: 61.954 | V82: 0 | W82: 66.666 | X82: 75.67 | Y82: 21.135 | Z82: 14.981 | AB82: 2859 | AC82: =IF(AND(ISNUMBER(H82),ISNUMBER(I82)),H82+I82,IF(ISNUMBER(K82),K82,IF(ISNUMBER(H82),H82,""))) | AD82: =IF(OR(NOT(ISNUMBER(J82)),NOT(ISNUMBER(H82)),H82<=0),기준표!$B$8,MIN(MAX(J82/H82,기준표!$B$6),기준표!$B$7)) | AE82: =IF(ISNUMBER(AC82),AC82*(1-AD82),"") | AF82: =IF(AND(NOT(ISNUMBER(T82)),NOT(ISNUMBER(V82))),"",IF(ISNUMBER(T82),T82,0)+IF(ISNUMBER(V82),V82,0)) | AG82: =IF(E82="금융","",IF(AND(ISNUMBER(P82),ISNUMBER(AF82),ISNUMBER(R82)),P82+AF82-R82,"")) | AH82: =IF(E82="금융","",IF(NOT(ISNUMBER(AG82)),"",IF(ISNUMBER(AA82),(AG82+AA82)/2,AG82))) | AI82: =IF(AND(ISNUMBER(AE82),ISNUMBER(AH82),AH82>0),AE82/AH82,"") | AJ82: =IF(E82="금융","",IF(AND(ISNUMBER(P82),ISNUMBER(AF82)),P82+AF82,"")) | AK82: =IF(OR(NOT(ISNUMBER(AE82)),NOT(ISNUMBER(AJ82)),AJ82<=0),"",IF(AND(ISNUMBER(G82),AJ82<0.1*G82),"",AE82/AJ82)) | AL82: =IF(NOT(ISNUMBER(P82)),"",IF(ISNUMBER(Q82),(P82+Q82)/2,P82)) | AM82: =IF(AND(ISNUMBER(L82),ISNUMBER(AL82),AL82>0),L82/AL82,"") | AN82: =IF(AND(ISNUMBER(AM82),ISNUMBER({ROIC})),AM82-{ROIC},"") | AO82: =IF(AND(ISNUMBER(AC82),ISNUMBER(M82)),AC82+M82,"") | AP82: =IF(AND(ISNUMBER(AF82),ISNUMBER(R82),ISNUMBER(AO82),AO82>0),(AF82-R82)/AO82,"") | AQ82: =IF(AND(ISNUMBER(AC82),ISNUMBER(I82),I82<>0,AC82>0),AC82/I82,"") | AR82: =IF(AND(ISNUMBER(W82),ISNUMBER(Y82)),W82-IF(ISNUMBER(R82),R82,0)-(Y82-IF(ISNUMBER(T82),T82,0)),"") | AS82: =IF(AND(ISNUMBER(X82),ISNUMBER(Z82)),X82-IF(ISNUMBER(S82),S82,0)-(Z82-IF(ISNUMBER(U82),U82,0)),"") | AT82: =IF(AND(ISNUMBER(AR82),ISNUMBER(AS82)),AR82-AS82,"") | AU82: =IF(E82="금융","",IF(AND(ISNUMBER(L82),ISNUMBER(M82),ISNUMBER(N82),ISNUMBER(AT82)),L82+M82-N82-AT82,IF(AND(ISNUMBER(O82),ISNUMBER(N82)),O82-N82,""))) | AV82: =IF(E82="금융","금융업 - 정의되지 않음",IF(AND(ISNUMBER(L82),ISNUMBER(M82),ISNUMBER(N82),ISNUMBER(AT82)),"순이익+감가상각-설비투자-운전자본증감",IF(AND(ISNUMBER(O82),ISNUMBER(N82)),"영업현금흐름-설비투자","산출불가"))) | AW82: =IF(AND(ISNUMBER(AU82),ISNUMBER(G82),G82<>0),AU82/G82,"") | AX82: =IF(AND(ISNUMBER(AC82),ISNUMBER(G82),G82<>0),AC82/G82,"")
A83: META | B83: Meta Platforms, Inc. | C83: 2022 | D83: 2022-12-31 | E83: 일반 | F83: 0001326801-25-000017 | G83: 116.609 | H83: 28.819 | I83: 0.16 | J83: 5.619 | K83: 28.944 | L83: 23.2 | M83: 8.686 | N83: 31.186 | O83: 50.475 | P83: 125.713 | Q83: 124.879 | R83: 40.738 | S83: 47.998 | V83: 9.923 | W83: 59.549 | X83: 66.666 | Y83: 27.026 | Z83: 21.135 | AA83: 76.881 | AB83: 2702 | AC83: =IF(AND(ISNUMBER(H83),ISNUMBER(I83)),H83+I83,IF(ISNUMBER(K83),K83,IF(ISNUMBER(H83),H83,""))) | AD83: =IF(OR(NOT(ISNUMBER(J83)),NOT(ISNUMBER(H83)),H83<=0),기준표!$B$8,MIN(MAX(J83/H83,기준표!$B$6),기준표!$B$7)) | AE83: =IF(ISNUMBER(AC83),AC83*(1-AD83),"") | AF83: =IF(AND(NOT(ISNUMBER(T83)),NOT(ISNUMBER(V83))),"",IF(ISNUMBER(T83),T83,0)+IF(ISNUMBER(V83),V83,0)) | AG83: =IF(E83="금융","",IF(AND(ISNUMBER(P83),ISNUMBER(AF83),ISNUMBER(R83)),P83+AF83-R83,"")) | AH83: =IF(E83="금융","",IF(NOT(ISNUMBER(AG83)),"",IF(ISNUMBER(AA83),(AG83+AA83)/2,AG83))) | AI83: =IF(AND(ISNUMBER(AE83),ISNUMBER(AH83),AH83>0),AE83/AH83,"") | AJ83: =IF(E83="금융","",IF(AND(ISNUMBER(P83),ISNUMBER(AF83)),P83+AF83,"")) | AK83: =IF(OR(NOT(ISNUMBER(AE83)),NOT(ISNUMBER(AJ83)),AJ83<=0),"",IF(AND(ISNUMBER(G83),AJ83<0.1*G83),"",AE83/AJ83)) | AL83: =IF(NOT(ISNUMBER(P83)),"",IF(ISNUMBER(Q83),(P83+Q83)/2,P83)) | AM83: =IF(AND(ISNUMBER(L83),ISNUMBER(AL83),AL83>0),L83/AL83,"") | AN83: =IF(AND(ISNUMBER(AM83),ISNUMBER({ROIC})),AM83-{ROIC},"") | AO83: =IF(AND(ISNUMBER(AC83),ISNUMBER(M83)),AC83+M83,"") | AP83: =IF(AND(ISNUMBER(AF83),ISNUMBER(R83),ISNUMBER(AO83),AO83>0),(AF83-R83)/AO83,"") | AQ83: =IF(AND(ISNUMBER(AC83),ISNUMBER(I83),I83<>0,AC83>0),AC83/I83,"") | AR83: =IF(AND(ISNUMBER(W83),ISNUMBER(Y83)),W83-IF(ISNUMBER(R83),R83,0)-(Y83-IF(ISNUMBER(T83),T83,0)),"") | AS83: =IF(AND(ISNUMBER(X83),ISNUMBER(Z83)),X83-IF(ISNUMBER(S83),S83,0)-(Z83-IF(ISNUMBER(U83),U83,0)),"") | AT83: =IF(AND(ISNUMBER(AR83),ISNUMBER(AS83)),AR83-AS83,"") | AU83: =IF(E83="금융","",IF(AND(ISNUMBER(L83),ISNUMBER(M83),ISNUMBER(N83),ISNUMBER(AT83)),L83+M83-N83-AT83,IF(AND(ISNUMBER(O83),ISNUMBER(N83)),O83-N83,""))) | AV83: =IF(E83="금융","금융업 - 정의되지 않음",IF(AND(ISNUMBER(L83),ISNUMBER(M83),ISNUMBER(N83),ISNUMBER(AT83)),"순이익+감가상각-설비투자-운전자본증감",IF(AND(ISNUMBER(O83),ISNUMBER(N83)),"영업현금흐름-설비투자","산출불가"))) | AW83: =IF(AND(ISNUMBER(AU83),ISNUMBER(G83),G83<>0),AU83/G83,"") | AX83: =IF(AND(ISNUMBER(AC83),ISNUMBER(G83),G83<>0),AC83/G83,"")
A84: META | B84: Meta Platforms, Inc. | C84: 2023 | D84: 2023-12-31 | E84: 일반 | F84: 0001628280-26-003942 | G84: 134.902 | H84: 47.428 | I84: 0.42 | J84: 8.33 | K84: 46.751 | L84: 39.098 | M84: 11.178 | N84: 27.045 | O84: 71.113 | P84: 153.168 | Q84: 125.713 | R84: 65.403 | S84: 40.738 | V84: 18.385 | W84: 85.365 | X84: 59.549 | Y84: 31.96 | Z84: 27.026 | AA84: 94.898 | AB84: 2629 | AC84: =IF(AND(ISNUMBER(H84),ISNUMBER(I84)),H84+I84,IF(ISNUMBER(K84),K84,IF(ISNUMBER(H84),H84,""))) | AD84: =IF(OR(NOT(ISNUMBER(J84)),NOT(ISNUMBER(H84)),H84<=0),기준표!$B$8,MIN(MAX(J84/H84,기준표!$B$6),기준표!$B$7)) | AE84: =IF(ISNUMBER(AC84),AC84*(1-AD84),"") | AF84: =IF(AND(NOT(ISNUMBER(T84)),NOT(ISNUMBER(V84))),"",IF(ISNUMBER(T84),T84,0)+IF(ISNUMBER(V84),V84,0)) | AG84: =IF(E84="금융","",IF(AND(ISNUMBER(P84),ISNUMBER(AF84),ISNUMBER(R84)),P84+AF84-R84,"")) | AH84: =IF(E84="금융","",IF(NOT(ISNUMBER(AG84)),"",IF(ISNUMBER(AA84),(AG84+AA84)/2,AG84))) | AI84: =IF(AND(ISNUMBER(AE84),ISNUMBER(AH84),AH84>0),AE84/AH84,"") | AJ84: =IF(E84="금융","",IF(AND(ISNUMBER(P84),ISNUMBER(AF84)),P84+AF84,"")) | AK84: =IF(OR(NOT(ISNUMBER(AE84)),NOT(ISNUMBER(AJ84)),AJ84<=0),"",IF(AND(ISNUMBER(G84),AJ84<0.1*G84),"",AE84/AJ84)) | AL84: =IF(NOT(ISNUMBER(P84)),"",IF(ISNUMBER(Q84),(P84+Q84)/2,P84)) | AM84: =IF(AND(ISNUMBER(L84),ISNUMBER(AL84),AL84>0),L84/AL84,"") | AN84: =IF(AND(ISNUMBER(AM84),ISNUMBER({ROIC})),AM84-{ROIC},"") | AO84: =IF(AND(ISNUMBER(AC84),ISNUMBER(M84)),AC84+M84,"") | AP84: =IF(AND(ISNUMBER(AF84),ISNUMBER(R84),ISNUMBER(AO84),AO84>0),(AF84-R84)/AO84,"") | AQ84: =IF(AND(ISNUMBER(AC84),ISNUMBER(I84),I84<>0,AC84>0),AC84/I84,"") | AR84: =IF(AND(ISNUMBER(W84),ISNUMBER(Y84)),W84-IF(ISNUMBER(R84),R84,0)-(Y84-IF(ISNUMBER(T84),T84,0)),"") | AS84: =IF(AND(ISNUMBER(X84),ISNUMBER(Z84)),X84-IF(ISNUMBER(S84),S84,0)-(Z84-IF(ISNUMBER(U84),U84,0)),"") | AT84: =IF(AND(ISNUMBER(AR84),ISNUMBER(AS84)),AR84-AS84,"") | AU84: =IF(E84="금융","",IF(AND(ISNUMBER(L84),ISNUMBER(M84),ISNUMBER(N84),ISNUMBER(AT84)),L84+M84-N84-AT84,IF(AND(ISNUMBER(O84),ISNUMBER(N84)),O84-N84,""))) | AV84: =IF(E84="금융","금융업 - 정의되지 않음",IF(AND(ISNUMBER(L84),ISNUMBER(M84),ISNUMBER(N84),ISNUMBER(AT84)),"순이익+감가상각-설비투자-운전자본증감",IF(AND(ISNUMBER(O84),ISNUMBER(N84)),"영업현금흐름-설비투자","산출불가"))) | AW84: =IF(AND(ISNUMBER(AU84),ISNUMBER(G84),G84<>0),AU84/G84,"") | AX84: =IF(AND(ISNUMBER(AC84),ISNUMBER(G84),G84<>0),AC84/G84,"")
A85: META | B85: Meta Platforms, Inc. | C85: 2024 | D85: 2024-12-31 | E85: 일반 | F85: 0001628280-26-003942 | G85: 164.501 | H85: 70.663 | I85: 0.683 | J85: 8.303 | K85: 69.38 | L85: 62.36 | M85: 15.498 | N85: 37.256 | O85: 91.328 | P85: 182.637 | Q85: 153.168 | R85: 77.815 | S85: 65.403 | V85: 28.826 | W85: 100.045 | X85: 85.365 | Y85: 33.596 | Z85: 31.96 | AA85: 106.15 | AB85: 2614 | AC85: =IF(AND(ISNUMBER(H85),ISNUMBER(I85)),H85+I85,IF(ISNUMBER(K85),K85,IF(ISNUMBER(H85),H85,""))) | AD85: =IF(OR(NOT(ISNUMBER(J85)),NOT(ISNUMBER(H85)),H85<=0),기준표!$B$8,MIN(MAX(J85/H85,기준표!$B$6),기준표!$B$7)) | AE85: =IF(ISNUMBER(AC85),AC85*(1-AD85),"") | AF85: =IF(AND(NOT(ISNUMBER(T85)),NOT(ISNUMBER(V85))),"",IF(ISNUMBER(T85),T85,0)+IF(ISNUMBER(V85),V85,0)) | AG85: =IF(E85="금융","",IF(AND(ISNUMBER(P85),ISNUMBER(AF85),ISNUMBER(R85)),P85+AF85-R85,"")) | AH85: =IF(E85="금융","",IF(NOT(ISNUMBER(AG85)),"",IF(ISNUMBER(AA85),(AG85+AA85)/2,AG85))) | AI85: =IF(AND(ISNUMBER(AE85),ISNUMBER(AH85),AH85>0),AE85/AH85,"") | AJ85: =IF(E85="금융","",IF(AND(ISNUMBER(P85),ISNUMBER(AF85)),P85+AF85,"")) | AK85: =IF(OR(NOT(ISNUMBER(AE85)),NOT(ISNUMBER(AJ85)),AJ85<=0),"",IF(AND(ISNUMBER(G85),AJ85<0.1*G85),"",AE85/AJ85)) | AL85: =IF(NOT(ISNUMBER(P85)),"",IF(ISNUMBER(Q85),(P85+Q85)/2,P85)) | AM85: =IF(AND(ISNUMBER(L85),ISNUMBER(AL85),AL85>0),L85/AL85,"") | AN85: =IF(AND(ISNUMBER(AM85),ISNUMBER({ROIC})),AM85-{ROIC},"") | AO85: =IF(AND(ISNUMBER(AC85),ISNUMBER(M85)),AC85+M85,"") | AP85: =IF(AND(ISNUMBER(AF85),ISNUMBER(R85),ISNUMBER(AO85),AO85>0),(AF85-R85)/AO85,"") | AQ85: =IF(AND(ISNUMBER(AC85),ISNUMBER(I85),I85<>0,AC85>0),AC85/I85,"") | AR85: =IF(AND(ISNUMBER(W85),ISNUMBER(Y85)),W85-IF(ISNUMBER(R85),R85,0)-(Y85-IF(ISNUMBER(T85),T85,0)),"") | AS85: =IF(AND(ISNUMBER(X85),ISNUMBER(Z85)),X85-IF(ISNUMBER(S85),S85,0)-(Z85-IF(ISNUMBER(U85),U85,0)),"") | AT85: =IF(AND(ISNUMBER(AR85),ISNUMBER(AS85)),AR85-AS85,"") | AU85: =IF(E85="금융","",IF(AND(ISNUMBER(L85),ISNUMBER(M85),ISNUMBER(N85),ISNUMBER(AT85)),L85+M85-N85-AT85,IF(AND(ISNUMBER(O85),ISNUMBER(N85)),O85-N85,""))) | AV85: =IF(E85="금융","금융업 - 정의되지 않음",IF(AND(ISNUMBER(L85),ISNUMBER(M85),ISNUMBER(N85),ISNUMBER(AT85)),"순이익+감가상각-설비투자-운전자본증감",IF(AND(ISNUMBER(O85),ISNUMBER(N85)),"영업현금흐름-설비투자","산출불가"))) | AW85: =IF(AND(ISNUMBER(AU85),ISNUMBER(G85),G85<>0),AU85/G85,"") | AX85: =IF(AND(ISNUMBER(AC85),ISNUMBER(G85),G85<>0),AC85/G85,"")
A86: META | B86: Meta Platforms, Inc. | C86: 2025 | D86: 2025-12-31 | E86: 일반 | F86: 0001628280-26-003942 | G86: 200.966 | H86: 85.932 | I86: 1.09 | J86: 25.474 | K86: 83.276 | L86: 60.458 | M86: 18.616 | N86: 69.691 | O86: 115.8 | P86: 217.243 | Q86: 182.637 | R86: 81.592 | S86: 77.815 | V86: 58.744 | W86: 108.722 | X86: 100.045 | Y86: 41.836 | Z86: 33.596 | AA86: 133.648 | AB86: 2574 | AC86: =IF(AND(ISNUMBER(H86),ISNUMBER(I86)),H86+I86,IF(ISNUMBER(K86),K86,IF(ISNUMBER(H86),H86,""))) | AD86: =IF(OR(NOT(ISNUMBER(J86)),NOT(ISNUMBER(H86)),H86<=0),기준표!$B$8,MIN(MAX(J86/H86,기준표!$B$6),기준표!$B$7)) | AE86: =IF(ISNUMBER(AC86),AC86*(1-AD86),"") | AF86: =IF(AND(NOT(ISNUMBER(T86)),NOT(ISNUMBER(V86))),"",IF(ISNUMBER(T86),T86,0)+IF(ISNUMBER(V86),V86,0)) | AG86: =IF(E86="금융","",IF(AND(ISNUMBER(P86),ISNUMBER(AF86),ISNUMBER(R86)),P86+AF86-R86,"")) | AH86: =IF(E86="금융","",IF(NOT(ISNUMBER(AG86)),"",IF(ISNUMBER(AA86),(AG86+AA86)/2,AG86))) | AI86: =IF(AND(ISNUMBER(AE86),ISNUMBER(AH86),AH86>0),AE86/AH86,"") | AJ86: =IF(E86="금융","",IF(AND(ISNUMBER(P86),ISNUMBER(AF86)),P86+AF86,"")) | AK86: =IF(OR(NOT(ISNUMBER(AE86)),NOT(ISNUMBER(AJ86)),AJ86<=0),"",IF(AND(ISNUMBER(G86),AJ86<0.1*G86),"",AE86/AJ86)) | AL86: =IF(NOT(ISNUMBER(P86)),"",IF(ISNUMBER(Q86),(P86+Q86)/2,P86)) | AM86: =IF(AND(ISNUMBER(L86),ISNUMBER(AL86),AL86>0),L86/AL86,"") | AN86: =IF(AND(ISNUMBER(AM86),ISNUMBER({ROIC})),AM86-{ROIC},"") | AO86: =IF(AND(ISNUMBER(AC86),ISNUMBER(M86)),AC86+M86,"") | AP86: =IF(AND(ISNUMBER(AF86),ISNUMBER(R86),ISNUMBER(AO86),AO86>0),(AF86-R86)/AO86,"") | AQ86: =IF(AND(ISNUMBER(AC86),ISNUMBER(I86),I86<>0,AC86>0),AC86/I86,"") | AR86: =IF(AND(ISNUMBER(W86),ISNUMBER(Y86)),W86-IF(ISNUMBER(R86),R86,0)-(Y86-IF(ISNUMBER(T86),T86,0)),"") | AS86: =IF(AND(ISNUMBER(X86),ISNUMBER(Z86)),X86-IF(ISNUMBER(S86),S86,0)-(Z86-IF(ISNUMBER(U86),U86,0)),"") | AT86: =IF(AND(ISNUMBER(AR86),ISNUMBER(AS86)),AR86-AS86,"") | AU86: =IF(E86="금융","",IF(AND(ISNUMBER(L86),ISNUMBER(M86),ISNUMBER(N86),ISNUMBER(AT86)),L86+M86-N86-AT86,IF(AND(ISNUMBER(O86),ISNUMBER(N86)),O86-N86,""))) | AV86: =IF(E86="금융","금융업 - 정의되지 않음",IF(AND(ISNUMBER(L86),ISNUMBER(M86),ISNUMBER(N86),ISNUMBER(AT86)),"순이익+감가상각-설비투자-운전자본증감",IF(AND(ISNUMBER(O86),ISNUMBER(N86)),"영업현금흐름-설비투자","산출불가"))) | AW86: =IF(AND(ISNUMBER(AU86),ISNUMBER(G86),G86<>0),AU86/G86,"") | AX86: =IF(AND(ISNUMBER(AC86),ISNUMBER(G86),G86<>0),AC86/G86,"")
